package com.google.android.gms.internal.ads;

import android.view.View;
import com.google.android.gms.ads.internal.g;

public final class c11 implements g {
  private g a;
  
  public final void a() {
    // Byte code:
    //   0: aload_0
    //   1: monitorenter
    //   2: aload_0
    //   3: getfield a : Lcom/google/android/gms/ads/internal/g;
    //   6: astore_1
    //   7: aload_1
    //   8: ifnull -> 17
    //   11: aload_1
    //   12: invokeinterface a : ()V
    //   17: aload_0
    //   18: monitorexit
    //   19: return
    //   20: astore_1
    //   21: aload_0
    //   22: monitorexit
    //   23: aload_1
    //   24: athrow
    // Exception table:
    //   from	to	target	type
    //   2	7	20	finally
    //   11	17	20	finally
  }
  
  public final void b() {
    // Byte code:
    //   0: aload_0
    //   1: monitorenter
    //   2: aload_0
    //   3: getfield a : Lcom/google/android/gms/ads/internal/g;
    //   6: astore_1
    //   7: aload_1
    //   8: ifnull -> 17
    //   11: aload_1
    //   12: invokeinterface b : ()V
    //   17: aload_0
    //   18: monitorexit
    //   19: return
    //   20: astore_1
    //   21: aload_0
    //   22: monitorexit
    //   23: aload_1
    //   24: athrow
    // Exception table:
    //   from	to	target	type
    //   2	7	20	finally
    //   11	17	20	finally
  }
  
  public final void c(View paramView) {
    // Byte code:
    //   0: aload_0
    //   1: monitorenter
    //   2: aload_0
    //   3: getfield a : Lcom/google/android/gms/ads/internal/g;
    //   6: astore_2
    //   7: aload_2
    //   8: ifnull -> 18
    //   11: aload_2
    //   12: aload_1
    //   13: invokeinterface c : (Landroid/view/View;)V
    //   18: aload_0
    //   19: monitorexit
    //   20: return
    //   21: astore_1
    //   22: aload_0
    //   23: monitorexit
    //   24: aload_1
    //   25: athrow
    // Exception table:
    //   from	to	target	type
    //   2	7	21	finally
    //   11	18	21	finally
  }
  
  public final void d(g paramg) {
    // Byte code:
    //   0: aload_0
    //   1: monitorenter
    //   2: aload_0
    //   3: aload_1
    //   4: putfield a : Lcom/google/android/gms/ads/internal/g;
    //   7: aload_0
    //   8: monitorexit
    //   9: return
    //   10: astore_1
    //   11: aload_0
    //   12: monitorexit
    //   13: aload_1
    //   14: athrow
    // Exception table:
    //   from	to	target	type
    //   2	7	10	finally
  }
}


/* Location:              /home/sumith/decompile/test/classes-dex2jar.jar!/com/google/android/gms/internal/ads/c11.class
 * Java compiler version: 6 (50.0)
 * JD-Core Version:       1.1.3
 */