package com.google.android.gms.internal.ads;

final class ca2 {
  static ju1 a;
  
  static boolean a(z92 paramz92) {
    // Byte code:
    //   0: getstatic com/google/android/gms/internal/ads/ca2.a : Lcom/google/android/gms/internal/ads/ju1;
    //   3: ifnull -> 8
    //   6: iconst_1
    //   7: ireturn
    //   8: getstatic com/google/android/gms/internal/ads/m0.X1 : Lcom/google/android/gms/internal/ads/x;
    //   11: astore_1
    //   12: invokestatic e : ()Lcom/google/android/gms/internal/ads/i0;
    //   15: aload_1
    //   16: invokevirtual c : (Lcom/google/android/gms/internal/ads/x;)Ljava/lang/Object;
    //   19: checkcast java/lang/String
    //   22: astore_2
    //   23: aload_2
    //   24: ifnull -> 36
    //   27: aload_2
    //   28: astore_1
    //   29: aload_2
    //   30: invokevirtual length : ()I
    //   33: ifne -> 82
    //   36: aload_0
    //   37: ifnonnull -> 45
    //   40: aconst_null
    //   41: astore_0
    //   42: goto -> 74
    //   45: aload_0
    //   46: ldc '/TbyeKn5BCGoFXpEYkmkevBjYiDI2cU9nEifSIchqqD5aWfWy6v5sZTpifn+5AIL'
    //   48: ldc 'PJXTpPH5Q3JP8R736KmmofmTne3UwIW4eaifsKPbWk4='
    //   50: invokevirtual e : (Ljava/lang/String;Ljava/lang/String;)Ljava/lang/reflect/Method;
    //   53: astore_0
    //   54: aload_0
    //   55: ifnonnull -> 61
    //   58: goto -> 40
    //   61: aload_0
    //   62: aconst_null
    //   63: iconst_0
    //   64: anewarray java/lang/Object
    //   67: invokevirtual invoke : (Ljava/lang/Object;[Ljava/lang/Object;)Ljava/lang/Object;
    //   70: checkcast java/lang/String
    //   73: astore_0
    //   74: aload_0
    //   75: astore_1
    //   76: aload_0
    //   77: ifnonnull -> 82
    //   80: iconst_0
    //   81: ireturn
    //   82: aload_1
    //   83: iconst_1
    //   84: invokestatic b : (Ljava/lang/String;Z)[B
    //   87: astore_0
    //   88: aload_0
    //   89: invokestatic a : ([B)Lcom/google/android/gms/internal/ads/tu1;
    //   92: astore_2
    //   93: getstatic com/google/android/gms/internal/ads/vw1.c : Lcom/google/android/gms/internal/ads/o02;
    //   96: invokevirtual J : ()Ljava/util/List;
    //   99: invokeinterface iterator : ()Ljava/util/Iterator;
    //   104: astore_1
    //   105: aload_1
    //   106: invokeinterface hasNext : ()Z
    //   111: ifeq -> 334
    //   114: aload_1
    //   115: invokeinterface next : ()Ljava/lang/Object;
    //   120: checkcast com/google/android/gms/internal/ads/b02
    //   123: astore_3
    //   124: aload_3
    //   125: invokevirtual J : ()Ljava/lang/String;
    //   128: invokevirtual isEmpty : ()Z
    //   131: ifne -> 322
    //   134: aload_3
    //   135: invokevirtual K : ()Ljava/lang/String;
    //   138: invokevirtual isEmpty : ()Z
    //   141: ifne -> 310
    //   144: aload_3
    //   145: invokevirtual N : ()Ljava/lang/String;
    //   148: invokevirtual isEmpty : ()Z
    //   151: ifne -> 298
    //   154: aload_3
    //   155: invokevirtual N : ()Ljava/lang/String;
    //   158: ldc 'TinkAead'
    //   160: invokevirtual equals : (Ljava/lang/Object;)Z
    //   163: ifne -> 105
    //   166: aload_3
    //   167: invokevirtual N : ()Ljava/lang/String;
    //   170: ldc 'TinkMac'
    //   172: invokevirtual equals : (Ljava/lang/Object;)Z
    //   175: ifne -> 105
    //   178: aload_3
    //   179: invokevirtual N : ()Ljava/lang/String;
    //   182: ldc 'TinkHybridDecrypt'
    //   184: invokevirtual equals : (Ljava/lang/Object;)Z
    //   187: ifne -> 105
    //   190: aload_3
    //   191: invokevirtual N : ()Ljava/lang/String;
    //   194: ldc 'TinkHybridEncrypt'
    //   196: invokevirtual equals : (Ljava/lang/Object;)Z
    //   199: ifne -> 105
    //   202: aload_3
    //   203: invokevirtual N : ()Ljava/lang/String;
    //   206: ldc 'TinkPublicKeySign'
    //   208: invokevirtual equals : (Ljava/lang/Object;)Z
    //   211: ifne -> 105
    //   214: aload_3
    //   215: invokevirtual N : ()Ljava/lang/String;
    //   218: ldc 'TinkPublicKeyVerify'
    //   220: invokevirtual equals : (Ljava/lang/Object;)Z
    //   223: ifne -> 105
    //   226: aload_3
    //   227: invokevirtual N : ()Ljava/lang/String;
    //   230: ldc 'TinkStreamingAead'
    //   232: invokevirtual equals : (Ljava/lang/Object;)Z
    //   235: ifne -> 105
    //   238: aload_3
    //   239: invokevirtual N : ()Ljava/lang/String;
    //   242: ldc 'TinkDeterministicAead'
    //   244: invokevirtual equals : (Ljava/lang/Object;)Z
    //   247: ifeq -> 253
    //   250: goto -> 105
    //   253: aload_3
    //   254: invokevirtual N : ()Ljava/lang/String;
    //   257: invokestatic r : (Ljava/lang/String;)Lcom/google/android/gms/internal/ads/fu1;
    //   260: astore_0
    //   261: aload_0
    //   262: invokeinterface b : ()Lcom/google/android/gms/internal/ads/yu1;
    //   267: invokestatic l : (Lcom/google/android/gms/internal/ads/yu1;)V
    //   270: aload_0
    //   271: aload_3
    //   272: invokevirtual J : ()Ljava/lang/String;
    //   275: aload_3
    //   276: invokevirtual K : ()Ljava/lang/String;
    //   279: aload_3
    //   280: invokevirtual L : ()I
    //   283: invokeinterface a : (Ljava/lang/String;Ljava/lang/String;I)Lcom/google/android/gms/internal/ads/mu1;
    //   288: aload_3
    //   289: invokevirtual M : ()Z
    //   292: invokestatic j : (Lcom/google/android/gms/internal/ads/mu1;Z)V
    //   295: goto -> 105
    //   298: new java/security/GeneralSecurityException
    //   301: astore_0
    //   302: aload_0
    //   303: ldc 'Missing catalogue_name.'
    //   305: invokespecial <init> : (Ljava/lang/String;)V
    //   308: aload_0
    //   309: athrow
    //   310: new java/security/GeneralSecurityException
    //   313: astore_0
    //   314: aload_0
    //   315: ldc 'Missing primitive_name.'
    //   317: invokespecial <init> : (Ljava/lang/String;)V
    //   320: aload_0
    //   321: athrow
    //   322: new java/security/GeneralSecurityException
    //   325: astore_0
    //   326: aload_0
    //   327: ldc 'Missing type_url.'
    //   329: invokespecial <init> : (Ljava/lang/String;)V
    //   332: aload_0
    //   333: athrow
    //   334: aload_2
    //   335: aconst_null
    //   336: invokestatic a : (Lcom/google/android/gms/internal/ads/tu1;Lcom/google/android/gms/internal/ads/mu1;)Lcom/google/android/gms/internal/ads/ju1;
    //   339: astore_0
    //   340: aload_0
    //   341: putstatic com/google/android/gms/internal/ads/ca2.a : Lcom/google/android/gms/internal/ads/ju1;
    //   344: aload_0
    //   345: ifnull -> 350
    //   348: iconst_1
    //   349: ireturn
    //   350: iconst_0
    //   351: ireturn
    //   352: astore_0
    //   353: goto -> 350
    // Exception table:
    //   from	to	target	type
    //   82	88	352	java/lang/IllegalArgumentException
    //   88	105	352	java/security/GeneralSecurityException
    //   105	250	352	java/security/GeneralSecurityException
    //   253	295	352	java/security/GeneralSecurityException
    //   298	310	352	java/security/GeneralSecurityException
    //   310	322	352	java/security/GeneralSecurityException
    //   322	334	352	java/security/GeneralSecurityException
    //   334	344	352	java/security/GeneralSecurityException
  }
}


/* Location:              /home/sumith/decompile/test/classes-dex2jar.jar!/com/google/android/gms/internal/ads/ca2.class
 * Java compiler version: 6 (50.0)
 * JD-Core Version:       1.1.3
 */