package com.google.android.gms.internal.ads;

import android.content.Context;
import org.json.JSONObject;

public final class ct0 implements kl1<bt0, et0> {
  private final Context a;
  
  private final String b;
  
  private final hh c;
  
  private final String d;
  
  private final int e;
  
  public ct0(Context paramContext, String paramString1, hh paramhh, String paramString2, int paramInt) {
    this.a = paramContext;
    this.b = paramString1;
    this.c = paramhh;
    this.d = paramString2;
    this.e = paramInt;
  }
  
  private final et0 b(String paramString1, vg paramvg, JSONObject paramJSONObject, String paramString2) {
    // Byte code:
    //   0: aload_3
    //   1: ldc 'http_timeout_millis'
    //   3: ldc 60000
    //   5: invokevirtual optInt : (Ljava/lang/String;I)I
    //   8: istore #5
    //   10: aload_2
    //   11: invokevirtual a : ()I
    //   14: bipush #-2
    //   16: if_icmpeq -> 74
    //   19: aload_2
    //   20: invokevirtual a : ()I
    //   23: iconst_1
    //   24: if_icmpne -> 61
    //   27: aload_2
    //   28: invokevirtual d : ()Ljava/util/List;
    //   31: ifnull -> 46
    //   34: ldc ', '
    //   36: aload_2
    //   37: invokevirtual d : ()Ljava/util/List;
    //   40: invokestatic join : (Ljava/lang/CharSequence;Ljava/lang/Iterable;)Ljava/lang/String;
    //   43: invokestatic g : (Ljava/lang/String;)V
    //   46: new com/google/android/gms/internal/ads/zzcmb
    //   49: astore_1
    //   50: aload_1
    //   51: getstatic com/google/android/gms/internal/ads/zzdom.c : Lcom/google/android/gms/internal/ads/zzdom;
    //   54: ldc 'Error building request URL.'
    //   56: invokespecial <init> : (Lcom/google/android/gms/internal/ads/zzdom;Ljava/lang/String;)V
    //   59: aload_1
    //   60: athrow
    //   61: new com/google/android/gms/internal/ads/zzcmb
    //   64: astore_1
    //   65: aload_1
    //   66: getstatic com/google/android/gms/internal/ads/zzdom.b : Lcom/google/android/gms/internal/ads/zzdom;
    //   69: invokespecial <init> : (Lcom/google/android/gms/internal/ads/zzdom;)V
    //   72: aload_1
    //   73: athrow
    //   74: new com/google/android/gms/internal/ads/et0
    //   77: astore #6
    //   79: aload #6
    //   81: invokespecial <init> : ()V
    //   84: aload_0
    //   85: getfield b : Ljava/lang/String;
    //   88: invokestatic valueOf : (Ljava/lang/Object;)Ljava/lang/String;
    //   91: astore #7
    //   93: aload #7
    //   95: invokevirtual length : ()I
    //   98: ifeq -> 113
    //   101: ldc 'SDK version: '
    //   103: aload #7
    //   105: invokevirtual concat : (Ljava/lang/String;)Ljava/lang/String;
    //   108: astore #7
    //   110: goto -> 124
    //   113: new java/lang/String
    //   116: dup
    //   117: ldc 'SDK version: '
    //   119: invokespecial <init> : (Ljava/lang/String;)V
    //   122: astore #7
    //   124: aload #7
    //   126: invokestatic h : (Ljava/lang/String;)V
    //   129: aload_1
    //   130: invokestatic valueOf : (Ljava/lang/Object;)Ljava/lang/String;
    //   133: astore #7
    //   135: aload #7
    //   137: invokevirtual length : ()I
    //   140: ifeq -> 155
    //   143: ldc 'AdRequestServiceImpl: Sending request: '
    //   145: aload #7
    //   147: invokevirtual concat : (Ljava/lang/String;)Ljava/lang/String;
    //   150: astore #7
    //   152: goto -> 166
    //   155: new java/lang/String
    //   158: dup
    //   159: ldc 'AdRequestServiceImpl: Sending request: '
    //   161: invokespecial <init> : (Ljava/lang/String;)V
    //   164: astore #7
    //   166: aload #7
    //   168: invokestatic e : (Ljava/lang/String;)V
    //   171: new java/net/URL
    //   174: astore #7
    //   176: aload #7
    //   178: aload_1
    //   179: invokespecial <init> : (Ljava/lang/String;)V
    //   182: new java/util/HashMap
    //   185: astore #8
    //   187: aload #8
    //   189: invokespecial <init> : ()V
    //   192: invokestatic j : ()Lcom/google/android/gms/common/util/e;
    //   195: invokeinterface b : ()J
    //   200: lstore #9
    //   202: iconst_0
    //   203: istore #11
    //   205: aload #7
    //   207: astore_1
    //   208: aload_0
    //   209: getfield c : Lcom/google/android/gms/internal/ads/hh;
    //   212: aload_0
    //   213: getfield e : I
    //   216: invokeinterface a : (I)V
    //   221: aload_1
    //   222: invokevirtual openConnection : ()Ljava/net/URLConnection;
    //   225: checkcast java/net/HttpURLConnection
    //   228: astore #7
    //   230: invokestatic c : ()Lcom/google/android/gms/ads/internal/util/h1;
    //   233: astore_1
    //   234: aload_0
    //   235: getfield a : Landroid/content/Context;
    //   238: astore #12
    //   240: aload_0
    //   241: getfield b : Ljava/lang/String;
    //   244: astore #13
    //   246: aload #7
    //   248: astore #14
    //   250: aload_1
    //   251: aload #12
    //   253: aload #13
    //   255: iconst_0
    //   256: aload #7
    //   258: iconst_0
    //   259: iload #5
    //   261: invokevirtual m : (Landroid/content/Context;Ljava/lang/String;ZLjava/net/HttpURLConnection;ZI)V
    //   264: aload_2
    //   265: invokevirtual h : ()Z
    //   268: ifeq -> 291
    //   271: aload #4
    //   273: invokestatic isEmpty : (Ljava/lang/CharSequence;)Z
    //   276: ifne -> 291
    //   279: aload #14
    //   281: ldc 'Cookie'
    //   283: aload #4
    //   285: invokevirtual addRequestProperty : (Ljava/lang/String;Ljava/lang/String;)V
    //   288: goto -> 291
    //   291: aload_2
    //   292: invokevirtual g : ()Z
    //   295: istore #15
    //   297: iload #15
    //   299: ifeq -> 379
    //   302: aload_3
    //   303: ldc 'pii'
    //   305: invokevirtual optJSONObject : (Ljava/lang/String;)Lorg/json/JSONObject;
    //   308: astore_1
    //   309: aload_1
    //   310: ifnull -> 374
    //   313: aload_1
    //   314: ldc 'doritos'
    //   316: ldc ''
    //   318: invokevirtual optString : (Ljava/lang/String;Ljava/lang/String;)Ljava/lang/String;
    //   321: invokestatic isEmpty : (Ljava/lang/CharSequence;)Z
    //   324: ifne -> 342
    //   327: aload #14
    //   329: ldc 'x-afma-drt-cookie'
    //   331: aload_1
    //   332: ldc 'doritos'
    //   334: ldc ''
    //   336: invokevirtual optString : (Ljava/lang/String;Ljava/lang/String;)Ljava/lang/String;
    //   339: invokevirtual addRequestProperty : (Ljava/lang/String;Ljava/lang/String;)V
    //   342: aload_1
    //   343: ldc 'doritos_v2'
    //   345: ldc ''
    //   347: invokevirtual optString : (Ljava/lang/String;Ljava/lang/String;)Ljava/lang/String;
    //   350: invokestatic isEmpty : (Ljava/lang/CharSequence;)Z
    //   353: ifne -> 379
    //   356: aload #14
    //   358: ldc 'x-afma-drt-v2-cookie'
    //   360: aload_1
    //   361: ldc 'doritos_v2'
    //   363: ldc ''
    //   365: invokevirtual optString : (Ljava/lang/String;Ljava/lang/String;)Ljava/lang/String;
    //   368: invokevirtual addRequestProperty : (Ljava/lang/String;Ljava/lang/String;)V
    //   371: goto -> 379
    //   374: ldc 'DSID signal does not exist.'
    //   376: invokestatic m : (Ljava/lang/String;)V
    //   379: aload_2
    //   380: invokevirtual f : ()Ljava/lang/String;
    //   383: invokestatic isEmpty : (Ljava/lang/CharSequence;)Z
    //   386: ifne -> 455
    //   389: aload #14
    //   391: iconst_1
    //   392: invokevirtual setDoOutput : (Z)V
    //   395: aload_2
    //   396: invokevirtual f : ()Ljava/lang/String;
    //   399: invokevirtual getBytes : ()[B
    //   402: astore_1
    //   403: aload #14
    //   405: aload_1
    //   406: arraylength
    //   407: invokevirtual setFixedLengthStreamingMode : (I)V
    //   410: new java/io/BufferedOutputStream
    //   413: astore #13
    //   415: aload #13
    //   417: aload #14
    //   419: invokevirtual getOutputStream : ()Ljava/io/OutputStream;
    //   422: invokespecial <init> : (Ljava/io/OutputStream;)V
    //   425: aload #13
    //   427: aload_1
    //   428: invokevirtual write : ([B)V
    //   431: aload #13
    //   433: invokestatic a : (Ljava/io/Closeable;)V
    //   436: goto -> 457
    //   439: astore_1
    //   440: aload #13
    //   442: astore_2
    //   443: goto -> 449
    //   446: astore_1
    //   447: aconst_null
    //   448: astore_2
    //   449: aload_2
    //   450: invokestatic a : (Ljava/io/Closeable;)V
    //   453: aload_1
    //   454: athrow
    //   455: aconst_null
    //   456: astore_1
    //   457: new com/google/android/gms/internal/ads/wl
    //   460: astore #13
    //   462: aload #13
    //   464: invokespecial <init> : ()V
    //   467: aload #13
    //   469: aload #14
    //   471: aload_1
    //   472: invokevirtual i : (Ljava/net/HttpURLConnection;[B)V
    //   475: aload #14
    //   477: invokevirtual getResponseCode : ()I
    //   480: istore #16
    //   482: aload #14
    //   484: invokevirtual getHeaderFields : ()Ljava/util/Map;
    //   487: invokeinterface entrySet : ()Ljava/util/Set;
    //   492: invokeinterface iterator : ()Ljava/util/Iterator;
    //   497: astore #12
    //   499: aload #12
    //   501: invokeinterface hasNext : ()Z
    //   506: ifeq -> 603
    //   509: aload #12
    //   511: invokeinterface next : ()Ljava/lang/Object;
    //   516: checkcast java/util/Map$Entry
    //   519: astore #17
    //   521: aload #17
    //   523: invokeinterface getKey : ()Ljava/lang/Object;
    //   528: checkcast java/lang/String
    //   531: astore_1
    //   532: aload #17
    //   534: invokeinterface getValue : ()Ljava/lang/Object;
    //   539: checkcast java/util/List
    //   542: astore #18
    //   544: aload #8
    //   546: aload_1
    //   547: invokeinterface containsKey : (Ljava/lang/Object;)Z
    //   552: ifeq -> 577
    //   555: aload #8
    //   557: aload_1
    //   558: invokeinterface get : (Ljava/lang/Object;)Ljava/lang/Object;
    //   563: checkcast java/util/List
    //   566: aload #18
    //   568: invokeinterface addAll : (Ljava/util/Collection;)Z
    //   573: pop
    //   574: goto -> 499
    //   577: new java/util/ArrayList
    //   580: astore #17
    //   582: aload #17
    //   584: aload #18
    //   586: invokespecial <init> : (Ljava/util/Collection;)V
    //   589: aload #8
    //   591: aload_1
    //   592: aload #17
    //   594: invokeinterface put : (Ljava/lang/Object;Ljava/lang/Object;)Ljava/lang/Object;
    //   599: pop
    //   600: goto -> 499
    //   603: aload #13
    //   605: aload #14
    //   607: iload #16
    //   609: invokevirtual h : (Ljava/net/HttpURLConnection;I)V
    //   612: aload #6
    //   614: iload #16
    //   616: putfield a : I
    //   619: aload #6
    //   621: aload #8
    //   623: putfield b : Ljava/util/Map;
    //   626: aload #6
    //   628: ldc ''
    //   630: putfield c : Ljava/lang/String;
    //   633: iload #16
    //   635: sipush #200
    //   638: if_icmplt -> 782
    //   641: iload #16
    //   643: sipush #300
    //   646: if_icmpge -> 782
    //   649: new java/io/InputStreamReader
    //   652: astore_1
    //   653: aload_1
    //   654: aload #14
    //   656: invokevirtual getInputStream : ()Ljava/io/InputStream;
    //   659: invokespecial <init> : (Ljava/io/InputStream;)V
    //   662: invokestatic c : ()Lcom/google/android/gms/ads/internal/util/h1;
    //   665: pop
    //   666: aload_1
    //   667: invokestatic g : (Ljava/io/InputStreamReader;)Ljava/lang/String;
    //   670: astore_2
    //   671: aload_1
    //   672: invokestatic a : (Ljava/io/Closeable;)V
    //   675: aload #13
    //   677: aload_2
    //   678: invokevirtual q : (Ljava/lang/String;)V
    //   681: aload #6
    //   683: aload_2
    //   684: putfield c : Ljava/lang/String;
    //   687: aload_2
    //   688: invokestatic isEmpty : (Ljava/lang/CharSequence;)Z
    //   691: ifeq -> 730
    //   694: getstatic com/google/android/gms/internal/ads/m0.b4 : Lcom/google/android/gms/internal/ads/x;
    //   697: astore_1
    //   698: invokestatic e : ()Lcom/google/android/gms/internal/ads/i0;
    //   701: aload_1
    //   702: invokevirtual c : (Lcom/google/android/gms/internal/ads/x;)Ljava/lang/Object;
    //   705: checkcast java/lang/Boolean
    //   708: invokevirtual booleanValue : ()Z
    //   711: ifeq -> 717
    //   714: goto -> 730
    //   717: new com/google/android/gms/internal/ads/zzcmb
    //   720: astore_1
    //   721: aload_1
    //   722: getstatic com/google/android/gms/internal/ads/zzdom.d : Lcom/google/android/gms/internal/ads/zzdom;
    //   725: invokespecial <init> : (Lcom/google/android/gms/internal/ads/zzdom;)V
    //   728: aload_1
    //   729: athrow
    //   730: aload #6
    //   732: invokestatic j : ()Lcom/google/android/gms/common/util/e;
    //   735: invokeinterface b : ()J
    //   740: lload #9
    //   742: lsub
    //   743: putfield d : J
    //   746: aload #14
    //   748: invokevirtual disconnect : ()V
    //   751: aload_0
    //   752: getfield c : Lcom/google/android/gms/internal/ads/hh;
    //   755: invokeinterface b : ()V
    //   760: aload #6
    //   762: areturn
    //   763: astore_2
    //   764: aload_2
    //   765: astore_3
    //   766: aload_1
    //   767: astore_2
    //   768: goto -> 776
    //   771: astore_1
    //   772: aconst_null
    //   773: astore_2
    //   774: aload_1
    //   775: astore_3
    //   776: aload_2
    //   777: invokestatic a : (Ljava/io/Closeable;)V
    //   780: aload_3
    //   781: athrow
    //   782: iload #16
    //   784: sipush #300
    //   787: if_icmplt -> 918
    //   790: iload #16
    //   792: sipush #400
    //   795: if_icmpge -> 918
    //   798: aload #14
    //   800: ldc_w 'Location'
    //   803: invokevirtual getHeaderField : (Ljava/lang/String;)Ljava/lang/String;
    //   806: astore #13
    //   808: aload #13
    //   810: invokestatic isEmpty : (Ljava/lang/CharSequence;)Z
    //   813: ifne -> 896
    //   816: new java/net/URL
    //   819: astore_1
    //   820: aload_1
    //   821: aload #13
    //   823: invokespecial <init> : (Ljava/lang/String;)V
    //   826: iinc #11, 1
    //   829: getstatic com/google/android/gms/internal/ads/m0.C3 : Lcom/google/android/gms/internal/ads/x;
    //   832: astore #13
    //   834: invokestatic e : ()Lcom/google/android/gms/internal/ads/i0;
    //   837: aload #13
    //   839: invokevirtual c : (Lcom/google/android/gms/internal/ads/x;)Ljava/lang/Object;
    //   842: checkcast java/lang/Integer
    //   845: invokevirtual intValue : ()I
    //   848: istore #16
    //   850: iload #11
    //   852: iload #16
    //   854: if_icmpgt -> 874
    //   857: aload #14
    //   859: invokevirtual disconnect : ()V
    //   862: aload_0
    //   863: getfield c : Lcom/google/android/gms/internal/ads/hh;
    //   866: invokeinterface b : ()V
    //   871: goto -> 208
    //   874: ldc_w 'Too many redirects.'
    //   877: invokestatic i : (Ljava/lang/String;)V
    //   880: new com/google/android/gms/internal/ads/zzcmb
    //   883: astore_1
    //   884: aload_1
    //   885: getstatic com/google/android/gms/internal/ads/zzdom.b : Lcom/google/android/gms/internal/ads/zzdom;
    //   888: ldc_w 'Too many redirects'
    //   891: invokespecial <init> : (Lcom/google/android/gms/internal/ads/zzdom;Ljava/lang/String;)V
    //   894: aload_1
    //   895: athrow
    //   896: ldc_w 'No location header to follow redirect.'
    //   899: invokestatic i : (Ljava/lang/String;)V
    //   902: new com/google/android/gms/internal/ads/zzcmb
    //   905: astore_1
    //   906: aload_1
    //   907: getstatic com/google/android/gms/internal/ads/zzdom.b : Lcom/google/android/gms/internal/ads/zzdom;
    //   910: ldc_w 'No location header to follow redirect'
    //   913: invokespecial <init> : (Lcom/google/android/gms/internal/ads/zzdom;Ljava/lang/String;)V
    //   916: aload_1
    //   917: athrow
    //   918: new java/lang/StringBuilder
    //   921: astore_1
    //   922: aload_1
    //   923: bipush #46
    //   925: invokespecial <init> : (I)V
    //   928: aload_1
    //   929: ldc_w 'Received error HTTP response code: '
    //   932: invokevirtual append : (Ljava/lang/String;)Ljava/lang/StringBuilder;
    //   935: pop
    //   936: aload_1
    //   937: iload #16
    //   939: invokevirtual append : (I)Ljava/lang/StringBuilder;
    //   942: pop
    //   943: aload_1
    //   944: invokevirtual toString : ()Ljava/lang/String;
    //   947: invokestatic i : (Ljava/lang/String;)V
    //   950: new com/google/android/gms/internal/ads/zzcmb
    //   953: astore_3
    //   954: getstatic com/google/android/gms/internal/ads/zzdom.b : Lcom/google/android/gms/internal/ads/zzdom;
    //   957: astore_1
    //   958: new java/lang/StringBuilder
    //   961: astore_2
    //   962: aload_2
    //   963: bipush #46
    //   965: invokespecial <init> : (I)V
    //   968: aload_2
    //   969: ldc_w 'Received error HTTP response code: '
    //   972: invokevirtual append : (Ljava/lang/String;)Ljava/lang/StringBuilder;
    //   975: pop
    //   976: aload_2
    //   977: iload #16
    //   979: invokevirtual append : (I)Ljava/lang/StringBuilder;
    //   982: pop
    //   983: aload_3
    //   984: aload_1
    //   985: aload_2
    //   986: invokevirtual toString : ()Ljava/lang/String;
    //   989: invokespecial <init> : (Lcom/google/android/gms/internal/ads/zzdom;Ljava/lang/String;)V
    //   992: aload_3
    //   993: athrow
    //   994: astore_1
    //   995: goto -> 1003
    //   998: astore_1
    //   999: goto -> 1059
    //   1002: astore_1
    //   1003: getstatic com/google/android/gms/internal/ads/m0.R5 : Lcom/google/android/gms/internal/ads/x;
    //   1006: astore_2
    //   1007: invokestatic e : ()Lcom/google/android/gms/internal/ads/i0;
    //   1010: aload_2
    //   1011: invokevirtual c : (Lcom/google/android/gms/internal/ads/x;)Ljava/lang/Object;
    //   1014: checkcast java/lang/Boolean
    //   1017: invokevirtual booleanValue : ()Z
    //   1020: ifeq -> 1056
    //   1023: aload #6
    //   1025: invokestatic j : ()Lcom/google/android/gms/common/util/e;
    //   1028: invokeinterface b : ()J
    //   1033: lload #9
    //   1035: lsub
    //   1036: putfield d : J
    //   1039: aload #7
    //   1041: invokevirtual disconnect : ()V
    //   1044: aload_0
    //   1045: getfield c : Lcom/google/android/gms/internal/ads/hh;
    //   1048: invokeinterface b : ()V
    //   1053: aload #6
    //   1055: areturn
    //   1056: aload_1
    //   1057: athrow
    //   1058: astore_1
    //   1059: aload #7
    //   1061: invokevirtual disconnect : ()V
    //   1064: aload_0
    //   1065: getfield c : Lcom/google/android/gms/internal/ads/hh;
    //   1068: invokeinterface b : ()V
    //   1073: aload_1
    //   1074: athrow
    //   1075: astore_2
    //   1076: aload_2
    //   1077: invokevirtual getMessage : ()Ljava/lang/String;
    //   1080: invokestatic valueOf : (Ljava/lang/Object;)Ljava/lang/String;
    //   1083: astore_1
    //   1084: aload_1
    //   1085: invokevirtual length : ()I
    //   1088: ifeq -> 1102
    //   1091: ldc_w 'Error while connecting to ad server: '
    //   1094: aload_1
    //   1095: invokevirtual concat : (Ljava/lang/String;)Ljava/lang/String;
    //   1098: astore_1
    //   1099: goto -> 1113
    //   1102: new java/lang/String
    //   1105: dup
    //   1106: ldc_w 'Error while connecting to ad server: '
    //   1109: invokespecial <init> : (Ljava/lang/String;)V
    //   1112: astore_1
    //   1113: aload_1
    //   1114: invokestatic i : (Ljava/lang/String;)V
    //   1117: new com/google/android/gms/internal/ads/zzcmb
    //   1120: dup
    //   1121: getstatic com/google/android/gms/internal/ads/zzdom.b : Lcom/google/android/gms/internal/ads/zzdom;
    //   1124: aload_1
    //   1125: aload_2
    //   1126: invokespecial <init> : (Lcom/google/android/gms/internal/ads/zzdom;Ljava/lang/String;Ljava/lang/Throwable;)V
    //   1129: astore_1
    //   1130: goto -> 1135
    //   1133: aload_1
    //   1134: athrow
    //   1135: goto -> 1133
    // Exception table:
    //   from	to	target	type
    //   0	46	1075	java/io/IOException
    //   46	61	1075	java/io/IOException
    //   61	74	1075	java/io/IOException
    //   74	110	1075	java/io/IOException
    //   113	124	1075	java/io/IOException
    //   124	152	1075	java/io/IOException
    //   155	166	1075	java/io/IOException
    //   166	202	1075	java/io/IOException
    //   208	230	1075	java/io/IOException
    //   230	246	1002	com/google/android/gms/internal/ads/zzcmb
    //   230	246	998	finally
    //   250	288	994	com/google/android/gms/internal/ads/zzcmb
    //   250	288	1058	finally
    //   291	297	994	com/google/android/gms/internal/ads/zzcmb
    //   291	297	1058	finally
    //   302	309	994	com/google/android/gms/internal/ads/zzcmb
    //   302	309	1058	finally
    //   313	342	994	com/google/android/gms/internal/ads/zzcmb
    //   313	342	1058	finally
    //   342	371	994	com/google/android/gms/internal/ads/zzcmb
    //   342	371	1058	finally
    //   374	379	994	com/google/android/gms/internal/ads/zzcmb
    //   374	379	1058	finally
    //   379	410	994	com/google/android/gms/internal/ads/zzcmb
    //   379	410	1058	finally
    //   410	425	446	finally
    //   425	431	439	finally
    //   431	436	994	com/google/android/gms/internal/ads/zzcmb
    //   431	436	1058	finally
    //   449	455	994	com/google/android/gms/internal/ads/zzcmb
    //   449	455	1058	finally
    //   457	499	994	com/google/android/gms/internal/ads/zzcmb
    //   457	499	1058	finally
    //   499	574	994	com/google/android/gms/internal/ads/zzcmb
    //   499	574	1058	finally
    //   577	600	994	com/google/android/gms/internal/ads/zzcmb
    //   577	600	1058	finally
    //   603	633	994	com/google/android/gms/internal/ads/zzcmb
    //   603	633	1058	finally
    //   649	662	771	finally
    //   662	671	763	finally
    //   671	714	994	com/google/android/gms/internal/ads/zzcmb
    //   671	714	1058	finally
    //   717	730	994	com/google/android/gms/internal/ads/zzcmb
    //   717	730	1058	finally
    //   730	746	994	com/google/android/gms/internal/ads/zzcmb
    //   730	746	1058	finally
    //   746	760	1075	java/io/IOException
    //   776	782	994	com/google/android/gms/internal/ads/zzcmb
    //   776	782	1058	finally
    //   798	826	994	com/google/android/gms/internal/ads/zzcmb
    //   798	826	1058	finally
    //   829	850	994	com/google/android/gms/internal/ads/zzcmb
    //   829	850	1058	finally
    //   857	871	1075	java/io/IOException
    //   874	896	994	com/google/android/gms/internal/ads/zzcmb
    //   874	896	1058	finally
    //   896	918	994	com/google/android/gms/internal/ads/zzcmb
    //   896	918	1058	finally
    //   918	994	994	com/google/android/gms/internal/ads/zzcmb
    //   918	994	1058	finally
    //   1003	1039	1058	finally
    //   1039	1053	1075	java/io/IOException
    //   1056	1058	1058	finally
    //   1059	1075	1075	java/io/IOException
  }
}


/* Location:              /home/sumith/decompile/test/classes-dex2jar.jar!/com/google/android/gms/internal/ads/ct0.class
 * Java compiler version: 6 (50.0)
 * JD-Core Version:       1.1.3
 */