package com.google.android.gms.internal.ads;

import android.os.Bundle;

public final class cx0 extends vb implements v50 {
  private sb b;
  
  private y50 c;
  
  public final void G7(String paramString) {
    // Byte code:
    //   0: aload_0
    //   1: monitorenter
    //   2: aload_0
    //   3: getfield b : Lcom/google/android/gms/internal/ads/sb;
    //   6: astore_2
    //   7: aload_2
    //   8: ifnull -> 18
    //   11: aload_2
    //   12: aload_1
    //   13: invokeinterface G7 : (Ljava/lang/String;)V
    //   18: aload_0
    //   19: monitorexit
    //   20: return
    //   21: astore_1
    //   22: aload_0
    //   23: monitorexit
    //   24: aload_1
    //   25: athrow
    // Exception table:
    //   from	to	target	type
    //   2	7	21	finally
    //   11	18	21	finally
  }
  
  public final void I0(i4 parami4, String paramString) {
    // Byte code:
    //   0: aload_0
    //   1: monitorenter
    //   2: aload_0
    //   3: getfield b : Lcom/google/android/gms/internal/ads/sb;
    //   6: astore_3
    //   7: aload_3
    //   8: ifnull -> 19
    //   11: aload_3
    //   12: aload_1
    //   13: aload_2
    //   14: invokeinterface I0 : (Lcom/google/android/gms/internal/ads/i4;Ljava/lang/String;)V
    //   19: aload_0
    //   20: monitorexit
    //   21: return
    //   22: astore_1
    //   23: aload_0
    //   24: monitorexit
    //   25: aload_1
    //   26: athrow
    // Exception table:
    //   from	to	target	type
    //   2	7	22	finally
    //   11	19	22	finally
  }
  
  public final void J0(zzvg paramzzvg) {
    // Byte code:
    //   0: aload_0
    //   1: monitorenter
    //   2: aload_0
    //   3: getfield b : Lcom/google/android/gms/internal/ads/sb;
    //   6: astore_2
    //   7: aload_2
    //   8: ifnull -> 18
    //   11: aload_2
    //   12: aload_1
    //   13: invokeinterface J0 : (Lcom/google/android/gms/internal/ads/zzvg;)V
    //   18: aload_0
    //   19: getfield c : Lcom/google/android/gms/internal/ads/y50;
    //   22: astore_2
    //   23: aload_2
    //   24: ifnull -> 34
    //   27: aload_2
    //   28: aload_1
    //   29: invokeinterface E : (Lcom/google/android/gms/internal/ads/zzvg;)V
    //   34: aload_0
    //   35: monitorexit
    //   36: return
    //   37: astore_1
    //   38: aload_0
    //   39: monitorexit
    //   40: aload_1
    //   41: athrow
    // Exception table:
    //   from	to	target	type
    //   2	7	37	finally
    //   11	18	37	finally
    //   18	23	37	finally
    //   27	34	37	finally
  }
  
  public final void L() {
    // Byte code:
    //   0: aload_0
    //   1: monitorenter
    //   2: aload_0
    //   3: getfield b : Lcom/google/android/gms/internal/ads/sb;
    //   6: astore_1
    //   7: aload_1
    //   8: ifnull -> 17
    //   11: aload_1
    //   12: invokeinterface L : ()V
    //   17: aload_0
    //   18: monitorexit
    //   19: return
    //   20: astore_1
    //   21: aload_0
    //   22: monitorexit
    //   23: aload_1
    //   24: athrow
    // Exception table:
    //   from	to	target	type
    //   2	7	20	finally
    //   11	17	20	finally
  }
  
  public final void N0() {
    // Byte code:
    //   0: aload_0
    //   1: monitorenter
    //   2: aload_0
    //   3: getfield b : Lcom/google/android/gms/internal/ads/sb;
    //   6: astore_1
    //   7: aload_1
    //   8: ifnull -> 17
    //   11: aload_1
    //   12: invokeinterface N0 : ()V
    //   17: aload_0
    //   18: monitorexit
    //   19: return
    //   20: astore_1
    //   21: aload_0
    //   22: monitorexit
    //   23: aload_1
    //   24: athrow
    // Exception table:
    //   from	to	target	type
    //   2	7	20	finally
    //   11	17	20	finally
  }
  
  public final void N3(int paramInt, String paramString) {
    // Byte code:
    //   0: aload_0
    //   1: monitorenter
    //   2: aload_0
    //   3: getfield b : Lcom/google/android/gms/internal/ads/sb;
    //   6: astore_3
    //   7: aload_3
    //   8: ifnull -> 19
    //   11: aload_3
    //   12: iload_1
    //   13: aload_2
    //   14: invokeinterface N3 : (ILjava/lang/String;)V
    //   19: aload_0
    //   20: getfield c : Lcom/google/android/gms/internal/ads/y50;
    //   23: astore_3
    //   24: aload_3
    //   25: ifnull -> 36
    //   28: aload_3
    //   29: iload_1
    //   30: aload_2
    //   31: invokeinterface a : (ILjava/lang/String;)V
    //   36: aload_0
    //   37: monitorexit
    //   38: return
    //   39: astore_2
    //   40: aload_0
    //   41: monitorexit
    //   42: aload_2
    //   43: athrow
    // Exception table:
    //   from	to	target	type
    //   2	7	39	finally
    //   11	19	39	finally
    //   19	24	39	finally
    //   28	36	39	finally
  }
  
  public final void O() {
    // Byte code:
    //   0: aload_0
    //   1: monitorenter
    //   2: aload_0
    //   3: getfield b : Lcom/google/android/gms/internal/ads/sb;
    //   6: astore_1
    //   7: aload_1
    //   8: ifnull -> 17
    //   11: aload_1
    //   12: invokeinterface O : ()V
    //   17: aload_0
    //   18: monitorexit
    //   19: return
    //   20: astore_1
    //   21: aload_0
    //   22: monitorexit
    //   23: aload_1
    //   24: athrow
    // Exception table:
    //   from	to	target	type
    //   2	7	20	finally
    //   11	17	20	finally
  }
  
  public final void S() {
    // Byte code:
    //   0: aload_0
    //   1: monitorenter
    //   2: aload_0
    //   3: getfield b : Lcom/google/android/gms/internal/ads/sb;
    //   6: astore_1
    //   7: aload_1
    //   8: ifnull -> 17
    //   11: aload_1
    //   12: invokeinterface S : ()V
    //   17: aload_0
    //   18: monitorexit
    //   19: return
    //   20: astore_1
    //   21: aload_0
    //   22: monitorexit
    //   23: aload_1
    //   24: athrow
    // Exception table:
    //   from	to	target	type
    //   2	7	20	finally
    //   11	17	20	finally
  }
  
  public final void S4(xb paramxb) {
    // Byte code:
    //   0: aload_0
    //   1: monitorenter
    //   2: aload_0
    //   3: getfield b : Lcom/google/android/gms/internal/ads/sb;
    //   6: astore_2
    //   7: aload_2
    //   8: ifnull -> 18
    //   11: aload_2
    //   12: aload_1
    //   13: invokeinterface S4 : (Lcom/google/android/gms/internal/ads/xb;)V
    //   18: aload_0
    //   19: monitorexit
    //   20: return
    //   21: astore_1
    //   22: aload_0
    //   23: monitorexit
    //   24: aload_1
    //   25: athrow
    // Exception table:
    //   from	to	target	type
    //   2	7	21	finally
    //   11	18	21	finally
  }
  
  public final void T8() {
    // Byte code:
    //   0: aload_0
    //   1: monitorenter
    //   2: aload_0
    //   3: getfield b : Lcom/google/android/gms/internal/ads/sb;
    //   6: astore_1
    //   7: aload_1
    //   8: ifnull -> 17
    //   11: aload_1
    //   12: invokeinterface T8 : ()V
    //   17: aload_0
    //   18: monitorexit
    //   19: return
    //   20: astore_1
    //   21: aload_0
    //   22: monitorexit
    //   23: aload_1
    //   24: athrow
    // Exception table:
    //   from	to	target	type
    //   2	7	20	finally
    //   11	17	20	finally
  }
  
  public final void T9(sb paramsb) {
    // Byte code:
    //   0: aload_0
    //   1: monitorenter
    //   2: aload_0
    //   3: aload_1
    //   4: putfield b : Lcom/google/android/gms/internal/ads/sb;
    //   7: aload_0
    //   8: monitorexit
    //   9: return
    //   10: astore_1
    //   11: aload_0
    //   12: monitorexit
    //   13: aload_1
    //   14: athrow
    // Exception table:
    //   from	to	target	type
    //   2	7	10	finally
  }
  
  public final void V6(int paramInt) {
    // Byte code:
    //   0: aload_0
    //   1: monitorenter
    //   2: aload_0
    //   3: getfield b : Lcom/google/android/gms/internal/ads/sb;
    //   6: astore_2
    //   7: aload_2
    //   8: ifnull -> 18
    //   11: aload_2
    //   12: iload_1
    //   13: invokeinterface V6 : (I)V
    //   18: aload_0
    //   19: monitorexit
    //   20: return
    //   21: astore_2
    //   22: aload_0
    //   23: monitorexit
    //   24: aload_2
    //   25: athrow
    // Exception table:
    //   from	to	target	type
    //   2	7	21	finally
    //   11	18	21	finally
  }
  
  public final void X5(y50 paramy50) {
    // Byte code:
    //   0: aload_0
    //   1: monitorenter
    //   2: aload_0
    //   3: aload_1
    //   4: putfield c : Lcom/google/android/gms/internal/ads/y50;
    //   7: aload_0
    //   8: monitorexit
    //   9: return
    //   10: astore_1
    //   11: aload_0
    //   12: monitorexit
    //   13: aload_1
    //   14: athrow
    // Exception table:
    //   from	to	target	type
    //   2	7	10	finally
  }
  
  public final void Y() {
    // Byte code:
    //   0: aload_0
    //   1: monitorenter
    //   2: aload_0
    //   3: getfield b : Lcom/google/android/gms/internal/ads/sb;
    //   6: astore_1
    //   7: aload_1
    //   8: ifnull -> 17
    //   11: aload_1
    //   12: invokeinterface Y : ()V
    //   17: aload_0
    //   18: monitorexit
    //   19: return
    //   20: astore_1
    //   21: aload_0
    //   22: monitorexit
    //   23: aload_1
    //   24: athrow
    // Exception table:
    //   from	to	target	type
    //   2	7	20	finally
    //   11	17	20	finally
  }
  
  public final void Z(int paramInt) {
    // Byte code:
    //   0: aload_0
    //   1: monitorenter
    //   2: aload_0
    //   3: getfield b : Lcom/google/android/gms/internal/ads/sb;
    //   6: astore_2
    //   7: aload_2
    //   8: ifnull -> 18
    //   11: aload_2
    //   12: iload_1
    //   13: invokeinterface Z : (I)V
    //   18: aload_0
    //   19: getfield c : Lcom/google/android/gms/internal/ads/y50;
    //   22: astore_2
    //   23: aload_2
    //   24: ifnull -> 34
    //   27: aload_2
    //   28: iload_1
    //   29: invokeinterface Z : (I)V
    //   34: aload_0
    //   35: monitorexit
    //   36: return
    //   37: astore_2
    //   38: aload_0
    //   39: monitorexit
    //   40: aload_2
    //   41: athrow
    // Exception table:
    //   from	to	target	type
    //   2	7	37	finally
    //   11	18	37	finally
    //   18	23	37	finally
    //   27	34	37	finally
  }
  
  public final void a1() {
    // Byte code:
    //   0: aload_0
    //   1: monitorenter
    //   2: aload_0
    //   3: getfield b : Lcom/google/android/gms/internal/ads/sb;
    //   6: astore_1
    //   7: aload_1
    //   8: ifnull -> 17
    //   11: aload_1
    //   12: invokeinterface a1 : ()V
    //   17: aload_0
    //   18: monitorexit
    //   19: return
    //   20: astore_1
    //   21: aload_0
    //   22: monitorexit
    //   23: aload_1
    //   24: athrow
    // Exception table:
    //   from	to	target	type
    //   2	7	20	finally
    //   11	17	20	finally
  }
  
  public final void h1(ki paramki) {
    // Byte code:
    //   0: aload_0
    //   1: monitorenter
    //   2: aload_0
    //   3: getfield b : Lcom/google/android/gms/internal/ads/sb;
    //   6: astore_2
    //   7: aload_2
    //   8: ifnull -> 18
    //   11: aload_2
    //   12: aload_1
    //   13: invokeinterface h1 : (Lcom/google/android/gms/internal/ads/ki;)V
    //   18: aload_0
    //   19: monitorexit
    //   20: return
    //   21: astore_1
    //   22: aload_0
    //   23: monitorexit
    //   24: aload_1
    //   25: athrow
    // Exception table:
    //   from	to	target	type
    //   2	7	21	finally
    //   11	18	21	finally
  }
  
  public final void i() {
    // Byte code:
    //   0: aload_0
    //   1: monitorenter
    //   2: aload_0
    //   3: getfield b : Lcom/google/android/gms/internal/ads/sb;
    //   6: astore_1
    //   7: aload_1
    //   8: ifnull -> 17
    //   11: aload_1
    //   12: invokeinterface i : ()V
    //   17: aload_0
    //   18: getfield c : Lcom/google/android/gms/internal/ads/y50;
    //   21: astore_1
    //   22: aload_1
    //   23: ifnull -> 32
    //   26: aload_1
    //   27: invokeinterface i : ()V
    //   32: aload_0
    //   33: monitorexit
    //   34: return
    //   35: astore_1
    //   36: aload_0
    //   37: monitorexit
    //   38: aload_1
    //   39: athrow
    // Exception table:
    //   from	to	target	type
    //   2	7	35	finally
    //   11	17	35	finally
    //   17	22	35	finally
    //   26	32	35	finally
  }
  
  public final void n(String paramString1, String paramString2) {
    // Byte code:
    //   0: aload_0
    //   1: monitorenter
    //   2: aload_0
    //   3: getfield b : Lcom/google/android/gms/internal/ads/sb;
    //   6: astore_3
    //   7: aload_3
    //   8: ifnull -> 19
    //   11: aload_3
    //   12: aload_1
    //   13: aload_2
    //   14: invokeinterface n : (Ljava/lang/String;Ljava/lang/String;)V
    //   19: aload_0
    //   20: monitorexit
    //   21: return
    //   22: astore_1
    //   23: aload_0
    //   24: monitorexit
    //   25: aload_1
    //   26: athrow
    // Exception table:
    //   from	to	target	type
    //   2	7	22	finally
    //   11	19	22	finally
  }
  
  public final void n9(zzavj paramzzavj) {
    // Byte code:
    //   0: aload_0
    //   1: monitorenter
    //   2: aload_0
    //   3: getfield b : Lcom/google/android/gms/internal/ads/sb;
    //   6: astore_2
    //   7: aload_2
    //   8: ifnull -> 18
    //   11: aload_2
    //   12: aload_1
    //   13: invokeinterface n9 : (Lcom/google/android/gms/internal/ads/zzavj;)V
    //   18: aload_0
    //   19: monitorexit
    //   20: return
    //   21: astore_1
    //   22: aload_0
    //   23: monitorexit
    //   24: aload_1
    //   25: athrow
    // Exception table:
    //   from	to	target	type
    //   2	7	21	finally
    //   11	18	21	finally
  }
  
  public final void p7(zzvg paramzzvg) {
    // Byte code:
    //   0: aload_0
    //   1: monitorenter
    //   2: aload_0
    //   3: getfield b : Lcom/google/android/gms/internal/ads/sb;
    //   6: astore_2
    //   7: aload_2
    //   8: ifnull -> 18
    //   11: aload_2
    //   12: aload_1
    //   13: invokeinterface p7 : (Lcom/google/android/gms/internal/ads/zzvg;)V
    //   18: aload_0
    //   19: monitorexit
    //   20: return
    //   21: astore_1
    //   22: aload_0
    //   23: monitorexit
    //   24: aload_1
    //   25: athrow
    // Exception table:
    //   from	to	target	type
    //   2	7	21	finally
    //   11	18	21	finally
  }
  
  public final void q0() {
    // Byte code:
    //   0: aload_0
    //   1: monitorenter
    //   2: aload_0
    //   3: getfield b : Lcom/google/android/gms/internal/ads/sb;
    //   6: astore_1
    //   7: aload_1
    //   8: ifnull -> 17
    //   11: aload_1
    //   12: invokeinterface q0 : ()V
    //   17: aload_0
    //   18: monitorexit
    //   19: return
    //   20: astore_1
    //   21: aload_0
    //   22: monitorexit
    //   23: aload_1
    //   24: athrow
    // Exception table:
    //   from	to	target	type
    //   2	7	20	finally
    //   11	17	20	finally
  }
  
  public final void q6(String paramString) {
    // Byte code:
    //   0: aload_0
    //   1: monitorenter
    //   2: aload_0
    //   3: getfield b : Lcom/google/android/gms/internal/ads/sb;
    //   6: astore_2
    //   7: aload_2
    //   8: ifnull -> 18
    //   11: aload_2
    //   12: aload_1
    //   13: invokeinterface q6 : (Ljava/lang/String;)V
    //   18: aload_0
    //   19: monitorexit
    //   20: return
    //   21: astore_1
    //   22: aload_0
    //   23: monitorexit
    //   24: aload_1
    //   25: athrow
    // Exception table:
    //   from	to	target	type
    //   2	7	21	finally
    //   11	18	21	finally
  }
  
  public final void v1() {
    // Byte code:
    //   0: aload_0
    //   1: monitorenter
    //   2: aload_0
    //   3: getfield b : Lcom/google/android/gms/internal/ads/sb;
    //   6: astore_1
    //   7: aload_1
    //   8: ifnull -> 17
    //   11: aload_1
    //   12: invokeinterface v1 : ()V
    //   17: aload_0
    //   18: monitorexit
    //   19: return
    //   20: astore_1
    //   21: aload_0
    //   22: monitorexit
    //   23: aload_1
    //   24: athrow
    // Exception table:
    //   from	to	target	type
    //   2	7	20	finally
    //   11	17	20	finally
  }
  
  public final void x() {
    // Byte code:
    //   0: aload_0
    //   1: monitorenter
    //   2: aload_0
    //   3: getfield b : Lcom/google/android/gms/internal/ads/sb;
    //   6: astore_1
    //   7: aload_1
    //   8: ifnull -> 17
    //   11: aload_1
    //   12: invokeinterface x : ()V
    //   17: aload_0
    //   18: monitorexit
    //   19: return
    //   20: astore_1
    //   21: aload_0
    //   22: monitorexit
    //   23: aload_1
    //   24: athrow
    // Exception table:
    //   from	to	target	type
    //   2	7	20	finally
    //   11	17	20	finally
  }
  
  public final void z(Bundle paramBundle) {
    // Byte code:
    //   0: aload_0
    //   1: monitorenter
    //   2: aload_0
    //   3: getfield b : Lcom/google/android/gms/internal/ads/sb;
    //   6: astore_2
    //   7: aload_2
    //   8: ifnull -> 18
    //   11: aload_2
    //   12: aload_1
    //   13: invokeinterface z : (Landroid/os/Bundle;)V
    //   18: aload_0
    //   19: monitorexit
    //   20: return
    //   21: astore_1
    //   22: aload_0
    //   23: monitorexit
    //   24: aload_1
    //   25: athrow
    // Exception table:
    //   from	to	target	type
    //   2	7	21	finally
    //   11	18	21	finally
  }
}


/* Location:              /home/sumith/decompile/test/classes-dex2jar.jar!/com/google/android/gms/internal/ads/cx0.class
 * Java compiler version: 6 (50.0)
 * JD-Core Version:       1.1.3
 */