package com.google.android.gms.internal.ads;

import android.content.Context;
import com.google.android.gms.ads.internal.a;
import com.google.android.gms.ads.internal.b;
import java.lang.ref.WeakReference;
import java.util.Map;
import java.util.concurrent.Executor;
import org.json.JSONObject;

public final class dk0 {
  private final lk0 a;
  
  private final b b;
  
  private final br c;
  
  private final Context d;
  
  private final jo0 e;
  
  private final pm1 f;
  
  private final Executor g;
  
  private final p12 h;
  
  private final zzazn i;
  
  private final f7 j;
  
  private final pu0 k;
  
  private final jn1 l;
  
  private ot1<tq> m;
  
  dk0(mk0 parammk0) {
    this.d = mk0.a(parammk0);
    this.g = mk0.b(parammk0);
    this.h = mk0.c(parammk0);
    this.i = mk0.d(parammk0);
    this.b = mk0.e(parammk0);
    this.a = new lk0(null);
    this.c = mk0.f(parammk0);
    this.j = new f7();
    this.k = mk0.g(parammk0);
    this.l = mk0.h(parammk0);
    this.e = mk0.i(parammk0);
    this.f = mk0.j(parammk0);
  }
  
  public final void a() {
    // Byte code:
    //   0: aload_0
    //   1: monitorenter
    //   2: aload_0
    //   3: getfield m : Lcom/google/android/gms/internal/ads/ot1;
    //   6: astore_1
    //   7: aload_1
    //   8: ifnonnull -> 14
    //   11: aload_0
    //   12: monitorexit
    //   13: return
    //   14: new com/google/android/gms/internal/ads/ek0
    //   17: astore_2
    //   18: aload_2
    //   19: aload_0
    //   20: invokespecial <init> : (Lcom/google/android/gms/internal/ads/dk0;)V
    //   23: aload_1
    //   24: aload_2
    //   25: aload_0
    //   26: getfield g : Ljava/util/concurrent/Executor;
    //   29: invokestatic g : (Lcom/google/android/gms/internal/ads/ot1;Lcom/google/android/gms/internal/ads/et1;Ljava/util/concurrent/Executor;)V
    //   32: aload_0
    //   33: aconst_null
    //   34: putfield m : Lcom/google/android/gms/internal/ads/ot1;
    //   37: aload_0
    //   38: monitorexit
    //   39: return
    //   40: astore_1
    //   41: aload_0
    //   42: monitorexit
    //   43: aload_1
    //   44: athrow
    // Exception table:
    //   from	to	target	type
    //   2	7	40	finally
    //   14	37	40	finally
  }
  
  public final void d(nh1 paramnh1, sh1 paramsh1) {
    // Byte code:
    //   0: aload_0
    //   1: monitorenter
    //   2: aload_0
    //   3: getfield m : Lcom/google/android/gms/internal/ads/ot1;
    //   6: astore_3
    //   7: aload_3
    //   8: ifnonnull -> 14
    //   11: aload_0
    //   12: monitorexit
    //   13: return
    //   14: new com/google/android/gms/internal/ads/ik0
    //   17: astore #4
    //   19: aload #4
    //   21: aload_0
    //   22: aload_1
    //   23: aload_2
    //   24: invokespecial <init> : (Lcom/google/android/gms/internal/ads/dk0;Lcom/google/android/gms/internal/ads/nh1;Lcom/google/android/gms/internal/ads/sh1;)V
    //   27: aload_3
    //   28: aload #4
    //   30: aload_0
    //   31: getfield g : Ljava/util/concurrent/Executor;
    //   34: invokestatic g : (Lcom/google/android/gms/internal/ads/ot1;Lcom/google/android/gms/internal/ads/et1;Ljava/util/concurrent/Executor;)V
    //   37: aload_0
    //   38: monitorexit
    //   39: return
    //   40: astore_1
    //   41: aload_0
    //   42: monitorexit
    //   43: aload_1
    //   44: athrow
    // Exception table:
    //   from	to	target	type
    //   2	7	40	finally
    //   14	37	40	finally
  }
  
  public final void e(String paramString, x6<Object> paramx6) {
    // Byte code:
    //   0: aload_0
    //   1: monitorenter
    //   2: aload_0
    //   3: getfield m : Lcom/google/android/gms/internal/ads/ot1;
    //   6: astore_3
    //   7: aload_3
    //   8: ifnonnull -> 14
    //   11: aload_0
    //   12: monitorexit
    //   13: return
    //   14: new com/google/android/gms/internal/ads/hk0
    //   17: astore #4
    //   19: aload #4
    //   21: aload_0
    //   22: aload_1
    //   23: aload_2
    //   24: invokespecial <init> : (Lcom/google/android/gms/internal/ads/dk0;Ljava/lang/String;Lcom/google/android/gms/internal/ads/x6;)V
    //   27: aload_3
    //   28: aload #4
    //   30: aload_0
    //   31: getfield g : Ljava/util/concurrent/Executor;
    //   34: invokestatic g : (Lcom/google/android/gms/internal/ads/ot1;Lcom/google/android/gms/internal/ads/et1;Ljava/util/concurrent/Executor;)V
    //   37: aload_0
    //   38: monitorexit
    //   39: return
    //   40: astore_1
    //   41: aload_0
    //   42: monitorexit
    //   43: aload_1
    //   44: athrow
    // Exception table:
    //   from	to	target	type
    //   2	7	40	finally
    //   14	37	40	finally
  }
  
  public final void f(String paramString, Map<String, ?> paramMap) {
    // Byte code:
    //   0: aload_0
    //   1: monitorenter
    //   2: aload_0
    //   3: getfield m : Lcom/google/android/gms/internal/ads/ot1;
    //   6: astore_3
    //   7: aload_3
    //   8: ifnonnull -> 14
    //   11: aload_0
    //   12: monitorexit
    //   13: return
    //   14: new com/google/android/gms/internal/ads/jk0
    //   17: astore #4
    //   19: aload #4
    //   21: aload_0
    //   22: aload_1
    //   23: aload_2
    //   24: invokespecial <init> : (Lcom/google/android/gms/internal/ads/dk0;Ljava/lang/String;Ljava/util/Map;)V
    //   27: aload_3
    //   28: aload #4
    //   30: aload_0
    //   31: getfield g : Ljava/util/concurrent/Executor;
    //   34: invokestatic g : (Lcom/google/android/gms/internal/ads/ot1;Lcom/google/android/gms/internal/ads/et1;Ljava/util/concurrent/Executor;)V
    //   37: aload_0
    //   38: monitorexit
    //   39: return
    //   40: astore_1
    //   41: aload_0
    //   42: monitorexit
    //   43: aload_1
    //   44: athrow
    // Exception table:
    //   from	to	target	type
    //   2	7	40	finally
    //   14	37	40	finally
  }
  
  public final <T> void g(WeakReference<T> paramWeakReference, String paramString, x6<T> paramx6) {
    e(paramString, new pk0(this, paramWeakReference, paramString, paramx6, null));
  }
  
  public final void h() {
    // Byte code:
    //   0: aload_0
    //   1: monitorenter
    //   2: aload_0
    //   3: getfield d : Landroid/content/Context;
    //   6: astore_1
    //   7: aload_0
    //   8: getfield i : Lcom/google/android/gms/internal/ads/zzazn;
    //   11: astore_2
    //   12: getstatic com/google/android/gms/internal/ads/m0.n2 : Lcom/google/android/gms/internal/ads/x;
    //   15: astore_3
    //   16: aload_1
    //   17: aload_2
    //   18: invokestatic e : ()Lcom/google/android/gms/internal/ads/i0;
    //   21: aload_3
    //   22: invokevirtual c : (Lcom/google/android/gms/internal/ads/x;)Ljava/lang/Object;
    //   25: checkcast java/lang/String
    //   28: aload_0
    //   29: getfield h : Lcom/google/android/gms/internal/ads/p12;
    //   32: aload_0
    //   33: getfield b : Lcom/google/android/gms/ads/internal/b;
    //   36: invokestatic b : (Landroid/content/Context;Lcom/google/android/gms/internal/ads/zzazn;Ljava/lang/String;Lcom/google/android/gms/internal/ads/p12;Lcom/google/android/gms/ads/internal/b;)Lcom/google/android/gms/internal/ads/ot1;
    //   39: astore_1
    //   40: new com/google/android/gms/internal/ads/ck0
    //   43: astore_3
    //   44: aload_3
    //   45: aload_0
    //   46: invokespecial <init> : (Lcom/google/android/gms/internal/ads/dk0;)V
    //   49: aload_1
    //   50: aload_3
    //   51: aload_0
    //   52: getfield g : Ljava/util/concurrent/Executor;
    //   55: invokestatic j : (Lcom/google/android/gms/internal/ads/ot1;Lcom/google/android/gms/internal/ads/kq1;Ljava/util/concurrent/Executor;)Lcom/google/android/gms/internal/ads/ot1;
    //   58: astore_1
    //   59: aload_0
    //   60: aload_1
    //   61: putfield m : Lcom/google/android/gms/internal/ads/ot1;
    //   64: aload_1
    //   65: ldc 'NativeJavascriptExecutor.initializeEngine'
    //   67: invokestatic a : (Lcom/google/android/gms/internal/ads/ot1;Ljava/lang/String;)V
    //   70: aload_0
    //   71: monitorexit
    //   72: return
    //   73: astore_1
    //   74: aload_0
    //   75: monitorexit
    //   76: aload_1
    //   77: athrow
    // Exception table:
    //   from	to	target	type
    //   2	70	73	finally
  }
  
  public final void i(String paramString, x6<Object> paramx6) {
    // Byte code:
    //   0: aload_0
    //   1: monitorenter
    //   2: aload_0
    //   3: getfield m : Lcom/google/android/gms/internal/ads/ot1;
    //   6: astore_3
    //   7: aload_3
    //   8: ifnonnull -> 14
    //   11: aload_0
    //   12: monitorexit
    //   13: return
    //   14: new com/google/android/gms/internal/ads/gk0
    //   17: astore #4
    //   19: aload #4
    //   21: aload_0
    //   22: aload_1
    //   23: aload_2
    //   24: invokespecial <init> : (Lcom/google/android/gms/internal/ads/dk0;Ljava/lang/String;Lcom/google/android/gms/internal/ads/x6;)V
    //   27: aload_3
    //   28: aload #4
    //   30: aload_0
    //   31: getfield g : Ljava/util/concurrent/Executor;
    //   34: invokestatic g : (Lcom/google/android/gms/internal/ads/ot1;Lcom/google/android/gms/internal/ads/et1;Ljava/util/concurrent/Executor;)V
    //   37: aload_0
    //   38: monitorexit
    //   39: return
    //   40: astore_1
    //   41: aload_0
    //   42: monitorexit
    //   43: aload_1
    //   44: athrow
    // Exception table:
    //   from	to	target	type
    //   2	7	40	finally
    //   14	37	40	finally
  }
  
  public final ot1<JSONObject> j(String paramString, JSONObject paramJSONObject) {
    // Byte code:
    //   0: aload_0
    //   1: monitorenter
    //   2: aload_0
    //   3: getfield m : Lcom/google/android/gms/internal/ads/ot1;
    //   6: astore_3
    //   7: aload_3
    //   8: ifnonnull -> 20
    //   11: aconst_null
    //   12: invokestatic h : (Ljava/lang/Object;)Lcom/google/android/gms/internal/ads/ot1;
    //   15: astore_1
    //   16: aload_0
    //   17: monitorexit
    //   18: aload_1
    //   19: areturn
    //   20: new com/google/android/gms/internal/ads/fk0
    //   23: astore #4
    //   25: aload #4
    //   27: aload_0
    //   28: aload_1
    //   29: aload_2
    //   30: invokespecial <init> : (Lcom/google/android/gms/internal/ads/dk0;Ljava/lang/String;Lorg/json/JSONObject;)V
    //   33: aload_3
    //   34: aload #4
    //   36: aload_0
    //   37: getfield g : Ljava/util/concurrent/Executor;
    //   40: invokestatic k : (Lcom/google/android/gms/internal/ads/ot1;Lcom/google/android/gms/internal/ads/qs1;Ljava/util/concurrent/Executor;)Lcom/google/android/gms/internal/ads/ot1;
    //   43: astore_1
    //   44: aload_0
    //   45: monitorexit
    //   46: aload_1
    //   47: areturn
    //   48: astore_1
    //   49: aload_0
    //   50: monitorexit
    //   51: aload_1
    //   52: athrow
    // Exception table:
    //   from	to	target	type
    //   2	7	48	finally
    //   11	16	48	finally
    //   20	44	48	finally
  }
}


/* Location:              /home/sumith/decompile/test/classes-dex2jar.jar!/com/google/android/gms/internal/ads/dk0.class
 * Java compiler version: 6 (50.0)
 * JD-Core Version:       1.1.3
 */