package com.google.android.gms.internal.ads;

import java.util.Set;

public final class e50 extends j90<f50> {
  private boolean c = false;
  
  public e50(Set<gb0<f50>> paramSet) {
    super(paramSet);
  }
  
  public final void S() {
    // Byte code:
    //   0: aload_0
    //   1: monitorenter
    //   2: aload_0
    //   3: getfield c : Z
    //   6: ifne -> 21
    //   9: aload_0
    //   10: getstatic com/google/android/gms/internal/ads/d50.a : Lcom/google/android/gms/internal/ads/l90;
    //   13: invokevirtual X0 : (Lcom/google/android/gms/internal/ads/l90;)V
    //   16: aload_0
    //   17: iconst_1
    //   18: putfield c : Z
    //   21: aload_0
    //   22: monitorexit
    //   23: return
    //   24: astore_1
    //   25: aload_0
    //   26: monitorexit
    //   27: aload_1
    //   28: athrow
    // Exception table:
    //   from	to	target	type
    //   2	21	24	finally
  }
}


/* Location:              /home/sumith/decompile/test/classes-dex2jar.jar!/com/google/android/gms/internal/ads/e50.class
 * Java compiler version: 6 (50.0)
 * JD-Core Version:       1.1.3
 */