package com.google.android.gms.internal.ads;

import android.content.Context;
import android.view.View;
import java.util.Map;
import java.util.Set;
import java.util.WeakHashMap;

public final class eb0 extends j90<yk2> implements yk2 {
  private Map<View, uk2> c = new WeakHashMap<View, uk2>(1);
  
  private final Context d;
  
  private final nh1 e;
  
  public eb0(Context paramContext, Set<gb0<yk2>> paramSet, nh1 paramnh1) {
    super(paramSet);
    this.d = paramContext;
    this.e = paramnh1;
  }
  
  public final void b1(View paramView) {
    // Byte code:
    //   0: aload_0
    //   1: monitorenter
    //   2: aload_0
    //   3: getfield c : Ljava/util/Map;
    //   6: aload_1
    //   7: invokeinterface get : (Ljava/lang/Object;)Ljava/lang/Object;
    //   12: checkcast com/google/android/gms/internal/ads/uk2
    //   15: astore_2
    //   16: aload_2
    //   17: astore_3
    //   18: aload_2
    //   19: ifnonnull -> 52
    //   22: new com/google/android/gms/internal/ads/uk2
    //   25: astore_3
    //   26: aload_3
    //   27: aload_0
    //   28: getfield d : Landroid/content/Context;
    //   31: aload_1
    //   32: invokespecial <init> : (Landroid/content/Context;Landroid/view/View;)V
    //   35: aload_3
    //   36: aload_0
    //   37: invokevirtual d : (Lcom/google/android/gms/internal/ads/yk2;)V
    //   40: aload_0
    //   41: getfield c : Ljava/util/Map;
    //   44: aload_1
    //   45: aload_3
    //   46: invokeinterface put : (Ljava/lang/Object;Ljava/lang/Object;)Ljava/lang/Object;
    //   51: pop
    //   52: aload_0
    //   53: getfield e : Lcom/google/android/gms/internal/ads/nh1;
    //   56: astore_1
    //   57: aload_1
    //   58: ifnull -> 112
    //   61: aload_1
    //   62: getfield R : Z
    //   65: ifeq -> 112
    //   68: getstatic com/google/android/gms/internal/ads/m0.k1 : Lcom/google/android/gms/internal/ads/x;
    //   71: astore_1
    //   72: invokestatic e : ()Lcom/google/android/gms/internal/ads/i0;
    //   75: aload_1
    //   76: invokevirtual c : (Lcom/google/android/gms/internal/ads/x;)Ljava/lang/Object;
    //   79: checkcast java/lang/Boolean
    //   82: invokevirtual booleanValue : ()Z
    //   85: ifeq -> 112
    //   88: getstatic com/google/android/gms/internal/ads/m0.j1 : Lcom/google/android/gms/internal/ads/x;
    //   91: astore_1
    //   92: aload_3
    //   93: invokestatic e : ()Lcom/google/android/gms/internal/ads/i0;
    //   96: aload_1
    //   97: invokevirtual c : (Lcom/google/android/gms/internal/ads/x;)Ljava/lang/Object;
    //   100: checkcast java/lang/Long
    //   103: invokevirtual longValue : ()J
    //   106: invokevirtual i : (J)V
    //   109: aload_0
    //   110: monitorexit
    //   111: return
    //   112: aload_3
    //   113: invokevirtual m : ()V
    //   116: aload_0
    //   117: monitorexit
    //   118: return
    //   119: astore_1
    //   120: aload_0
    //   121: monitorexit
    //   122: aload_1
    //   123: athrow
    // Exception table:
    //   from	to	target	type
    //   2	16	119	finally
    //   22	52	119	finally
    //   52	57	119	finally
    //   61	109	119	finally
    //   112	116	119	finally
  }
  
  public final void c1(View paramView) {
    // Byte code:
    //   0: aload_0
    //   1: monitorenter
    //   2: aload_0
    //   3: getfield c : Ljava/util/Map;
    //   6: aload_1
    //   7: invokeinterface containsKey : (Ljava/lang/Object;)Z
    //   12: ifeq -> 43
    //   15: aload_0
    //   16: getfield c : Ljava/util/Map;
    //   19: aload_1
    //   20: invokeinterface get : (Ljava/lang/Object;)Ljava/lang/Object;
    //   25: checkcast com/google/android/gms/internal/ads/uk2
    //   28: aload_0
    //   29: invokevirtual e : (Lcom/google/android/gms/internal/ads/yk2;)V
    //   32: aload_0
    //   33: getfield c : Ljava/util/Map;
    //   36: aload_1
    //   37: invokeinterface remove : (Ljava/lang/Object;)Ljava/lang/Object;
    //   42: pop
    //   43: aload_0
    //   44: monitorexit
    //   45: return
    //   46: astore_1
    //   47: aload_0
    //   48: monitorexit
    //   49: aload_1
    //   50: athrow
    // Exception table:
    //   from	to	target	type
    //   2	43	46	finally
  }
  
  public final void k0(zk2 paramzk2) {
    // Byte code:
    //   0: aload_0
    //   1: monitorenter
    //   2: new com/google/android/gms/internal/ads/ib0
    //   5: astore_2
    //   6: aload_2
    //   7: aload_1
    //   8: invokespecial <init> : (Lcom/google/android/gms/internal/ads/zk2;)V
    //   11: aload_0
    //   12: aload_2
    //   13: invokevirtual X0 : (Lcom/google/android/gms/internal/ads/l90;)V
    //   16: aload_0
    //   17: monitorexit
    //   18: return
    //   19: astore_1
    //   20: aload_0
    //   21: monitorexit
    //   22: aload_1
    //   23: athrow
    // Exception table:
    //   from	to	target	type
    //   2	16	19	finally
  }
}


/* Location:              /home/sumith/decompile/test/classes-dex2jar.jar!/com/google/android/gms/internal/ads/eb0.class
 * Java compiler version: 6 (50.0)
 * JD-Core Version:       1.1.3
 */