package com.google.android.gms.internal.ads;

import java.util.concurrent.Executor;

public final class fe1<R extends u30<AdT>, AdT extends p00> implements cf1<R, AdT> {
  private final cf1<R, AdT> a;
  
  private final cf1<R, pe1<AdT>> b;
  
  private final jk1<AdT> c;
  
  private R d;
  
  private final Executor e;
  
  public fe1(cf1<R, AdT> paramcf1, cf1<R, pe1<AdT>> paramcf11, jk1<AdT> paramjk1, Executor paramExecutor) {
    this.a = paramcf1;
    this.b = paramcf11;
    this.c = paramjk1;
    this.e = paramExecutor;
  }
  
  private final ot1<AdT> e(bk1<AdT> parambk1, df1 paramdf1, ef1<R> paramef1) {
    u30 u301;
    x30<R> x30 = paramef1.a(paramdf1.b);
    if (parambk1.c != null) {
      u301 = (u30)x30.n();
      if (u301.d() != null)
        parambk1.c.e().y(u301.d()); 
      return dt1.h(parambk1.c);
    } 
    x30.u(parambk1.b);
    ot1<AdT> ot1 = this.a.b((df1)u301, new he1(x30));
    this.d = this.a.a();
    return ot1;
  }
  
  private final R f() {
    // Byte code:
    //   0: aload_0
    //   1: monitorenter
    //   2: aload_0
    //   3: getfield d : Lcom/google/android/gms/internal/ads/u30;
    //   6: astore_1
    //   7: aload_0
    //   8: monitorexit
    //   9: aload_1
    //   10: areturn
    //   11: astore_1
    //   12: aload_0
    //   13: monitorexit
    //   14: aload_1
    //   15: athrow
    // Exception table:
    //   from	to	target	type
    //   2	7	11	finally
  }
  
  public final ot1<AdT> b(df1 paramdf1, ef1<R> paramef1) {
    // Byte code:
    //   0: aload_0
    //   1: monitorenter
    //   2: aload_2
    //   3: aload_1
    //   4: getfield b : Lcom/google/android/gms/internal/ads/bf1;
    //   7: invokeinterface a : (Lcom/google/android/gms/internal/ads/bf1;)Lcom/google/android/gms/internal/ads/x30;
    //   12: invokeinterface n : ()Ljava/lang/Object;
    //   17: checkcast com/google/android/gms/internal/ads/u30
    //   20: invokeinterface c : ()Lcom/google/android/gms/internal/ads/gi1;
    //   25: astore_3
    //   26: aload_3
    //   27: getfield d : Lcom/google/android/gms/internal/ads/zzvl;
    //   30: astore #4
    //   32: aload_3
    //   33: getfield f : Ljava/lang/String;
    //   36: astore #5
    //   38: aload_3
    //   39: getfield j : Lcom/google/android/gms/internal/ads/zzvx;
    //   42: astore #6
    //   44: new com/google/android/gms/internal/ads/ie1
    //   47: astore_3
    //   48: aload_3
    //   49: aload_2
    //   50: aload_1
    //   51: aload #4
    //   53: aload #5
    //   55: aload_0
    //   56: getfield e : Ljava/util/concurrent/Executor;
    //   59: aload #6
    //   61: aconst_null
    //   62: invokespecial <init> : (Lcom/google/android/gms/internal/ads/ef1;Lcom/google/android/gms/internal/ads/df1;Lcom/google/android/gms/internal/ads/zzvl;Ljava/lang/String;Ljava/util/concurrent/Executor;Lcom/google/android/gms/internal/ads/zzvx;Lcom/google/android/gms/internal/ads/ak1;)V
    //   65: aload_0
    //   66: getfield b : Lcom/google/android/gms/internal/ads/cf1;
    //   69: aload_1
    //   70: aload_2
    //   71: invokeinterface b : (Lcom/google/android/gms/internal/ads/df1;Lcom/google/android/gms/internal/ads/ef1;)Lcom/google/android/gms/internal/ads/ot1;
    //   76: invokestatic H : (Lcom/google/android/gms/internal/ads/ot1;)Lcom/google/android/gms/internal/ads/ys1;
    //   79: astore #5
    //   81: new com/google/android/gms/internal/ads/ee1
    //   84: astore #4
    //   86: aload #4
    //   88: aload_0
    //   89: aload_1
    //   90: aload_3
    //   91: aload_2
    //   92: invokespecial <init> : (Lcom/google/android/gms/internal/ads/fe1;Lcom/google/android/gms/internal/ads/df1;Lcom/google/android/gms/internal/ads/ie1;Lcom/google/android/gms/internal/ads/ef1;)V
    //   95: aload #5
    //   97: aload #4
    //   99: aload_0
    //   100: getfield e : Ljava/util/concurrent/Executor;
    //   103: invokevirtual G : (Lcom/google/android/gms/internal/ads/qs1;Ljava/util/concurrent/Executor;)Lcom/google/android/gms/internal/ads/ys1;
    //   106: astore_1
    //   107: aload_0
    //   108: monitorexit
    //   109: aload_1
    //   110: areturn
    //   111: astore_1
    //   112: aload_0
    //   113: monitorexit
    //   114: aload_1
    //   115: athrow
    // Exception table:
    //   from	to	target	type
    //   2	107	111	finally
  }
}


/* Location:              /home/sumith/decompile/test/classes-dex2jar.jar!/com/google/android/gms/internal/ads/fe1.class
 * Java compiler version: 6 (50.0)
 * JD-Core Version:       1.1.3
 */