package com.google.android.gms.internal.ads;

public final class fn0 implements r40, f50, d60, d70, g90, bq2 {
  private final xn2 b;
  
  private boolean c = false;
  
  public fn0(xn2 paramxn2, kf1 paramkf1) {
    this.b = paramxn2;
    paramxn2.a(zztw$zza$zza.c);
    if (paramkf1 != null)
      paramxn2.a(zztw$zza$zza.J); 
  }
  
  public final void C(boolean paramBoolean) {
    zztw$zza$zza zztw$zza$zza;
    xn2 xn21 = this.b;
    if (paramBoolean) {
      zztw$zza$zza = zztw$zza$zza.P;
    } else {
      zztw$zza$zza = zztw$zza$zza.Q;
    } 
    xn21.a(zztw$zza$zza);
  }
  
  public final void D0(zzug$zzb paramzzug$zzb) {
    this.b.b(new gn0(paramzzug$zzb));
    this.b.a(zztw$zza$zza.K);
  }
  
  public final void E(zzvg paramzzvg) {
    switch (paramzzvg.b) {
      default:
        this.b.a(zztw$zza$zza.t);
        return;
      case 7:
        this.b.a(zztw$zza$zza.A);
        return;
      case 6:
        this.b.a(zztw$zza$zza.z);
        return;
      case 5:
        this.b.a(zztw$zza$zza.y);
        return;
      case 4:
        this.b.a(zztw$zza$zza.x);
        return;
      case 3:
        this.b.a(zztw$zza$zza.u);
        return;
      case 2:
        this.b.a(zztw$zza$zza.w);
        return;
      case 1:
        break;
    } 
    this.b.a(zztw$zza$zza.v);
  }
  
  public final void J(zzatq paramzzatq) {}
  
  public final void L(zzug$zzb paramzzug$zzb) {
    this.b.b(new hn0(paramzzug$zzb));
    this.b.a(zztw$zza$zza.L);
  }
  
  public final void S() {
    // Byte code:
    //   0: aload_0
    //   1: monitorenter
    //   2: aload_0
    //   3: getfield b : Lcom/google/android/gms/internal/ads/xn2;
    //   6: getstatic com/google/android/gms/internal/ads/zztw$zza$zza.e : Lcom/google/android/gms/internal/ads/zztw$zza$zza;
    //   9: invokevirtual a : (Lcom/google/android/gms/internal/ads/zztw$zza$zza;)V
    //   12: aload_0
    //   13: monitorexit
    //   14: return
    //   15: astore_1
    //   16: aload_0
    //   17: monitorexit
    //   18: aload_1
    //   19: athrow
    // Exception table:
    //   from	to	target	type
    //   2	12	15	finally
  }
  
  public final void W0() {
    this.b.a(zztw$zza$zza.R);
  }
  
  public final void i() {
    this.b.a(zztw$zza$zza.d);
  }
  
  public final void i0(ci1 paramci1) {
    this.b.b(new en0(paramci1));
  }
  
  public final void q0(zzug$zzb paramzzug$zzb) {
    this.b.b(new jn0(paramzzug$zzb));
    this.b.a(zztw$zza$zza.M);
  }
  
  public final void r(boolean paramBoolean) {
    zztw$zza$zza zztw$zza$zza;
    xn2 xn21 = this.b;
    if (paramBoolean) {
      zztw$zza$zza = zztw$zza$zza.N;
    } else {
      zztw$zza$zza = zztw$zza$zza.O;
    } 
    xn21.a(zztw$zza$zza);
  }
  
  public final void x() {
    // Byte code:
    //   0: aload_0
    //   1: monitorenter
    //   2: aload_0
    //   3: getfield c : Z
    //   6: ifne -> 27
    //   9: aload_0
    //   10: getfield b : Lcom/google/android/gms/internal/ads/xn2;
    //   13: getstatic com/google/android/gms/internal/ads/zztw$zza$zza.f : Lcom/google/android/gms/internal/ads/zztw$zza$zza;
    //   16: invokevirtual a : (Lcom/google/android/gms/internal/ads/zztw$zza$zza;)V
    //   19: aload_0
    //   20: iconst_1
    //   21: putfield c : Z
    //   24: aload_0
    //   25: monitorexit
    //   26: return
    //   27: aload_0
    //   28: getfield b : Lcom/google/android/gms/internal/ads/xn2;
    //   31: getstatic com/google/android/gms/internal/ads/zztw$zza$zza.g : Lcom/google/android/gms/internal/ads/zztw$zza$zza;
    //   34: invokevirtual a : (Lcom/google/android/gms/internal/ads/zztw$zza$zza;)V
    //   37: aload_0
    //   38: monitorexit
    //   39: return
    //   40: astore_1
    //   41: aload_0
    //   42: monitorexit
    //   43: aload_1
    //   44: athrow
    // Exception table:
    //   from	to	target	type
    //   2	24	40	finally
    //   27	37	40	finally
  }
}


/* Location:              /home/sumith/decompile/test/classes-dex2jar.jar!/com/google/android/gms/internal/ads/fn0.class
 * Java compiler version: 6 (50.0)
 * JD-Core Version:       1.1.3
 */