package com.google.android.gms.internal.ads;

import android.os.Bundle;
import com.google.android.gms.dynamic.a;

public final class fx0 extends ei implements v50 {
  private fi b;
  
  private y50 c;
  
  private tb0 d;
  
  public final void I3(a parama) {
    // Byte code:
    //   0: aload_0
    //   1: monitorenter
    //   2: aload_0
    //   3: getfield b : Lcom/google/android/gms/internal/ads/fi;
    //   6: astore_2
    //   7: aload_2
    //   8: ifnull -> 18
    //   11: aload_2
    //   12: aload_1
    //   13: invokeinterface I3 : (Lcom/google/android/gms/dynamic/a;)V
    //   18: aload_0
    //   19: monitorexit
    //   20: return
    //   21: astore_1
    //   22: aload_0
    //   23: monitorexit
    //   24: aload_1
    //   25: athrow
    // Exception table:
    //   from	to	target	type
    //   2	7	21	finally
    //   11	18	21	finally
  }
  
  public final void O1(a parama) {
    // Byte code:
    //   0: aload_0
    //   1: monitorenter
    //   2: aload_0
    //   3: getfield b : Lcom/google/android/gms/internal/ads/fi;
    //   6: astore_2
    //   7: aload_2
    //   8: ifnull -> 18
    //   11: aload_2
    //   12: aload_1
    //   13: invokeinterface O1 : (Lcom/google/android/gms/dynamic/a;)V
    //   18: aload_0
    //   19: getfield c : Lcom/google/android/gms/internal/ads/y50;
    //   22: astore_1
    //   23: aload_1
    //   24: ifnull -> 33
    //   27: aload_1
    //   28: invokeinterface i : ()V
    //   33: aload_0
    //   34: monitorexit
    //   35: return
    //   36: astore_1
    //   37: aload_0
    //   38: monitorexit
    //   39: aload_1
    //   40: athrow
    // Exception table:
    //   from	to	target	type
    //   2	7	36	finally
    //   11	18	36	finally
    //   18	23	36	finally
    //   27	33	36	finally
  }
  
  public final void T9(fi paramfi) {
    // Byte code:
    //   0: aload_0
    //   1: monitorenter
    //   2: aload_0
    //   3: aload_1
    //   4: putfield b : Lcom/google/android/gms/internal/ads/fi;
    //   7: aload_0
    //   8: monitorexit
    //   9: return
    //   10: astore_1
    //   11: aload_0
    //   12: monitorexit
    //   13: aload_1
    //   14: athrow
    // Exception table:
    //   from	to	target	type
    //   2	7	10	finally
  }
  
  public final void U9(tb0 paramtb0) {
    // Byte code:
    //   0: aload_0
    //   1: monitorenter
    //   2: aload_0
    //   3: aload_1
    //   4: putfield d : Lcom/google/android/gms/internal/ads/tb0;
    //   7: aload_0
    //   8: monitorexit
    //   9: return
    //   10: astore_1
    //   11: aload_0
    //   12: monitorexit
    //   13: aload_1
    //   14: athrow
    // Exception table:
    //   from	to	target	type
    //   2	7	10	finally
  }
  
  public final void V5(a parama) {
    // Byte code:
    //   0: aload_0
    //   1: monitorenter
    //   2: aload_0
    //   3: getfield b : Lcom/google/android/gms/internal/ads/fi;
    //   6: astore_2
    //   7: aload_2
    //   8: ifnull -> 18
    //   11: aload_2
    //   12: aload_1
    //   13: invokeinterface V5 : (Lcom/google/android/gms/dynamic/a;)V
    //   18: aload_0
    //   19: monitorexit
    //   20: return
    //   21: astore_1
    //   22: aload_0
    //   23: monitorexit
    //   24: aload_1
    //   25: athrow
    // Exception table:
    //   from	to	target	type
    //   2	7	21	finally
    //   11	18	21	finally
  }
  
  public final void X2(a parama) {
    // Byte code:
    //   0: aload_0
    //   1: monitorenter
    //   2: aload_0
    //   3: getfield b : Lcom/google/android/gms/internal/ads/fi;
    //   6: astore_2
    //   7: aload_2
    //   8: ifnull -> 18
    //   11: aload_2
    //   12: aload_1
    //   13: invokeinterface X2 : (Lcom/google/android/gms/dynamic/a;)V
    //   18: aload_0
    //   19: monitorexit
    //   20: return
    //   21: astore_1
    //   22: aload_0
    //   23: monitorexit
    //   24: aload_1
    //   25: athrow
    // Exception table:
    //   from	to	target	type
    //   2	7	21	finally
    //   11	18	21	finally
  }
  
  public final void X3(a parama, zzavj paramzzavj) {
    // Byte code:
    //   0: aload_0
    //   1: monitorenter
    //   2: aload_0
    //   3: getfield b : Lcom/google/android/gms/internal/ads/fi;
    //   6: astore_3
    //   7: aload_3
    //   8: ifnull -> 19
    //   11: aload_3
    //   12: aload_1
    //   13: aload_2
    //   14: invokeinterface X3 : (Lcom/google/android/gms/dynamic/a;Lcom/google/android/gms/internal/ads/zzavj;)V
    //   19: aload_0
    //   20: monitorexit
    //   21: return
    //   22: astore_1
    //   23: aload_0
    //   24: monitorexit
    //   25: aload_1
    //   26: athrow
    // Exception table:
    //   from	to	target	type
    //   2	7	22	finally
    //   11	19	22	finally
  }
  
  public final void X5(y50 paramy50) {
    // Byte code:
    //   0: aload_0
    //   1: monitorenter
    //   2: aload_0
    //   3: aload_1
    //   4: putfield c : Lcom/google/android/gms/internal/ads/y50;
    //   7: aload_0
    //   8: monitorexit
    //   9: return
    //   10: astore_1
    //   11: aload_0
    //   12: monitorexit
    //   13: aload_1
    //   14: athrow
    // Exception table:
    //   from	to	target	type
    //   2	7	10	finally
  }
  
  public final void a5(a parama) {
    // Byte code:
    //   0: aload_0
    //   1: monitorenter
    //   2: aload_0
    //   3: getfield b : Lcom/google/android/gms/internal/ads/fi;
    //   6: astore_2
    //   7: aload_2
    //   8: ifnull -> 18
    //   11: aload_2
    //   12: aload_1
    //   13: invokeinterface a5 : (Lcom/google/android/gms/dynamic/a;)V
    //   18: aload_0
    //   19: getfield d : Lcom/google/android/gms/internal/ads/tb0;
    //   22: astore_1
    //   23: aload_1
    //   24: ifnull -> 33
    //   27: aload_1
    //   28: invokeinterface W0 : ()V
    //   33: aload_0
    //   34: monitorexit
    //   35: return
    //   36: astore_1
    //   37: aload_0
    //   38: monitorexit
    //   39: aload_1
    //   40: athrow
    // Exception table:
    //   from	to	target	type
    //   2	7	36	finally
    //   11	18	36	finally
    //   18	23	36	finally
    //   27	33	36	finally
  }
  
  public final void k9(a parama) {
    // Byte code:
    //   0: aload_0
    //   1: monitorenter
    //   2: aload_0
    //   3: getfield b : Lcom/google/android/gms/internal/ads/fi;
    //   6: astore_2
    //   7: aload_2
    //   8: ifnull -> 18
    //   11: aload_2
    //   12: aload_1
    //   13: invokeinterface k9 : (Lcom/google/android/gms/dynamic/a;)V
    //   18: aload_0
    //   19: monitorexit
    //   20: return
    //   21: astore_1
    //   22: aload_0
    //   23: monitorexit
    //   24: aload_1
    //   25: athrow
    // Exception table:
    //   from	to	target	type
    //   2	7	21	finally
    //   11	18	21	finally
  }
  
  public final void u2(a parama, int paramInt) {
    // Byte code:
    //   0: aload_0
    //   1: monitorenter
    //   2: aload_0
    //   3: getfield b : Lcom/google/android/gms/internal/ads/fi;
    //   6: astore_3
    //   7: aload_3
    //   8: ifnull -> 19
    //   11: aload_3
    //   12: aload_1
    //   13: iload_2
    //   14: invokeinterface u2 : (Lcom/google/android/gms/dynamic/a;I)V
    //   19: aload_0
    //   20: getfield d : Lcom/google/android/gms/internal/ads/tb0;
    //   23: astore_1
    //   24: aload_1
    //   25: ifnull -> 35
    //   28: aload_1
    //   29: iload_2
    //   30: invokeinterface a : (I)V
    //   35: aload_0
    //   36: monitorexit
    //   37: return
    //   38: astore_1
    //   39: aload_0
    //   40: monitorexit
    //   41: aload_1
    //   42: athrow
    // Exception table:
    //   from	to	target	type
    //   2	7	38	finally
    //   11	19	38	finally
    //   19	24	38	finally
    //   28	35	38	finally
  }
  
  public final void u7(a parama) {
    // Byte code:
    //   0: aload_0
    //   1: monitorenter
    //   2: aload_0
    //   3: getfield b : Lcom/google/android/gms/internal/ads/fi;
    //   6: astore_2
    //   7: aload_2
    //   8: ifnull -> 18
    //   11: aload_2
    //   12: aload_1
    //   13: invokeinterface u7 : (Lcom/google/android/gms/dynamic/a;)V
    //   18: aload_0
    //   19: monitorexit
    //   20: return
    //   21: astore_1
    //   22: aload_0
    //   23: monitorexit
    //   24: aload_1
    //   25: athrow
    // Exception table:
    //   from	to	target	type
    //   2	7	21	finally
    //   11	18	21	finally
  }
  
  public final void w3(a parama, int paramInt) {
    // Byte code:
    //   0: aload_0
    //   1: monitorenter
    //   2: aload_0
    //   3: getfield b : Lcom/google/android/gms/internal/ads/fi;
    //   6: astore_3
    //   7: aload_3
    //   8: ifnull -> 19
    //   11: aload_3
    //   12: aload_1
    //   13: iload_2
    //   14: invokeinterface w3 : (Lcom/google/android/gms/dynamic/a;I)V
    //   19: aload_0
    //   20: getfield c : Lcom/google/android/gms/internal/ads/y50;
    //   23: astore_1
    //   24: aload_1
    //   25: ifnull -> 35
    //   28: aload_1
    //   29: iload_2
    //   30: invokeinterface Z : (I)V
    //   35: aload_0
    //   36: monitorexit
    //   37: return
    //   38: astore_1
    //   39: aload_0
    //   40: monitorexit
    //   41: aload_1
    //   42: athrow
    // Exception table:
    //   from	to	target	type
    //   2	7	38	finally
    //   11	19	38	finally
    //   19	24	38	finally
    //   28	35	38	finally
  }
  
  public final void y8(a parama) {
    // Byte code:
    //   0: aload_0
    //   1: monitorenter
    //   2: aload_0
    //   3: getfield b : Lcom/google/android/gms/internal/ads/fi;
    //   6: astore_2
    //   7: aload_2
    //   8: ifnull -> 18
    //   11: aload_2
    //   12: aload_1
    //   13: invokeinterface y8 : (Lcom/google/android/gms/dynamic/a;)V
    //   18: aload_0
    //   19: monitorexit
    //   20: return
    //   21: astore_1
    //   22: aload_0
    //   23: monitorexit
    //   24: aload_1
    //   25: athrow
    // Exception table:
    //   from	to	target	type
    //   2	7	21	finally
    //   11	18	21	finally
  }
  
  public final void z(Bundle paramBundle) {
    // Byte code:
    //   0: aload_0
    //   1: monitorenter
    //   2: aload_0
    //   3: getfield b : Lcom/google/android/gms/internal/ads/fi;
    //   6: astore_2
    //   7: aload_2
    //   8: ifnull -> 18
    //   11: aload_2
    //   12: aload_1
    //   13: invokeinterface z : (Landroid/os/Bundle;)V
    //   18: aload_0
    //   19: monitorexit
    //   20: return
    //   21: astore_1
    //   22: aload_0
    //   23: monitorexit
    //   24: aload_1
    //   25: athrow
    // Exception table:
    //   from	to	target	type
    //   2	7	21	finally
    //   11	18	21	finally
  }
}


/* Location:              /home/sumith/decompile/test/classes-dex2jar.jar!/com/google/android/gms/internal/ads/fx0.class
 * Java compiler version: 6 (50.0)
 * JD-Core Version:       1.1.3
 */