package com.google.android.gms.internal.ads;

public final class gb2 extends kb2 {
  public gb2(z92 paramz92, String paramString1, String paramString2, zzcf$zza.a parama, int paramInt1, int paramInt2) {
    super(paramz92, paramString1, paramString2, parama, paramInt1, 48);
  }
  
  protected final void a() {
    // Byte code:
    //   0: aload_0
    //   1: getfield e : Lcom/google/android/gms/internal/ads/zzcf$zza$a;
    //   4: getstatic com/google/android/gms/internal/ads/zzcq.d : Lcom/google/android/gms/internal/ads/zzcq;
    //   7: invokevirtual t0 : (Lcom/google/android/gms/internal/ads/zzcq;)Lcom/google/android/gms/internal/ads/zzcf$zza$a;
    //   10: pop
    //   11: aload_0
    //   12: getfield f : Ljava/lang/reflect/Method;
    //   15: aconst_null
    //   16: iconst_1
    //   17: anewarray java/lang/Object
    //   20: dup
    //   21: iconst_0
    //   22: aload_0
    //   23: getfield b : Lcom/google/android/gms/internal/ads/z92;
    //   26: invokevirtual a : ()Landroid/content/Context;
    //   29: aastore
    //   30: invokevirtual invoke : (Ljava/lang/Object;[Ljava/lang/Object;)Ljava/lang/Object;
    //   33: checkcast java/lang/Boolean
    //   36: invokevirtual booleanValue : ()Z
    //   39: istore_1
    //   40: aload_0
    //   41: getfield e : Lcom/google/android/gms/internal/ads/zzcf$zza$a;
    //   44: astore_2
    //   45: aload_2
    //   46: monitorenter
    //   47: iload_1
    //   48: ifeq -> 65
    //   51: aload_0
    //   52: getfield e : Lcom/google/android/gms/internal/ads/zzcf$zza$a;
    //   55: getstatic com/google/android/gms/internal/ads/zzcq.c : Lcom/google/android/gms/internal/ads/zzcq;
    //   58: invokevirtual t0 : (Lcom/google/android/gms/internal/ads/zzcq;)Lcom/google/android/gms/internal/ads/zzcf$zza$a;
    //   61: pop
    //   62: goto -> 76
    //   65: aload_0
    //   66: getfield e : Lcom/google/android/gms/internal/ads/zzcf$zza$a;
    //   69: getstatic com/google/android/gms/internal/ads/zzcq.b : Lcom/google/android/gms/internal/ads/zzcq;
    //   72: invokevirtual t0 : (Lcom/google/android/gms/internal/ads/zzcq;)Lcom/google/android/gms/internal/ads/zzcf$zza$a;
    //   75: pop
    //   76: aload_2
    //   77: monitorexit
    //   78: return
    //   79: astore_3
    //   80: aload_2
    //   81: monitorexit
    //   82: aload_3
    //   83: athrow
    // Exception table:
    //   from	to	target	type
    //   51	62	79	finally
    //   65	76	79	finally
    //   76	78	79	finally
    //   80	82	79	finally
  }
}


/* Location:              /home/sumith/decompile/test/classes-dex2jar.jar!/com/google/android/gms/internal/ads/gb2.class
 * Java compiler version: 6 (50.0)
 * JD-Core Version:       1.1.3
 */