package com.google.android.gms.internal.ads;

import android.os.Handler;
import android.os.HandlerThread;
import android.os.Message;
import android.os.SystemClock;
import android.util.Log;
import android.util.Pair;

final class gc2 implements Handler.Callback, jh2, lh2, qi2 {
  private long A;
  
  private int B;
  
  private lc2 C;
  
  private long D;
  
  private jc2 E;
  
  private jc2 F;
  
  private jc2 G;
  
  private vc2 H;
  
  private final pc2[] b;
  
  private final tc2[] c;
  
  private final ni2 d;
  
  private final oc2 e;
  
  private final vj2 f;
  
  private final Handler g;
  
  private final HandlerThread h;
  
  private final Handler i;
  
  private final bc2 j;
  
  private final wc2 k;
  
  private final xc2 l;
  
  private ic2 m;
  
  private qc2 n;
  
  private pc2 o;
  
  private nj2 p;
  
  private mh2 q;
  
  private pc2[] r;
  
  private boolean s;
  
  private boolean t;
  
  private boolean u;
  
  private boolean v;
  
  private int w;
  
  private int x;
  
  private int y;
  
  private int z;
  
  public gc2(pc2[] paramArrayOfpc2, ni2 paramni2, oc2 paramoc2, boolean paramBoolean, int paramInt, Handler paramHandler, ic2 paramic2, bc2 parambc2) {
    this.b = paramArrayOfpc2;
    this.d = paramni2;
    this.e = paramoc2;
    this.t = paramBoolean;
    this.x = 0;
    this.i = paramHandler;
    this.w = 1;
    this.m = paramic2;
    this.j = parambc2;
    this.c = new tc2[paramArrayOfpc2.length];
    for (paramInt = 0; paramInt < paramArrayOfpc2.length; paramInt++) {
      paramArrayOfpc2[paramInt].q(paramInt);
      this.c[paramInt] = paramArrayOfpc2[paramInt].g();
    } 
    this.f = new vj2();
    this.r = new pc2[0];
    this.k = new wc2();
    this.l = new xc2();
    paramni2.c(this);
    this.n = qc2.a;
    HandlerThread handlerThread = new HandlerThread("ExoPlayerImplInternal:Handler", -16);
    this.h = handlerThread;
    handlerThread.start();
    this.g = new Handler(handlerThread.getLooper(), this);
  }
  
  private final void A() {
    byte b = 0;
    this.u = false;
    this.f.a();
    pc2[] arrayOfPc2 = this.r;
    int i = arrayOfPc2.length;
    while (b < i) {
      arrayOfPc2[b].start();
      b++;
    } 
  }
  
  private final void B() {
    this.f.b();
    pc2[] arrayOfPc2 = this.r;
    int i = arrayOfPc2.length;
    for (byte b = 0; b < i; b++)
      m(arrayOfPc2[b]); 
  }
  
  private final void C() {
    jc2 jc21 = this.G;
    if (jc21 == null)
      return; 
    long l1 = jc21.a.n();
    if (l1 != -9223372036854775807L) {
      y(l1);
    } else {
      pc2 pc21 = this.o;
      if (pc21 != null && !pc21.b()) {
        l1 = this.p.s();
        this.D = l1;
        this.f.d(l1);
      } else {
        this.D = this.f.s();
      } 
      jc2 jc22 = this.G;
      l1 = this.D - jc22.e();
    } 
    this.m.c = l1;
    this.A = SystemClock.elapsedRealtime() * 1000L;
    if (this.r.length == 0) {
      l1 = Long.MIN_VALUE;
    } else {
      l1 = this.G.a.h();
    } 
    ic2 ic21 = this.m;
    long l2 = l1;
    if (l1 == Long.MIN_VALUE)
      l2 = (this.H.e(this.G.g, this.l, false)).d; 
    ic21.d = l2;
  }
  
  private final void D() {
    I(true);
    this.e.b();
    f(1);
  }
  
  private final void E() {
    jc2 jc21 = this.E;
    if (jc21 != null && !jc21.j) {
      jc2 jc22 = this.F;
      if (jc22 == null || jc22.l == jc21) {
        pc2[] arrayOfPc2 = this.r;
        int i = arrayOfPc2.length;
        for (byte b = 0; b < i; b++) {
          if (!arrayOfPc2[b].c())
            return; 
        } 
        this.E.a.q();
      } 
    } 
  }
  
  private final void F() {
    long l1;
    jc2 jc21 = this.E;
    if (!jc21.j) {
      l1 = 0L;
    } else {
      l1 = jc21.a.b();
    } 
    if (l1 == Long.MIN_VALUE) {
      H(false);
      return;
    } 
    jc21 = this.E;
    long l2 = this.D - jc21.e();
    boolean bool = this.e.c(l1 - l2);
    H(bool);
    if (bool)
      this.E.a.a(l2); 
  }
  
  private final void H(boolean paramBoolean) {
    if (this.v != paramBoolean) {
      this.v = paramBoolean;
      this.i.obtainMessage(2, paramBoolean, 0).sendToTarget();
    } 
  }
  
  private final void I(boolean paramBoolean) {
    this.g.removeMessages(2);
    this.u = false;
    this.f.b();
    this.p = null;
    this.o = null;
    this.D = 60000000L;
    for (pc2 pc21 : this.r) {
      try {
        m(pc21);
        pc21.p();
      } catch (zzhe zzhe) {
        Log.e("ExoPlayerImplInternal", "Stop failed.", zzhe);
      } catch (RuntimeException runtimeException) {}
    } 
    this.r = new pc2[0];
    jc2 jc21 = this.G;
    if (jc21 == null)
      jc21 = this.E; 
    l(jc21);
    this.E = null;
    this.F = null;
    this.G = null;
    H(false);
    if (paramBoolean) {
      mh2 mh21 = this.q;
      if (mh21 != null) {
        mh21.f();
        this.q = null;
      } 
      this.H = null;
    } 
  }
  
  private final boolean J(int paramInt) {
    this.H.e(paramInt, this.l, false);
    this.H.c(0, this.k, false);
    return (this.H.b(paramInt, this.l, this.k, this.x) == -1);
  }
  
  private final void f(int paramInt) {
    if (this.w != paramInt) {
      this.w = paramInt;
      this.i.obtainMessage(1, paramInt, 0).sendToTarget();
    } 
  }
  
  private final int h(int paramInt, vc2 paramvc21, vc2 paramvc22) {
    int i = paramvc21.h();
    byte b = 0;
    byte b1 = -1;
    int j = paramInt;
    paramInt = b1;
    while (b < i && paramInt == -1) {
      j = paramvc21.b(j, this.l, this.k, this.x);
      paramInt = paramvc22.f((paramvc21.e(j, this.l, true)).b);
      b++;
    } 
    return paramInt;
  }
  
  private final Pair<Integer, Long> i(lc2 paramlc2) {
    vc2 vc21;
    vc2 vc22 = paramlc2.a;
    vc2 vc23 = vc22;
    if (vc22.a())
      vc23 = this.H; 
    try {
      Pair<Integer, Long> pair = t(vc23, paramlc2.b, paramlc2.c);
      vc21 = this.H;
      if (vc21 == vc23)
        return pair; 
      int i = vc21.f((vc23.e(((Integer)pair.first).intValue(), this.l, true)).b);
      if (i != -1)
        return Pair.create(Integer.valueOf(i), pair.second); 
      i = h(((Integer)pair.first).intValue(), vc23, this.H);
      if (i != -1) {
        this.H.e(i, this.l, false);
        return x(0, -9223372036854775807L);
      } 
      return null;
    } catch (IndexOutOfBoundsException indexOutOfBoundsException) {
      throw new zzhu(this.H, vc21.b, vc21.c);
    } 
  }
  
  private final Pair<Integer, Long> j(vc2 paramvc2, int paramInt, long paramLong1, long paramLong2) {
    jj2.g(paramInt, 0, paramvc2.g());
    paramvc2.d(paramInt, this.k, false, paramLong2);
    paramLong2 = paramLong1;
    if (paramLong1 == -9223372036854775807L)
      paramLong2 = 0L; 
    paramLong1 = paramLong2 + 0L;
    paramLong2 = (paramvc2.e(0, this.l, false)).d;
    if (paramLong2 != -9223372036854775807L);
    return Pair.create(Integer.valueOf(0), Long.valueOf(paramLong1));
  }
  
  private final void k(long paramLong1, long paramLong2) {
    this.g.removeMessages(2);
    paramLong1 = paramLong1 + paramLong2 - SystemClock.elapsedRealtime();
    if (paramLong1 <= 0L) {
      this.g.sendEmptyMessage(2);
      return;
    } 
    this.g.sendEmptyMessageDelayed(2, paramLong1);
  }
  
  private static void l(jc2 paramjc2) {
    while (paramjc2 != null) {
      paramjc2.a();
      paramjc2 = paramjc2.l;
    } 
  }
  
  private static void m(pc2 parampc2) {
    if (parampc2.getState() == 2)
      parampc2.stop(); 
  }
  
  private final void p(Object paramObject, int paramInt) {
    this.m = new ic2(0, 0L);
    v(paramObject, paramInt);
    this.m = new ic2(0, -9223372036854775807L);
    f(4);
    I(false);
  }
  
  private final void r(boolean[] paramArrayOfboolean, int paramInt) {
    this.r = new pc2[paramInt];
    byte b = 0;
    paramInt = 0;
    while (true) {
      pc2[] arrayOfPc2 = this.b;
      if (b < arrayOfPc2.length) {
        pc2 pc21 = arrayOfPc2[b];
        mi2 mi2 = this.G.m.b.a(b);
        int i = paramInt;
        if (mi2 != null) {
          this.r[paramInt] = pc21;
          if (pc21.getState() == 0) {
            boolean bool;
            sc2 sc2 = this.G.m.d[b];
            if (this.t && this.w == 3) {
              i = 1;
            } else {
              i = 0;
            } 
            if (!paramArrayOfboolean[b] && i != 0) {
              bool = true;
            } else {
              bool = false;
            } 
            int j = mi2.length();
            zzht[] arrayOfZzht = new zzht[j];
            for (byte b1 = 0; b1 < j; b1++)
              arrayOfZzht[b1] = mi2.c(b1); 
            jc2 jc21 = this.G;
            pc21.t(sc2, arrayOfZzht, jc21.d[b], this.D, bool, jc21.e());
            nj2 nj21 = pc21.i();
            if (nj21 != null)
              if (this.p == null) {
                this.p = nj21;
                this.o = pc21;
                nj21.k(this.n);
              } else {
                throw zzhe.zza(new IllegalStateException("Multiple renderer media clocks enabled."));
              }  
            if (i != 0)
              pc21.start(); 
          } 
          i = paramInt + 1;
        } 
        b++;
        paramInt = i;
        continue;
      } 
      break;
    } 
  }
  
  private final long s(int paramInt, long paramLong) {
    jc2 jc22;
    B();
    this.u = false;
    f(2);
    jc2 jc21 = this.G;
    if (jc21 == null) {
      jc21 = this.E;
      if (jc21 != null)
        jc21.a(); 
      jc22 = null;
    } else {
      jc2 jc23 = null;
      while (true) {
        jc22 = jc23;
        if (jc21 != null) {
          if (jc21.g == paramInt && jc21.j) {
            jc23 = jc21;
          } else {
            jc21.a();
          } 
          jc21 = jc21.l;
          continue;
        } 
        break;
      } 
    } 
    jc21 = this.G;
    if (jc21 != jc22 || jc21 != this.F) {
      pc2[] arrayOfPc2 = this.r;
      int i = arrayOfPc2.length;
      for (paramInt = 0; paramInt < i; paramInt++)
        arrayOfPc2[paramInt].p(); 
      this.r = new pc2[0];
      this.p = null;
      this.o = null;
      this.G = null;
    } 
    if (jc22 != null) {
      jc22.l = null;
      this.E = jc22;
      this.F = jc22;
      u(jc22);
      jc21 = this.G;
      long l = paramLong;
      if (jc21.k)
        l = jc21.a.i(paramLong); 
      y(l);
      F();
      paramLong = l;
    } else {
      this.E = null;
      this.F = null;
      this.G = null;
      y(paramLong);
    } 
    this.g.sendEmptyMessage(2);
    return paramLong;
  }
  
  private final Pair<Integer, Long> t(vc2 paramvc2, int paramInt, long paramLong) {
    return j(paramvc2, paramInt, paramLong, 0L);
  }
  
  private final void u(jc2 paramjc2) {
    if (this.G == paramjc2)
      return; 
    boolean[] arrayOfBoolean = new boolean[this.b.length];
    byte b = 0;
    int i = 0;
    while (true) {
      pc2[] arrayOfPc2 = this.b;
      if (b < arrayOfPc2.length) {
        boolean bool;
        pc2 pc21 = arrayOfPc2[b];
        if (pc21.getState() != 0) {
          bool = true;
        } else {
          bool = false;
        } 
        arrayOfBoolean[b] = bool;
        mi2 mi2 = paramjc2.m.b.a(b);
        int j = i;
        if (mi2 != null)
          j = i + 1; 
        if (arrayOfBoolean[b] && (mi2 == null || (pc21.u() && pc21.j() == this.G.d[b]))) {
          if (pc21 == this.o) {
            this.f.c(this.p);
            this.p = null;
            this.o = null;
          } 
          m(pc21);
          pc21.p();
        } 
        b++;
        i = j;
        continue;
      } 
      this.G = paramjc2;
      this.i.obtainMessage(3, paramjc2.m).sendToTarget();
      r(arrayOfBoolean, i);
      return;
    } 
  }
  
  private final void v(Object paramObject, int paramInt) {
    this.i.obtainMessage(6, new kc2(this.H, paramObject, this.m, paramInt)).sendToTarget();
  }
  
  private final Pair<Integer, Long> x(int paramInt, long paramLong) {
    return t(this.H, 0, -9223372036854775807L);
  }
  
  private final void y(long paramLong) {
    long l;
    jc2 jc21 = this.G;
    if (jc21 == null) {
      l = 60000000L;
    } else {
      l = jc21.e();
    } 
    paramLong += l;
    this.D = paramLong;
    this.f.d(paramLong);
    pc2[] arrayOfPc2 = this.r;
    int i = arrayOfPc2.length;
    for (byte b = 0; b < i; b++)
      arrayOfPc2[b].d(this.D); 
  }
  
  private final boolean z(long paramLong) {
    if (paramLong != -9223372036854775807L && this.m.c >= paramLong) {
      jc2 jc21 = this.G.l;
      if (jc21 == null || !jc21.j)
        return false; 
    } 
    return true;
  }
  
  public final void G(boolean paramBoolean) {
    this.g.obtainMessage(1, paramBoolean, 0).sendToTarget();
  }
  
  public final void a() {
    this.g.sendEmptyMessage(10);
  }
  
  public final void b() {
    // Byte code:
    //   0: aload_0
    //   1: monitorenter
    //   2: aload_0
    //   3: getfield s : Z
    //   6: istore_1
    //   7: iload_1
    //   8: ifeq -> 14
    //   11: aload_0
    //   12: monitorexit
    //   13: return
    //   14: aload_0
    //   15: getfield g : Landroid/os/Handler;
    //   18: bipush #6
    //   20: invokevirtual sendEmptyMessage : (I)Z
    //   23: pop
    //   24: aload_0
    //   25: getfield s : Z
    //   28: istore_1
    //   29: iload_1
    //   30: ifne -> 50
    //   33: aload_0
    //   34: invokevirtual wait : ()V
    //   37: goto -> 24
    //   40: astore_2
    //   41: invokestatic currentThread : ()Ljava/lang/Thread;
    //   44: invokevirtual interrupt : ()V
    //   47: goto -> 24
    //   50: aload_0
    //   51: getfield h : Landroid/os/HandlerThread;
    //   54: invokevirtual quit : ()Z
    //   57: pop
    //   58: aload_0
    //   59: monitorexit
    //   60: return
    //   61: astore_2
    //   62: aload_0
    //   63: monitorexit
    //   64: goto -> 69
    //   67: aload_2
    //   68: athrow
    //   69: goto -> 67
    // Exception table:
    //   from	to	target	type
    //   2	7	61	finally
    //   14	24	61	finally
    //   24	29	61	finally
    //   33	37	40	java/lang/InterruptedException
    //   33	37	61	finally
    //   41	47	61	finally
    //   50	58	61	finally
  }
  
  public final void d(vc2 paramvc2, Object paramObject) {
    this.g.obtainMessage(7, Pair.create(paramvc2, paramObject)).sendToTarget();
  }
  
  public final void e(kh2 paramkh2) {
    this.g.obtainMessage(8, paramkh2).sendToTarget();
  }
  
  public final void g() {
    this.g.sendEmptyMessage(5);
  }
  
  public final boolean handleMessage(Message paramMessage) {
    // Byte code:
    //   0: aload_1
    //   1: getfield what : I
    //   4: istore_2
    //   5: lconst_0
    //   6: lstore_3
    //   7: iconst_0
    //   8: istore #5
    //   10: iconst_0
    //   11: istore #6
    //   13: iload_2
    //   14: tableswitch default -> 80, 0 -> 4046, 1 -> 3958, 2 -> 2258, 3 -> 1885, 4 -> 1825, 5 -> 1819, 6 -> 1780, 7 -> 1068, 8 -> 976, 9 -> 939, 10 -> 473, 11 -> 358, 12 -> 82
    //   80: iconst_0
    //   81: ireturn
    //   82: aload_1
    //   83: getfield arg1 : I
    //   86: istore #5
    //   88: aload_0
    //   89: iload #5
    //   91: putfield x : I
    //   94: aload_0
    //   95: getfield G : Lcom/google/android/gms/internal/ads/jc2;
    //   98: astore_1
    //   99: aload_1
    //   100: ifnull -> 106
    //   103: goto -> 111
    //   106: aload_0
    //   107: getfield E : Lcom/google/android/gms/internal/ads/jc2;
    //   110: astore_1
    //   111: aload_1
    //   112: ifnull -> 356
    //   115: aload_1
    //   116: aload_0
    //   117: getfield F : Lcom/google/android/gms/internal/ads/jc2;
    //   120: if_acmpne -> 128
    //   123: iconst_1
    //   124: istore_2
    //   125: goto -> 130
    //   128: iconst_0
    //   129: istore_2
    //   130: aload_1
    //   131: aload_0
    //   132: getfield E : Lcom/google/android/gms/internal/ads/jc2;
    //   135: if_acmpne -> 144
    //   138: iconst_1
    //   139: istore #6
    //   141: goto -> 147
    //   144: iconst_0
    //   145: istore #6
    //   147: aload_0
    //   148: getfield H : Lcom/google/android/gms/internal/ads/vc2;
    //   151: aload_1
    //   152: getfield g : I
    //   155: aload_0
    //   156: getfield l : Lcom/google/android/gms/internal/ads/xc2;
    //   159: aload_0
    //   160: getfield k : Lcom/google/android/gms/internal/ads/wc2;
    //   163: iload #5
    //   165: invokevirtual b : (ILcom/google/android/gms/internal/ads/xc2;Lcom/google/android/gms/internal/ads/wc2;I)I
    //   168: istore #7
    //   170: aload_1
    //   171: getfield l : Lcom/google/android/gms/internal/ads/jc2;
    //   174: astore #8
    //   176: aload #8
    //   178: ifnull -> 252
    //   181: iload #7
    //   183: iconst_m1
    //   184: if_icmpeq -> 252
    //   187: aload #8
    //   189: getfield g : I
    //   192: iload #7
    //   194: if_icmpne -> 252
    //   197: aload #8
    //   199: aload_0
    //   200: getfield F : Lcom/google/android/gms/internal/ads/jc2;
    //   203: if_acmpne -> 212
    //   206: iconst_1
    //   207: istore #7
    //   209: goto -> 215
    //   212: iconst_0
    //   213: istore #7
    //   215: iload_2
    //   216: iload #7
    //   218: ior
    //   219: istore #7
    //   221: aload #8
    //   223: aload_0
    //   224: getfield E : Lcom/google/android/gms/internal/ads/jc2;
    //   227: if_acmpne -> 235
    //   230: iconst_1
    //   231: istore_2
    //   232: goto -> 237
    //   235: iconst_0
    //   236: istore_2
    //   237: iload #6
    //   239: iload_2
    //   240: ior
    //   241: istore #6
    //   243: aload #8
    //   245: astore_1
    //   246: iload #7
    //   248: istore_2
    //   249: goto -> 147
    //   252: aload #8
    //   254: ifnull -> 267
    //   257: aload #8
    //   259: invokestatic l : (Lcom/google/android/gms/internal/ads/jc2;)V
    //   262: aload_1
    //   263: aconst_null
    //   264: putfield l : Lcom/google/android/gms/internal/ads/jc2;
    //   267: aload_1
    //   268: aload_0
    //   269: aload_1
    //   270: getfield g : I
    //   273: invokespecial J : (I)Z
    //   276: putfield i : Z
    //   279: iload #6
    //   281: ifne -> 289
    //   284: aload_0
    //   285: aload_1
    //   286: putfield E : Lcom/google/android/gms/internal/ads/jc2;
    //   289: iload_2
    //   290: ifne -> 338
    //   293: aload_0
    //   294: getfield G : Lcom/google/android/gms/internal/ads/jc2;
    //   297: astore_1
    //   298: aload_1
    //   299: ifnull -> 338
    //   302: aload_1
    //   303: getfield g : I
    //   306: istore #6
    //   308: aload_0
    //   309: iload #6
    //   311: aload_0
    //   312: getfield m : Lcom/google/android/gms/internal/ads/ic2;
    //   315: getfield c : J
    //   318: invokespecial s : (IJ)J
    //   321: lstore_3
    //   322: new com/google/android/gms/internal/ads/ic2
    //   325: astore_1
    //   326: aload_1
    //   327: iload #6
    //   329: lload_3
    //   330: invokespecial <init> : (IJ)V
    //   333: aload_0
    //   334: aload_1
    //   335: putfield m : Lcom/google/android/gms/internal/ads/ic2;
    //   338: aload_0
    //   339: getfield w : I
    //   342: iconst_4
    //   343: if_icmpne -> 356
    //   346: iload #5
    //   348: ifeq -> 356
    //   351: aload_0
    //   352: iconst_2
    //   353: invokespecial f : (I)V
    //   356: iconst_1
    //   357: ireturn
    //   358: aload_1
    //   359: getfield obj : Ljava/lang/Object;
    //   362: checkcast [Lcom/google/android/gms/internal/ads/cc2;
    //   365: astore #8
    //   367: aload #8
    //   369: arraylength
    //   370: istore_2
    //   371: iload #6
    //   373: iload_2
    //   374: if_icmpge -> 406
    //   377: aload #8
    //   379: iload #6
    //   381: aaload
    //   382: astore_1
    //   383: aload_1
    //   384: getfield a : Lcom/google/android/gms/internal/ads/dc2;
    //   387: aload_1
    //   388: getfield b : I
    //   391: aload_1
    //   392: getfield c : Ljava/lang/Object;
    //   395: invokeinterface a : (ILjava/lang/Object;)V
    //   400: iinc #6, 1
    //   403: goto -> 371
    //   406: aload_0
    //   407: getfield q : Lcom/google/android/gms/internal/ads/mh2;
    //   410: ifnull -> 422
    //   413: aload_0
    //   414: getfield g : Landroid/os/Handler;
    //   417: iconst_2
    //   418: invokevirtual sendEmptyMessage : (I)Z
    //   421: pop
    //   422: aload_0
    //   423: monitorenter
    //   424: aload_0
    //   425: aload_0
    //   426: getfield z : I
    //   429: iconst_1
    //   430: iadd
    //   431: putfield z : I
    //   434: aload_0
    //   435: invokevirtual notifyAll : ()V
    //   438: aload_0
    //   439: monitorexit
    //   440: iconst_1
    //   441: ireturn
    //   442: astore_1
    //   443: aload_0
    //   444: monitorexit
    //   445: aload_1
    //   446: athrow
    //   447: astore_1
    //   448: aload_0
    //   449: monitorenter
    //   450: aload_0
    //   451: aload_0
    //   452: getfield z : I
    //   455: iconst_1
    //   456: iadd
    //   457: putfield z : I
    //   460: aload_0
    //   461: invokevirtual notifyAll : ()V
    //   464: aload_0
    //   465: monitorexit
    //   466: aload_1
    //   467: athrow
    //   468: astore_1
    //   469: aload_0
    //   470: monitorexit
    //   471: aload_1
    //   472: athrow
    //   473: aload_0
    //   474: getfield G : Lcom/google/android/gms/internal/ads/jc2;
    //   477: astore_1
    //   478: aload_1
    //   479: ifnull -> 937
    //   482: iconst_1
    //   483: istore #6
    //   485: aload_1
    //   486: ifnull -> 937
    //   489: aload_1
    //   490: getfield j : Z
    //   493: ifne -> 499
    //   496: goto -> 937
    //   499: aload_1
    //   500: invokevirtual g : ()Z
    //   503: ifne -> 525
    //   506: aload_1
    //   507: aload_0
    //   508: getfield F : Lcom/google/android/gms/internal/ads/jc2;
    //   511: if_acmpne -> 517
    //   514: iconst_0
    //   515: istore #6
    //   517: aload_1
    //   518: getfield l : Lcom/google/android/gms/internal/ads/jc2;
    //   521: astore_1
    //   522: goto -> 485
    //   525: iload #6
    //   527: ifeq -> 850
    //   530: aload_0
    //   531: getfield F : Lcom/google/android/gms/internal/ads/jc2;
    //   534: astore #9
    //   536: aload_0
    //   537: getfield G : Lcom/google/android/gms/internal/ads/jc2;
    //   540: astore #8
    //   542: aload #9
    //   544: aload #8
    //   546: if_acmpeq -> 555
    //   549: iconst_1
    //   550: istore #10
    //   552: goto -> 558
    //   555: iconst_0
    //   556: istore #10
    //   558: aload #8
    //   560: getfield l : Lcom/google/android/gms/internal/ads/jc2;
    //   563: invokestatic l : (Lcom/google/android/gms/internal/ads/jc2;)V
    //   566: aload_0
    //   567: getfield G : Lcom/google/android/gms/internal/ads/jc2;
    //   570: astore #9
    //   572: aload #9
    //   574: aconst_null
    //   575: putfield l : Lcom/google/android/gms/internal/ads/jc2;
    //   578: aload_0
    //   579: aload #9
    //   581: putfield E : Lcom/google/android/gms/internal/ads/jc2;
    //   584: aload_0
    //   585: aload #9
    //   587: putfield F : Lcom/google/android/gms/internal/ads/jc2;
    //   590: aload_0
    //   591: getfield b : [Lcom/google/android/gms/internal/ads/pc2;
    //   594: arraylength
    //   595: newarray boolean
    //   597: astore #8
    //   599: aload #9
    //   601: aload_0
    //   602: getfield m : Lcom/google/android/gms/internal/ads/ic2;
    //   605: getfield c : J
    //   608: iload #10
    //   610: aload #8
    //   612: invokevirtual b : (JZ[Z)J
    //   615: lstore_3
    //   616: lload_3
    //   617: aload_0
    //   618: getfield m : Lcom/google/android/gms/internal/ads/ic2;
    //   621: getfield c : J
    //   624: lcmp
    //   625: ifeq -> 641
    //   628: aload_0
    //   629: getfield m : Lcom/google/android/gms/internal/ads/ic2;
    //   632: lload_3
    //   633: putfield c : J
    //   636: aload_0
    //   637: lload_3
    //   638: invokespecial y : (J)V
    //   641: aload_0
    //   642: getfield b : [Lcom/google/android/gms/internal/ads/pc2;
    //   645: arraylength
    //   646: newarray boolean
    //   648: astore #9
    //   650: iconst_0
    //   651: istore #6
    //   653: iconst_0
    //   654: istore_2
    //   655: aload_0
    //   656: getfield b : [Lcom/google/android/gms/internal/ads/pc2;
    //   659: astore #11
    //   661: iload #6
    //   663: aload #11
    //   665: arraylength
    //   666: if_icmpge -> 825
    //   669: aload #11
    //   671: iload #6
    //   673: aaload
    //   674: astore #12
    //   676: aload #12
    //   678: invokeinterface getState : ()I
    //   683: ifeq -> 692
    //   686: iconst_1
    //   687: istore #10
    //   689: goto -> 695
    //   692: iconst_0
    //   693: istore #10
    //   695: aload #9
    //   697: iload #6
    //   699: iload #10
    //   701: bastore
    //   702: aload_0
    //   703: getfield G : Lcom/google/android/gms/internal/ads/jc2;
    //   706: getfield d : [Lcom/google/android/gms/internal/ads/uh2;
    //   709: iload #6
    //   711: aaload
    //   712: astore #11
    //   714: iload_2
    //   715: istore #7
    //   717: aload #11
    //   719: ifnull -> 727
    //   722: iload_2
    //   723: iconst_1
    //   724: iadd
    //   725: istore #7
    //   727: aload #9
    //   729: iload #6
    //   731: baload
    //   732: ifeq -> 816
    //   735: aload #11
    //   737: aload #12
    //   739: invokeinterface j : ()Lcom/google/android/gms/internal/ads/uh2;
    //   744: if_acmpeq -> 797
    //   747: aload #12
    //   749: aload_0
    //   750: getfield o : Lcom/google/android/gms/internal/ads/pc2;
    //   753: if_acmpne -> 782
    //   756: aload #11
    //   758: ifnonnull -> 772
    //   761: aload_0
    //   762: getfield f : Lcom/google/android/gms/internal/ads/vj2;
    //   765: aload_0
    //   766: getfield p : Lcom/google/android/gms/internal/ads/nj2;
    //   769: invokevirtual c : (Lcom/google/android/gms/internal/ads/nj2;)V
    //   772: aload_0
    //   773: aconst_null
    //   774: putfield p : Lcom/google/android/gms/internal/ads/nj2;
    //   777: aload_0
    //   778: aconst_null
    //   779: putfield o : Lcom/google/android/gms/internal/ads/pc2;
    //   782: aload #12
    //   784: invokestatic m : (Lcom/google/android/gms/internal/ads/pc2;)V
    //   787: aload #12
    //   789: invokeinterface p : ()V
    //   794: goto -> 816
    //   797: aload #8
    //   799: iload #6
    //   801: baload
    //   802: ifeq -> 816
    //   805: aload #12
    //   807: aload_0
    //   808: getfield D : J
    //   811: invokeinterface d : (J)V
    //   816: iinc #6, 1
    //   819: iload #7
    //   821: istore_2
    //   822: goto -> 655
    //   825: aload_0
    //   826: getfield i : Landroid/os/Handler;
    //   829: iconst_3
    //   830: aload_1
    //   831: getfield m : Lcom/google/android/gms/internal/ads/pi2;
    //   834: invokevirtual obtainMessage : (ILjava/lang/Object;)Landroid/os/Message;
    //   837: invokevirtual sendToTarget : ()V
    //   840: aload_0
    //   841: aload #9
    //   843: iload_2
    //   844: invokespecial r : ([ZI)V
    //   847: goto -> 920
    //   850: aload_0
    //   851: aload_1
    //   852: putfield E : Lcom/google/android/gms/internal/ads/jc2;
    //   855: aload_1
    //   856: getfield l : Lcom/google/android/gms/internal/ads/jc2;
    //   859: astore_1
    //   860: aload_1
    //   861: ifnull -> 876
    //   864: aload_1
    //   865: invokevirtual a : ()V
    //   868: aload_1
    //   869: getfield l : Lcom/google/android/gms/internal/ads/jc2;
    //   872: astore_1
    //   873: goto -> 860
    //   876: aload_0
    //   877: getfield E : Lcom/google/android/gms/internal/ads/jc2;
    //   880: astore_1
    //   881: aload_1
    //   882: aconst_null
    //   883: putfield l : Lcom/google/android/gms/internal/ads/jc2;
    //   886: aload_1
    //   887: getfield j : Z
    //   890: ifeq -> 920
    //   893: aload_1
    //   894: getfield h : J
    //   897: aload_0
    //   898: getfield D : J
    //   901: aload_1
    //   902: invokevirtual e : ()J
    //   905: lsub
    //   906: invokestatic max : (JJ)J
    //   909: lstore_3
    //   910: aload_0
    //   911: getfield E : Lcom/google/android/gms/internal/ads/jc2;
    //   914: lload_3
    //   915: iconst_0
    //   916: invokevirtual c : (JZ)J
    //   919: pop2
    //   920: aload_0
    //   921: invokespecial F : ()V
    //   924: aload_0
    //   925: invokespecial C : ()V
    //   928: aload_0
    //   929: getfield g : Landroid/os/Handler;
    //   932: iconst_2
    //   933: invokevirtual sendEmptyMessage : (I)Z
    //   936: pop
    //   937: iconst_1
    //   938: ireturn
    //   939: aload_1
    //   940: getfield obj : Ljava/lang/Object;
    //   943: checkcast com/google/android/gms/internal/ads/kh2
    //   946: astore_1
    //   947: aload_0
    //   948: getfield E : Lcom/google/android/gms/internal/ads/jc2;
    //   951: astore #8
    //   953: aload #8
    //   955: ifnull -> 974
    //   958: aload #8
    //   960: getfield a : Lcom/google/android/gms/internal/ads/kh2;
    //   963: aload_1
    //   964: if_acmpeq -> 970
    //   967: goto -> 974
    //   970: aload_0
    //   971: invokespecial F : ()V
    //   974: iconst_1
    //   975: ireturn
    //   976: aload_1
    //   977: getfield obj : Ljava/lang/Object;
    //   980: checkcast com/google/android/gms/internal/ads/kh2
    //   983: astore #8
    //   985: aload_0
    //   986: getfield E : Lcom/google/android/gms/internal/ads/jc2;
    //   989: astore_1
    //   990: aload_1
    //   991: ifnull -> 1066
    //   994: aload_1
    //   995: getfield a : Lcom/google/android/gms/internal/ads/kh2;
    //   998: aload #8
    //   1000: if_acmpeq -> 1006
    //   1003: goto -> 1066
    //   1006: aload_1
    //   1007: iconst_1
    //   1008: putfield j : Z
    //   1011: aload_1
    //   1012: invokevirtual g : ()Z
    //   1015: pop
    //   1016: aload_1
    //   1017: aload_1
    //   1018: aload_1
    //   1019: getfield h : J
    //   1022: iconst_0
    //   1023: invokevirtual c : (JZ)J
    //   1026: putfield h : J
    //   1029: aload_0
    //   1030: getfield G : Lcom/google/android/gms/internal/ads/jc2;
    //   1033: ifnonnull -> 1062
    //   1036: aload_0
    //   1037: getfield E : Lcom/google/android/gms/internal/ads/jc2;
    //   1040: astore_1
    //   1041: aload_0
    //   1042: aload_1
    //   1043: putfield F : Lcom/google/android/gms/internal/ads/jc2;
    //   1046: aload_0
    //   1047: aload_1
    //   1048: getfield h : J
    //   1051: invokespecial y : (J)V
    //   1054: aload_0
    //   1055: aload_0
    //   1056: getfield F : Lcom/google/android/gms/internal/ads/jc2;
    //   1059: invokespecial u : (Lcom/google/android/gms/internal/ads/jc2;)V
    //   1062: aload_0
    //   1063: invokespecial F : ()V
    //   1066: iconst_1
    //   1067: ireturn
    //   1068: aload_1
    //   1069: getfield obj : Ljava/lang/Object;
    //   1072: checkcast android/util/Pair
    //   1075: astore #9
    //   1077: aload_0
    //   1078: getfield H : Lcom/google/android/gms/internal/ads/vc2;
    //   1081: astore #8
    //   1083: aload #9
    //   1085: getfield first : Ljava/lang/Object;
    //   1088: checkcast com/google/android/gms/internal/ads/vc2
    //   1091: astore_1
    //   1092: aload_0
    //   1093: aload_1
    //   1094: putfield H : Lcom/google/android/gms/internal/ads/vc2;
    //   1097: aload #9
    //   1099: getfield second : Ljava/lang/Object;
    //   1102: astore #9
    //   1104: aload #8
    //   1106: ifnonnull -> 1270
    //   1109: aload_0
    //   1110: getfield B : I
    //   1113: ifle -> 1194
    //   1116: aload_0
    //   1117: aload_0
    //   1118: getfield C : Lcom/google/android/gms/internal/ads/lc2;
    //   1121: invokespecial i : (Lcom/google/android/gms/internal/ads/lc2;)Landroid/util/Pair;
    //   1124: astore #11
    //   1126: aload_0
    //   1127: getfield B : I
    //   1130: istore_2
    //   1131: aload_0
    //   1132: iconst_0
    //   1133: putfield B : I
    //   1136: aload_0
    //   1137: aconst_null
    //   1138: putfield C : Lcom/google/android/gms/internal/ads/lc2;
    //   1141: aload #11
    //   1143: ifnonnull -> 1156
    //   1146: aload_0
    //   1147: aload #9
    //   1149: iload_2
    //   1150: invokespecial p : (Ljava/lang/Object;I)V
    //   1153: goto -> 1778
    //   1156: new com/google/android/gms/internal/ads/ic2
    //   1159: astore_1
    //   1160: aload_1
    //   1161: aload #11
    //   1163: getfield first : Ljava/lang/Object;
    //   1166: checkcast java/lang/Integer
    //   1169: invokevirtual intValue : ()I
    //   1172: aload #11
    //   1174: getfield second : Ljava/lang/Object;
    //   1177: checkcast java/lang/Long
    //   1180: invokevirtual longValue : ()J
    //   1183: invokespecial <init> : (IJ)V
    //   1186: aload_0
    //   1187: aload_1
    //   1188: putfield m : Lcom/google/android/gms/internal/ads/ic2;
    //   1191: goto -> 1272
    //   1194: aload_0
    //   1195: getfield m : Lcom/google/android/gms/internal/ads/ic2;
    //   1198: getfield b : J
    //   1201: ldc2_w -9223372036854775807
    //   1204: lcmp
    //   1205: ifne -> 1270
    //   1208: aload_1
    //   1209: invokevirtual a : ()Z
    //   1212: ifeq -> 1225
    //   1215: aload_0
    //   1216: aload #9
    //   1218: iconst_0
    //   1219: invokespecial p : (Ljava/lang/Object;I)V
    //   1222: goto -> 1778
    //   1225: aload_0
    //   1226: iconst_0
    //   1227: ldc2_w -9223372036854775807
    //   1230: invokespecial x : (IJ)Landroid/util/Pair;
    //   1233: astore_1
    //   1234: new com/google/android/gms/internal/ads/ic2
    //   1237: astore #11
    //   1239: aload #11
    //   1241: aload_1
    //   1242: getfield first : Ljava/lang/Object;
    //   1245: checkcast java/lang/Integer
    //   1248: invokevirtual intValue : ()I
    //   1251: aload_1
    //   1252: getfield second : Ljava/lang/Object;
    //   1255: checkcast java/lang/Long
    //   1258: invokevirtual longValue : ()J
    //   1261: invokespecial <init> : (IJ)V
    //   1264: aload_0
    //   1265: aload #11
    //   1267: putfield m : Lcom/google/android/gms/internal/ads/ic2;
    //   1270: iconst_0
    //   1271: istore_2
    //   1272: aload_0
    //   1273: getfield G : Lcom/google/android/gms/internal/ads/jc2;
    //   1276: astore_1
    //   1277: aload_1
    //   1278: ifnull -> 1284
    //   1281: goto -> 1289
    //   1284: aload_0
    //   1285: getfield E : Lcom/google/android/gms/internal/ads/jc2;
    //   1288: astore_1
    //   1289: aload_1
    //   1290: ifnull -> 1771
    //   1293: aload_0
    //   1294: getfield H : Lcom/google/android/gms/internal/ads/vc2;
    //   1297: aload_1
    //   1298: getfield b : Ljava/lang/Object;
    //   1301: invokevirtual f : (Ljava/lang/Object;)I
    //   1304: istore #13
    //   1306: iload #13
    //   1308: iconst_m1
    //   1309: if_icmpne -> 1490
    //   1312: aload_0
    //   1313: aload_1
    //   1314: getfield g : I
    //   1317: aload #8
    //   1319: aload_0
    //   1320: getfield H : Lcom/google/android/gms/internal/ads/vc2;
    //   1323: invokespecial h : (ILcom/google/android/gms/internal/ads/vc2;Lcom/google/android/gms/internal/ads/vc2;)I
    //   1326: istore #6
    //   1328: iload #6
    //   1330: iconst_m1
    //   1331: if_icmpne -> 1344
    //   1334: aload_0
    //   1335: aload #9
    //   1337: iload_2
    //   1338: invokespecial p : (Ljava/lang/Object;I)V
    //   1341: goto -> 1778
    //   1344: aload_0
    //   1345: getfield H : Lcom/google/android/gms/internal/ads/vc2;
    //   1348: iload #6
    //   1350: aload_0
    //   1351: getfield l : Lcom/google/android/gms/internal/ads/xc2;
    //   1354: iconst_0
    //   1355: invokevirtual e : (ILcom/google/android/gms/internal/ads/xc2;Z)Lcom/google/android/gms/internal/ads/xc2;
    //   1358: pop
    //   1359: aload_0
    //   1360: iconst_0
    //   1361: ldc2_w -9223372036854775807
    //   1364: invokespecial x : (IJ)Landroid/util/Pair;
    //   1367: astore #8
    //   1369: aload #8
    //   1371: getfield first : Ljava/lang/Object;
    //   1374: checkcast java/lang/Integer
    //   1377: invokevirtual intValue : ()I
    //   1380: istore #7
    //   1382: aload #8
    //   1384: getfield second : Ljava/lang/Object;
    //   1387: checkcast java/lang/Long
    //   1390: invokevirtual longValue : ()J
    //   1393: lstore_3
    //   1394: aload_0
    //   1395: getfield H : Lcom/google/android/gms/internal/ads/vc2;
    //   1398: iload #7
    //   1400: aload_0
    //   1401: getfield l : Lcom/google/android/gms/internal/ads/xc2;
    //   1404: iconst_1
    //   1405: invokevirtual e : (ILcom/google/android/gms/internal/ads/xc2;Z)Lcom/google/android/gms/internal/ads/xc2;
    //   1408: pop
    //   1409: aload_0
    //   1410: getfield l : Lcom/google/android/gms/internal/ads/xc2;
    //   1413: getfield b : Ljava/lang/Object;
    //   1416: astore #8
    //   1418: aload_1
    //   1419: iconst_m1
    //   1420: putfield g : I
    //   1423: aload_1
    //   1424: getfield l : Lcom/google/android/gms/internal/ads/jc2;
    //   1427: astore_1
    //   1428: aload_1
    //   1429: ifnull -> 1463
    //   1432: aload_1
    //   1433: getfield b : Ljava/lang/Object;
    //   1436: aload #8
    //   1438: invokevirtual equals : (Ljava/lang/Object;)Z
    //   1441: ifeq -> 1451
    //   1444: iload #7
    //   1446: istore #6
    //   1448: goto -> 1454
    //   1451: iconst_m1
    //   1452: istore #6
    //   1454: aload_1
    //   1455: iload #6
    //   1457: putfield g : I
    //   1460: goto -> 1423
    //   1463: aload_0
    //   1464: iload #7
    //   1466: lload_3
    //   1467: invokespecial s : (IJ)J
    //   1470: lstore_3
    //   1471: new com/google/android/gms/internal/ads/ic2
    //   1474: astore_1
    //   1475: aload_1
    //   1476: iload #7
    //   1478: lload_3
    //   1479: invokespecial <init> : (IJ)V
    //   1482: aload_0
    //   1483: aload_1
    //   1484: putfield m : Lcom/google/android/gms/internal/ads/ic2;
    //   1487: goto -> 1771
    //   1490: aload_1
    //   1491: iload #13
    //   1493: aload_0
    //   1494: iload #13
    //   1496: invokespecial J : (I)Z
    //   1499: invokevirtual d : (IZ)V
    //   1502: aload_1
    //   1503: aload_0
    //   1504: getfield F : Lcom/google/android/gms/internal/ads/jc2;
    //   1507: if_acmpne -> 1516
    //   1510: iconst_1
    //   1511: istore #6
    //   1513: goto -> 1519
    //   1516: iconst_0
    //   1517: istore #6
    //   1519: aload_0
    //   1520: getfield m : Lcom/google/android/gms/internal/ads/ic2;
    //   1523: astore #11
    //   1525: iload #6
    //   1527: istore #7
    //   1529: aload_1
    //   1530: astore #8
    //   1532: iload #13
    //   1534: istore #5
    //   1536: iload #13
    //   1538: aload #11
    //   1540: getfield a : I
    //   1543: if_icmpeq -> 1600
    //   1546: new com/google/android/gms/internal/ads/ic2
    //   1549: astore #8
    //   1551: aload #8
    //   1553: iload #13
    //   1555: aload #11
    //   1557: getfield b : J
    //   1560: invokespecial <init> : (IJ)V
    //   1563: aload #8
    //   1565: aload #11
    //   1567: getfield c : J
    //   1570: putfield c : J
    //   1573: aload #8
    //   1575: aload #11
    //   1577: getfield d : J
    //   1580: putfield d : J
    //   1583: aload_0
    //   1584: aload #8
    //   1586: putfield m : Lcom/google/android/gms/internal/ads/ic2;
    //   1589: iload #13
    //   1591: istore #5
    //   1593: aload_1
    //   1594: astore #8
    //   1596: iload #6
    //   1598: istore #7
    //   1600: aload #8
    //   1602: getfield l : Lcom/google/android/gms/internal/ads/jc2;
    //   1605: astore_1
    //   1606: aload_1
    //   1607: ifnull -> 1771
    //   1610: aload_0
    //   1611: getfield H : Lcom/google/android/gms/internal/ads/vc2;
    //   1614: iload #5
    //   1616: aload_0
    //   1617: getfield l : Lcom/google/android/gms/internal/ads/xc2;
    //   1620: aload_0
    //   1621: getfield k : Lcom/google/android/gms/internal/ads/wc2;
    //   1624: aload_0
    //   1625: getfield x : I
    //   1628: invokevirtual b : (ILcom/google/android/gms/internal/ads/xc2;Lcom/google/android/gms/internal/ads/wc2;I)I
    //   1631: istore #5
    //   1633: iload #5
    //   1635: iconst_m1
    //   1636: if_icmpeq -> 1708
    //   1639: aload_1
    //   1640: getfield b : Ljava/lang/Object;
    //   1643: aload_0
    //   1644: getfield H : Lcom/google/android/gms/internal/ads/vc2;
    //   1647: iload #5
    //   1649: aload_0
    //   1650: getfield l : Lcom/google/android/gms/internal/ads/xc2;
    //   1653: iconst_1
    //   1654: invokevirtual e : (ILcom/google/android/gms/internal/ads/xc2;Z)Lcom/google/android/gms/internal/ads/xc2;
    //   1657: getfield b : Ljava/lang/Object;
    //   1660: invokevirtual equals : (Ljava/lang/Object;)Z
    //   1663: ifeq -> 1708
    //   1666: aload_1
    //   1667: iload #5
    //   1669: aload_0
    //   1670: iload #5
    //   1672: invokespecial J : (I)Z
    //   1675: invokevirtual d : (IZ)V
    //   1678: aload_1
    //   1679: aload_0
    //   1680: getfield F : Lcom/google/android/gms/internal/ads/jc2;
    //   1683: if_acmpne -> 1692
    //   1686: iconst_1
    //   1687: istore #6
    //   1689: goto -> 1695
    //   1692: iconst_0
    //   1693: istore #6
    //   1695: iload #7
    //   1697: iload #6
    //   1699: ior
    //   1700: istore #7
    //   1702: aload_1
    //   1703: astore #8
    //   1705: goto -> 1600
    //   1708: iload #7
    //   1710: ifne -> 1755
    //   1713: aload_0
    //   1714: getfield G : Lcom/google/android/gms/internal/ads/jc2;
    //   1717: getfield g : I
    //   1720: istore #6
    //   1722: aload_0
    //   1723: iload #6
    //   1725: aload_0
    //   1726: getfield m : Lcom/google/android/gms/internal/ads/ic2;
    //   1729: getfield c : J
    //   1732: invokespecial s : (IJ)J
    //   1735: lstore_3
    //   1736: new com/google/android/gms/internal/ads/ic2
    //   1739: astore_1
    //   1740: aload_1
    //   1741: iload #6
    //   1743: lload_3
    //   1744: invokespecial <init> : (IJ)V
    //   1747: aload_0
    //   1748: aload_1
    //   1749: putfield m : Lcom/google/android/gms/internal/ads/ic2;
    //   1752: goto -> 1771
    //   1755: aload_0
    //   1756: aload #8
    //   1758: putfield E : Lcom/google/android/gms/internal/ads/jc2;
    //   1761: aload #8
    //   1763: aconst_null
    //   1764: putfield l : Lcom/google/android/gms/internal/ads/jc2;
    //   1767: aload_1
    //   1768: invokestatic l : (Lcom/google/android/gms/internal/ads/jc2;)V
    //   1771: aload_0
    //   1772: aload #9
    //   1774: iload_2
    //   1775: invokespecial v : (Ljava/lang/Object;I)V
    //   1778: iconst_1
    //   1779: ireturn
    //   1780: aload_0
    //   1781: iconst_1
    //   1782: invokespecial I : (Z)V
    //   1785: aload_0
    //   1786: getfield e : Lcom/google/android/gms/internal/ads/oc2;
    //   1789: invokeinterface f : ()V
    //   1794: aload_0
    //   1795: iconst_1
    //   1796: invokespecial f : (I)V
    //   1799: aload_0
    //   1800: monitorenter
    //   1801: aload_0
    //   1802: iconst_1
    //   1803: putfield s : Z
    //   1806: aload_0
    //   1807: invokevirtual notifyAll : ()V
    //   1810: aload_0
    //   1811: monitorexit
    //   1812: iconst_1
    //   1813: ireturn
    //   1814: astore_1
    //   1815: aload_0
    //   1816: monitorexit
    //   1817: aload_1
    //   1818: athrow
    //   1819: aload_0
    //   1820: invokespecial D : ()V
    //   1823: iconst_1
    //   1824: ireturn
    //   1825: aload_1
    //   1826: getfield obj : Ljava/lang/Object;
    //   1829: checkcast com/google/android/gms/internal/ads/qc2
    //   1832: astore #8
    //   1834: aload_0
    //   1835: getfield p : Lcom/google/android/gms/internal/ads/nj2;
    //   1838: astore_1
    //   1839: aload_1
    //   1840: ifnull -> 1855
    //   1843: aload_1
    //   1844: aload #8
    //   1846: invokeinterface k : (Lcom/google/android/gms/internal/ads/qc2;)Lcom/google/android/gms/internal/ads/qc2;
    //   1851: astore_1
    //   1852: goto -> 1865
    //   1855: aload_0
    //   1856: getfield f : Lcom/google/android/gms/internal/ads/vj2;
    //   1859: aload #8
    //   1861: invokevirtual k : (Lcom/google/android/gms/internal/ads/qc2;)Lcom/google/android/gms/internal/ads/qc2;
    //   1864: astore_1
    //   1865: aload_0
    //   1866: aload_1
    //   1867: putfield n : Lcom/google/android/gms/internal/ads/qc2;
    //   1870: aload_0
    //   1871: getfield i : Landroid/os/Handler;
    //   1874: bipush #7
    //   1876: aload_1
    //   1877: invokevirtual obtainMessage : (ILjava/lang/Object;)Landroid/os/Message;
    //   1880: invokevirtual sendToTarget : ()V
    //   1883: iconst_1
    //   1884: ireturn
    //   1885: aload_1
    //   1886: getfield obj : Ljava/lang/Object;
    //   1889: checkcast com/google/android/gms/internal/ads/lc2
    //   1892: astore_1
    //   1893: aload_0
    //   1894: getfield H : Lcom/google/android/gms/internal/ads/vc2;
    //   1897: ifnonnull -> 1918
    //   1900: aload_0
    //   1901: aload_0
    //   1902: getfield B : I
    //   1905: iconst_1
    //   1906: iadd
    //   1907: putfield B : I
    //   1910: aload_0
    //   1911: aload_1
    //   1912: putfield C : Lcom/google/android/gms/internal/ads/lc2;
    //   1915: goto -> 2202
    //   1918: aload_0
    //   1919: aload_1
    //   1920: invokespecial i : (Lcom/google/android/gms/internal/ads/lc2;)Landroid/util/Pair;
    //   1923: astore #8
    //   1925: aload #8
    //   1927: ifnonnull -> 1989
    //   1930: new com/google/android/gms/internal/ads/ic2
    //   1933: astore_1
    //   1934: aload_1
    //   1935: iconst_0
    //   1936: lconst_0
    //   1937: invokespecial <init> : (IJ)V
    //   1940: aload_0
    //   1941: aload_1
    //   1942: putfield m : Lcom/google/android/gms/internal/ads/ic2;
    //   1945: aload_0
    //   1946: getfield i : Landroid/os/Handler;
    //   1949: iconst_4
    //   1950: iconst_1
    //   1951: iconst_0
    //   1952: aload_1
    //   1953: invokevirtual obtainMessage : (IIILjava/lang/Object;)Landroid/os/Message;
    //   1956: invokevirtual sendToTarget : ()V
    //   1959: new com/google/android/gms/internal/ads/ic2
    //   1962: astore_1
    //   1963: aload_1
    //   1964: iconst_0
    //   1965: ldc2_w -9223372036854775807
    //   1968: invokespecial <init> : (IJ)V
    //   1971: aload_0
    //   1972: aload_1
    //   1973: putfield m : Lcom/google/android/gms/internal/ads/ic2;
    //   1976: aload_0
    //   1977: iconst_4
    //   1978: invokespecial f : (I)V
    //   1981: aload_0
    //   1982: iconst_0
    //   1983: invokespecial I : (Z)V
    //   1986: goto -> 2202
    //   1989: aload_1
    //   1990: getfield c : J
    //   1993: ldc2_w -9223372036854775807
    //   1996: lcmp
    //   1997: ifne -> 2006
    //   2000: iconst_1
    //   2001: istore #6
    //   2003: goto -> 2009
    //   2006: iconst_0
    //   2007: istore #6
    //   2009: aload #8
    //   2011: getfield first : Ljava/lang/Object;
    //   2014: checkcast java/lang/Integer
    //   2017: invokevirtual intValue : ()I
    //   2020: istore #7
    //   2022: aload #8
    //   2024: getfield second : Ljava/lang/Object;
    //   2027: checkcast java/lang/Long
    //   2030: invokevirtual longValue : ()J
    //   2033: lstore_3
    //   2034: aload_0
    //   2035: getfield m : Lcom/google/android/gms/internal/ads/ic2;
    //   2038: astore_1
    //   2039: iload #7
    //   2041: aload_1
    //   2042: getfield a : I
    //   2045: if_icmpne -> 2125
    //   2048: lload_3
    //   2049: ldc2_w 1000
    //   2052: ldiv
    //   2053: lstore #14
    //   2055: aload_1
    //   2056: getfield c : J
    //   2059: ldc2_w 1000
    //   2062: ldiv
    //   2063: lstore #16
    //   2065: lload #14
    //   2067: lload #16
    //   2069: lcmp
    //   2070: ifne -> 2125
    //   2073: new com/google/android/gms/internal/ads/ic2
    //   2076: astore_1
    //   2077: aload_1
    //   2078: iload #7
    //   2080: lload_3
    //   2081: invokespecial <init> : (IJ)V
    //   2084: aload_0
    //   2085: aload_1
    //   2086: putfield m : Lcom/google/android/gms/internal/ads/ic2;
    //   2089: aload_0
    //   2090: getfield i : Landroid/os/Handler;
    //   2093: astore #8
    //   2095: iload #6
    //   2097: ifeq -> 2106
    //   2100: iconst_1
    //   2101: istore #6
    //   2103: goto -> 2109
    //   2106: iconst_0
    //   2107: istore #6
    //   2109: aload #8
    //   2111: iconst_4
    //   2112: iload #6
    //   2114: iconst_0
    //   2115: aload_1
    //   2116: invokevirtual obtainMessage : (IIILjava/lang/Object;)Landroid/os/Message;
    //   2119: invokevirtual sendToTarget : ()V
    //   2122: goto -> 2202
    //   2125: aload_0
    //   2126: iload #7
    //   2128: lload_3
    //   2129: invokespecial s : (IJ)J
    //   2132: lstore #14
    //   2134: lload_3
    //   2135: lload #14
    //   2137: lcmp
    //   2138: ifeq -> 2146
    //   2141: iconst_1
    //   2142: istore_2
    //   2143: goto -> 2148
    //   2146: iconst_0
    //   2147: istore_2
    //   2148: new com/google/android/gms/internal/ads/ic2
    //   2151: astore #8
    //   2153: aload #8
    //   2155: iload #7
    //   2157: lload #14
    //   2159: invokespecial <init> : (IJ)V
    //   2162: aload_0
    //   2163: aload #8
    //   2165: putfield m : Lcom/google/android/gms/internal/ads/ic2;
    //   2168: aload_0
    //   2169: getfield i : Landroid/os/Handler;
    //   2172: astore_1
    //   2173: iload #6
    //   2175: iload_2
    //   2176: ior
    //   2177: ifeq -> 2186
    //   2180: iconst_1
    //   2181: istore #6
    //   2183: goto -> 2189
    //   2186: iconst_0
    //   2187: istore #6
    //   2189: aload_1
    //   2190: iconst_4
    //   2191: iload #6
    //   2193: iconst_0
    //   2194: aload #8
    //   2196: invokevirtual obtainMessage : (IIILjava/lang/Object;)Landroid/os/Message;
    //   2199: invokevirtual sendToTarget : ()V
    //   2202: iconst_1
    //   2203: ireturn
    //   2204: astore #9
    //   2206: new com/google/android/gms/internal/ads/ic2
    //   2209: astore_1
    //   2210: aload_1
    //   2211: iload #7
    //   2213: lload_3
    //   2214: invokespecial <init> : (IJ)V
    //   2217: aload_0
    //   2218: aload_1
    //   2219: putfield m : Lcom/google/android/gms/internal/ads/ic2;
    //   2222: aload_0
    //   2223: getfield i : Landroid/os/Handler;
    //   2226: astore #8
    //   2228: iload #6
    //   2230: ifeq -> 2239
    //   2233: iconst_1
    //   2234: istore #6
    //   2236: goto -> 2242
    //   2239: iconst_0
    //   2240: istore #6
    //   2242: aload #8
    //   2244: iconst_4
    //   2245: iload #6
    //   2247: iconst_0
    //   2248: aload_1
    //   2249: invokevirtual obtainMessage : (IIILjava/lang/Object;)Landroid/os/Message;
    //   2252: invokevirtual sendToTarget : ()V
    //   2255: aload #9
    //   2257: athrow
    //   2258: invokestatic elapsedRealtime : ()J
    //   2261: lstore #16
    //   2263: aload_0
    //   2264: getfield H : Lcom/google/android/gms/internal/ads/vc2;
    //   2267: ifnonnull -> 2282
    //   2270: aload_0
    //   2271: getfield q : Lcom/google/android/gms/internal/ads/mh2;
    //   2274: invokeinterface c : ()V
    //   2279: goto -> 3287
    //   2282: aload_0
    //   2283: getfield E : Lcom/google/android/gms/internal/ads/jc2;
    //   2286: astore_1
    //   2287: aload_1
    //   2288: ifnonnull -> 2303
    //   2291: aload_0
    //   2292: getfield m : Lcom/google/android/gms/internal/ads/ic2;
    //   2295: getfield a : I
    //   2298: istore #6
    //   2300: goto -> 2399
    //   2303: aload_1
    //   2304: getfield g : I
    //   2307: istore #6
    //   2309: aload_1
    //   2310: getfield i : Z
    //   2313: ifne -> 2420
    //   2316: aload_1
    //   2317: invokevirtual f : ()Z
    //   2320: ifeq -> 2420
    //   2323: aload_0
    //   2324: getfield H : Lcom/google/android/gms/internal/ads/vc2;
    //   2327: iload #6
    //   2329: aload_0
    //   2330: getfield l : Lcom/google/android/gms/internal/ads/xc2;
    //   2333: iconst_0
    //   2334: invokevirtual e : (ILcom/google/android/gms/internal/ads/xc2;Z)Lcom/google/android/gms/internal/ads/xc2;
    //   2337: getfield d : J
    //   2340: ldc2_w -9223372036854775807
    //   2343: lcmp
    //   2344: ifne -> 2350
    //   2347: goto -> 2420
    //   2350: aload_0
    //   2351: getfield G : Lcom/google/android/gms/internal/ads/jc2;
    //   2354: astore_1
    //   2355: aload_1
    //   2356: ifnull -> 2376
    //   2359: aload_0
    //   2360: getfield E : Lcom/google/android/gms/internal/ads/jc2;
    //   2363: getfield c : I
    //   2366: aload_1
    //   2367: getfield c : I
    //   2370: isub
    //   2371: bipush #100
    //   2373: if_icmpeq -> 2420
    //   2376: aload_0
    //   2377: getfield H : Lcom/google/android/gms/internal/ads/vc2;
    //   2380: iload #6
    //   2382: aload_0
    //   2383: getfield l : Lcom/google/android/gms/internal/ads/xc2;
    //   2386: aload_0
    //   2387: getfield k : Lcom/google/android/gms/internal/ads/wc2;
    //   2390: aload_0
    //   2391: getfield x : I
    //   2394: invokevirtual b : (ILcom/google/android/gms/internal/ads/xc2;Lcom/google/android/gms/internal/ads/wc2;I)I
    //   2397: istore #6
    //   2399: iload #6
    //   2401: aload_0
    //   2402: getfield H : Lcom/google/android/gms/internal/ads/vc2;
    //   2405: invokevirtual h : ()I
    //   2408: if_icmplt -> 2423
    //   2411: aload_0
    //   2412: getfield q : Lcom/google/android/gms/internal/ads/mh2;
    //   2415: invokeinterface c : ()V
    //   2420: goto -> 2745
    //   2423: aload_0
    //   2424: getfield E : Lcom/google/android/gms/internal/ads/jc2;
    //   2427: ifnonnull -> 2441
    //   2430: aload_0
    //   2431: getfield m : Lcom/google/android/gms/internal/ads/ic2;
    //   2434: getfield c : J
    //   2437: lstore_3
    //   2438: goto -> 2567
    //   2441: aload_0
    //   2442: getfield H : Lcom/google/android/gms/internal/ads/vc2;
    //   2445: iload #6
    //   2447: aload_0
    //   2448: getfield l : Lcom/google/android/gms/internal/ads/xc2;
    //   2451: iconst_0
    //   2452: invokevirtual e : (ILcom/google/android/gms/internal/ads/xc2;Z)Lcom/google/android/gms/internal/ads/xc2;
    //   2455: pop
    //   2456: aload_0
    //   2457: getfield H : Lcom/google/android/gms/internal/ads/vc2;
    //   2460: iconst_0
    //   2461: aload_0
    //   2462: getfield k : Lcom/google/android/gms/internal/ads/wc2;
    //   2465: iconst_0
    //   2466: invokevirtual c : (ILcom/google/android/gms/internal/ads/wc2;Z)Lcom/google/android/gms/internal/ads/wc2;
    //   2469: pop
    //   2470: iload #6
    //   2472: ifeq -> 2478
    //   2475: goto -> 2438
    //   2478: aload_0
    //   2479: getfield E : Lcom/google/android/gms/internal/ads/jc2;
    //   2482: invokevirtual e : ()J
    //   2485: lstore #18
    //   2487: aload_0
    //   2488: getfield H : Lcom/google/android/gms/internal/ads/vc2;
    //   2491: aload_0
    //   2492: getfield E : Lcom/google/android/gms/internal/ads/jc2;
    //   2495: getfield g : I
    //   2498: aload_0
    //   2499: getfield l : Lcom/google/android/gms/internal/ads/xc2;
    //   2502: iconst_0
    //   2503: invokevirtual e : (ILcom/google/android/gms/internal/ads/xc2;Z)Lcom/google/android/gms/internal/ads/xc2;
    //   2506: getfield d : J
    //   2509: lstore #14
    //   2511: aload_0
    //   2512: getfield D : J
    //   2515: lstore_3
    //   2516: aload_0
    //   2517: aload_0
    //   2518: getfield H : Lcom/google/android/gms/internal/ads/vc2;
    //   2521: iconst_0
    //   2522: ldc2_w -9223372036854775807
    //   2525: lconst_0
    //   2526: lload #18
    //   2528: lload #14
    //   2530: ladd
    //   2531: lload_3
    //   2532: lsub
    //   2533: invokestatic max : (JJ)J
    //   2536: invokespecial j : (Lcom/google/android/gms/internal/ads/vc2;IJJ)Landroid/util/Pair;
    //   2539: astore_1
    //   2540: aload_1
    //   2541: ifnull -> 2745
    //   2544: aload_1
    //   2545: getfield first : Ljava/lang/Object;
    //   2548: checkcast java/lang/Integer
    //   2551: invokevirtual intValue : ()I
    //   2554: istore #6
    //   2556: aload_1
    //   2557: getfield second : Ljava/lang/Object;
    //   2560: checkcast java/lang/Long
    //   2563: invokevirtual longValue : ()J
    //   2566: lstore_3
    //   2567: aload_0
    //   2568: getfield E : Lcom/google/android/gms/internal/ads/jc2;
    //   2571: astore_1
    //   2572: aload_1
    //   2573: ifnonnull -> 2586
    //   2576: ldc2_w 60000000
    //   2579: lload_3
    //   2580: ladd
    //   2581: lstore #14
    //   2583: goto -> 2618
    //   2586: aload_1
    //   2587: invokevirtual e : ()J
    //   2590: aload_0
    //   2591: getfield H : Lcom/google/android/gms/internal/ads/vc2;
    //   2594: aload_0
    //   2595: getfield E : Lcom/google/android/gms/internal/ads/jc2;
    //   2598: getfield g : I
    //   2601: aload_0
    //   2602: getfield l : Lcom/google/android/gms/internal/ads/xc2;
    //   2605: iconst_0
    //   2606: invokevirtual e : (ILcom/google/android/gms/internal/ads/xc2;Z)Lcom/google/android/gms/internal/ads/xc2;
    //   2609: getfield d : J
    //   2612: ladd
    //   2613: lstore #14
    //   2615: goto -> 2583
    //   2618: aload_0
    //   2619: getfield E : Lcom/google/android/gms/internal/ads/jc2;
    //   2622: astore_1
    //   2623: aload_1
    //   2624: ifnonnull -> 2632
    //   2627: iconst_0
    //   2628: istore_2
    //   2629: goto -> 2639
    //   2632: aload_1
    //   2633: getfield c : I
    //   2636: iconst_1
    //   2637: iadd
    //   2638: istore_2
    //   2639: aload_0
    //   2640: iload #6
    //   2642: invokespecial J : (I)Z
    //   2645: istore #10
    //   2647: aload_0
    //   2648: getfield H : Lcom/google/android/gms/internal/ads/vc2;
    //   2651: iload #6
    //   2653: aload_0
    //   2654: getfield l : Lcom/google/android/gms/internal/ads/xc2;
    //   2657: iconst_1
    //   2658: invokevirtual e : (ILcom/google/android/gms/internal/ads/xc2;Z)Lcom/google/android/gms/internal/ads/xc2;
    //   2661: pop
    //   2662: new com/google/android/gms/internal/ads/jc2
    //   2665: astore #8
    //   2667: aload #8
    //   2669: aload_0
    //   2670: getfield b : [Lcom/google/android/gms/internal/ads/pc2;
    //   2673: aload_0
    //   2674: getfield c : [Lcom/google/android/gms/internal/ads/tc2;
    //   2677: lload #14
    //   2679: aload_0
    //   2680: getfield d : Lcom/google/android/gms/internal/ads/ni2;
    //   2683: aload_0
    //   2684: getfield e : Lcom/google/android/gms/internal/ads/oc2;
    //   2687: aload_0
    //   2688: getfield q : Lcom/google/android/gms/internal/ads/mh2;
    //   2691: aload_0
    //   2692: getfield l : Lcom/google/android/gms/internal/ads/xc2;
    //   2695: getfield b : Ljava/lang/Object;
    //   2698: iload_2
    //   2699: iload #6
    //   2701: iload #10
    //   2703: lload_3
    //   2704: invokespecial <init> : ([Lcom/google/android/gms/internal/ads/pc2;[Lcom/google/android/gms/internal/ads/tc2;JLcom/google/android/gms/internal/ads/ni2;Lcom/google/android/gms/internal/ads/oc2;Lcom/google/android/gms/internal/ads/mh2;Ljava/lang/Object;IIZJ)V
    //   2707: aload_0
    //   2708: getfield E : Lcom/google/android/gms/internal/ads/jc2;
    //   2711: astore_1
    //   2712: aload_1
    //   2713: ifnull -> 2722
    //   2716: aload_1
    //   2717: aload #8
    //   2719: putfield l : Lcom/google/android/gms/internal/ads/jc2;
    //   2722: aload_0
    //   2723: aload #8
    //   2725: putfield E : Lcom/google/android/gms/internal/ads/jc2;
    //   2728: aload #8
    //   2730: getfield a : Lcom/google/android/gms/internal/ads/kh2;
    //   2733: aload_0
    //   2734: lload_3
    //   2735: invokeinterface k : (Lcom/google/android/gms/internal/ads/jh2;J)V
    //   2740: aload_0
    //   2741: iconst_1
    //   2742: invokespecial H : (Z)V
    //   2745: aload_0
    //   2746: getfield E : Lcom/google/android/gms/internal/ads/jc2;
    //   2749: astore_1
    //   2750: aload_1
    //   2751: ifnull -> 2785
    //   2754: aload_1
    //   2755: invokevirtual f : ()Z
    //   2758: ifeq -> 2764
    //   2761: goto -> 2785
    //   2764: aload_0
    //   2765: getfield E : Lcom/google/android/gms/internal/ads/jc2;
    //   2768: ifnull -> 2790
    //   2771: aload_0
    //   2772: getfield v : Z
    //   2775: ifne -> 2790
    //   2778: aload_0
    //   2779: invokespecial F : ()V
    //   2782: goto -> 2790
    //   2785: aload_0
    //   2786: iconst_0
    //   2787: invokespecial H : (Z)V
    //   2790: aload_0
    //   2791: getfield G : Lcom/google/android/gms/internal/ads/jc2;
    //   2794: ifnull -> 3287
    //   2797: aload_0
    //   2798: getfield G : Lcom/google/android/gms/internal/ads/jc2;
    //   2801: astore #8
    //   2803: aload_0
    //   2804: getfield F : Lcom/google/android/gms/internal/ads/jc2;
    //   2807: astore_1
    //   2808: aload #8
    //   2810: aload_1
    //   2811: if_acmpeq -> 2897
    //   2814: aload_0
    //   2815: getfield D : J
    //   2818: aload #8
    //   2820: getfield l : Lcom/google/android/gms/internal/ads/jc2;
    //   2823: getfield f : J
    //   2826: lcmp
    //   2827: iflt -> 2897
    //   2830: aload #8
    //   2832: invokevirtual a : ()V
    //   2835: aload_0
    //   2836: aload_0
    //   2837: getfield G : Lcom/google/android/gms/internal/ads/jc2;
    //   2840: getfield l : Lcom/google/android/gms/internal/ads/jc2;
    //   2843: invokespecial u : (Lcom/google/android/gms/internal/ads/jc2;)V
    //   2846: new com/google/android/gms/internal/ads/ic2
    //   2849: astore #8
    //   2851: aload_0
    //   2852: getfield G : Lcom/google/android/gms/internal/ads/jc2;
    //   2855: astore_1
    //   2856: aload #8
    //   2858: aload_1
    //   2859: getfield g : I
    //   2862: aload_1
    //   2863: getfield h : J
    //   2866: invokespecial <init> : (IJ)V
    //   2869: aload_0
    //   2870: aload #8
    //   2872: putfield m : Lcom/google/android/gms/internal/ads/ic2;
    //   2875: aload_0
    //   2876: invokespecial C : ()V
    //   2879: aload_0
    //   2880: getfield i : Landroid/os/Handler;
    //   2883: iconst_5
    //   2884: aload_0
    //   2885: getfield m : Lcom/google/android/gms/internal/ads/ic2;
    //   2888: invokevirtual obtainMessage : (ILjava/lang/Object;)Landroid/os/Message;
    //   2891: invokevirtual sendToTarget : ()V
    //   2894: goto -> 2797
    //   2897: aload_1
    //   2898: getfield i : Z
    //   2901: ifeq -> 2974
    //   2904: iconst_0
    //   2905: istore #6
    //   2907: aload_0
    //   2908: getfield b : [Lcom/google/android/gms/internal/ads/pc2;
    //   2911: astore_1
    //   2912: iload #6
    //   2914: aload_1
    //   2915: arraylength
    //   2916: if_icmpge -> 3287
    //   2919: aload_1
    //   2920: iload #6
    //   2922: aaload
    //   2923: astore #8
    //   2925: aload_0
    //   2926: getfield F : Lcom/google/android/gms/internal/ads/jc2;
    //   2929: getfield d : [Lcom/google/android/gms/internal/ads/uh2;
    //   2932: iload #6
    //   2934: aaload
    //   2935: astore_1
    //   2936: aload_1
    //   2937: ifnull -> 2968
    //   2940: aload #8
    //   2942: invokeinterface j : ()Lcom/google/android/gms/internal/ads/uh2;
    //   2947: aload_1
    //   2948: if_acmpne -> 2968
    //   2951: aload #8
    //   2953: invokeinterface c : ()Z
    //   2958: ifeq -> 2968
    //   2961: aload #8
    //   2963: invokeinterface e : ()V
    //   2968: iinc #6, 1
    //   2971: goto -> 2907
    //   2974: iconst_0
    //   2975: istore #6
    //   2977: aload_0
    //   2978: getfield b : [Lcom/google/android/gms/internal/ads/pc2;
    //   2981: astore_1
    //   2982: iload #6
    //   2984: aload_1
    //   2985: arraylength
    //   2986: if_icmpge -> 3040
    //   2989: aload_1
    //   2990: iload #6
    //   2992: aaload
    //   2993: astore #8
    //   2995: aload_0
    //   2996: getfield F : Lcom/google/android/gms/internal/ads/jc2;
    //   2999: getfield d : [Lcom/google/android/gms/internal/ads/uh2;
    //   3002: iload #6
    //   3004: aaload
    //   3005: astore_1
    //   3006: aload #8
    //   3008: invokeinterface j : ()Lcom/google/android/gms/internal/ads/uh2;
    //   3013: aload_1
    //   3014: if_acmpne -> 3287
    //   3017: aload_1
    //   3018: ifnull -> 3034
    //   3021: aload #8
    //   3023: invokeinterface c : ()Z
    //   3028: ifne -> 3034
    //   3031: goto -> 3287
    //   3034: iinc #6, 1
    //   3037: goto -> 2977
    //   3040: aload_0
    //   3041: getfield F : Lcom/google/android/gms/internal/ads/jc2;
    //   3044: astore_1
    //   3045: aload_1
    //   3046: getfield l : Lcom/google/android/gms/internal/ads/jc2;
    //   3049: astore #9
    //   3051: aload #9
    //   3053: ifnull -> 3287
    //   3056: aload #9
    //   3058: getfield j : Z
    //   3061: ifeq -> 3287
    //   3064: aload_1
    //   3065: getfield m : Lcom/google/android/gms/internal/ads/pi2;
    //   3068: astore #8
    //   3070: aload_0
    //   3071: aload #9
    //   3073: putfield F : Lcom/google/android/gms/internal/ads/jc2;
    //   3076: aload #9
    //   3078: getfield m : Lcom/google/android/gms/internal/ads/pi2;
    //   3081: astore_1
    //   3082: aload #9
    //   3084: getfield a : Lcom/google/android/gms/internal/ads/kh2;
    //   3087: invokeinterface n : ()J
    //   3092: ldc2_w -9223372036854775807
    //   3095: lcmp
    //   3096: ifeq -> 3105
    //   3099: iconst_1
    //   3100: istore #6
    //   3102: goto -> 3108
    //   3105: iconst_0
    //   3106: istore #6
    //   3108: iconst_0
    //   3109: istore_2
    //   3110: aload_0
    //   3111: getfield b : [Lcom/google/android/gms/internal/ads/pc2;
    //   3114: astore #9
    //   3116: iload_2
    //   3117: aload #9
    //   3119: arraylength
    //   3120: if_icmpge -> 3287
    //   3123: aload #9
    //   3125: iload_2
    //   3126: aaload
    //   3127: astore #9
    //   3129: aload #8
    //   3131: getfield b : Lcom/google/android/gms/internal/ads/oi2;
    //   3134: iload_2
    //   3135: invokevirtual a : (I)Lcom/google/android/gms/internal/ads/mi2;
    //   3138: ifnull -> 3281
    //   3141: iload #6
    //   3143: ifne -> 3274
    //   3146: aload #9
    //   3148: invokeinterface u : ()Z
    //   3153: ifne -> 3281
    //   3156: aload_1
    //   3157: getfield b : Lcom/google/android/gms/internal/ads/oi2;
    //   3160: iload_2
    //   3161: invokevirtual a : (I)Lcom/google/android/gms/internal/ads/mi2;
    //   3164: astore #11
    //   3166: aload #8
    //   3168: getfield d : [Lcom/google/android/gms/internal/ads/sc2;
    //   3171: iload_2
    //   3172: aaload
    //   3173: astore #12
    //   3175: aload_1
    //   3176: getfield d : [Lcom/google/android/gms/internal/ads/sc2;
    //   3179: iload_2
    //   3180: aaload
    //   3181: astore #20
    //   3183: aload #11
    //   3185: ifnull -> 3274
    //   3188: aload #20
    //   3190: aload #12
    //   3192: invokevirtual equals : (Ljava/lang/Object;)Z
    //   3195: ifeq -> 3274
    //   3198: aload #11
    //   3200: invokeinterface length : ()I
    //   3205: istore #13
    //   3207: iload #13
    //   3209: anewarray com/google/android/gms/internal/ads/zzht
    //   3212: astore #12
    //   3214: iconst_0
    //   3215: istore #7
    //   3217: iload #7
    //   3219: iload #13
    //   3221: if_icmpge -> 3244
    //   3224: aload #12
    //   3226: iload #7
    //   3228: aload #11
    //   3230: iload #7
    //   3232: invokeinterface c : (I)Lcom/google/android/gms/internal/ads/zzht;
    //   3237: aastore
    //   3238: iinc #7, 1
    //   3241: goto -> 3217
    //   3244: aload_0
    //   3245: getfield F : Lcom/google/android/gms/internal/ads/jc2;
    //   3248: astore #11
    //   3250: aload #9
    //   3252: aload #12
    //   3254: aload #11
    //   3256: getfield d : [Lcom/google/android/gms/internal/ads/uh2;
    //   3259: iload_2
    //   3260: aaload
    //   3261: aload #11
    //   3263: invokevirtual e : ()J
    //   3266: invokeinterface f : ([Lcom/google/android/gms/internal/ads/zzht;Lcom/google/android/gms/internal/ads/uh2;J)V
    //   3271: goto -> 3281
    //   3274: aload #9
    //   3276: invokeinterface e : ()V
    //   3281: iinc #2, 1
    //   3284: goto -> 3110
    //   3287: aload_0
    //   3288: getfield G : Lcom/google/android/gms/internal/ads/jc2;
    //   3291: ifnonnull -> 3310
    //   3294: aload_0
    //   3295: invokespecial E : ()V
    //   3298: aload_0
    //   3299: lload #16
    //   3301: ldc2_w 10
    //   3304: invokespecial k : (JJ)V
    //   3307: goto -> 3956
    //   3310: ldc_w 'doSomeWork'
    //   3313: invokestatic a : (Ljava/lang/String;)V
    //   3316: aload_0
    //   3317: invokespecial C : ()V
    //   3320: aload_0
    //   3321: getfield G : Lcom/google/android/gms/internal/ads/jc2;
    //   3324: getfield a : Lcom/google/android/gms/internal/ads/kh2;
    //   3327: aload_0
    //   3328: getfield m : Lcom/google/android/gms/internal/ads/ic2;
    //   3331: getfield c : J
    //   3334: invokeinterface f : (J)V
    //   3339: aload_0
    //   3340: getfield r : [Lcom/google/android/gms/internal/ads/pc2;
    //   3343: astore_1
    //   3344: aload_1
    //   3345: arraylength
    //   3346: istore #13
    //   3348: iconst_0
    //   3349: istore_2
    //   3350: iconst_1
    //   3351: istore #10
    //   3353: iconst_1
    //   3354: istore #6
    //   3356: iload_2
    //   3357: iload #13
    //   3359: if_icmpge -> 3475
    //   3362: aload_1
    //   3363: iload_2
    //   3364: aaload
    //   3365: astore #8
    //   3367: aload #8
    //   3369: aload_0
    //   3370: getfield D : J
    //   3373: aload_0
    //   3374: getfield A : J
    //   3377: invokeinterface h : (JJ)V
    //   3382: iload #6
    //   3384: ifeq -> 3403
    //   3387: aload #8
    //   3389: invokeinterface b : ()Z
    //   3394: ifeq -> 3403
    //   3397: iconst_1
    //   3398: istore #6
    //   3400: goto -> 3406
    //   3403: iconst_0
    //   3404: istore #6
    //   3406: aload #8
    //   3408: invokeinterface m : ()Z
    //   3413: ifne -> 3435
    //   3416: aload #8
    //   3418: invokeinterface b : ()Z
    //   3423: ifeq -> 3429
    //   3426: goto -> 3435
    //   3429: iconst_0
    //   3430: istore #7
    //   3432: goto -> 3438
    //   3435: iconst_1
    //   3436: istore #7
    //   3438: iload #7
    //   3440: ifne -> 3450
    //   3443: aload #8
    //   3445: invokeinterface v : ()V
    //   3450: iload #10
    //   3452: ifeq -> 3466
    //   3455: iload #7
    //   3457: ifeq -> 3466
    //   3460: iconst_1
    //   3461: istore #10
    //   3463: goto -> 3469
    //   3466: iconst_0
    //   3467: istore #10
    //   3469: iinc #2, 1
    //   3472: goto -> 3356
    //   3475: iload #10
    //   3477: ifne -> 3484
    //   3480: aload_0
    //   3481: invokespecial E : ()V
    //   3484: aload_0
    //   3485: getfield p : Lcom/google/android/gms/internal/ads/nj2;
    //   3488: astore_1
    //   3489: aload_1
    //   3490: ifnull -> 3540
    //   3493: aload_1
    //   3494: invokeinterface l : ()Lcom/google/android/gms/internal/ads/qc2;
    //   3499: astore_1
    //   3500: aload_1
    //   3501: aload_0
    //   3502: getfield n : Lcom/google/android/gms/internal/ads/qc2;
    //   3505: invokevirtual equals : (Ljava/lang/Object;)Z
    //   3508: ifne -> 3540
    //   3511: aload_0
    //   3512: aload_1
    //   3513: putfield n : Lcom/google/android/gms/internal/ads/qc2;
    //   3516: aload_0
    //   3517: getfield f : Lcom/google/android/gms/internal/ads/vj2;
    //   3520: aload_0
    //   3521: getfield p : Lcom/google/android/gms/internal/ads/nj2;
    //   3524: invokevirtual c : (Lcom/google/android/gms/internal/ads/nj2;)V
    //   3527: aload_0
    //   3528: getfield i : Landroid/os/Handler;
    //   3531: bipush #7
    //   3533: aload_1
    //   3534: invokevirtual obtainMessage : (ILjava/lang/Object;)Landroid/os/Message;
    //   3537: invokevirtual sendToTarget : ()V
    //   3540: aload_0
    //   3541: getfield H : Lcom/google/android/gms/internal/ads/vc2;
    //   3544: aload_0
    //   3545: getfield G : Lcom/google/android/gms/internal/ads/jc2;
    //   3548: getfield g : I
    //   3551: aload_0
    //   3552: getfield l : Lcom/google/android/gms/internal/ads/xc2;
    //   3555: iconst_0
    //   3556: invokevirtual e : (ILcom/google/android/gms/internal/ads/xc2;Z)Lcom/google/android/gms/internal/ads/xc2;
    //   3559: getfield d : J
    //   3562: lstore_3
    //   3563: iload #6
    //   3565: ifeq -> 3610
    //   3568: lload_3
    //   3569: ldc2_w -9223372036854775807
    //   3572: lcmp
    //   3573: ifeq -> 3588
    //   3576: lload_3
    //   3577: aload_0
    //   3578: getfield m : Lcom/google/android/gms/internal/ads/ic2;
    //   3581: getfield c : J
    //   3584: lcmp
    //   3585: ifgt -> 3610
    //   3588: aload_0
    //   3589: getfield G : Lcom/google/android/gms/internal/ads/jc2;
    //   3592: getfield i : Z
    //   3595: ifeq -> 3610
    //   3598: aload_0
    //   3599: iconst_4
    //   3600: invokespecial f : (I)V
    //   3603: aload_0
    //   3604: invokespecial B : ()V
    //   3607: goto -> 3849
    //   3610: aload_0
    //   3611: getfield w : I
    //   3614: istore #6
    //   3616: iload #6
    //   3618: iconst_2
    //   3619: if_icmpne -> 3803
    //   3622: aload_0
    //   3623: getfield r : [Lcom/google/android/gms/internal/ads/pc2;
    //   3626: arraylength
    //   3627: ifle -> 3772
    //   3630: iload #10
    //   3632: ifeq -> 3766
    //   3635: aload_0
    //   3636: getfield u : Z
    //   3639: istore #10
    //   3641: aload_0
    //   3642: getfield E : Lcom/google/android/gms/internal/ads/jc2;
    //   3645: astore_1
    //   3646: aload_1
    //   3647: getfield j : Z
    //   3650: ifne -> 3661
    //   3653: aload_1
    //   3654: getfield h : J
    //   3657: lstore_3
    //   3658: goto -> 3671
    //   3661: aload_1
    //   3662: getfield a : Lcom/google/android/gms/internal/ads/kh2;
    //   3665: invokeinterface h : ()J
    //   3670: lstore_3
    //   3671: lload_3
    //   3672: lstore #14
    //   3674: lload_3
    //   3675: ldc2_w -9223372036854775808
    //   3678: lcmp
    //   3679: ifne -> 3721
    //   3682: aload_0
    //   3683: getfield E : Lcom/google/android/gms/internal/ads/jc2;
    //   3686: astore_1
    //   3687: aload_1
    //   3688: getfield i : Z
    //   3691: ifeq -> 3700
    //   3694: iconst_1
    //   3695: istore #10
    //   3697: goto -> 3755
    //   3700: aload_0
    //   3701: getfield H : Lcom/google/android/gms/internal/ads/vc2;
    //   3704: aload_1
    //   3705: getfield g : I
    //   3708: aload_0
    //   3709: getfield l : Lcom/google/android/gms/internal/ads/xc2;
    //   3712: iconst_0
    //   3713: invokevirtual e : (ILcom/google/android/gms/internal/ads/xc2;Z)Lcom/google/android/gms/internal/ads/xc2;
    //   3716: getfield d : J
    //   3719: lstore #14
    //   3721: aload_0
    //   3722: getfield e : Lcom/google/android/gms/internal/ads/oc2;
    //   3725: astore #8
    //   3727: aload_0
    //   3728: getfield E : Lcom/google/android/gms/internal/ads/jc2;
    //   3731: astore_1
    //   3732: aload #8
    //   3734: lload #14
    //   3736: aload_0
    //   3737: getfield D : J
    //   3740: aload_1
    //   3741: invokevirtual e : ()J
    //   3744: lsub
    //   3745: lsub
    //   3746: iload #10
    //   3748: invokeinterface g : (JZ)Z
    //   3753: istore #10
    //   3755: iload #10
    //   3757: ifeq -> 3766
    //   3760: iconst_1
    //   3761: istore #10
    //   3763: goto -> 3779
    //   3766: iconst_0
    //   3767: istore #10
    //   3769: goto -> 3779
    //   3772: aload_0
    //   3773: lload_3
    //   3774: invokespecial z : (J)Z
    //   3777: istore #10
    //   3779: iload #10
    //   3781: ifeq -> 3849
    //   3784: aload_0
    //   3785: iconst_3
    //   3786: invokespecial f : (I)V
    //   3789: aload_0
    //   3790: getfield t : Z
    //   3793: ifeq -> 3849
    //   3796: aload_0
    //   3797: invokespecial A : ()V
    //   3800: goto -> 3849
    //   3803: iload #6
    //   3805: iconst_3
    //   3806: if_icmpne -> 3849
    //   3809: aload_0
    //   3810: getfield r : [Lcom/google/android/gms/internal/ads/pc2;
    //   3813: arraylength
    //   3814: ifle -> 3820
    //   3817: goto -> 3827
    //   3820: aload_0
    //   3821: lload_3
    //   3822: invokespecial z : (J)Z
    //   3825: istore #10
    //   3827: iload #10
    //   3829: ifne -> 3849
    //   3832: aload_0
    //   3833: aload_0
    //   3834: getfield t : Z
    //   3837: putfield u : Z
    //   3840: aload_0
    //   3841: iconst_2
    //   3842: invokespecial f : (I)V
    //   3845: aload_0
    //   3846: invokespecial B : ()V
    //   3849: aload_0
    //   3850: getfield w : I
    //   3853: iconst_2
    //   3854: if_icmpne -> 3890
    //   3857: aload_0
    //   3858: getfield r : [Lcom/google/android/gms/internal/ads/pc2;
    //   3861: astore_1
    //   3862: aload_1
    //   3863: arraylength
    //   3864: istore_2
    //   3865: iload #5
    //   3867: istore #6
    //   3869: iload #6
    //   3871: iload_2
    //   3872: if_icmpge -> 3890
    //   3875: aload_1
    //   3876: iload #6
    //   3878: aaload
    //   3879: invokeinterface v : ()V
    //   3884: iinc #6, 1
    //   3887: goto -> 3869
    //   3890: aload_0
    //   3891: getfield t : Z
    //   3894: ifeq -> 3905
    //   3897: aload_0
    //   3898: getfield w : I
    //   3901: iconst_3
    //   3902: if_icmpeq -> 3913
    //   3905: aload_0
    //   3906: getfield w : I
    //   3909: iconst_2
    //   3910: if_icmpne -> 3925
    //   3913: aload_0
    //   3914: lload #16
    //   3916: ldc2_w 10
    //   3919: invokespecial k : (JJ)V
    //   3922: goto -> 3953
    //   3925: aload_0
    //   3926: getfield r : [Lcom/google/android/gms/internal/ads/pc2;
    //   3929: arraylength
    //   3930: ifeq -> 3945
    //   3933: aload_0
    //   3934: lload #16
    //   3936: ldc2_w 1000
    //   3939: invokespecial k : (JJ)V
    //   3942: goto -> 3953
    //   3945: aload_0
    //   3946: getfield g : Landroid/os/Handler;
    //   3949: iconst_2
    //   3950: invokevirtual removeMessages : (I)V
    //   3953: invokestatic b : ()V
    //   3956: iconst_1
    //   3957: ireturn
    //   3958: aload_1
    //   3959: getfield arg1 : I
    //   3962: ifeq -> 3971
    //   3965: iconst_1
    //   3966: istore #10
    //   3968: goto -> 3974
    //   3971: iconst_0
    //   3972: istore #10
    //   3974: aload_0
    //   3975: iconst_0
    //   3976: putfield u : Z
    //   3979: aload_0
    //   3980: iload #10
    //   3982: putfield t : Z
    //   3985: iload #10
    //   3987: ifne -> 4001
    //   3990: aload_0
    //   3991: invokespecial B : ()V
    //   3994: aload_0
    //   3995: invokespecial C : ()V
    //   3998: goto -> 4044
    //   4001: aload_0
    //   4002: getfield w : I
    //   4005: istore #6
    //   4007: iload #6
    //   4009: iconst_3
    //   4010: if_icmpne -> 4029
    //   4013: aload_0
    //   4014: invokespecial A : ()V
    //   4017: aload_0
    //   4018: getfield g : Landroid/os/Handler;
    //   4021: iconst_2
    //   4022: invokevirtual sendEmptyMessage : (I)Z
    //   4025: pop
    //   4026: goto -> 4044
    //   4029: iload #6
    //   4031: iconst_2
    //   4032: if_icmpne -> 4044
    //   4035: aload_0
    //   4036: getfield g : Landroid/os/Handler;
    //   4039: iconst_2
    //   4040: invokevirtual sendEmptyMessage : (I)Z
    //   4043: pop
    //   4044: iconst_1
    //   4045: ireturn
    //   4046: aload_1
    //   4047: getfield obj : Ljava/lang/Object;
    //   4050: checkcast com/google/android/gms/internal/ads/mh2
    //   4053: astore #8
    //   4055: aload_1
    //   4056: getfield arg1 : I
    //   4059: ifeq -> 4068
    //   4062: iconst_1
    //   4063: istore #6
    //   4065: goto -> 4071
    //   4068: iconst_0
    //   4069: istore #6
    //   4071: aload_0
    //   4072: getfield i : Landroid/os/Handler;
    //   4075: iconst_0
    //   4076: invokevirtual sendEmptyMessage : (I)Z
    //   4079: pop
    //   4080: aload_0
    //   4081: iconst_1
    //   4082: invokespecial I : (Z)V
    //   4085: aload_0
    //   4086: getfield e : Lcom/google/android/gms/internal/ads/oc2;
    //   4089: invokeinterface a : ()V
    //   4094: iload #6
    //   4096: ifeq -> 4116
    //   4099: new com/google/android/gms/internal/ads/ic2
    //   4102: astore_1
    //   4103: aload_1
    //   4104: iconst_0
    //   4105: ldc2_w -9223372036854775807
    //   4108: invokespecial <init> : (IJ)V
    //   4111: aload_0
    //   4112: aload_1
    //   4113: putfield m : Lcom/google/android/gms/internal/ads/ic2;
    //   4116: aload_0
    //   4117: aload #8
    //   4119: putfield q : Lcom/google/android/gms/internal/ads/mh2;
    //   4122: aload #8
    //   4124: aload_0
    //   4125: getfield j : Lcom/google/android/gms/internal/ads/bc2;
    //   4128: iconst_1
    //   4129: aload_0
    //   4130: invokeinterface e : (Lcom/google/android/gms/internal/ads/bc2;ZLcom/google/android/gms/internal/ads/lh2;)V
    //   4135: aload_0
    //   4136: iconst_2
    //   4137: invokespecial f : (I)V
    //   4140: aload_0
    //   4141: getfield g : Landroid/os/Handler;
    //   4144: iconst_2
    //   4145: invokevirtual sendEmptyMessage : (I)Z
    //   4148: pop
    //   4149: iconst_1
    //   4150: ireturn
    //   4151: astore_1
    //   4152: goto -> 4194
    //   4155: astore_1
    //   4156: goto -> 4228
    //   4159: astore_1
    //   4160: ldc_w 'ExoPlayerImplInternal'
    //   4163: ldc_w 'Internal runtime error.'
    //   4166: aload_1
    //   4167: invokestatic e : (Ljava/lang/String;Ljava/lang/String;Ljava/lang/Throwable;)I
    //   4170: pop
    //   4171: aload_0
    //   4172: getfield i : Landroid/os/Handler;
    //   4175: bipush #8
    //   4177: aload_1
    //   4178: invokestatic zza : (Ljava/lang/RuntimeException;)Lcom/google/android/gms/internal/ads/zzhe;
    //   4181: invokevirtual obtainMessage : (ILjava/lang/Object;)Landroid/os/Message;
    //   4184: invokevirtual sendToTarget : ()V
    //   4187: aload_0
    //   4188: invokespecial D : ()V
    //   4191: iconst_1
    //   4192: ireturn
    //   4193: astore_1
    //   4194: ldc_w 'ExoPlayerImplInternal'
    //   4197: ldc_w 'Source error.'
    //   4200: aload_1
    //   4201: invokestatic e : (Ljava/lang/String;Ljava/lang/String;Ljava/lang/Throwable;)I
    //   4204: pop
    //   4205: aload_0
    //   4206: getfield i : Landroid/os/Handler;
    //   4209: bipush #8
    //   4211: aload_1
    //   4212: invokestatic zza : (Ljava/io/IOException;)Lcom/google/android/gms/internal/ads/zzhe;
    //   4215: invokevirtual obtainMessage : (ILjava/lang/Object;)Landroid/os/Message;
    //   4218: invokevirtual sendToTarget : ()V
    //   4221: aload_0
    //   4222: invokespecial D : ()V
    //   4225: iconst_1
    //   4226: ireturn
    //   4227: astore_1
    //   4228: ldc_w 'ExoPlayerImplInternal'
    //   4231: ldc_w 'Renderer error.'
    //   4234: aload_1
    //   4235: invokestatic e : (Ljava/lang/String;Ljava/lang/String;Ljava/lang/Throwable;)I
    //   4238: pop
    //   4239: aload_0
    //   4240: getfield i : Landroid/os/Handler;
    //   4243: bipush #8
    //   4245: aload_1
    //   4246: invokevirtual obtainMessage : (ILjava/lang/Object;)Landroid/os/Message;
    //   4249: invokevirtual sendToTarget : ()V
    //   4252: aload_0
    //   4253: invokespecial D : ()V
    //   4256: iconst_1
    //   4257: ireturn
    // Exception table:
    //   from	to	target	type
    //   0	5	4227	com/google/android/gms/internal/ads/zzhe
    //   0	5	4193	java/io/IOException
    //   0	5	4159	java/lang/RuntimeException
    //   82	99	4155	com/google/android/gms/internal/ads/zzhe
    //   82	99	4151	java/io/IOException
    //   82	99	4159	java/lang/RuntimeException
    //   106	111	4155	com/google/android/gms/internal/ads/zzhe
    //   106	111	4151	java/io/IOException
    //   106	111	4159	java/lang/RuntimeException
    //   115	123	4155	com/google/android/gms/internal/ads/zzhe
    //   115	123	4151	java/io/IOException
    //   115	123	4159	java/lang/RuntimeException
    //   130	138	4155	com/google/android/gms/internal/ads/zzhe
    //   130	138	4151	java/io/IOException
    //   130	138	4159	java/lang/RuntimeException
    //   147	176	4155	com/google/android/gms/internal/ads/zzhe
    //   147	176	4151	java/io/IOException
    //   147	176	4159	java/lang/RuntimeException
    //   187	206	4155	com/google/android/gms/internal/ads/zzhe
    //   187	206	4151	java/io/IOException
    //   187	206	4159	java/lang/RuntimeException
    //   221	230	4155	com/google/android/gms/internal/ads/zzhe
    //   221	230	4151	java/io/IOException
    //   221	230	4159	java/lang/RuntimeException
    //   257	267	4155	com/google/android/gms/internal/ads/zzhe
    //   257	267	4151	java/io/IOException
    //   257	267	4159	java/lang/RuntimeException
    //   267	279	4155	com/google/android/gms/internal/ads/zzhe
    //   267	279	4151	java/io/IOException
    //   267	279	4159	java/lang/RuntimeException
    //   284	289	4155	com/google/android/gms/internal/ads/zzhe
    //   284	289	4151	java/io/IOException
    //   284	289	4159	java/lang/RuntimeException
    //   293	298	4155	com/google/android/gms/internal/ads/zzhe
    //   293	298	4151	java/io/IOException
    //   293	298	4159	java/lang/RuntimeException
    //   302	338	4155	com/google/android/gms/internal/ads/zzhe
    //   302	338	4151	java/io/IOException
    //   302	338	4159	java/lang/RuntimeException
    //   338	346	4155	com/google/android/gms/internal/ads/zzhe
    //   338	346	4151	java/io/IOException
    //   338	346	4159	java/lang/RuntimeException
    //   351	356	4155	com/google/android/gms/internal/ads/zzhe
    //   351	356	4151	java/io/IOException
    //   351	356	4159	java/lang/RuntimeException
    //   358	367	4155	com/google/android/gms/internal/ads/zzhe
    //   358	367	4151	java/io/IOException
    //   358	367	4159	java/lang/RuntimeException
    //   367	371	447	finally
    //   383	400	447	finally
    //   406	422	447	finally
    //   422	424	4155	com/google/android/gms/internal/ads/zzhe
    //   422	424	4151	java/io/IOException
    //   422	424	4159	java/lang/RuntimeException
    //   424	440	442	finally
    //   443	445	442	finally
    //   445	447	4155	com/google/android/gms/internal/ads/zzhe
    //   445	447	4151	java/io/IOException
    //   445	447	4159	java/lang/RuntimeException
    //   448	450	4155	com/google/android/gms/internal/ads/zzhe
    //   448	450	4151	java/io/IOException
    //   448	450	4159	java/lang/RuntimeException
    //   450	466	468	finally
    //   466	468	4155	com/google/android/gms/internal/ads/zzhe
    //   466	468	4151	java/io/IOException
    //   466	468	4159	java/lang/RuntimeException
    //   469	471	468	finally
    //   471	473	4155	com/google/android/gms/internal/ads/zzhe
    //   471	473	4151	java/io/IOException
    //   471	473	4159	java/lang/RuntimeException
    //   473	478	4155	com/google/android/gms/internal/ads/zzhe
    //   473	478	4151	java/io/IOException
    //   473	478	4159	java/lang/RuntimeException
    //   489	496	4155	com/google/android/gms/internal/ads/zzhe
    //   489	496	4151	java/io/IOException
    //   489	496	4159	java/lang/RuntimeException
    //   499	506	4155	com/google/android/gms/internal/ads/zzhe
    //   499	506	4151	java/io/IOException
    //   499	506	4159	java/lang/RuntimeException
    //   506	514	4155	com/google/android/gms/internal/ads/zzhe
    //   506	514	4151	java/io/IOException
    //   506	514	4159	java/lang/RuntimeException
    //   517	522	4155	com/google/android/gms/internal/ads/zzhe
    //   517	522	4151	java/io/IOException
    //   517	522	4159	java/lang/RuntimeException
    //   530	542	4155	com/google/android/gms/internal/ads/zzhe
    //   530	542	4151	java/io/IOException
    //   530	542	4159	java/lang/RuntimeException
    //   558	641	4155	com/google/android/gms/internal/ads/zzhe
    //   558	641	4151	java/io/IOException
    //   558	641	4159	java/lang/RuntimeException
    //   641	650	4155	com/google/android/gms/internal/ads/zzhe
    //   641	650	4151	java/io/IOException
    //   641	650	4159	java/lang/RuntimeException
    //   655	669	4155	com/google/android/gms/internal/ads/zzhe
    //   655	669	4151	java/io/IOException
    //   655	669	4159	java/lang/RuntimeException
    //   676	686	4155	com/google/android/gms/internal/ads/zzhe
    //   676	686	4151	java/io/IOException
    //   676	686	4159	java/lang/RuntimeException
    //   702	714	4155	com/google/android/gms/internal/ads/zzhe
    //   702	714	4151	java/io/IOException
    //   702	714	4159	java/lang/RuntimeException
    //   735	756	4155	com/google/android/gms/internal/ads/zzhe
    //   735	756	4151	java/io/IOException
    //   735	756	4159	java/lang/RuntimeException
    //   761	772	4155	com/google/android/gms/internal/ads/zzhe
    //   761	772	4151	java/io/IOException
    //   761	772	4159	java/lang/RuntimeException
    //   772	782	4155	com/google/android/gms/internal/ads/zzhe
    //   772	782	4151	java/io/IOException
    //   772	782	4159	java/lang/RuntimeException
    //   782	794	4155	com/google/android/gms/internal/ads/zzhe
    //   782	794	4151	java/io/IOException
    //   782	794	4159	java/lang/RuntimeException
    //   805	816	4155	com/google/android/gms/internal/ads/zzhe
    //   805	816	4151	java/io/IOException
    //   805	816	4159	java/lang/RuntimeException
    //   825	847	4155	com/google/android/gms/internal/ads/zzhe
    //   825	847	4151	java/io/IOException
    //   825	847	4159	java/lang/RuntimeException
    //   850	860	4155	com/google/android/gms/internal/ads/zzhe
    //   850	860	4151	java/io/IOException
    //   850	860	4159	java/lang/RuntimeException
    //   864	873	4155	com/google/android/gms/internal/ads/zzhe
    //   864	873	4151	java/io/IOException
    //   864	873	4159	java/lang/RuntimeException
    //   876	920	4155	com/google/android/gms/internal/ads/zzhe
    //   876	920	4151	java/io/IOException
    //   876	920	4159	java/lang/RuntimeException
    //   920	937	4155	com/google/android/gms/internal/ads/zzhe
    //   920	937	4151	java/io/IOException
    //   920	937	4159	java/lang/RuntimeException
    //   939	953	4155	com/google/android/gms/internal/ads/zzhe
    //   939	953	4151	java/io/IOException
    //   939	953	4159	java/lang/RuntimeException
    //   958	967	4155	com/google/android/gms/internal/ads/zzhe
    //   958	967	4151	java/io/IOException
    //   958	967	4159	java/lang/RuntimeException
    //   970	974	4155	com/google/android/gms/internal/ads/zzhe
    //   970	974	4151	java/io/IOException
    //   970	974	4159	java/lang/RuntimeException
    //   976	990	4155	com/google/android/gms/internal/ads/zzhe
    //   976	990	4151	java/io/IOException
    //   976	990	4159	java/lang/RuntimeException
    //   994	1003	4155	com/google/android/gms/internal/ads/zzhe
    //   994	1003	4151	java/io/IOException
    //   994	1003	4159	java/lang/RuntimeException
    //   1006	1062	4155	com/google/android/gms/internal/ads/zzhe
    //   1006	1062	4151	java/io/IOException
    //   1006	1062	4159	java/lang/RuntimeException
    //   1062	1066	4155	com/google/android/gms/internal/ads/zzhe
    //   1062	1066	4151	java/io/IOException
    //   1062	1066	4159	java/lang/RuntimeException
    //   1068	1104	4155	com/google/android/gms/internal/ads/zzhe
    //   1068	1104	4151	java/io/IOException
    //   1068	1104	4159	java/lang/RuntimeException
    //   1109	1141	4155	com/google/android/gms/internal/ads/zzhe
    //   1109	1141	4151	java/io/IOException
    //   1109	1141	4159	java/lang/RuntimeException
    //   1146	1153	4155	com/google/android/gms/internal/ads/zzhe
    //   1146	1153	4151	java/io/IOException
    //   1146	1153	4159	java/lang/RuntimeException
    //   1156	1191	4155	com/google/android/gms/internal/ads/zzhe
    //   1156	1191	4151	java/io/IOException
    //   1156	1191	4159	java/lang/RuntimeException
    //   1194	1222	4155	com/google/android/gms/internal/ads/zzhe
    //   1194	1222	4151	java/io/IOException
    //   1194	1222	4159	java/lang/RuntimeException
    //   1225	1270	4155	com/google/android/gms/internal/ads/zzhe
    //   1225	1270	4151	java/io/IOException
    //   1225	1270	4159	java/lang/RuntimeException
    //   1272	1277	4155	com/google/android/gms/internal/ads/zzhe
    //   1272	1277	4151	java/io/IOException
    //   1272	1277	4159	java/lang/RuntimeException
    //   1284	1289	4155	com/google/android/gms/internal/ads/zzhe
    //   1284	1289	4151	java/io/IOException
    //   1284	1289	4159	java/lang/RuntimeException
    //   1293	1306	4155	com/google/android/gms/internal/ads/zzhe
    //   1293	1306	4151	java/io/IOException
    //   1293	1306	4159	java/lang/RuntimeException
    //   1312	1328	4155	com/google/android/gms/internal/ads/zzhe
    //   1312	1328	4151	java/io/IOException
    //   1312	1328	4159	java/lang/RuntimeException
    //   1334	1341	4155	com/google/android/gms/internal/ads/zzhe
    //   1334	1341	4151	java/io/IOException
    //   1334	1341	4159	java/lang/RuntimeException
    //   1344	1423	4155	com/google/android/gms/internal/ads/zzhe
    //   1344	1423	4151	java/io/IOException
    //   1344	1423	4159	java/lang/RuntimeException
    //   1423	1428	4155	com/google/android/gms/internal/ads/zzhe
    //   1423	1428	4151	java/io/IOException
    //   1423	1428	4159	java/lang/RuntimeException
    //   1432	1444	4155	com/google/android/gms/internal/ads/zzhe
    //   1432	1444	4151	java/io/IOException
    //   1432	1444	4159	java/lang/RuntimeException
    //   1454	1460	4155	com/google/android/gms/internal/ads/zzhe
    //   1454	1460	4151	java/io/IOException
    //   1454	1460	4159	java/lang/RuntimeException
    //   1463	1487	4155	com/google/android/gms/internal/ads/zzhe
    //   1463	1487	4151	java/io/IOException
    //   1463	1487	4159	java/lang/RuntimeException
    //   1490	1510	4155	com/google/android/gms/internal/ads/zzhe
    //   1490	1510	4151	java/io/IOException
    //   1490	1510	4159	java/lang/RuntimeException
    //   1519	1525	4155	com/google/android/gms/internal/ads/zzhe
    //   1519	1525	4151	java/io/IOException
    //   1519	1525	4159	java/lang/RuntimeException
    //   1536	1589	4155	com/google/android/gms/internal/ads/zzhe
    //   1536	1589	4151	java/io/IOException
    //   1536	1589	4159	java/lang/RuntimeException
    //   1600	1606	4155	com/google/android/gms/internal/ads/zzhe
    //   1600	1606	4151	java/io/IOException
    //   1600	1606	4159	java/lang/RuntimeException
    //   1610	1633	4155	com/google/android/gms/internal/ads/zzhe
    //   1610	1633	4151	java/io/IOException
    //   1610	1633	4159	java/lang/RuntimeException
    //   1639	1686	4155	com/google/android/gms/internal/ads/zzhe
    //   1639	1686	4151	java/io/IOException
    //   1639	1686	4159	java/lang/RuntimeException
    //   1713	1752	4155	com/google/android/gms/internal/ads/zzhe
    //   1713	1752	4151	java/io/IOException
    //   1713	1752	4159	java/lang/RuntimeException
    //   1755	1771	4155	com/google/android/gms/internal/ads/zzhe
    //   1755	1771	4151	java/io/IOException
    //   1755	1771	4159	java/lang/RuntimeException
    //   1771	1778	4155	com/google/android/gms/internal/ads/zzhe
    //   1771	1778	4151	java/io/IOException
    //   1771	1778	4159	java/lang/RuntimeException
    //   1780	1801	4155	com/google/android/gms/internal/ads/zzhe
    //   1780	1801	4151	java/io/IOException
    //   1780	1801	4159	java/lang/RuntimeException
    //   1801	1812	1814	finally
    //   1815	1817	1814	finally
    //   1817	1819	4155	com/google/android/gms/internal/ads/zzhe
    //   1817	1819	4151	java/io/IOException
    //   1817	1819	4159	java/lang/RuntimeException
    //   1819	1823	4155	com/google/android/gms/internal/ads/zzhe
    //   1819	1823	4151	java/io/IOException
    //   1819	1823	4159	java/lang/RuntimeException
    //   1825	1839	4155	com/google/android/gms/internal/ads/zzhe
    //   1825	1839	4151	java/io/IOException
    //   1825	1839	4159	java/lang/RuntimeException
    //   1843	1852	4155	com/google/android/gms/internal/ads/zzhe
    //   1843	1852	4151	java/io/IOException
    //   1843	1852	4159	java/lang/RuntimeException
    //   1855	1865	4155	com/google/android/gms/internal/ads/zzhe
    //   1855	1865	4151	java/io/IOException
    //   1855	1865	4159	java/lang/RuntimeException
    //   1865	1883	4155	com/google/android/gms/internal/ads/zzhe
    //   1865	1883	4151	java/io/IOException
    //   1865	1883	4159	java/lang/RuntimeException
    //   1885	1915	4155	com/google/android/gms/internal/ads/zzhe
    //   1885	1915	4151	java/io/IOException
    //   1885	1915	4159	java/lang/RuntimeException
    //   1918	1925	4155	com/google/android/gms/internal/ads/zzhe
    //   1918	1925	4151	java/io/IOException
    //   1918	1925	4159	java/lang/RuntimeException
    //   1930	1986	4155	com/google/android/gms/internal/ads/zzhe
    //   1930	1986	4151	java/io/IOException
    //   1930	1986	4159	java/lang/RuntimeException
    //   1989	2000	4155	com/google/android/gms/internal/ads/zzhe
    //   1989	2000	4151	java/io/IOException
    //   1989	2000	4159	java/lang/RuntimeException
    //   2009	2034	4155	com/google/android/gms/internal/ads/zzhe
    //   2009	2034	4151	java/io/IOException
    //   2009	2034	4159	java/lang/RuntimeException
    //   2034	2065	2204	finally
    //   2073	2095	4155	com/google/android/gms/internal/ads/zzhe
    //   2073	2095	4151	java/io/IOException
    //   2073	2095	4159	java/lang/RuntimeException
    //   2109	2122	4155	com/google/android/gms/internal/ads/zzhe
    //   2109	2122	4151	java/io/IOException
    //   2109	2122	4159	java/lang/RuntimeException
    //   2125	2134	2204	finally
    //   2148	2173	4155	com/google/android/gms/internal/ads/zzhe
    //   2148	2173	4151	java/io/IOException
    //   2148	2173	4159	java/lang/RuntimeException
    //   2189	2202	4155	com/google/android/gms/internal/ads/zzhe
    //   2189	2202	4151	java/io/IOException
    //   2189	2202	4159	java/lang/RuntimeException
    //   2206	2228	4155	com/google/android/gms/internal/ads/zzhe
    //   2206	2228	4151	java/io/IOException
    //   2206	2228	4159	java/lang/RuntimeException
    //   2242	2258	4155	com/google/android/gms/internal/ads/zzhe
    //   2242	2258	4151	java/io/IOException
    //   2242	2258	4159	java/lang/RuntimeException
    //   2258	2279	4155	com/google/android/gms/internal/ads/zzhe
    //   2258	2279	4151	java/io/IOException
    //   2258	2279	4159	java/lang/RuntimeException
    //   2282	2287	4155	com/google/android/gms/internal/ads/zzhe
    //   2282	2287	4151	java/io/IOException
    //   2282	2287	4159	java/lang/RuntimeException
    //   2291	2300	4155	com/google/android/gms/internal/ads/zzhe
    //   2291	2300	4151	java/io/IOException
    //   2291	2300	4159	java/lang/RuntimeException
    //   2303	2347	4155	com/google/android/gms/internal/ads/zzhe
    //   2303	2347	4151	java/io/IOException
    //   2303	2347	4159	java/lang/RuntimeException
    //   2350	2355	4155	com/google/android/gms/internal/ads/zzhe
    //   2350	2355	4151	java/io/IOException
    //   2350	2355	4159	java/lang/RuntimeException
    //   2359	2376	4155	com/google/android/gms/internal/ads/zzhe
    //   2359	2376	4151	java/io/IOException
    //   2359	2376	4159	java/lang/RuntimeException
    //   2376	2399	4155	com/google/android/gms/internal/ads/zzhe
    //   2376	2399	4151	java/io/IOException
    //   2376	2399	4159	java/lang/RuntimeException
    //   2399	2420	4155	com/google/android/gms/internal/ads/zzhe
    //   2399	2420	4151	java/io/IOException
    //   2399	2420	4159	java/lang/RuntimeException
    //   2423	2438	4155	com/google/android/gms/internal/ads/zzhe
    //   2423	2438	4151	java/io/IOException
    //   2423	2438	4159	java/lang/RuntimeException
    //   2441	2470	4155	com/google/android/gms/internal/ads/zzhe
    //   2441	2470	4151	java/io/IOException
    //   2441	2470	4159	java/lang/RuntimeException
    //   2478	2540	4155	com/google/android/gms/internal/ads/zzhe
    //   2478	2540	4151	java/io/IOException
    //   2478	2540	4159	java/lang/RuntimeException
    //   2544	2567	4155	com/google/android/gms/internal/ads/zzhe
    //   2544	2567	4151	java/io/IOException
    //   2544	2567	4159	java/lang/RuntimeException
    //   2567	2572	4155	com/google/android/gms/internal/ads/zzhe
    //   2567	2572	4151	java/io/IOException
    //   2567	2572	4159	java/lang/RuntimeException
    //   2586	2615	4155	com/google/android/gms/internal/ads/zzhe
    //   2586	2615	4151	java/io/IOException
    //   2586	2615	4159	java/lang/RuntimeException
    //   2618	2623	4155	com/google/android/gms/internal/ads/zzhe
    //   2618	2623	4151	java/io/IOException
    //   2618	2623	4159	java/lang/RuntimeException
    //   2632	2639	4155	com/google/android/gms/internal/ads/zzhe
    //   2632	2639	4151	java/io/IOException
    //   2632	2639	4159	java/lang/RuntimeException
    //   2639	2712	4155	com/google/android/gms/internal/ads/zzhe
    //   2639	2712	4151	java/io/IOException
    //   2639	2712	4159	java/lang/RuntimeException
    //   2716	2722	4155	com/google/android/gms/internal/ads/zzhe
    //   2716	2722	4151	java/io/IOException
    //   2716	2722	4159	java/lang/RuntimeException
    //   2722	2745	4155	com/google/android/gms/internal/ads/zzhe
    //   2722	2745	4151	java/io/IOException
    //   2722	2745	4159	java/lang/RuntimeException
    //   2745	2750	4155	com/google/android/gms/internal/ads/zzhe
    //   2745	2750	4151	java/io/IOException
    //   2745	2750	4159	java/lang/RuntimeException
    //   2754	2761	4155	com/google/android/gms/internal/ads/zzhe
    //   2754	2761	4151	java/io/IOException
    //   2754	2761	4159	java/lang/RuntimeException
    //   2764	2782	4155	com/google/android/gms/internal/ads/zzhe
    //   2764	2782	4151	java/io/IOException
    //   2764	2782	4159	java/lang/RuntimeException
    //   2785	2790	4155	com/google/android/gms/internal/ads/zzhe
    //   2785	2790	4151	java/io/IOException
    //   2785	2790	4159	java/lang/RuntimeException
    //   2790	2797	4155	com/google/android/gms/internal/ads/zzhe
    //   2790	2797	4151	java/io/IOException
    //   2790	2797	4159	java/lang/RuntimeException
    //   2797	2808	4155	com/google/android/gms/internal/ads/zzhe
    //   2797	2808	4151	java/io/IOException
    //   2797	2808	4159	java/lang/RuntimeException
    //   2814	2894	4155	com/google/android/gms/internal/ads/zzhe
    //   2814	2894	4151	java/io/IOException
    //   2814	2894	4159	java/lang/RuntimeException
    //   2897	2904	4155	com/google/android/gms/internal/ads/zzhe
    //   2897	2904	4151	java/io/IOException
    //   2897	2904	4159	java/lang/RuntimeException
    //   2907	2919	4155	com/google/android/gms/internal/ads/zzhe
    //   2907	2919	4151	java/io/IOException
    //   2907	2919	4159	java/lang/RuntimeException
    //   2925	2936	4155	com/google/android/gms/internal/ads/zzhe
    //   2925	2936	4151	java/io/IOException
    //   2925	2936	4159	java/lang/RuntimeException
    //   2940	2968	4155	com/google/android/gms/internal/ads/zzhe
    //   2940	2968	4151	java/io/IOException
    //   2940	2968	4159	java/lang/RuntimeException
    //   2977	2989	4155	com/google/android/gms/internal/ads/zzhe
    //   2977	2989	4151	java/io/IOException
    //   2977	2989	4159	java/lang/RuntimeException
    //   2995	3017	4155	com/google/android/gms/internal/ads/zzhe
    //   2995	3017	4151	java/io/IOException
    //   2995	3017	4159	java/lang/RuntimeException
    //   3021	3031	4155	com/google/android/gms/internal/ads/zzhe
    //   3021	3031	4151	java/io/IOException
    //   3021	3031	4159	java/lang/RuntimeException
    //   3040	3051	4155	com/google/android/gms/internal/ads/zzhe
    //   3040	3051	4151	java/io/IOException
    //   3040	3051	4159	java/lang/RuntimeException
    //   3056	3099	4155	com/google/android/gms/internal/ads/zzhe
    //   3056	3099	4151	java/io/IOException
    //   3056	3099	4159	java/lang/RuntimeException
    //   3110	3123	4155	com/google/android/gms/internal/ads/zzhe
    //   3110	3123	4151	java/io/IOException
    //   3110	3123	4159	java/lang/RuntimeException
    //   3129	3141	4155	com/google/android/gms/internal/ads/zzhe
    //   3129	3141	4151	java/io/IOException
    //   3129	3141	4159	java/lang/RuntimeException
    //   3146	3183	4155	com/google/android/gms/internal/ads/zzhe
    //   3146	3183	4151	java/io/IOException
    //   3146	3183	4159	java/lang/RuntimeException
    //   3188	3214	4155	com/google/android/gms/internal/ads/zzhe
    //   3188	3214	4151	java/io/IOException
    //   3188	3214	4159	java/lang/RuntimeException
    //   3224	3238	4155	com/google/android/gms/internal/ads/zzhe
    //   3224	3238	4151	java/io/IOException
    //   3224	3238	4159	java/lang/RuntimeException
    //   3244	3271	4155	com/google/android/gms/internal/ads/zzhe
    //   3244	3271	4151	java/io/IOException
    //   3244	3271	4159	java/lang/RuntimeException
    //   3274	3281	4155	com/google/android/gms/internal/ads/zzhe
    //   3274	3281	4151	java/io/IOException
    //   3274	3281	4159	java/lang/RuntimeException
    //   3287	3307	4155	com/google/android/gms/internal/ads/zzhe
    //   3287	3307	4151	java/io/IOException
    //   3287	3307	4159	java/lang/RuntimeException
    //   3310	3348	4155	com/google/android/gms/internal/ads/zzhe
    //   3310	3348	4151	java/io/IOException
    //   3310	3348	4159	java/lang/RuntimeException
    //   3367	3382	4155	com/google/android/gms/internal/ads/zzhe
    //   3367	3382	4151	java/io/IOException
    //   3367	3382	4159	java/lang/RuntimeException
    //   3387	3397	4155	com/google/android/gms/internal/ads/zzhe
    //   3387	3397	4151	java/io/IOException
    //   3387	3397	4159	java/lang/RuntimeException
    //   3406	3426	4155	com/google/android/gms/internal/ads/zzhe
    //   3406	3426	4151	java/io/IOException
    //   3406	3426	4159	java/lang/RuntimeException
    //   3443	3450	4155	com/google/android/gms/internal/ads/zzhe
    //   3443	3450	4151	java/io/IOException
    //   3443	3450	4159	java/lang/RuntimeException
    //   3480	3484	4155	com/google/android/gms/internal/ads/zzhe
    //   3480	3484	4151	java/io/IOException
    //   3480	3484	4159	java/lang/RuntimeException
    //   3484	3489	4155	com/google/android/gms/internal/ads/zzhe
    //   3484	3489	4151	java/io/IOException
    //   3484	3489	4159	java/lang/RuntimeException
    //   3493	3540	4155	com/google/android/gms/internal/ads/zzhe
    //   3493	3540	4151	java/io/IOException
    //   3493	3540	4159	java/lang/RuntimeException
    //   3540	3563	4155	com/google/android/gms/internal/ads/zzhe
    //   3540	3563	4151	java/io/IOException
    //   3540	3563	4159	java/lang/RuntimeException
    //   3576	3588	4155	com/google/android/gms/internal/ads/zzhe
    //   3576	3588	4151	java/io/IOException
    //   3576	3588	4159	java/lang/RuntimeException
    //   3588	3607	4155	com/google/android/gms/internal/ads/zzhe
    //   3588	3607	4151	java/io/IOException
    //   3588	3607	4159	java/lang/RuntimeException
    //   3610	3616	4155	com/google/android/gms/internal/ads/zzhe
    //   3610	3616	4151	java/io/IOException
    //   3610	3616	4159	java/lang/RuntimeException
    //   3622	3630	4155	com/google/android/gms/internal/ads/zzhe
    //   3622	3630	4151	java/io/IOException
    //   3622	3630	4159	java/lang/RuntimeException
    //   3635	3658	4155	com/google/android/gms/internal/ads/zzhe
    //   3635	3658	4151	java/io/IOException
    //   3635	3658	4159	java/lang/RuntimeException
    //   3661	3671	4155	com/google/android/gms/internal/ads/zzhe
    //   3661	3671	4151	java/io/IOException
    //   3661	3671	4159	java/lang/RuntimeException
    //   3682	3694	4155	com/google/android/gms/internal/ads/zzhe
    //   3682	3694	4151	java/io/IOException
    //   3682	3694	4159	java/lang/RuntimeException
    //   3700	3721	4155	com/google/android/gms/internal/ads/zzhe
    //   3700	3721	4151	java/io/IOException
    //   3700	3721	4159	java/lang/RuntimeException
    //   3721	3755	4155	com/google/android/gms/internal/ads/zzhe
    //   3721	3755	4151	java/io/IOException
    //   3721	3755	4159	java/lang/RuntimeException
    //   3772	3779	4155	com/google/android/gms/internal/ads/zzhe
    //   3772	3779	4151	java/io/IOException
    //   3772	3779	4159	java/lang/RuntimeException
    //   3784	3800	4155	com/google/android/gms/internal/ads/zzhe
    //   3784	3800	4151	java/io/IOException
    //   3784	3800	4159	java/lang/RuntimeException
    //   3809	3817	4155	com/google/android/gms/internal/ads/zzhe
    //   3809	3817	4151	java/io/IOException
    //   3809	3817	4159	java/lang/RuntimeException
    //   3820	3827	4155	com/google/android/gms/internal/ads/zzhe
    //   3820	3827	4151	java/io/IOException
    //   3820	3827	4159	java/lang/RuntimeException
    //   3832	3849	4155	com/google/android/gms/internal/ads/zzhe
    //   3832	3849	4151	java/io/IOException
    //   3832	3849	4159	java/lang/RuntimeException
    //   3849	3865	4155	com/google/android/gms/internal/ads/zzhe
    //   3849	3865	4151	java/io/IOException
    //   3849	3865	4159	java/lang/RuntimeException
    //   3875	3884	4155	com/google/android/gms/internal/ads/zzhe
    //   3875	3884	4151	java/io/IOException
    //   3875	3884	4159	java/lang/RuntimeException
    //   3890	3905	4155	com/google/android/gms/internal/ads/zzhe
    //   3890	3905	4151	java/io/IOException
    //   3890	3905	4159	java/lang/RuntimeException
    //   3905	3913	4155	com/google/android/gms/internal/ads/zzhe
    //   3905	3913	4151	java/io/IOException
    //   3905	3913	4159	java/lang/RuntimeException
    //   3913	3922	4155	com/google/android/gms/internal/ads/zzhe
    //   3913	3922	4151	java/io/IOException
    //   3913	3922	4159	java/lang/RuntimeException
    //   3925	3942	4155	com/google/android/gms/internal/ads/zzhe
    //   3925	3942	4151	java/io/IOException
    //   3925	3942	4159	java/lang/RuntimeException
    //   3945	3953	4155	com/google/android/gms/internal/ads/zzhe
    //   3945	3953	4151	java/io/IOException
    //   3945	3953	4159	java/lang/RuntimeException
    //   3953	3956	4155	com/google/android/gms/internal/ads/zzhe
    //   3953	3956	4151	java/io/IOException
    //   3953	3956	4159	java/lang/RuntimeException
    //   3958	3965	4155	com/google/android/gms/internal/ads/zzhe
    //   3958	3965	4151	java/io/IOException
    //   3958	3965	4159	java/lang/RuntimeException
    //   3974	3985	4155	com/google/android/gms/internal/ads/zzhe
    //   3974	3985	4151	java/io/IOException
    //   3974	3985	4159	java/lang/RuntimeException
    //   3990	3998	4155	com/google/android/gms/internal/ads/zzhe
    //   3990	3998	4151	java/io/IOException
    //   3990	3998	4159	java/lang/RuntimeException
    //   4001	4007	4155	com/google/android/gms/internal/ads/zzhe
    //   4001	4007	4151	java/io/IOException
    //   4001	4007	4159	java/lang/RuntimeException
    //   4013	4026	4155	com/google/android/gms/internal/ads/zzhe
    //   4013	4026	4151	java/io/IOException
    //   4013	4026	4159	java/lang/RuntimeException
    //   4035	4044	4155	com/google/android/gms/internal/ads/zzhe
    //   4035	4044	4151	java/io/IOException
    //   4035	4044	4159	java/lang/RuntimeException
    //   4046	4062	4155	com/google/android/gms/internal/ads/zzhe
    //   4046	4062	4151	java/io/IOException
    //   4046	4062	4159	java/lang/RuntimeException
    //   4071	4094	4155	com/google/android/gms/internal/ads/zzhe
    //   4071	4094	4151	java/io/IOException
    //   4071	4094	4159	java/lang/RuntimeException
    //   4099	4116	4155	com/google/android/gms/internal/ads/zzhe
    //   4099	4116	4151	java/io/IOException
    //   4099	4116	4159	java/lang/RuntimeException
    //   4116	4149	4155	com/google/android/gms/internal/ads/zzhe
    //   4116	4149	4151	java/io/IOException
    //   4116	4149	4159	java/lang/RuntimeException
  }
  
  public final void n(vc2 paramvc2, int paramInt, long paramLong) {
    this.g.obtainMessage(3, new lc2(paramvc2, paramInt, paramLong)).sendToTarget();
  }
  
  public final void o(mh2 parammh2, boolean paramBoolean) {
    this.g.obtainMessage(0, 1, 0, parammh2).sendToTarget();
  }
  
  public final void q(cc2... paramVarArgs) {
    if (this.s) {
      Log.w("ExoPlayerImplInternal", "Ignoring messages sent after release.");
      return;
    } 
    this.y++;
    this.g.obtainMessage(11, paramVarArgs).sendToTarget();
  }
  
  public final void w(cc2... paramVarArgs) {
    // Byte code:
    //   0: aload_0
    //   1: monitorenter
    //   2: aload_0
    //   3: getfield s : Z
    //   6: ifeq -> 22
    //   9: ldc_w 'ExoPlayerImplInternal'
    //   12: ldc_w 'Ignoring messages sent after release.'
    //   15: invokestatic w : (Ljava/lang/String;Ljava/lang/String;)I
    //   18: pop
    //   19: aload_0
    //   20: monitorexit
    //   21: return
    //   22: aload_0
    //   23: getfield y : I
    //   26: istore_2
    //   27: aload_0
    //   28: iload_2
    //   29: iconst_1
    //   30: iadd
    //   31: putfield y : I
    //   34: aload_0
    //   35: getfield g : Landroid/os/Handler;
    //   38: bipush #11
    //   40: aload_1
    //   41: invokevirtual obtainMessage : (ILjava/lang/Object;)Landroid/os/Message;
    //   44: invokevirtual sendToTarget : ()V
    //   47: aload_0
    //   48: getfield z : I
    //   51: istore_3
    //   52: iload_3
    //   53: iload_2
    //   54: if_icmpgt -> 74
    //   57: aload_0
    //   58: invokevirtual wait : ()V
    //   61: goto -> 47
    //   64: astore_1
    //   65: invokestatic currentThread : ()Ljava/lang/Thread;
    //   68: invokevirtual interrupt : ()V
    //   71: goto -> 47
    //   74: aload_0
    //   75: monitorexit
    //   76: return
    //   77: astore_1
    //   78: aload_0
    //   79: monitorexit
    //   80: goto -> 85
    //   83: aload_1
    //   84: athrow
    //   85: goto -> 83
    // Exception table:
    //   from	to	target	type
    //   2	19	77	finally
    //   22	47	77	finally
    //   47	52	77	finally
    //   57	61	64	java/lang/InterruptedException
    //   57	61	77	finally
    //   65	71	77	finally
  }
}


/* Location:              /home/sumith/decompile/test/classes-dex2jar.jar!/com/google/android/gms/internal/ads/gc2.class
 * Java compiler version: 6 (50.0)
 * JD-Core Version:       1.1.3
 */