package com.google.android.gms.internal.ads;

import java.util.HashMap;
import java.util.Iterator;
import java.util.List;
import java.util.Map;

public final class gm0 {
  private final Map<String, dm0> a = new HashMap<String, dm0>();
  
  private final dm0 c(String paramString) {
    // Byte code:
    //   0: aload_0
    //   1: monitorenter
    //   2: aload_0
    //   3: getfield a : Ljava/util/Map;
    //   6: aload_1
    //   7: invokeinterface get : (Ljava/lang/Object;)Ljava/lang/Object;
    //   12: checkcast com/google/android/gms/internal/ads/dm0
    //   15: astore_1
    //   16: aload_0
    //   17: monitorexit
    //   18: aload_1
    //   19: areturn
    //   20: astore_1
    //   21: aload_0
    //   22: monitorexit
    //   23: aload_1
    //   24: athrow
    // Exception table:
    //   from	to	target	type
    //   2	16	20	finally
  }
  
  final void a(String paramString, kd paramkd) {
    // Byte code:
    //   0: aload_0
    //   1: monitorenter
    //   2: aload_0
    //   3: getfield a : Ljava/util/Map;
    //   6: aload_1
    //   7: invokeinterface containsKey : (Ljava/lang/Object;)Z
    //   12: istore_3
    //   13: iload_3
    //   14: ifeq -> 20
    //   17: aload_0
    //   18: monitorexit
    //   19: return
    //   20: aload_2
    //   21: invokeinterface F0 : ()Lcom/google/android/gms/internal/ads/zzapy;
    //   26: astore #4
    //   28: aload_2
    //   29: invokeinterface v0 : ()Lcom/google/android/gms/internal/ads/zzapy;
    //   34: astore_2
    //   35: new com/google/android/gms/internal/ads/dm0
    //   38: astore #5
    //   40: aload #5
    //   42: aload_1
    //   43: aload #4
    //   45: aload_2
    //   46: invokespecial <init> : (Ljava/lang/String;Lcom/google/android/gms/internal/ads/zzapy;Lcom/google/android/gms/internal/ads/zzapy;)V
    //   49: aload_0
    //   50: getfield a : Ljava/util/Map;
    //   53: aload_1
    //   54: aload #5
    //   56: invokeinterface put : (Ljava/lang/Object;Ljava/lang/Object;)Ljava/lang/Object;
    //   61: pop
    //   62: aload_0
    //   63: monitorexit
    //   64: return
    //   65: astore_1
    //   66: aload_0
    //   67: monitorexit
    //   68: return
    //   69: astore_1
    //   70: aload_0
    //   71: monitorexit
    //   72: aload_1
    //   73: athrow
    // Exception table:
    //   from	to	target	type
    //   2	13	69	finally
    //   20	35	65	finally
    //   35	62	69	finally
  }
  
  final void b(String paramString, xi1 paramxi1) {
    // Byte code:
    //   0: aload_0
    //   1: monitorenter
    //   2: aload_0
    //   3: getfield a : Ljava/util/Map;
    //   6: aload_1
    //   7: invokeinterface containsKey : (Ljava/lang/Object;)Z
    //   12: istore_3
    //   13: iload_3
    //   14: ifeq -> 20
    //   17: aload_0
    //   18: monitorexit
    //   19: return
    //   20: aload_2
    //   21: invokevirtual A : ()Lcom/google/android/gms/internal/ads/zzapy;
    //   24: astore #4
    //   26: aload_2
    //   27: invokevirtual B : ()Lcom/google/android/gms/internal/ads/zzapy;
    //   30: astore #5
    //   32: new com/google/android/gms/internal/ads/dm0
    //   35: astore_2
    //   36: aload_2
    //   37: aload_1
    //   38: aload #4
    //   40: aload #5
    //   42: invokespecial <init> : (Ljava/lang/String;Lcom/google/android/gms/internal/ads/zzapy;Lcom/google/android/gms/internal/ads/zzapy;)V
    //   45: aload_0
    //   46: getfield a : Ljava/util/Map;
    //   49: aload_1
    //   50: aload_2
    //   51: invokeinterface put : (Ljava/lang/Object;Ljava/lang/Object;)Ljava/lang/Object;
    //   56: pop
    //   57: aload_0
    //   58: monitorexit
    //   59: return
    //   60: astore_1
    //   61: aload_0
    //   62: monitorexit
    //   63: return
    //   64: astore_1
    //   65: aload_0
    //   66: monitorexit
    //   67: aload_1
    //   68: athrow
    // Exception table:
    //   from	to	target	type
    //   2	13	64	finally
    //   20	32	60	com/google/android/gms/internal/ads/zzdnt
    //   20	32	64	finally
    //   32	57	64	finally
  }
  
  public final dm0 d(List<String> paramList) {
    Iterator<String> iterator = paramList.iterator();
    while (iterator.hasNext()) {
      dm0 dm0 = c(iterator.next());
      if (dm0 != null)
        return dm0; 
    } 
    return null;
  }
}


/* Location:              /home/sumith/decompile/test/classes-dex2jar.jar!/com/google/android/gms/internal/ads/gm0.class
 * Java compiler version: 6 (50.0)
 * JD-Core Version:       1.1.3
 */