package com.google.android.gms.internal.ads;

import android.content.Context;
import com.google.android.gms.dynamic.a;

public final class i00 implements f50, d60 {
  private final Context b;
  
  private final tq c;
  
  private final nh1 d;
  
  private final zzazn e;
  
  private a f;
  
  private boolean g;
  
  public i00(Context paramContext, tq paramtq, nh1 paramnh1, zzazn paramzzazn) {
    this.b = paramContext;
    this.c = paramtq;
    this.d = paramnh1;
    this.e = paramzzazn;
  }
  
  private final void a() {
    // Byte code:
    //   0: aload_0
    //   1: monitorenter
    //   2: aload_0
    //   3: getfield d : Lcom/google/android/gms/internal/ads/nh1;
    //   6: getfield N : Z
    //   9: istore_1
    //   10: iload_1
    //   11: ifne -> 17
    //   14: aload_0
    //   15: monitorexit
    //   16: return
    //   17: aload_0
    //   18: getfield c : Lcom/google/android/gms/internal/ads/tq;
    //   21: astore_2
    //   22: aload_2
    //   23: ifnonnull -> 29
    //   26: aload_0
    //   27: monitorexit
    //   28: return
    //   29: invokestatic r : ()Lcom/google/android/gms/internal/ads/ze;
    //   32: aload_0
    //   33: getfield b : Landroid/content/Context;
    //   36: invokevirtual k : (Landroid/content/Context;)Z
    //   39: istore_1
    //   40: iload_1
    //   41: ifne -> 47
    //   44: aload_0
    //   45: monitorexit
    //   46: return
    //   47: aload_0
    //   48: getfield e : Lcom/google/android/gms/internal/ads/zzazn;
    //   51: astore_2
    //   52: aload_2
    //   53: getfield c : I
    //   56: istore_3
    //   57: aload_2
    //   58: getfield d : I
    //   61: istore #4
    //   63: new java/lang/StringBuilder
    //   66: astore_2
    //   67: aload_2
    //   68: bipush #23
    //   70: invokespecial <init> : (I)V
    //   73: aload_2
    //   74: iload_3
    //   75: invokevirtual append : (I)Ljava/lang/StringBuilder;
    //   78: pop
    //   79: aload_2
    //   80: ldc '.'
    //   82: invokevirtual append : (Ljava/lang/String;)Ljava/lang/StringBuilder;
    //   85: pop
    //   86: aload_2
    //   87: iload #4
    //   89: invokevirtual append : (I)Ljava/lang/StringBuilder;
    //   92: pop
    //   93: aload_2
    //   94: invokevirtual toString : ()Ljava/lang/String;
    //   97: astore #5
    //   99: aload_0
    //   100: getfield d : Lcom/google/android/gms/internal/ads/nh1;
    //   103: getfield P : Lcom/google/android/gms/ads/nonagon/transaction/omid/a;
    //   106: invokevirtual b : ()Ljava/lang/String;
    //   109: astore #6
    //   111: getstatic com/google/android/gms/internal/ads/m0.G3 : Lcom/google/android/gms/internal/ads/x;
    //   114: astore_2
    //   115: invokestatic e : ()Lcom/google/android/gms/internal/ads/i0;
    //   118: aload_2
    //   119: invokevirtual c : (Lcom/google/android/gms/internal/ads/x;)Ljava/lang/Object;
    //   122: checkcast java/lang/Boolean
    //   125: invokevirtual booleanValue : ()Z
    //   128: ifeq -> 229
    //   131: aload_0
    //   132: getfield d : Lcom/google/android/gms/internal/ads/nh1;
    //   135: getfield P : Lcom/google/android/gms/ads/nonagon/transaction/omid/a;
    //   138: invokevirtual a : ()Lcom/google/android/gms/ads/nonagon/transaction/omid/OmidMediaType;
    //   141: getstatic com/google/android/gms/ads/nonagon/transaction/omid/OmidMediaType.b : Lcom/google/android/gms/ads/nonagon/transaction/omid/OmidMediaType;
    //   144: if_acmpne -> 159
    //   147: getstatic com/google/android/gms/internal/ads/zzarn.d : Lcom/google/android/gms/internal/ads/zzarn;
    //   150: astore #7
    //   152: getstatic com/google/android/gms/internal/ads/zzarm.c : Lcom/google/android/gms/internal/ads/zzarm;
    //   155: astore_2
    //   156: goto -> 189
    //   159: getstatic com/google/android/gms/internal/ads/zzarn.b : Lcom/google/android/gms/internal/ads/zzarn;
    //   162: astore #7
    //   164: aload_0
    //   165: getfield d : Lcom/google/android/gms/internal/ads/nh1;
    //   168: getfield e : I
    //   171: iconst_1
    //   172: if_icmpne -> 182
    //   175: getstatic com/google/android/gms/internal/ads/zzarm.d : Lcom/google/android/gms/internal/ads/zzarm;
    //   178: astore_2
    //   179: goto -> 156
    //   182: getstatic com/google/android/gms/internal/ads/zzarm.b : Lcom/google/android/gms/internal/ads/zzarm;
    //   185: astore_2
    //   186: goto -> 156
    //   189: aload_0
    //   190: invokestatic r : ()Lcom/google/android/gms/internal/ads/ze;
    //   193: aload #5
    //   195: aload_0
    //   196: getfield c : Lcom/google/android/gms/internal/ads/tq;
    //   199: invokeinterface getWebView : ()Landroid/webkit/WebView;
    //   204: ldc ''
    //   206: ldc 'javascript'
    //   208: aload #6
    //   210: aload_2
    //   211: aload #7
    //   213: aload_0
    //   214: getfield d : Lcom/google/android/gms/internal/ads/nh1;
    //   217: getfield f0 : Ljava/lang/String;
    //   220: invokevirtual c : (Ljava/lang/String;Landroid/webkit/WebView;Ljava/lang/String;Ljava/lang/String;Ljava/lang/String;Lcom/google/android/gms/internal/ads/zzarm;Lcom/google/android/gms/internal/ads/zzarn;Ljava/lang/String;)Lcom/google/android/gms/dynamic/a;
    //   223: putfield f : Lcom/google/android/gms/dynamic/a;
    //   226: goto -> 256
    //   229: aload_0
    //   230: invokestatic r : ()Lcom/google/android/gms/internal/ads/ze;
    //   233: aload #5
    //   235: aload_0
    //   236: getfield c : Lcom/google/android/gms/internal/ads/tq;
    //   239: invokeinterface getWebView : ()Landroid/webkit/WebView;
    //   244: ldc ''
    //   246: ldc 'javascript'
    //   248: aload #6
    //   250: invokevirtual b : (Ljava/lang/String;Landroid/webkit/WebView;Ljava/lang/String;Ljava/lang/String;Ljava/lang/String;)Lcom/google/android/gms/dynamic/a;
    //   253: putfield f : Lcom/google/android/gms/dynamic/a;
    //   256: aload_0
    //   257: getfield c : Lcom/google/android/gms/internal/ads/tq;
    //   260: invokeinterface getView : ()Landroid/view/View;
    //   265: astore_2
    //   266: aload_0
    //   267: getfield f : Lcom/google/android/gms/dynamic/a;
    //   270: ifnull -> 361
    //   273: aload_2
    //   274: ifnull -> 361
    //   277: invokestatic r : ()Lcom/google/android/gms/internal/ads/ze;
    //   280: aload_0
    //   281: getfield f : Lcom/google/android/gms/dynamic/a;
    //   284: aload_2
    //   285: invokevirtual f : (Lcom/google/android/gms/dynamic/a;Landroid/view/View;)V
    //   288: aload_0
    //   289: getfield c : Lcom/google/android/gms/internal/ads/tq;
    //   292: aload_0
    //   293: getfield f : Lcom/google/android/gms/dynamic/a;
    //   296: invokeinterface H0 : (Lcom/google/android/gms/dynamic/a;)V
    //   301: invokestatic r : ()Lcom/google/android/gms/internal/ads/ze;
    //   304: aload_0
    //   305: getfield f : Lcom/google/android/gms/dynamic/a;
    //   308: invokevirtual g : (Lcom/google/android/gms/dynamic/a;)V
    //   311: aload_0
    //   312: iconst_1
    //   313: putfield g : Z
    //   316: getstatic com/google/android/gms/internal/ads/m0.J3 : Lcom/google/android/gms/internal/ads/x;
    //   319: astore_2
    //   320: invokestatic e : ()Lcom/google/android/gms/internal/ads/i0;
    //   323: aload_2
    //   324: invokevirtual c : (Lcom/google/android/gms/internal/ads/x;)Ljava/lang/Object;
    //   327: checkcast java/lang/Boolean
    //   330: invokevirtual booleanValue : ()Z
    //   333: ifeq -> 361
    //   336: aload_0
    //   337: getfield c : Lcom/google/android/gms/internal/ads/tq;
    //   340: astore_2
    //   341: new b/e/a
    //   344: astore #7
    //   346: aload #7
    //   348: invokespecial <init> : ()V
    //   351: aload_2
    //   352: ldc 'onSdkLoaded'
    //   354: aload #7
    //   356: invokeinterface B : (Ljava/lang/String;Ljava/util/Map;)V
    //   361: aload_0
    //   362: monitorexit
    //   363: return
    //   364: astore_2
    //   365: aload_0
    //   366: monitorexit
    //   367: goto -> 372
    //   370: aload_2
    //   371: athrow
    //   372: goto -> 370
    // Exception table:
    //   from	to	target	type
    //   2	10	364	finally
    //   17	22	364	finally
    //   29	40	364	finally
    //   47	156	364	finally
    //   159	179	364	finally
    //   182	186	364	finally
    //   189	226	364	finally
    //   229	256	364	finally
    //   256	273	364	finally
    //   277	361	364	finally
  }
  
  public final void S() {
    // Byte code:
    //   0: aload_0
    //   1: monitorenter
    //   2: aload_0
    //   3: getfield g : Z
    //   6: ifne -> 13
    //   9: aload_0
    //   10: invokespecial a : ()V
    //   13: aload_0
    //   14: getfield d : Lcom/google/android/gms/internal/ads/nh1;
    //   17: getfield N : Z
    //   20: ifeq -> 56
    //   23: aload_0
    //   24: getfield f : Lcom/google/android/gms/dynamic/a;
    //   27: ifnull -> 56
    //   30: aload_0
    //   31: getfield c : Lcom/google/android/gms/internal/ads/tq;
    //   34: astore_1
    //   35: aload_1
    //   36: ifnull -> 56
    //   39: new b/e/a
    //   42: astore_2
    //   43: aload_2
    //   44: invokespecial <init> : ()V
    //   47: aload_1
    //   48: ldc 'onSdkImpression'
    //   50: aload_2
    //   51: invokeinterface B : (Ljava/lang/String;Ljava/util/Map;)V
    //   56: aload_0
    //   57: monitorexit
    //   58: return
    //   59: astore_2
    //   60: aload_0
    //   61: monitorexit
    //   62: aload_2
    //   63: athrow
    // Exception table:
    //   from	to	target	type
    //   2	13	59	finally
    //   13	35	59	finally
    //   39	56	59	finally
  }
  
  public final void i() {
    // Byte code:
    //   0: aload_0
    //   1: monitorenter
    //   2: aload_0
    //   3: getfield g : Z
    //   6: istore_1
    //   7: iload_1
    //   8: ifeq -> 14
    //   11: aload_0
    //   12: monitorexit
    //   13: return
    //   14: aload_0
    //   15: invokespecial a : ()V
    //   18: aload_0
    //   19: monitorexit
    //   20: return
    //   21: astore_2
    //   22: aload_0
    //   23: monitorexit
    //   24: aload_2
    //   25: athrow
    // Exception table:
    //   from	to	target	type
    //   2	7	21	finally
    //   14	18	21	finally
  }
}


/* Location:              /home/sumith/decompile/test/classes-dex2jar.jar!/com/google/android/gms/internal/ads/i00.class
 * Java compiler version: 6 (50.0)
 * JD-Core Version:       1.1.3
 */