package com.google.android.gms.internal.ads;

import java.util.HashMap;
import java.util.Map;
import java.util.Set;
import java.util.concurrent.Executor;

public class j90<ListenerT> {
  private final Map<ListenerT, Executor> b = new HashMap<ListenerT, Executor>();
  
  protected j90(Set<gb0<ListenerT>> paramSet) {
    a1(paramSet);
  }
  
  private final void a1(Set<gb0<ListenerT>> paramSet) {
    // Byte code:
    //   0: aload_0
    //   1: monitorenter
    //   2: aload_1
    //   3: invokeinterface iterator : ()Ljava/util/Iterator;
    //   8: astore_1
    //   9: aload_1
    //   10: invokeinterface hasNext : ()Z
    //   15: ifeq -> 34
    //   18: aload_0
    //   19: aload_1
    //   20: invokeinterface next : ()Ljava/lang/Object;
    //   25: checkcast com/google/android/gms/internal/ads/gb0
    //   28: invokevirtual Y0 : (Lcom/google/android/gms/internal/ads/gb0;)V
    //   31: goto -> 9
    //   34: aload_0
    //   35: monitorexit
    //   36: return
    //   37: astore_1
    //   38: aload_0
    //   39: monitorexit
    //   40: goto -> 45
    //   43: aload_1
    //   44: athrow
    //   45: goto -> 43
    // Exception table:
    //   from	to	target	type
    //   2	9	37	finally
    //   9	31	37	finally
  }
  
  protected final void X0(l90<ListenerT> paraml90) {
    // Byte code:
    //   0: aload_0
    //   1: monitorenter
    //   2: aload_0
    //   3: getfield b : Ljava/util/Map;
    //   6: invokeinterface entrySet : ()Ljava/util/Set;
    //   11: invokeinterface iterator : ()Ljava/util/Iterator;
    //   16: astore_2
    //   17: aload_2
    //   18: invokeinterface hasNext : ()Z
    //   23: ifeq -> 77
    //   26: aload_2
    //   27: invokeinterface next : ()Ljava/lang/Object;
    //   32: checkcast java/util/Map$Entry
    //   35: astore_3
    //   36: aload_3
    //   37: invokeinterface getKey : ()Ljava/lang/Object;
    //   42: astore #4
    //   44: aload_3
    //   45: invokeinterface getValue : ()Ljava/lang/Object;
    //   50: checkcast java/util/concurrent/Executor
    //   53: astore #5
    //   55: new com/google/android/gms/internal/ads/i90
    //   58: astore_3
    //   59: aload_3
    //   60: aload_1
    //   61: aload #4
    //   63: invokespecial <init> : (Lcom/google/android/gms/internal/ads/l90;Ljava/lang/Object;)V
    //   66: aload #5
    //   68: aload_3
    //   69: invokeinterface execute : (Ljava/lang/Runnable;)V
    //   74: goto -> 17
    //   77: aload_0
    //   78: monitorexit
    //   79: return
    //   80: astore_1
    //   81: aload_0
    //   82: monitorexit
    //   83: goto -> 88
    //   86: aload_1
    //   87: athrow
    //   88: goto -> 86
    // Exception table:
    //   from	to	target	type
    //   2	17	80	finally
    //   17	74	80	finally
  }
  
  public final void Y0(gb0<ListenerT> paramgb0) {
    // Byte code:
    //   0: aload_0
    //   1: monitorenter
    //   2: aload_0
    //   3: aload_1
    //   4: getfield a : Ljava/lang/Object;
    //   7: aload_1
    //   8: getfield b : Ljava/util/concurrent/Executor;
    //   11: invokevirtual Z0 : (Ljava/lang/Object;Ljava/util/concurrent/Executor;)V
    //   14: aload_0
    //   15: monitorexit
    //   16: return
    //   17: astore_1
    //   18: aload_0
    //   19: monitorexit
    //   20: aload_1
    //   21: athrow
    // Exception table:
    //   from	to	target	type
    //   2	14	17	finally
  }
  
  public final void Z0(ListenerT paramListenerT, Executor paramExecutor) {
    // Byte code:
    //   0: aload_0
    //   1: monitorenter
    //   2: aload_0
    //   3: getfield b : Ljava/util/Map;
    //   6: aload_1
    //   7: aload_2
    //   8: invokeinterface put : (Ljava/lang/Object;Ljava/lang/Object;)Ljava/lang/Object;
    //   13: pop
    //   14: aload_0
    //   15: monitorexit
    //   16: return
    //   17: astore_1
    //   18: aload_0
    //   19: monitorexit
    //   20: aload_1
    //   21: athrow
    // Exception table:
    //   from	to	target	type
    //   2	14	17	finally
  }
}


/* Location:              /home/sumith/decompile/test/classes-dex2jar.jar!/com/google/android/gms/internal/ads/j90.class
 * Java compiler version: 6 (50.0)
 * JD-Core Version:       1.1.3
 */