package com.google.android.gms.internal.ads;

import com.google.android.gms.ads.internal.overlay.p;
import com.google.android.gms.ads.internal.overlay.zzn;
import java.util.Set;

public final class l60 extends j90<p> implements p {
  public l60(Set<gb0<p>> paramSet) {
    super(paramSet);
  }
  
  public final void M0() {
    // Byte code:
    //   0: aload_0
    //   1: monitorenter
    //   2: aload_0
    //   3: getstatic com/google/android/gms/internal/ads/n60.a : Lcom/google/android/gms/internal/ads/l90;
    //   6: invokevirtual X0 : (Lcom/google/android/gms/internal/ads/l90;)V
    //   9: aload_0
    //   10: monitorexit
    //   11: return
    //   12: astore_1
    //   13: aload_0
    //   14: monitorexit
    //   15: aload_1
    //   16: athrow
    // Exception table:
    //   from	to	target	type
    //   2	9	12	finally
  }
  
  public final void R5(zzn paramzzn) {
    // Byte code:
    //   0: aload_0
    //   1: monitorenter
    //   2: new com/google/android/gms/internal/ads/k60
    //   5: astore_2
    //   6: aload_2
    //   7: aload_1
    //   8: invokespecial <init> : (Lcom/google/android/gms/ads/internal/overlay/zzn;)V
    //   11: aload_0
    //   12: aload_2
    //   13: invokevirtual X0 : (Lcom/google/android/gms/internal/ads/l90;)V
    //   16: aload_0
    //   17: monitorexit
    //   18: return
    //   19: astore_1
    //   20: aload_0
    //   21: monitorexit
    //   22: aload_1
    //   23: athrow
    // Exception table:
    //   from	to	target	type
    //   2	16	19	finally
  }
  
  public final void onPause() {
    // Byte code:
    //   0: aload_0
    //   1: monitorenter
    //   2: aload_0
    //   3: getstatic com/google/android/gms/internal/ads/m60.a : Lcom/google/android/gms/internal/ads/l90;
    //   6: invokevirtual X0 : (Lcom/google/android/gms/internal/ads/l90;)V
    //   9: aload_0
    //   10: monitorexit
    //   11: return
    //   12: astore_1
    //   13: aload_0
    //   14: monitorexit
    //   15: aload_1
    //   16: athrow
    // Exception table:
    //   from	to	target	type
    //   2	9	12	finally
  }
  
  public final void onResume() {
    // Byte code:
    //   0: aload_0
    //   1: monitorenter
    //   2: aload_0
    //   3: getstatic com/google/android/gms/internal/ads/p60.a : Lcom/google/android/gms/internal/ads/l90;
    //   6: invokevirtual X0 : (Lcom/google/android/gms/internal/ads/l90;)V
    //   9: aload_0
    //   10: monitorexit
    //   11: return
    //   12: astore_1
    //   13: aload_0
    //   14: monitorexit
    //   15: aload_1
    //   16: athrow
    // Exception table:
    //   from	to	target	type
    //   2	9	12	finally
  }
  
  public final void u9() {
    // Byte code:
    //   0: aload_0
    //   1: monitorenter
    //   2: aload_0
    //   3: getstatic com/google/android/gms/internal/ads/o60.a : Lcom/google/android/gms/internal/ads/l90;
    //   6: invokevirtual X0 : (Lcom/google/android/gms/internal/ads/l90;)V
    //   9: aload_0
    //   10: monitorexit
    //   11: return
    //   12: astore_1
    //   13: aload_0
    //   14: monitorexit
    //   15: aload_1
    //   16: athrow
    // Exception table:
    //   from	to	target	type
    //   2	9	12	finally
  }
}


/* Location:              /home/sumith/decompile/test/classes-dex2jar.jar!/com/google/android/gms/internal/ads/l60.class
 * Java compiler version: 6 (50.0)
 * JD-Core Version:       1.1.3
 */