package com.google.android.gms.internal.ads;

import java.util.List;
import org.json.JSONObject;

public final class lb {
  public final List<ib> a;
  
  private final long b;
  
  private final List<String> c;
  
  private final List<String> d;
  
  private final List<String> e;
  
  private final List<String> f;
  
  private final List<String> g;
  
  private final boolean h;
  
  private final String i;
  
  private final long j;
  
  private final String k;
  
  private final int l;
  
  private final int m;
  
  private final long n;
  
  private final boolean o;
  
  private final boolean p;
  
  private final boolean q;
  
  private final boolean r;
  
  private int s;
  
  private int t;
  
  private boolean u;
  
  public lb(JSONObject paramJSONObject) {
    // Byte code:
    //   0: aload_0
    //   1: invokespecial <init> : ()V
    //   4: iconst_2
    //   5: invokestatic a : (I)Z
    //   8: ifeq -> 51
    //   11: aload_1
    //   12: iconst_2
    //   13: invokevirtual toString : (I)Ljava/lang/String;
    //   16: invokestatic valueOf : (Ljava/lang/Object;)Ljava/lang/String;
    //   19: astore_2
    //   20: aload_2
    //   21: invokevirtual length : ()I
    //   24: ifeq -> 37
    //   27: ldc 'Mediation Response JSON: '
    //   29: aload_2
    //   30: invokevirtual concat : (Ljava/lang/String;)Ljava/lang/String;
    //   33: astore_2
    //   34: goto -> 47
    //   37: new java/lang/String
    //   40: dup
    //   41: ldc 'Mediation Response JSON: '
    //   43: invokespecial <init> : (Ljava/lang/String;)V
    //   46: astore_2
    //   47: aload_2
    //   48: invokestatic m : (Ljava/lang/String;)V
    //   51: aload_1
    //   52: ldc 'ad_networks'
    //   54: invokevirtual getJSONArray : (Ljava/lang/String;)Lorg/json/JSONArray;
    //   57: astore_2
    //   58: new java/util/ArrayList
    //   61: dup
    //   62: aload_2
    //   63: invokevirtual length : ()I
    //   66: invokespecial <init> : (I)V
    //   69: astore_3
    //   70: iconst_0
    //   71: istore #4
    //   73: iconst_m1
    //   74: istore #5
    //   76: iload #4
    //   78: aload_2
    //   79: invokevirtual length : ()I
    //   82: if_icmpge -> 213
    //   85: new com/google/android/gms/internal/ads/ib
    //   88: astore #6
    //   90: aload #6
    //   92: aload_2
    //   93: iload #4
    //   95: invokevirtual getJSONObject : (I)Lorg/json/JSONObject;
    //   98: invokespecial <init> : (Lorg/json/JSONObject;)V
    //   101: ldc 'banner'
    //   103: aload #6
    //   105: getfield v : Ljava/lang/String;
    //   108: invokevirtual equalsIgnoreCase : (Ljava/lang/String;)Z
    //   111: istore #7
    //   113: iconst_1
    //   114: istore #8
    //   116: iload #7
    //   118: ifeq -> 126
    //   121: aload_0
    //   122: iconst_1
    //   123: putfield u : Z
    //   126: aload_3
    //   127: aload #6
    //   129: invokeinterface add : (Ljava/lang/Object;)Z
    //   134: pop
    //   135: iload #5
    //   137: istore #9
    //   139: iload #5
    //   141: ifge -> 203
    //   144: aload #6
    //   146: getfield c : Ljava/util/List;
    //   149: invokeinterface iterator : ()Ljava/util/Iterator;
    //   154: astore #6
    //   156: aload #6
    //   158: invokeinterface hasNext : ()Z
    //   163: ifeq -> 187
    //   166: aload #6
    //   168: invokeinterface next : ()Ljava/lang/Object;
    //   173: checkcast java/lang/String
    //   176: ldc 'com.google.ads.mediation.admob.AdMobAdapter'
    //   178: invokevirtual equals : (Ljava/lang/Object;)Z
    //   181: ifeq -> 156
    //   184: goto -> 190
    //   187: iconst_0
    //   188: istore #8
    //   190: iload #5
    //   192: istore #9
    //   194: iload #8
    //   196: ifeq -> 203
    //   199: iload #4
    //   201: istore #9
    //   203: iinc #4, 1
    //   206: iload #9
    //   208: istore #5
    //   210: goto -> 76
    //   213: aload_0
    //   214: iload #5
    //   216: putfield s : I
    //   219: aload_0
    //   220: aload_2
    //   221: invokevirtual length : ()I
    //   224: putfield t : I
    //   227: aload_0
    //   228: aload_3
    //   229: invokestatic unmodifiableList : (Ljava/util/List;)Ljava/util/List;
    //   232: putfield a : Ljava/util/List;
    //   235: aload_0
    //   236: aload_1
    //   237: ldc 'qdata'
    //   239: invokevirtual optString : (Ljava/lang/String;)Ljava/lang/String;
    //   242: putfield i : Ljava/lang/String;
    //   245: aload_0
    //   246: aload_1
    //   247: ldc 'fs_model_type'
    //   249: iconst_m1
    //   250: invokevirtual optInt : (Ljava/lang/String;I)I
    //   253: putfield m : I
    //   256: ldc2_w -1
    //   259: lstore #10
    //   261: aload_0
    //   262: aload_1
    //   263: ldc 'timeout_ms'
    //   265: ldc2_w -1
    //   268: invokevirtual optLong : (Ljava/lang/String;J)J
    //   271: putfield n : J
    //   274: aload_1
    //   275: ldc 'settings'
    //   277: invokevirtual optJSONObject : (Ljava/lang/String;)Lorg/json/JSONObject;
    //   280: astore_1
    //   281: aload_1
    //   282: ifnull -> 500
    //   285: aload_0
    //   286: aload_1
    //   287: ldc 'ad_network_timeout_millis'
    //   289: ldc2_w -1
    //   292: invokevirtual optLong : (Ljava/lang/String;J)J
    //   295: putfield b : J
    //   298: invokestatic u : ()Lcom/google/android/gms/internal/ads/kb;
    //   301: pop
    //   302: aload_0
    //   303: aload_1
    //   304: ldc 'click_urls'
    //   306: invokestatic a : (Lorg/json/JSONObject;Ljava/lang/String;)Ljava/util/List;
    //   309: putfield c : Ljava/util/List;
    //   312: invokestatic u : ()Lcom/google/android/gms/internal/ads/kb;
    //   315: pop
    //   316: aload_0
    //   317: aload_1
    //   318: ldc 'imp_urls'
    //   320: invokestatic a : (Lorg/json/JSONObject;Ljava/lang/String;)Ljava/util/List;
    //   323: putfield d : Ljava/util/List;
    //   326: invokestatic u : ()Lcom/google/android/gms/internal/ads/kb;
    //   329: pop
    //   330: aload_0
    //   331: aload_1
    //   332: ldc 'downloaded_imp_urls'
    //   334: invokestatic a : (Lorg/json/JSONObject;Ljava/lang/String;)Ljava/util/List;
    //   337: putfield e : Ljava/util/List;
    //   340: invokestatic u : ()Lcom/google/android/gms/internal/ads/kb;
    //   343: pop
    //   344: aload_0
    //   345: aload_1
    //   346: ldc 'nofill_urls'
    //   348: invokestatic a : (Lorg/json/JSONObject;Ljava/lang/String;)Ljava/util/List;
    //   351: putfield f : Ljava/util/List;
    //   354: invokestatic u : ()Lcom/google/android/gms/internal/ads/kb;
    //   357: pop
    //   358: aload_0
    //   359: aload_1
    //   360: ldc 'remote_ping_urls'
    //   362: invokestatic a : (Lorg/json/JSONObject;Ljava/lang/String;)Ljava/util/List;
    //   365: putfield g : Ljava/util/List;
    //   368: aload_0
    //   369: aload_1
    //   370: ldc 'render_in_browser'
    //   372: iconst_0
    //   373: invokevirtual optBoolean : (Ljava/lang/String;Z)Z
    //   376: putfield h : Z
    //   379: aload_1
    //   380: ldc 'refresh'
    //   382: ldc2_w -1
    //   385: invokevirtual optLong : (Ljava/lang/String;J)J
    //   388: lstore #12
    //   390: lload #12
    //   392: lconst_0
    //   393: lcmp
    //   394: ifle -> 405
    //   397: ldc2_w 1000
    //   400: lload #12
    //   402: lmul
    //   403: lstore #10
    //   405: aload_0
    //   406: lload #10
    //   408: putfield j : J
    //   411: aload_1
    //   412: ldc 'rewards'
    //   414: invokevirtual optJSONArray : (Ljava/lang/String;)Lorg/json/JSONArray;
    //   417: invokestatic o0 : (Lorg/json/JSONArray;)Lcom/google/android/gms/internal/ads/zzavj;
    //   420: astore_2
    //   421: aload_2
    //   422: ifnonnull -> 438
    //   425: aload_0
    //   426: aconst_null
    //   427: putfield k : Ljava/lang/String;
    //   430: aload_0
    //   431: iconst_0
    //   432: putfield l : I
    //   435: goto -> 454
    //   438: aload_0
    //   439: aload_2
    //   440: getfield b : Ljava/lang/String;
    //   443: putfield k : Ljava/lang/String;
    //   446: aload_0
    //   447: aload_2
    //   448: getfield c : I
    //   451: putfield l : I
    //   454: aload_0
    //   455: aload_1
    //   456: ldc 'use_displayed_impression'
    //   458: iconst_0
    //   459: invokevirtual optBoolean : (Ljava/lang/String;Z)Z
    //   462: putfield o : Z
    //   465: aload_0
    //   466: aload_1
    //   467: ldc 'allow_pub_rendered_attribution'
    //   469: iconst_0
    //   470: invokevirtual optBoolean : (Ljava/lang/String;Z)Z
    //   473: putfield p : Z
    //   476: aload_0
    //   477: aload_1
    //   478: ldc 'allow_pub_owned_ad_view'
    //   480: iconst_0
    //   481: invokevirtual optBoolean : (Ljava/lang/String;Z)Z
    //   484: putfield q : Z
    //   487: aload_0
    //   488: aload_1
    //   489: ldc_w 'allow_custom_click_gesture'
    //   492: iconst_0
    //   493: invokevirtual optBoolean : (Ljava/lang/String;Z)Z
    //   496: putfield r : Z
    //   499: return
    //   500: aload_0
    //   501: ldc2_w -1
    //   504: putfield b : J
    //   507: aload_0
    //   508: aconst_null
    //   509: putfield c : Ljava/util/List;
    //   512: aload_0
    //   513: aconst_null
    //   514: putfield d : Ljava/util/List;
    //   517: aload_0
    //   518: aconst_null
    //   519: putfield e : Ljava/util/List;
    //   522: aload_0
    //   523: aconst_null
    //   524: putfield f : Ljava/util/List;
    //   527: aload_0
    //   528: aconst_null
    //   529: putfield g : Ljava/util/List;
    //   532: aload_0
    //   533: ldc2_w -1
    //   536: putfield j : J
    //   539: aload_0
    //   540: aconst_null
    //   541: putfield k : Ljava/lang/String;
    //   544: aload_0
    //   545: iconst_0
    //   546: putfield l : I
    //   549: aload_0
    //   550: iconst_0
    //   551: putfield o : Z
    //   554: aload_0
    //   555: iconst_0
    //   556: putfield h : Z
    //   559: aload_0
    //   560: iconst_0
    //   561: putfield p : Z
    //   564: aload_0
    //   565: iconst_0
    //   566: putfield q : Z
    //   569: aload_0
    //   570: iconst_0
    //   571: putfield r : Z
    //   574: return
    //   575: astore #6
    //   577: iload #5
    //   579: istore #9
    //   581: goto -> 203
    // Exception table:
    //   from	to	target	type
    //   85	101	575	org/json/JSONException
  }
}


/* Location:              /home/sumith/decompile/test/classes-dex2jar.jar!/com/google/android/gms/internal/ads/lb.class
 * Java compiler version: 6 (50.0)
 * JD-Core Version:       1.1.3
 */