package com.google.android.gms.internal.ads;

import android.os.Bundle;
import com.google.android.gms.ads.internal.overlay.p;
import com.google.android.gms.ads.internal.overlay.u;
import com.google.android.gms.ads.internal.overlay.zzn;

final class lk0 implements p, u, z5, b6, bq2 {
  private bq2 b;
  
  private z5 c;
  
  private p d;
  
  private b6 e;
  
  private u f;
  
  private lk0() {}
  
  private final void t(bq2 parambq2, z5 paramz5, p paramp, b6 paramb6, u paramu) {
    // Byte code:
    //   0: aload_0
    //   1: monitorenter
    //   2: aload_0
    //   3: aload_1
    //   4: putfield b : Lcom/google/android/gms/internal/ads/bq2;
    //   7: aload_0
    //   8: aload_2
    //   9: putfield c : Lcom/google/android/gms/internal/ads/z5;
    //   12: aload_0
    //   13: aload_3
    //   14: putfield d : Lcom/google/android/gms/ads/internal/overlay/p;
    //   17: aload_0
    //   18: aload #4
    //   20: putfield e : Lcom/google/android/gms/internal/ads/b6;
    //   23: aload_0
    //   24: aload #5
    //   26: putfield f : Lcom/google/android/gms/ads/internal/overlay/u;
    //   29: aload_0
    //   30: monitorexit
    //   31: return
    //   32: astore_1
    //   33: aload_0
    //   34: monitorexit
    //   35: aload_1
    //   36: athrow
    // Exception table:
    //   from	to	target	type
    //   2	29	32	finally
  }
  
  public final void M0() {
    // Byte code:
    //   0: aload_0
    //   1: monitorenter
    //   2: aload_0
    //   3: getfield d : Lcom/google/android/gms/ads/internal/overlay/p;
    //   6: astore_1
    //   7: aload_1
    //   8: ifnull -> 17
    //   11: aload_1
    //   12: invokeinterface M0 : ()V
    //   17: aload_0
    //   18: monitorexit
    //   19: return
    //   20: astore_1
    //   21: aload_0
    //   22: monitorexit
    //   23: aload_1
    //   24: athrow
    // Exception table:
    //   from	to	target	type
    //   2	7	20	finally
    //   11	17	20	finally
  }
  
  public final void R5(zzn paramzzn) {
    // Byte code:
    //   0: aload_0
    //   1: monitorenter
    //   2: aload_0
    //   3: getfield d : Lcom/google/android/gms/ads/internal/overlay/p;
    //   6: astore_2
    //   7: aload_2
    //   8: ifnull -> 18
    //   11: aload_2
    //   12: aload_1
    //   13: invokeinterface R5 : (Lcom/google/android/gms/ads/internal/overlay/zzn;)V
    //   18: aload_0
    //   19: monitorexit
    //   20: return
    //   21: astore_1
    //   22: aload_0
    //   23: monitorexit
    //   24: aload_1
    //   25: athrow
    // Exception table:
    //   from	to	target	type
    //   2	7	21	finally
    //   11	18	21	finally
  }
  
  public final void i() {
    // Byte code:
    //   0: aload_0
    //   1: monitorenter
    //   2: aload_0
    //   3: getfield f : Lcom/google/android/gms/ads/internal/overlay/u;
    //   6: astore_1
    //   7: aload_1
    //   8: ifnull -> 17
    //   11: aload_1
    //   12: invokeinterface i : ()V
    //   17: aload_0
    //   18: monitorexit
    //   19: return
    //   20: astore_1
    //   21: aload_0
    //   22: monitorexit
    //   23: aload_1
    //   24: athrow
    // Exception table:
    //   from	to	target	type
    //   2	7	20	finally
    //   11	17	20	finally
  }
  
  public final void l0(String paramString, Bundle paramBundle) {
    // Byte code:
    //   0: aload_0
    //   1: monitorenter
    //   2: aload_0
    //   3: getfield c : Lcom/google/android/gms/internal/ads/z5;
    //   6: astore_3
    //   7: aload_3
    //   8: ifnull -> 19
    //   11: aload_3
    //   12: aload_1
    //   13: aload_2
    //   14: invokeinterface l0 : (Ljava/lang/String;Landroid/os/Bundle;)V
    //   19: aload_0
    //   20: monitorexit
    //   21: return
    //   22: astore_1
    //   23: aload_0
    //   24: monitorexit
    //   25: aload_1
    //   26: athrow
    // Exception table:
    //   from	to	target	type
    //   2	7	22	finally
    //   11	19	22	finally
  }
  
  public final void n(String paramString1, String paramString2) {
    // Byte code:
    //   0: aload_0
    //   1: monitorenter
    //   2: aload_0
    //   3: getfield e : Lcom/google/android/gms/internal/ads/b6;
    //   6: astore_3
    //   7: aload_3
    //   8: ifnull -> 19
    //   11: aload_3
    //   12: aload_1
    //   13: aload_2
    //   14: invokeinterface n : (Ljava/lang/String;Ljava/lang/String;)V
    //   19: aload_0
    //   20: monitorexit
    //   21: return
    //   22: astore_1
    //   23: aload_0
    //   24: monitorexit
    //   25: aload_1
    //   26: athrow
    // Exception table:
    //   from	to	target	type
    //   2	7	22	finally
    //   11	19	22	finally
  }
  
  public final void onPause() {
    // Byte code:
    //   0: aload_0
    //   1: monitorenter
    //   2: aload_0
    //   3: getfield d : Lcom/google/android/gms/ads/internal/overlay/p;
    //   6: astore_1
    //   7: aload_1
    //   8: ifnull -> 17
    //   11: aload_1
    //   12: invokeinterface onPause : ()V
    //   17: aload_0
    //   18: monitorexit
    //   19: return
    //   20: astore_1
    //   21: aload_0
    //   22: monitorexit
    //   23: aload_1
    //   24: athrow
    // Exception table:
    //   from	to	target	type
    //   2	7	20	finally
    //   11	17	20	finally
  }
  
  public final void onResume() {
    // Byte code:
    //   0: aload_0
    //   1: monitorenter
    //   2: aload_0
    //   3: getfield d : Lcom/google/android/gms/ads/internal/overlay/p;
    //   6: astore_1
    //   7: aload_1
    //   8: ifnull -> 17
    //   11: aload_1
    //   12: invokeinterface onResume : ()V
    //   17: aload_0
    //   18: monitorexit
    //   19: return
    //   20: astore_1
    //   21: aload_0
    //   22: monitorexit
    //   23: aload_1
    //   24: athrow
    // Exception table:
    //   from	to	target	type
    //   2	7	20	finally
    //   11	17	20	finally
  }
  
  public final void u9() {
    // Byte code:
    //   0: aload_0
    //   1: monitorenter
    //   2: aload_0
    //   3: getfield d : Lcom/google/android/gms/ads/internal/overlay/p;
    //   6: astore_1
    //   7: aload_1
    //   8: ifnull -> 17
    //   11: aload_1
    //   12: invokeinterface u9 : ()V
    //   17: aload_0
    //   18: monitorexit
    //   19: return
    //   20: astore_1
    //   21: aload_0
    //   22: monitorexit
    //   23: aload_1
    //   24: athrow
    // Exception table:
    //   from	to	target	type
    //   2	7	20	finally
    //   11	17	20	finally
  }
  
  public final void x() {
    // Byte code:
    //   0: aload_0
    //   1: monitorenter
    //   2: aload_0
    //   3: getfield b : Lcom/google/android/gms/internal/ads/bq2;
    //   6: astore_1
    //   7: aload_1
    //   8: ifnull -> 17
    //   11: aload_1
    //   12: invokeinterface x : ()V
    //   17: aload_0
    //   18: monitorexit
    //   19: return
    //   20: astore_1
    //   21: aload_0
    //   22: monitorexit
    //   23: aload_1
    //   24: athrow
    // Exception table:
    //   from	to	target	type
    //   2	7	20	finally
    //   11	17	20	finally
  }
}


/* Location:              /home/sumith/decompile/test/classes-dex2jar.jar!/com/google/android/gms/internal/ads/lk0.class
 * Java compiler version: 6 (50.0)
 * JD-Core Version:       1.1.3
 */