package com.google.android.gms.internal.ads;

public final class of0 {
  private i3 a;
  
  public of0(df0 paramdf0) {
    this.a = paramdf0;
  }
  
  public final void a(i3 parami3) {
    // Byte code:
    //   0: aload_0
    //   1: monitorenter
    //   2: aload_0
    //   3: aload_1
    //   4: putfield a : Lcom/google/android/gms/internal/ads/i3;
    //   7: aload_0
    //   8: monitorexit
    //   9: return
    //   10: astore_1
    //   11: aload_0
    //   12: monitorexit
    //   13: aload_1
    //   14: athrow
    // Exception table:
    //   from	to	target	type
    //   2	7	10	finally
  }
  
  public final i3 b() {
    // Byte code:
    //   0: aload_0
    //   1: monitorenter
    //   2: aload_0
    //   3: getfield a : Lcom/google/android/gms/internal/ads/i3;
    //   6: astore_1
    //   7: aload_0
    //   8: monitorexit
    //   9: aload_1
    //   10: areturn
    //   11: astore_1
    //   12: aload_0
    //   13: monitorexit
    //   14: aload_1
    //   15: athrow
    // Exception table:
    //   from	to	target	type
    //   2	7	11	finally
  }
}


/* Location:              /home/sumith/decompile/test/classes-dex2jar.jar!/com/google/android/gms/internal/ads/of0.class
 * Java compiler version: 6 (50.0)
 * JD-Core Version:       1.1.3
 */