package com.google.android.gms.internal.ads;

import android.os.Bundle;
import android.os.IBinder;
import android.os.RemoteException;
import android.view.View;
import b.e.g;
import com.google.android.gms.dynamic.a;
import com.google.android.gms.dynamic.b;
import java.util.Collections;
import java.util.List;

public final class pf0 {
  private int a;
  
  private nt2 b;
  
  private f3 c;
  
  private View d;
  
  private List<?> e;
  
  private List<du2> f = Collections.emptyList();
  
  private du2 g;
  
  private Bundle h;
  
  private tq i;
  
  private tq j;
  
  private a k;
  
  private View l;
  
  private a m;
  
  private double n;
  
  private m3 o;
  
  private m3 p;
  
  private String q;
  
  private g<String, a3> r = new g();
  
  private g<String, String> s = new g();
  
  private float t;
  
  private String u;
  
  private static <T> T M(a parama) {
    return (T)((parama == null) ? null : b.o1(parama));
  }
  
  public static pf0 N(zb paramzb) {
    try {
      return t(u(paramzb.getVideoController(), null), paramzb.g(), M(paramzb.a0()), paramzb.f(), paramzb.k(), paramzb.j(), paramzb.d(), paramzb.h(), M(paramzb.W()), paramzb.e(), paramzb.C(), paramzb.s(), paramzb.w(), paramzb.t(), null, 0.0F);
    } catch (RemoteException remoteException) {
      cm.d("Failed to get native ad assets from app install ad mapper", (Throwable)remoteException);
      return null;
    } 
  }
  
  public static pf0 O(ac paramac) {
    try {
      return t(u(paramac.getVideoController(), null), paramac.g(), M(paramac.a0()), paramac.f(), paramac.k(), paramac.j(), paramac.d(), paramac.h(), M(paramac.W()), paramac.e(), null, null, -1.0D, paramac.k1(), paramac.B(), 0.0F);
    } catch (RemoteException remoteException) {
      cm.d("Failed to get native ad assets from content ad mapper", (Throwable)remoteException);
      return null;
    } 
  }
  
  public static pf0 P(fc paramfc) {
    try {
      return t(u(paramfc.getVideoController(), paramfc), paramfc.g(), M(paramfc.a0()), paramfc.f(), paramfc.k(), paramfc.j(), paramfc.d(), paramfc.h(), M(paramfc.W()), paramfc.e(), paramfc.C(), paramfc.s(), paramfc.w(), paramfc.t(), paramfc.B(), paramfc.b2());
    } catch (RemoteException remoteException) {
      cm.d("Failed to get native ad assets from unified ad mapper", (Throwable)remoteException);
      return null;
    } 
  }
  
  private final String W(String paramString) {
    // Byte code:
    //   0: aload_0
    //   1: monitorenter
    //   2: aload_0
    //   3: getfield s : Lb/e/g;
    //   6: aload_1
    //   7: invokevirtual get : (Ljava/lang/Object;)Ljava/lang/Object;
    //   10: checkcast java/lang/String
    //   13: astore_1
    //   14: aload_0
    //   15: monitorexit
    //   16: aload_1
    //   17: areturn
    //   18: astore_1
    //   19: aload_0
    //   20: monitorexit
    //   21: aload_1
    //   22: athrow
    // Exception table:
    //   from	to	target	type
    //   2	14	18	finally
  }
  
  private final void p(float paramFloat) {
    // Byte code:
    //   0: aload_0
    //   1: monitorenter
    //   2: aload_0
    //   3: fload_1
    //   4: putfield t : F
    //   7: aload_0
    //   8: monitorexit
    //   9: return
    //   10: astore_2
    //   11: aload_0
    //   12: monitorexit
    //   13: aload_2
    //   14: athrow
    // Exception table:
    //   from	to	target	type
    //   2	7	10	finally
  }
  
  public static pf0 r(zb paramzb) {
    try {
      qf0 qf0 = u(paramzb.getVideoController(), null);
      f3 f31 = paramzb.g();
      View view1 = M(paramzb.a0());
      String str1 = paramzb.f();
      List<?> list = paramzb.k();
      String str2 = paramzb.j();
      Bundle bundle = paramzb.d();
      String str3 = paramzb.h();
      View view2 = M(paramzb.W());
      a a1 = paramzb.e();
      String str4 = paramzb.C();
      String str5 = paramzb.s();
      double d = paramzb.w();
      m3 m31 = paramzb.t();
      pf0 pf01 = new pf0();
      this();
      pf01.a = 2;
      pf01.b = qf0;
      pf01.c = f31;
      pf01.d = view1;
      pf01.Z("headline", str1);
      pf01.e = list;
      pf01.Z("body", str2);
      pf01.h = bundle;
      pf01.Z("call_to_action", str3);
      pf01.l = view2;
      pf01.m = a1;
      pf01.Z("store", str4);
      pf01.Z("price", str5);
      pf01.n = d;
      pf01.o = m31;
      return pf01;
    } catch (RemoteException remoteException) {
      cm.d("Failed to get native ad from app install ad mapper", (Throwable)remoteException);
      return null;
    } 
  }
  
  public static pf0 s(ac paramac) {
    try {
      qf0 qf0 = u(paramac.getVideoController(), null);
      f3 f31 = paramac.g();
      View view1 = M(paramac.a0());
      String str1 = paramac.f();
      List<?> list = paramac.k();
      String str2 = paramac.j();
      Bundle bundle = paramac.d();
      String str3 = paramac.h();
      View view2 = M(paramac.W());
      a a1 = paramac.e();
      String str4 = paramac.B();
      m3 m31 = paramac.k1();
      pf0 pf01 = new pf0();
      this();
      pf01.a = 1;
      pf01.b = qf0;
      pf01.c = f31;
      pf01.d = view1;
      pf01.Z("headline", str1);
      pf01.e = list;
      pf01.Z("body", str2);
      pf01.h = bundle;
      pf01.Z("call_to_action", str3);
      pf01.l = view2;
      pf01.m = a1;
      pf01.Z("advertiser", str4);
      pf01.p = m31;
      return pf01;
    } catch (RemoteException remoteException) {
      cm.d("Failed to get native ad from content ad mapper", (Throwable)remoteException);
      return null;
    } 
  }
  
  private static pf0 t(nt2 paramnt2, f3 paramf3, View paramView1, String paramString1, List<?> paramList, String paramString2, Bundle paramBundle, String paramString3, View paramView2, a parama, String paramString4, String paramString5, double paramDouble, m3 paramm3, String paramString6, float paramFloat) {
    pf0 pf01 = new pf0();
    pf01.a = 6;
    pf01.b = paramnt2;
    pf01.c = paramf3;
    pf01.d = paramView1;
    pf01.Z("headline", paramString1);
    pf01.e = paramList;
    pf01.Z("body", paramString2);
    pf01.h = paramBundle;
    pf01.Z("call_to_action", paramString3);
    pf01.l = paramView2;
    pf01.m = parama;
    pf01.Z("store", paramString4);
    pf01.Z("price", paramString5);
    pf01.n = paramDouble;
    pf01.o = paramm3;
    pf01.Z("advertiser", paramString6);
    pf01.p(paramFloat);
    return pf01;
  }
  
  private static qf0 u(nt2 paramnt2, fc paramfc) {
    return (paramnt2 == null) ? null : new qf0(paramnt2, paramfc);
  }
  
  public final int A() {
    // Byte code:
    //   0: aload_0
    //   1: monitorenter
    //   2: aload_0
    //   3: getfield a : I
    //   6: istore_1
    //   7: aload_0
    //   8: monitorexit
    //   9: iload_1
    //   10: ireturn
    //   11: astore_2
    //   12: aload_0
    //   13: monitorexit
    //   14: aload_2
    //   15: athrow
    // Exception table:
    //   from	to	target	type
    //   2	7	11	finally
  }
  
  public final View B() {
    // Byte code:
    //   0: aload_0
    //   1: monitorenter
    //   2: aload_0
    //   3: getfield d : Landroid/view/View;
    //   6: astore_1
    //   7: aload_0
    //   8: monitorexit
    //   9: aload_1
    //   10: areturn
    //   11: astore_1
    //   12: aload_0
    //   13: monitorexit
    //   14: aload_1
    //   15: athrow
    // Exception table:
    //   from	to	target	type
    //   2	7	11	finally
  }
  
  public final m3 C() {
    List<?> list = this.e;
    if (list != null && list.size() != 0) {
      list = (List<?>)this.e.get(0);
      if (list instanceof IBinder)
        return l3.S9((IBinder)list); 
    } 
    return null;
  }
  
  public final du2 D() {
    // Byte code:
    //   0: aload_0
    //   1: monitorenter
    //   2: aload_0
    //   3: getfield g : Lcom/google/android/gms/internal/ads/du2;
    //   6: astore_1
    //   7: aload_0
    //   8: monitorexit
    //   9: aload_1
    //   10: areturn
    //   11: astore_1
    //   12: aload_0
    //   13: monitorexit
    //   14: aload_1
    //   15: athrow
    // Exception table:
    //   from	to	target	type
    //   2	7	11	finally
  }
  
  public final View E() {
    // Byte code:
    //   0: aload_0
    //   1: monitorenter
    //   2: aload_0
    //   3: getfield l : Landroid/view/View;
    //   6: astore_1
    //   7: aload_0
    //   8: monitorexit
    //   9: aload_1
    //   10: areturn
    //   11: astore_1
    //   12: aload_0
    //   13: monitorexit
    //   14: aload_1
    //   15: athrow
    // Exception table:
    //   from	to	target	type
    //   2	7	11	finally
  }
  
  public final tq F() {
    // Byte code:
    //   0: aload_0
    //   1: monitorenter
    //   2: aload_0
    //   3: getfield i : Lcom/google/android/gms/internal/ads/tq;
    //   6: astore_1
    //   7: aload_0
    //   8: monitorexit
    //   9: aload_1
    //   10: areturn
    //   11: astore_1
    //   12: aload_0
    //   13: monitorexit
    //   14: aload_1
    //   15: athrow
    // Exception table:
    //   from	to	target	type
    //   2	7	11	finally
  }
  
  public final tq G() {
    // Byte code:
    //   0: aload_0
    //   1: monitorenter
    //   2: aload_0
    //   3: getfield j : Lcom/google/android/gms/internal/ads/tq;
    //   6: astore_1
    //   7: aload_0
    //   8: monitorexit
    //   9: aload_1
    //   10: areturn
    //   11: astore_1
    //   12: aload_0
    //   13: monitorexit
    //   14: aload_1
    //   15: athrow
    // Exception table:
    //   from	to	target	type
    //   2	7	11	finally
  }
  
  public final a H() {
    // Byte code:
    //   0: aload_0
    //   1: monitorenter
    //   2: aload_0
    //   3: getfield k : Lcom/google/android/gms/dynamic/a;
    //   6: astore_1
    //   7: aload_0
    //   8: monitorexit
    //   9: aload_1
    //   10: areturn
    //   11: astore_1
    //   12: aload_0
    //   13: monitorexit
    //   14: aload_1
    //   15: athrow
    // Exception table:
    //   from	to	target	type
    //   2	7	11	finally
  }
  
  public final g<String, a3> I() {
    // Byte code:
    //   0: aload_0
    //   1: monitorenter
    //   2: aload_0
    //   3: getfield r : Lb/e/g;
    //   6: astore_1
    //   7: aload_0
    //   8: monitorexit
    //   9: aload_1
    //   10: areturn
    //   11: astore_1
    //   12: aload_0
    //   13: monitorexit
    //   14: aload_1
    //   15: athrow
    // Exception table:
    //   from	to	target	type
    //   2	7	11	finally
  }
  
  public final String J() {
    // Byte code:
    //   0: aload_0
    //   1: monitorenter
    //   2: aload_0
    //   3: getfield u : Ljava/lang/String;
    //   6: astore_1
    //   7: aload_0
    //   8: monitorexit
    //   9: aload_1
    //   10: areturn
    //   11: astore_1
    //   12: aload_0
    //   13: monitorexit
    //   14: aload_1
    //   15: athrow
    // Exception table:
    //   from	to	target	type
    //   2	7	11	finally
  }
  
  public final g<String, String> K() {
    // Byte code:
    //   0: aload_0
    //   1: monitorenter
    //   2: aload_0
    //   3: getfield s : Lb/e/g;
    //   6: astore_1
    //   7: aload_0
    //   8: monitorexit
    //   9: aload_1
    //   10: areturn
    //   11: astore_1
    //   12: aload_0
    //   13: monitorexit
    //   14: aload_1
    //   15: athrow
    // Exception table:
    //   from	to	target	type
    //   2	7	11	finally
  }
  
  public final void L(a parama) {
    // Byte code:
    //   0: aload_0
    //   1: monitorenter
    //   2: aload_0
    //   3: aload_1
    //   4: putfield k : Lcom/google/android/gms/dynamic/a;
    //   7: aload_0
    //   8: monitorexit
    //   9: return
    //   10: astore_1
    //   11: aload_0
    //   12: monitorexit
    //   13: aload_1
    //   14: athrow
    // Exception table:
    //   from	to	target	type
    //   2	7	10	finally
  }
  
  public final void Q(m3 paramm3) {
    // Byte code:
    //   0: aload_0
    //   1: monitorenter
    //   2: aload_0
    //   3: aload_1
    //   4: putfield p : Lcom/google/android/gms/internal/ads/m3;
    //   7: aload_0
    //   8: monitorexit
    //   9: return
    //   10: astore_1
    //   11: aload_0
    //   12: monitorexit
    //   13: aload_1
    //   14: athrow
    // Exception table:
    //   from	to	target	type
    //   2	7	10	finally
  }
  
  public final void R(nt2 paramnt2) {
    // Byte code:
    //   0: aload_0
    //   1: monitorenter
    //   2: aload_0
    //   3: aload_1
    //   4: putfield b : Lcom/google/android/gms/internal/ads/nt2;
    //   7: aload_0
    //   8: monitorexit
    //   9: return
    //   10: astore_1
    //   11: aload_0
    //   12: monitorexit
    //   13: aload_1
    //   14: athrow
    // Exception table:
    //   from	to	target	type
    //   2	7	10	finally
  }
  
  public final void S(int paramInt) {
    // Byte code:
    //   0: aload_0
    //   1: monitorenter
    //   2: aload_0
    //   3: iload_1
    //   4: putfield a : I
    //   7: aload_0
    //   8: monitorexit
    //   9: return
    //   10: astore_2
    //   11: aload_0
    //   12: monitorexit
    //   13: aload_2
    //   14: athrow
    // Exception table:
    //   from	to	target	type
    //   2	7	10	finally
  }
  
  public final void T(tq paramtq) {
    // Byte code:
    //   0: aload_0
    //   1: monitorenter
    //   2: aload_0
    //   3: aload_1
    //   4: putfield i : Lcom/google/android/gms/internal/ads/tq;
    //   7: aload_0
    //   8: monitorexit
    //   9: return
    //   10: astore_1
    //   11: aload_0
    //   12: monitorexit
    //   13: aload_1
    //   14: athrow
    // Exception table:
    //   from	to	target	type
    //   2	7	10	finally
  }
  
  public final void U(String paramString) {
    // Byte code:
    //   0: aload_0
    //   1: monitorenter
    //   2: aload_0
    //   3: aload_1
    //   4: putfield q : Ljava/lang/String;
    //   7: aload_0
    //   8: monitorexit
    //   9: return
    //   10: astore_1
    //   11: aload_0
    //   12: monitorexit
    //   13: aload_1
    //   14: athrow
    // Exception table:
    //   from	to	target	type
    //   2	7	10	finally
  }
  
  public final void V(String paramString) {
    // Byte code:
    //   0: aload_0
    //   1: monitorenter
    //   2: aload_0
    //   3: aload_1
    //   4: putfield u : Ljava/lang/String;
    //   7: aload_0
    //   8: monitorexit
    //   9: return
    //   10: astore_1
    //   11: aload_0
    //   12: monitorexit
    //   13: aload_1
    //   14: athrow
    // Exception table:
    //   from	to	target	type
    //   2	7	10	finally
  }
  
  public final void X(tq paramtq) {
    // Byte code:
    //   0: aload_0
    //   1: monitorenter
    //   2: aload_0
    //   3: aload_1
    //   4: putfield j : Lcom/google/android/gms/internal/ads/tq;
    //   7: aload_0
    //   8: monitorexit
    //   9: return
    //   10: astore_1
    //   11: aload_0
    //   12: monitorexit
    //   13: aload_1
    //   14: athrow
    // Exception table:
    //   from	to	target	type
    //   2	7	10	finally
  }
  
  public final void Y(List<du2> paramList) {
    // Byte code:
    //   0: aload_0
    //   1: monitorenter
    //   2: aload_0
    //   3: aload_1
    //   4: putfield f : Ljava/util/List;
    //   7: aload_0
    //   8: monitorexit
    //   9: return
    //   10: astore_1
    //   11: aload_0
    //   12: monitorexit
    //   13: aload_1
    //   14: athrow
    // Exception table:
    //   from	to	target	type
    //   2	7	10	finally
  }
  
  public final void Z(String paramString1, String paramString2) {
    // Byte code:
    //   0: aload_0
    //   1: monitorenter
    //   2: aload_2
    //   3: ifnonnull -> 18
    //   6: aload_0
    //   7: getfield s : Lb/e/g;
    //   10: aload_1
    //   11: invokevirtual remove : (Ljava/lang/Object;)Ljava/lang/Object;
    //   14: pop
    //   15: aload_0
    //   16: monitorexit
    //   17: return
    //   18: aload_0
    //   19: getfield s : Lb/e/g;
    //   22: aload_1
    //   23: aload_2
    //   24: invokevirtual put : (Ljava/lang/Object;Ljava/lang/Object;)Ljava/lang/Object;
    //   27: pop
    //   28: aload_0
    //   29: monitorexit
    //   30: return
    //   31: astore_1
    //   32: aload_0
    //   33: monitorexit
    //   34: aload_1
    //   35: athrow
    // Exception table:
    //   from	to	target	type
    //   6	15	31	finally
    //   18	28	31	finally
  }
  
  public final void a() {
    // Byte code:
    //   0: aload_0
    //   1: monitorenter
    //   2: aload_0
    //   3: getfield i : Lcom/google/android/gms/internal/ads/tq;
    //   6: astore_1
    //   7: aload_1
    //   8: ifnull -> 22
    //   11: aload_1
    //   12: invokeinterface destroy : ()V
    //   17: aload_0
    //   18: aconst_null
    //   19: putfield i : Lcom/google/android/gms/internal/ads/tq;
    //   22: aload_0
    //   23: getfield j : Lcom/google/android/gms/internal/ads/tq;
    //   26: astore_1
    //   27: aload_1
    //   28: ifnull -> 42
    //   31: aload_1
    //   32: invokeinterface destroy : ()V
    //   37: aload_0
    //   38: aconst_null
    //   39: putfield j : Lcom/google/android/gms/internal/ads/tq;
    //   42: aload_0
    //   43: aconst_null
    //   44: putfield k : Lcom/google/android/gms/dynamic/a;
    //   47: aload_0
    //   48: getfield r : Lb/e/g;
    //   51: invokevirtual clear : ()V
    //   54: aload_0
    //   55: getfield s : Lb/e/g;
    //   58: invokevirtual clear : ()V
    //   61: aload_0
    //   62: aconst_null
    //   63: putfield b : Lcom/google/android/gms/internal/ads/nt2;
    //   66: aload_0
    //   67: aconst_null
    //   68: putfield c : Lcom/google/android/gms/internal/ads/f3;
    //   71: aload_0
    //   72: aconst_null
    //   73: putfield d : Landroid/view/View;
    //   76: aload_0
    //   77: aconst_null
    //   78: putfield e : Ljava/util/List;
    //   81: aload_0
    //   82: aconst_null
    //   83: putfield h : Landroid/os/Bundle;
    //   86: aload_0
    //   87: aconst_null
    //   88: putfield l : Landroid/view/View;
    //   91: aload_0
    //   92: aconst_null
    //   93: putfield m : Lcom/google/android/gms/dynamic/a;
    //   96: aload_0
    //   97: aconst_null
    //   98: putfield o : Lcom/google/android/gms/internal/ads/m3;
    //   101: aload_0
    //   102: aconst_null
    //   103: putfield p : Lcom/google/android/gms/internal/ads/m3;
    //   106: aload_0
    //   107: aconst_null
    //   108: putfield q : Ljava/lang/String;
    //   111: aload_0
    //   112: monitorexit
    //   113: return
    //   114: astore_1
    //   115: aload_0
    //   116: monitorexit
    //   117: aload_1
    //   118: athrow
    // Exception table:
    //   from	to	target	type
    //   2	7	114	finally
    //   11	22	114	finally
    //   22	27	114	finally
    //   31	42	114	finally
    //   42	111	114	finally
  }
  
  public final m3 a0() {
    // Byte code:
    //   0: aload_0
    //   1: monitorenter
    //   2: aload_0
    //   3: getfield o : Lcom/google/android/gms/internal/ads/m3;
    //   6: astore_1
    //   7: aload_0
    //   8: monitorexit
    //   9: aload_1
    //   10: areturn
    //   11: astore_1
    //   12: aload_0
    //   13: monitorexit
    //   14: aload_1
    //   15: athrow
    // Exception table:
    //   from	to	target	type
    //   2	7	11	finally
  }
  
  public final String b() {
    // Byte code:
    //   0: aload_0
    //   1: monitorenter
    //   2: aload_0
    //   3: ldc 'advertiser'
    //   5: invokespecial W : (Ljava/lang/String;)Ljava/lang/String;
    //   8: astore_1
    //   9: aload_0
    //   10: monitorexit
    //   11: aload_1
    //   12: areturn
    //   13: astore_1
    //   14: aload_0
    //   15: monitorexit
    //   16: aload_1
    //   17: athrow
    // Exception table:
    //   from	to	target	type
    //   2	9	13	finally
  }
  
  public final f3 b0() {
    // Byte code:
    //   0: aload_0
    //   1: monitorenter
    //   2: aload_0
    //   3: getfield c : Lcom/google/android/gms/internal/ads/f3;
    //   6: astore_1
    //   7: aload_0
    //   8: monitorexit
    //   9: aload_1
    //   10: areturn
    //   11: astore_1
    //   12: aload_0
    //   13: monitorexit
    //   14: aload_1
    //   15: athrow
    // Exception table:
    //   from	to	target	type
    //   2	7	11	finally
  }
  
  public final String c() {
    // Byte code:
    //   0: aload_0
    //   1: monitorenter
    //   2: aload_0
    //   3: ldc 'body'
    //   5: invokespecial W : (Ljava/lang/String;)Ljava/lang/String;
    //   8: astore_1
    //   9: aload_0
    //   10: monitorexit
    //   11: aload_1
    //   12: areturn
    //   13: astore_1
    //   14: aload_0
    //   15: monitorexit
    //   16: aload_1
    //   17: athrow
    // Exception table:
    //   from	to	target	type
    //   2	9	13	finally
  }
  
  public final a c0() {
    // Byte code:
    //   0: aload_0
    //   1: monitorenter
    //   2: aload_0
    //   3: getfield m : Lcom/google/android/gms/dynamic/a;
    //   6: astore_1
    //   7: aload_0
    //   8: monitorexit
    //   9: aload_1
    //   10: areturn
    //   11: astore_1
    //   12: aload_0
    //   13: monitorexit
    //   14: aload_1
    //   15: athrow
    // Exception table:
    //   from	to	target	type
    //   2	7	11	finally
  }
  
  public final String d() {
    // Byte code:
    //   0: aload_0
    //   1: monitorenter
    //   2: aload_0
    //   3: ldc 'call_to_action'
    //   5: invokespecial W : (Ljava/lang/String;)Ljava/lang/String;
    //   8: astore_1
    //   9: aload_0
    //   10: monitorexit
    //   11: aload_1
    //   12: areturn
    //   13: astore_1
    //   14: aload_0
    //   15: monitorexit
    //   16: aload_1
    //   17: athrow
    // Exception table:
    //   from	to	target	type
    //   2	9	13	finally
  }
  
  public final m3 d0() {
    // Byte code:
    //   0: aload_0
    //   1: monitorenter
    //   2: aload_0
    //   3: getfield p : Lcom/google/android/gms/internal/ads/m3;
    //   6: astore_1
    //   7: aload_0
    //   8: monitorexit
    //   9: aload_1
    //   10: areturn
    //   11: astore_1
    //   12: aload_0
    //   13: monitorexit
    //   14: aload_1
    //   15: athrow
    // Exception table:
    //   from	to	target	type
    //   2	7	11	finally
  }
  
  public final String e() {
    // Byte code:
    //   0: aload_0
    //   1: monitorenter
    //   2: aload_0
    //   3: getfield q : Ljava/lang/String;
    //   6: astore_1
    //   7: aload_0
    //   8: monitorexit
    //   9: aload_1
    //   10: areturn
    //   11: astore_1
    //   12: aload_0
    //   13: monitorexit
    //   14: aload_1
    //   15: athrow
    // Exception table:
    //   from	to	target	type
    //   2	7	11	finally
  }
  
  public final Bundle f() {
    // Byte code:
    //   0: aload_0
    //   1: monitorenter
    //   2: aload_0
    //   3: getfield h : Landroid/os/Bundle;
    //   6: ifnonnull -> 22
    //   9: new android/os/Bundle
    //   12: astore_1
    //   13: aload_1
    //   14: invokespecial <init> : ()V
    //   17: aload_0
    //   18: aload_1
    //   19: putfield h : Landroid/os/Bundle;
    //   22: aload_0
    //   23: getfield h : Landroid/os/Bundle;
    //   26: astore_1
    //   27: aload_0
    //   28: monitorexit
    //   29: aload_1
    //   30: areturn
    //   31: astore_1
    //   32: aload_0
    //   33: monitorexit
    //   34: aload_1
    //   35: athrow
    // Exception table:
    //   from	to	target	type
    //   2	22	31	finally
    //   22	27	31	finally
  }
  
  public final String g() {
    // Byte code:
    //   0: aload_0
    //   1: monitorenter
    //   2: aload_0
    //   3: ldc 'headline'
    //   5: invokespecial W : (Ljava/lang/String;)Ljava/lang/String;
    //   8: astore_1
    //   9: aload_0
    //   10: monitorexit
    //   11: aload_1
    //   12: areturn
    //   13: astore_1
    //   14: aload_0
    //   15: monitorexit
    //   16: aload_1
    //   17: athrow
    // Exception table:
    //   from	to	target	type
    //   2	9	13	finally
  }
  
  public final List<?> h() {
    // Byte code:
    //   0: aload_0
    //   1: monitorenter
    //   2: aload_0
    //   3: getfield e : Ljava/util/List;
    //   6: astore_1
    //   7: aload_0
    //   8: monitorexit
    //   9: aload_1
    //   10: areturn
    //   11: astore_1
    //   12: aload_0
    //   13: monitorexit
    //   14: aload_1
    //   15: athrow
    // Exception table:
    //   from	to	target	type
    //   2	7	11	finally
  }
  
  public final float i() {
    // Byte code:
    //   0: aload_0
    //   1: monitorenter
    //   2: aload_0
    //   3: getfield t : F
    //   6: fstore_1
    //   7: aload_0
    //   8: monitorexit
    //   9: fload_1
    //   10: freturn
    //   11: astore_2
    //   12: aload_0
    //   13: monitorexit
    //   14: aload_2
    //   15: athrow
    // Exception table:
    //   from	to	target	type
    //   2	7	11	finally
  }
  
  public final List<du2> j() {
    // Byte code:
    //   0: aload_0
    //   1: monitorenter
    //   2: aload_0
    //   3: getfield f : Ljava/util/List;
    //   6: astore_1
    //   7: aload_0
    //   8: monitorexit
    //   9: aload_1
    //   10: areturn
    //   11: astore_1
    //   12: aload_0
    //   13: monitorexit
    //   14: aload_1
    //   15: athrow
    // Exception table:
    //   from	to	target	type
    //   2	7	11	finally
  }
  
  public final String k() {
    // Byte code:
    //   0: aload_0
    //   1: monitorenter
    //   2: aload_0
    //   3: ldc 'price'
    //   5: invokespecial W : (Ljava/lang/String;)Ljava/lang/String;
    //   8: astore_1
    //   9: aload_0
    //   10: monitorexit
    //   11: aload_1
    //   12: areturn
    //   13: astore_1
    //   14: aload_0
    //   15: monitorexit
    //   16: aload_1
    //   17: athrow
    // Exception table:
    //   from	to	target	type
    //   2	9	13	finally
  }
  
  public final double l() {
    // Byte code:
    //   0: aload_0
    //   1: monitorenter
    //   2: aload_0
    //   3: getfield n : D
    //   6: dstore_1
    //   7: aload_0
    //   8: monitorexit
    //   9: dload_1
    //   10: dreturn
    //   11: astore_3
    //   12: aload_0
    //   13: monitorexit
    //   14: aload_3
    //   15: athrow
    // Exception table:
    //   from	to	target	type
    //   2	7	11	finally
  }
  
  public final String m() {
    // Byte code:
    //   0: aload_0
    //   1: monitorenter
    //   2: aload_0
    //   3: ldc 'store'
    //   5: invokespecial W : (Ljava/lang/String;)Ljava/lang/String;
    //   8: astore_1
    //   9: aload_0
    //   10: monitorexit
    //   11: aload_1
    //   12: areturn
    //   13: astore_1
    //   14: aload_0
    //   15: monitorexit
    //   16: aload_1
    //   17: athrow
    // Exception table:
    //   from	to	target	type
    //   2	9	13	finally
  }
  
  public final nt2 n() {
    // Byte code:
    //   0: aload_0
    //   1: monitorenter
    //   2: aload_0
    //   3: getfield b : Lcom/google/android/gms/internal/ads/nt2;
    //   6: astore_1
    //   7: aload_0
    //   8: monitorexit
    //   9: aload_1
    //   10: areturn
    //   11: astore_1
    //   12: aload_0
    //   13: monitorexit
    //   14: aload_1
    //   15: athrow
    // Exception table:
    //   from	to	target	type
    //   2	7	11	finally
  }
  
  public final void o(List<a3> paramList) {
    // Byte code:
    //   0: aload_0
    //   1: monitorenter
    //   2: aload_0
    //   3: aload_1
    //   4: putfield e : Ljava/util/List;
    //   7: aload_0
    //   8: monitorexit
    //   9: return
    //   10: astore_1
    //   11: aload_0
    //   12: monitorexit
    //   13: aload_1
    //   14: athrow
    // Exception table:
    //   from	to	target	type
    //   2	7	10	finally
  }
  
  public final void q(double paramDouble) {
    // Byte code:
    //   0: aload_0
    //   1: monitorenter
    //   2: aload_0
    //   3: dload_1
    //   4: putfield n : D
    //   7: aload_0
    //   8: monitorexit
    //   9: return
    //   10: astore_3
    //   11: aload_0
    //   12: monitorexit
    //   13: aload_3
    //   14: athrow
    // Exception table:
    //   from	to	target	type
    //   2	7	10	finally
  }
  
  public final void v(f3 paramf3) {
    // Byte code:
    //   0: aload_0
    //   1: monitorenter
    //   2: aload_0
    //   3: aload_1
    //   4: putfield c : Lcom/google/android/gms/internal/ads/f3;
    //   7: aload_0
    //   8: monitorexit
    //   9: return
    //   10: astore_1
    //   11: aload_0
    //   12: monitorexit
    //   13: aload_1
    //   14: athrow
    // Exception table:
    //   from	to	target	type
    //   2	7	10	finally
  }
  
  public final void w(m3 paramm3) {
    // Byte code:
    //   0: aload_0
    //   1: monitorenter
    //   2: aload_0
    //   3: aload_1
    //   4: putfield o : Lcom/google/android/gms/internal/ads/m3;
    //   7: aload_0
    //   8: monitorexit
    //   9: return
    //   10: astore_1
    //   11: aload_0
    //   12: monitorexit
    //   13: aload_1
    //   14: athrow
    // Exception table:
    //   from	to	target	type
    //   2	7	10	finally
  }
  
  public final void x(du2 paramdu2) {
    // Byte code:
    //   0: aload_0
    //   1: monitorenter
    //   2: aload_0
    //   3: aload_1
    //   4: putfield g : Lcom/google/android/gms/internal/ads/du2;
    //   7: aload_0
    //   8: monitorexit
    //   9: return
    //   10: astore_1
    //   11: aload_0
    //   12: monitorexit
    //   13: aload_1
    //   14: athrow
    // Exception table:
    //   from	to	target	type
    //   2	7	10	finally
  }
  
  public final void y(String paramString, a3 parama3) {
    // Byte code:
    //   0: aload_0
    //   1: monitorenter
    //   2: aload_2
    //   3: ifnonnull -> 18
    //   6: aload_0
    //   7: getfield r : Lb/e/g;
    //   10: aload_1
    //   11: invokevirtual remove : (Ljava/lang/Object;)Ljava/lang/Object;
    //   14: pop
    //   15: aload_0
    //   16: monitorexit
    //   17: return
    //   18: aload_0
    //   19: getfield r : Lb/e/g;
    //   22: aload_1
    //   23: aload_2
    //   24: invokevirtual put : (Ljava/lang/Object;Ljava/lang/Object;)Ljava/lang/Object;
    //   27: pop
    //   28: aload_0
    //   29: monitorexit
    //   30: return
    //   31: astore_1
    //   32: aload_0
    //   33: monitorexit
    //   34: aload_1
    //   35: athrow
    // Exception table:
    //   from	to	target	type
    //   6	15	31	finally
    //   18	28	31	finally
  }
  
  public final void z(View paramView) {
    // Byte code:
    //   0: aload_0
    //   1: monitorenter
    //   2: aload_0
    //   3: aload_1
    //   4: putfield l : Landroid/view/View;
    //   7: aload_0
    //   8: monitorexit
    //   9: return
    //   10: astore_1
    //   11: aload_0
    //   12: monitorexit
    //   13: aload_1
    //   14: athrow
    // Exception table:
    //   from	to	target	type
    //   2	7	10	finally
  }
}


/* Location:              /home/sumith/decompile/test/classes-dex2jar.jar!/com/google/android/gms/internal/ads/pf0.class
 * Java compiler version: 6 (50.0)
 * JD-Core Version:       1.1.3
 */