package com.google.android.gms.internal.ads;

import java.util.Set;

public final class qb0 extends j90<j7> implements j7 {
  public qb0(Set<gb0<j7>> paramSet) {
    super(paramSet);
  }
  
  public final void G0() {
    X0(rb0.a);
  }
  
  public final void P0() {
    // Byte code:
    //   0: aload_0
    //   1: monitorenter
    //   2: aload_0
    //   3: getstatic com/google/android/gms/internal/ads/pb0.a : Lcom/google/android/gms/internal/ads/l90;
    //   6: invokevirtual X0 : (Lcom/google/android/gms/internal/ads/l90;)V
    //   9: aload_0
    //   10: monitorexit
    //   11: return
    //   12: astore_1
    //   13: aload_0
    //   14: monitorexit
    //   15: aload_1
    //   16: athrow
    // Exception table:
    //   from	to	target	type
    //   2	9	12	finally
  }
  
  public final void t(zzavj paramzzavj) {
    X0(new sb0(paramzzavj));
  }
}


/* Location:              /home/sumith/decompile/test/classes-dex2jar.jar!/com/google/android/gms/internal/ads/qb0.class
 * Java compiler version: 6 (50.0)
 * JD-Core Version:       1.1.3
 */