package com.google.android.gms.internal.ads;

final class rh2 {
  private int a = 1000;
  
  private int[] b = new int[1000];
  
  private long[] c = new long[1000];
  
  private int[] d = new int[1000];
  
  private int[] e = new int[1000];
  
  private long[] f = new long[1000];
  
  private xe2[] g = new xe2[1000];
  
  private zzht[] h = new zzht[1000];
  
  private int i;
  
  private int j;
  
  private int k;
  
  private int l;
  
  private long m = Long.MIN_VALUE;
  
  private long n = Long.MIN_VALUE;
  
  private boolean o = true;
  
  private boolean p = true;
  
  private zzht q;
  
  public final int a(nc2 paramnc2, ce2 paramce2, boolean paramBoolean1, boolean paramBoolean2, zzht paramzzht, qh2 paramqh2) {
    // Byte code:
    //   0: aload_0
    //   1: monitorenter
    //   2: aload_0
    //   3: invokevirtual j : ()Z
    //   6: ifne -> 58
    //   9: iload #4
    //   11: ifeq -> 24
    //   14: aload_2
    //   15: iconst_4
    //   16: invokevirtual b : (I)V
    //   19: aload_0
    //   20: monitorexit
    //   21: bipush #-4
    //   23: ireturn
    //   24: aload_0
    //   25: getfield q : Lcom/google/android/gms/internal/ads/zzht;
    //   28: astore_2
    //   29: aload_2
    //   30: ifnull -> 53
    //   33: iload_3
    //   34: ifne -> 43
    //   37: aload_2
    //   38: aload #5
    //   40: if_acmpeq -> 53
    //   43: aload_1
    //   44: aload_2
    //   45: putfield a : Lcom/google/android/gms/internal/ads/zzht;
    //   48: aload_0
    //   49: monitorexit
    //   50: bipush #-5
    //   52: ireturn
    //   53: aload_0
    //   54: monitorexit
    //   55: bipush #-3
    //   57: ireturn
    //   58: iload_3
    //   59: ifne -> 293
    //   62: aload_0
    //   63: getfield h : [Lcom/google/android/gms/internal/ads/zzht;
    //   66: astore #7
    //   68: aload_0
    //   69: getfield k : I
    //   72: istore #8
    //   74: aload #7
    //   76: iload #8
    //   78: aaload
    //   79: aload #5
    //   81: if_acmpeq -> 87
    //   84: goto -> 293
    //   87: aload_2
    //   88: getfield c : Ljava/nio/ByteBuffer;
    //   91: astore_1
    //   92: aload_1
    //   93: ifnonnull -> 102
    //   96: iconst_1
    //   97: istore #9
    //   99: goto -> 105
    //   102: iconst_0
    //   103: istore #9
    //   105: iload #9
    //   107: ifeq -> 115
    //   110: aload_0
    //   111: monitorexit
    //   112: bipush #-3
    //   114: ireturn
    //   115: aload_2
    //   116: aload_0
    //   117: getfield f : [J
    //   120: iload #8
    //   122: laload
    //   123: putfield d : J
    //   126: aload_2
    //   127: aload_0
    //   128: getfield e : [I
    //   131: iload #8
    //   133: iaload
    //   134: invokevirtual b : (I)V
    //   137: aload_0
    //   138: getfield d : [I
    //   141: astore_1
    //   142: aload_0
    //   143: getfield k : I
    //   146: istore #9
    //   148: aload #6
    //   150: aload_1
    //   151: iload #9
    //   153: iaload
    //   154: putfield a : I
    //   157: aload #6
    //   159: aload_0
    //   160: getfield c : [J
    //   163: iload #9
    //   165: laload
    //   166: putfield b : J
    //   169: aload #6
    //   171: aload_0
    //   172: getfield g : [Lcom/google/android/gms/internal/ads/xe2;
    //   175: iload #9
    //   177: aaload
    //   178: putfield d : Lcom/google/android/gms/internal/ads/xe2;
    //   181: aload_0
    //   182: aload_0
    //   183: getfield m : J
    //   186: aload_2
    //   187: getfield d : J
    //   190: invokestatic max : (JJ)J
    //   193: putfield m : J
    //   196: aload_0
    //   197: getfield i : I
    //   200: iconst_1
    //   201: isub
    //   202: istore #9
    //   204: aload_0
    //   205: iload #9
    //   207: putfield i : I
    //   210: aload_0
    //   211: getfield k : I
    //   214: iconst_1
    //   215: iadd
    //   216: istore #8
    //   218: aload_0
    //   219: iload #8
    //   221: putfield k : I
    //   224: aload_0
    //   225: aload_0
    //   226: getfield j : I
    //   229: iconst_1
    //   230: iadd
    //   231: putfield j : I
    //   234: iload #8
    //   236: aload_0
    //   237: getfield a : I
    //   240: if_icmpne -> 248
    //   243: aload_0
    //   244: iconst_0
    //   245: putfield k : I
    //   248: iload #9
    //   250: ifle -> 267
    //   253: aload_0
    //   254: getfield c : [J
    //   257: aload_0
    //   258: getfield k : I
    //   261: laload
    //   262: lstore #10
    //   264: goto -> 281
    //   267: aload #6
    //   269: getfield b : J
    //   272: aload #6
    //   274: getfield a : I
    //   277: i2l
    //   278: ladd
    //   279: lstore #10
    //   281: aload #6
    //   283: lload #10
    //   285: putfield c : J
    //   288: aload_0
    //   289: monitorexit
    //   290: bipush #-4
    //   292: ireturn
    //   293: aload_1
    //   294: aload_0
    //   295: getfield h : [Lcom/google/android/gms/internal/ads/zzht;
    //   298: aload_0
    //   299: getfield k : I
    //   302: aaload
    //   303: putfield a : Lcom/google/android/gms/internal/ads/zzht;
    //   306: aload_0
    //   307: monitorexit
    //   308: bipush #-5
    //   310: ireturn
    //   311: astore_1
    //   312: aload_0
    //   313: monitorexit
    //   314: aload_1
    //   315: athrow
    // Exception table:
    //   from	to	target	type
    //   2	9	311	finally
    //   14	19	311	finally
    //   24	29	311	finally
    //   43	48	311	finally
    //   62	74	311	finally
    //   87	92	311	finally
    //   115	248	311	finally
    //   253	264	311	finally
    //   267	281	311	finally
    //   281	288	311	finally
    //   293	306	311	finally
  }
  
  public final void b(long paramLong1, int paramInt1, long paramLong2, int paramInt2, xe2 paramxe2) {
    // Byte code:
    //   0: aload_0
    //   1: monitorenter
    //   2: aload_0
    //   3: getfield o : Z
    //   6: istore #8
    //   8: iload #8
    //   10: ifeq -> 27
    //   13: iload_3
    //   14: iconst_1
    //   15: iand
    //   16: ifne -> 22
    //   19: aload_0
    //   20: monitorexit
    //   21: return
    //   22: aload_0
    //   23: iconst_0
    //   24: putfield o : Z
    //   27: aload_0
    //   28: getfield p : Z
    //   31: ifne -> 40
    //   34: iconst_1
    //   35: istore #8
    //   37: goto -> 43
    //   40: iconst_0
    //   41: istore #8
    //   43: iload #8
    //   45: invokestatic e : (Z)V
    //   48: aload_0
    //   49: lload_1
    //   50: invokevirtual d : (J)V
    //   53: aload_0
    //   54: getfield f : [J
    //   57: astore #9
    //   59: aload_0
    //   60: getfield l : I
    //   63: istore #10
    //   65: aload #9
    //   67: iload #10
    //   69: lload_1
    //   70: lastore
    //   71: aload_0
    //   72: getfield c : [J
    //   75: astore #9
    //   77: aload #9
    //   79: iload #10
    //   81: lload #4
    //   83: lastore
    //   84: aload_0
    //   85: getfield d : [I
    //   88: iload #10
    //   90: iload #6
    //   92: iastore
    //   93: aload_0
    //   94: getfield e : [I
    //   97: iload #10
    //   99: iload_3
    //   100: iastore
    //   101: aload_0
    //   102: getfield g : [Lcom/google/android/gms/internal/ads/xe2;
    //   105: iload #10
    //   107: aload #7
    //   109: aastore
    //   110: aload_0
    //   111: getfield h : [Lcom/google/android/gms/internal/ads/zzht;
    //   114: iload #10
    //   116: aload_0
    //   117: getfield q : Lcom/google/android/gms/internal/ads/zzht;
    //   120: aastore
    //   121: aload_0
    //   122: getfield b : [I
    //   125: iload #10
    //   127: iconst_0
    //   128: iastore
    //   129: aload_0
    //   130: getfield i : I
    //   133: iconst_1
    //   134: iadd
    //   135: istore #6
    //   137: aload_0
    //   138: iload #6
    //   140: putfield i : I
    //   143: aload_0
    //   144: getfield a : I
    //   147: istore_3
    //   148: iload #6
    //   150: iload_3
    //   151: if_icmpne -> 485
    //   154: iload_3
    //   155: sipush #1000
    //   158: iadd
    //   159: istore #6
    //   161: iload #6
    //   163: newarray int
    //   165: astore #7
    //   167: iload #6
    //   169: newarray long
    //   171: astore #11
    //   173: iload #6
    //   175: newarray long
    //   177: astore #12
    //   179: iload #6
    //   181: newarray int
    //   183: astore #13
    //   185: iload #6
    //   187: newarray int
    //   189: astore #14
    //   191: iload #6
    //   193: anewarray com/google/android/gms/internal/ads/xe2
    //   196: astore #15
    //   198: iload #6
    //   200: anewarray com/google/android/gms/internal/ads/zzht
    //   203: astore #16
    //   205: aload_0
    //   206: getfield k : I
    //   209: istore #10
    //   211: iload_3
    //   212: iload #10
    //   214: isub
    //   215: istore_3
    //   216: aload #9
    //   218: iload #10
    //   220: aload #11
    //   222: iconst_0
    //   223: iload_3
    //   224: invokestatic arraycopy : (Ljava/lang/Object;ILjava/lang/Object;II)V
    //   227: aload_0
    //   228: getfield f : [J
    //   231: aload_0
    //   232: getfield k : I
    //   235: aload #12
    //   237: iconst_0
    //   238: iload_3
    //   239: invokestatic arraycopy : (Ljava/lang/Object;ILjava/lang/Object;II)V
    //   242: aload_0
    //   243: getfield e : [I
    //   246: aload_0
    //   247: getfield k : I
    //   250: aload #13
    //   252: iconst_0
    //   253: iload_3
    //   254: invokestatic arraycopy : (Ljava/lang/Object;ILjava/lang/Object;II)V
    //   257: aload_0
    //   258: getfield d : [I
    //   261: aload_0
    //   262: getfield k : I
    //   265: aload #14
    //   267: iconst_0
    //   268: iload_3
    //   269: invokestatic arraycopy : (Ljava/lang/Object;ILjava/lang/Object;II)V
    //   272: aload_0
    //   273: getfield g : [Lcom/google/android/gms/internal/ads/xe2;
    //   276: aload_0
    //   277: getfield k : I
    //   280: aload #15
    //   282: iconst_0
    //   283: iload_3
    //   284: invokestatic arraycopy : (Ljava/lang/Object;ILjava/lang/Object;II)V
    //   287: aload_0
    //   288: getfield h : [Lcom/google/android/gms/internal/ads/zzht;
    //   291: aload_0
    //   292: getfield k : I
    //   295: aload #16
    //   297: iconst_0
    //   298: iload_3
    //   299: invokestatic arraycopy : (Ljava/lang/Object;ILjava/lang/Object;II)V
    //   302: aload_0
    //   303: getfield b : [I
    //   306: aload_0
    //   307: getfield k : I
    //   310: aload #7
    //   312: iconst_0
    //   313: iload_3
    //   314: invokestatic arraycopy : (Ljava/lang/Object;ILjava/lang/Object;II)V
    //   317: aload_0
    //   318: getfield k : I
    //   321: istore #10
    //   323: aload_0
    //   324: getfield c : [J
    //   327: iconst_0
    //   328: aload #11
    //   330: iload_3
    //   331: iload #10
    //   333: invokestatic arraycopy : (Ljava/lang/Object;ILjava/lang/Object;II)V
    //   336: aload_0
    //   337: getfield f : [J
    //   340: iconst_0
    //   341: aload #12
    //   343: iload_3
    //   344: iload #10
    //   346: invokestatic arraycopy : (Ljava/lang/Object;ILjava/lang/Object;II)V
    //   349: aload_0
    //   350: getfield e : [I
    //   353: iconst_0
    //   354: aload #13
    //   356: iload_3
    //   357: iload #10
    //   359: invokestatic arraycopy : (Ljava/lang/Object;ILjava/lang/Object;II)V
    //   362: aload_0
    //   363: getfield d : [I
    //   366: iconst_0
    //   367: aload #14
    //   369: iload_3
    //   370: iload #10
    //   372: invokestatic arraycopy : (Ljava/lang/Object;ILjava/lang/Object;II)V
    //   375: aload_0
    //   376: getfield g : [Lcom/google/android/gms/internal/ads/xe2;
    //   379: iconst_0
    //   380: aload #15
    //   382: iload_3
    //   383: iload #10
    //   385: invokestatic arraycopy : (Ljava/lang/Object;ILjava/lang/Object;II)V
    //   388: aload_0
    //   389: getfield h : [Lcom/google/android/gms/internal/ads/zzht;
    //   392: iconst_0
    //   393: aload #16
    //   395: iload_3
    //   396: iload #10
    //   398: invokestatic arraycopy : (Ljava/lang/Object;ILjava/lang/Object;II)V
    //   401: aload_0
    //   402: getfield b : [I
    //   405: iconst_0
    //   406: aload #7
    //   408: iload_3
    //   409: iload #10
    //   411: invokestatic arraycopy : (Ljava/lang/Object;ILjava/lang/Object;II)V
    //   414: aload_0
    //   415: aload #11
    //   417: putfield c : [J
    //   420: aload_0
    //   421: aload #12
    //   423: putfield f : [J
    //   426: aload_0
    //   427: aload #13
    //   429: putfield e : [I
    //   432: aload_0
    //   433: aload #14
    //   435: putfield d : [I
    //   438: aload_0
    //   439: aload #15
    //   441: putfield g : [Lcom/google/android/gms/internal/ads/xe2;
    //   444: aload_0
    //   445: aload #16
    //   447: putfield h : [Lcom/google/android/gms/internal/ads/zzht;
    //   450: aload_0
    //   451: aload #7
    //   453: putfield b : [I
    //   456: aload_0
    //   457: iconst_0
    //   458: putfield k : I
    //   461: aload_0
    //   462: getfield a : I
    //   465: istore_3
    //   466: aload_0
    //   467: iload_3
    //   468: putfield l : I
    //   471: aload_0
    //   472: iload_3
    //   473: putfield i : I
    //   476: aload_0
    //   477: iload #6
    //   479: putfield a : I
    //   482: aload_0
    //   483: monitorexit
    //   484: return
    //   485: iload #10
    //   487: iconst_1
    //   488: iadd
    //   489: istore #6
    //   491: aload_0
    //   492: iload #6
    //   494: putfield l : I
    //   497: iload #6
    //   499: iload_3
    //   500: if_icmpne -> 508
    //   503: aload_0
    //   504: iconst_0
    //   505: putfield l : I
    //   508: aload_0
    //   509: monitorexit
    //   510: return
    //   511: astore #7
    //   513: aload_0
    //   514: monitorexit
    //   515: aload #7
    //   517: athrow
    // Exception table:
    //   from	to	target	type
    //   2	8	511	finally
    //   22	27	511	finally
    //   27	34	511	finally
    //   43	65	511	finally
    //   71	77	511	finally
    //   84	148	511	finally
    //   161	211	511	finally
    //   216	482	511	finally
    //   491	497	511	finally
    //   503	508	511	finally
  }
  
  public final long c(long paramLong, boolean paramBoolean) {
    // Byte code:
    //   0: aload_0
    //   1: monitorenter
    //   2: aload_0
    //   3: invokevirtual j : ()Z
    //   6: ifeq -> 183
    //   9: aload_0
    //   10: getfield f : [J
    //   13: astore #4
    //   15: aload_0
    //   16: getfield k : I
    //   19: istore #5
    //   21: lload_1
    //   22: aload #4
    //   24: iload #5
    //   26: laload
    //   27: lcmp
    //   28: ifge -> 34
    //   31: goto -> 183
    //   34: aload_0
    //   35: getfield n : J
    //   38: lstore #6
    //   40: lload_1
    //   41: lload #6
    //   43: lcmp
    //   44: ifle -> 57
    //   47: iload_3
    //   48: ifne -> 57
    //   51: aload_0
    //   52: monitorexit
    //   53: ldc2_w -1
    //   56: lreturn
    //   57: iconst_0
    //   58: istore #8
    //   60: iconst_m1
    //   61: istore #9
    //   63: iload #5
    //   65: aload_0
    //   66: getfield l : I
    //   69: if_icmpeq -> 117
    //   72: aload_0
    //   73: getfield f : [J
    //   76: iload #5
    //   78: laload
    //   79: lload_1
    //   80: lcmp
    //   81: ifgt -> 117
    //   84: aload_0
    //   85: getfield e : [I
    //   88: iload #5
    //   90: iaload
    //   91: iconst_1
    //   92: iand
    //   93: ifeq -> 100
    //   96: iload #8
    //   98: istore #9
    //   100: iload #5
    //   102: iconst_1
    //   103: iadd
    //   104: aload_0
    //   105: getfield a : I
    //   108: irem
    //   109: istore #5
    //   111: iinc #8, 1
    //   114: goto -> 63
    //   117: iload #9
    //   119: iconst_m1
    //   120: if_icmpne -> 129
    //   123: aload_0
    //   124: monitorexit
    //   125: ldc2_w -1
    //   128: lreturn
    //   129: aload_0
    //   130: getfield k : I
    //   133: iload #9
    //   135: iadd
    //   136: aload_0
    //   137: getfield a : I
    //   140: irem
    //   141: istore #8
    //   143: aload_0
    //   144: iload #8
    //   146: putfield k : I
    //   149: aload_0
    //   150: aload_0
    //   151: getfield j : I
    //   154: iload #9
    //   156: iadd
    //   157: putfield j : I
    //   160: aload_0
    //   161: aload_0
    //   162: getfield i : I
    //   165: iload #9
    //   167: isub
    //   168: putfield i : I
    //   171: aload_0
    //   172: getfield c : [J
    //   175: iload #8
    //   177: laload
    //   178: lstore_1
    //   179: aload_0
    //   180: monitorexit
    //   181: lload_1
    //   182: lreturn
    //   183: aload_0
    //   184: monitorexit
    //   185: ldc2_w -1
    //   188: lreturn
    //   189: astore #4
    //   191: aload_0
    //   192: monitorexit
    //   193: goto -> 199
    //   196: aload #4
    //   198: athrow
    //   199: goto -> 196
    // Exception table:
    //   from	to	target	type
    //   2	21	189	finally
    //   34	40	189	finally
    //   63	84	189	finally
    //   84	96	189	finally
    //   100	111	189	finally
    //   129	179	189	finally
  }
  
  public final void d(long paramLong) {
    // Byte code:
    //   0: aload_0
    //   1: monitorenter
    //   2: aload_0
    //   3: aload_0
    //   4: getfield n : J
    //   7: lload_1
    //   8: invokestatic max : (JJ)J
    //   11: putfield n : J
    //   14: aload_0
    //   15: monitorexit
    //   16: return
    //   17: astore_3
    //   18: aload_0
    //   19: monitorexit
    //   20: aload_3
    //   21: athrow
    // Exception table:
    //   from	to	target	type
    //   2	14	17	finally
  }
  
  public final boolean e(zzht paramzzht) {
    // Byte code:
    //   0: aload_0
    //   1: monitorenter
    //   2: aload_1
    //   3: ifnonnull -> 15
    //   6: aload_0
    //   7: iconst_1
    //   8: putfield p : Z
    //   11: aload_0
    //   12: monitorexit
    //   13: iconst_0
    //   14: ireturn
    //   15: aload_0
    //   16: iconst_0
    //   17: putfield p : Z
    //   20: aload_1
    //   21: aload_0
    //   22: getfield q : Lcom/google/android/gms/internal/ads/zzht;
    //   25: invokestatic g : (Ljava/lang/Object;Ljava/lang/Object;)Z
    //   28: istore_2
    //   29: iload_2
    //   30: ifeq -> 37
    //   33: aload_0
    //   34: monitorexit
    //   35: iconst_0
    //   36: ireturn
    //   37: aload_0
    //   38: aload_1
    //   39: putfield q : Lcom/google/android/gms/internal/ads/zzht;
    //   42: aload_0
    //   43: monitorexit
    //   44: iconst_1
    //   45: ireturn
    //   46: astore_1
    //   47: aload_0
    //   48: monitorexit
    //   49: aload_1
    //   50: athrow
    // Exception table:
    //   from	to	target	type
    //   6	11	46	finally
    //   15	29	46	finally
    //   37	42	46	finally
  }
  
  public final long f() {
    // Byte code:
    //   0: aload_0
    //   1: monitorenter
    //   2: aload_0
    //   3: getfield m : J
    //   6: aload_0
    //   7: getfield n : J
    //   10: invokestatic max : (JJ)J
    //   13: lstore_1
    //   14: aload_0
    //   15: monitorexit
    //   16: lload_1
    //   17: lreturn
    //   18: astore_3
    //   19: aload_0
    //   20: monitorexit
    //   21: aload_3
    //   22: athrow
    // Exception table:
    //   from	to	target	type
    //   2	14	18	finally
  }
  
  public final void g() {
    this.j = 0;
    this.k = 0;
    this.l = 0;
    this.i = 0;
    this.o = true;
  }
  
  public final void h() {
    this.m = Long.MIN_VALUE;
    this.n = Long.MIN_VALUE;
  }
  
  public final int i() {
    return this.j + this.i;
  }
  
  public final boolean j() {
    // Byte code:
    //   0: aload_0
    //   1: monitorenter
    //   2: aload_0
    //   3: getfield i : I
    //   6: istore_1
    //   7: iload_1
    //   8: ifeq -> 17
    //   11: iconst_1
    //   12: istore_2
    //   13: aload_0
    //   14: monitorexit
    //   15: iload_2
    //   16: ireturn
    //   17: iconst_0
    //   18: istore_2
    //   19: goto -> 13
    //   22: astore_3
    //   23: aload_0
    //   24: monitorexit
    //   25: goto -> 30
    //   28: aload_3
    //   29: athrow
    //   30: goto -> 28
    // Exception table:
    //   from	to	target	type
    //   2	7	22	finally
  }
  
  public final zzht k() {
    // Byte code:
    //   0: aload_0
    //   1: monitorenter
    //   2: aload_0
    //   3: getfield p : Z
    //   6: istore_1
    //   7: iload_1
    //   8: ifeq -> 15
    //   11: aload_0
    //   12: monitorexit
    //   13: aconst_null
    //   14: areturn
    //   15: aload_0
    //   16: getfield q : Lcom/google/android/gms/internal/ads/zzht;
    //   19: astore_2
    //   20: aload_0
    //   21: monitorexit
    //   22: aload_2
    //   23: areturn
    //   24: astore_2
    //   25: aload_0
    //   26: monitorexit
    //   27: aload_2
    //   28: athrow
    // Exception table:
    //   from	to	target	type
    //   2	7	24	finally
    //   15	20	24	finally
  }
  
  public final long l() {
    // Byte code:
    //   0: aload_0
    //   1: monitorenter
    //   2: aload_0
    //   3: invokevirtual j : ()Z
    //   6: istore_1
    //   7: iload_1
    //   8: ifne -> 17
    //   11: aload_0
    //   12: monitorexit
    //   13: ldc2_w -1
    //   16: lreturn
    //   17: aload_0
    //   18: getfield k : I
    //   21: istore_2
    //   22: aload_0
    //   23: getfield i : I
    //   26: istore_3
    //   27: aload_0
    //   28: getfield a : I
    //   31: istore #4
    //   33: iload_2
    //   34: iload_3
    //   35: iadd
    //   36: iconst_1
    //   37: isub
    //   38: iload #4
    //   40: irem
    //   41: istore #5
    //   43: aload_0
    //   44: iload_2
    //   45: iload_3
    //   46: iadd
    //   47: iload #4
    //   49: irem
    //   50: putfield k : I
    //   53: aload_0
    //   54: aload_0
    //   55: getfield j : I
    //   58: iload_3
    //   59: iadd
    //   60: putfield j : I
    //   63: aload_0
    //   64: iconst_0
    //   65: putfield i : I
    //   68: aload_0
    //   69: getfield c : [J
    //   72: iload #5
    //   74: laload
    //   75: lstore #6
    //   77: aload_0
    //   78: getfield d : [I
    //   81: iload #5
    //   83: iaload
    //   84: istore_2
    //   85: iload_2
    //   86: i2l
    //   87: lstore #8
    //   89: aload_0
    //   90: monitorexit
    //   91: lload #6
    //   93: lload #8
    //   95: ladd
    //   96: lreturn
    //   97: astore #10
    //   99: aload_0
    //   100: monitorexit
    //   101: aload #10
    //   103: athrow
    // Exception table:
    //   from	to	target	type
    //   2	7	97	finally
    //   17	33	97	finally
    //   43	85	97	finally
  }
}


/* Location:              /home/sumith/decompile/test/classes-dex2jar.jar!/com/google/android/gms/internal/ads/rh2.class
 * Java compiler version: 6 (50.0)
 * JD-Core Version:       1.1.3
 */