package com.google.android.gms.internal.ads;

import android.content.Context;
import java.util.concurrent.Executor;
import java.util.concurrent.ScheduledExecutorService;

public abstract class ss implements wv {
  private static ss a;
  
  @Deprecated
  public static ss A(Context paramContext, int paramInt) {
    // Byte code:
    //   0: ldc com/google/android/gms/internal/ads/ss
    //   2: monitorenter
    //   3: getstatic com/google/android/gms/internal/ads/ss.a : Lcom/google/android/gms/internal/ads/ss;
    //   6: astore_2
    //   7: aload_2
    //   8: ifnull -> 16
    //   11: ldc com/google/android/gms/internal/ads/ss
    //   13: monitorexit
    //   14: aload_2
    //   15: areturn
    //   16: ldc com/google/android/gms/internal/ads/ss
    //   18: monitorexit
    //   19: new com/google/android/gms/internal/ads/zzazn
    //   22: dup
    //   23: ldc 204204000
    //   25: iload_1
    //   26: iconst_1
    //   27: iconst_0
    //   28: invokespecial <init> : (IIZZ)V
    //   31: aload_0
    //   32: new com/google/android/gms/internal/ads/mt
    //   35: dup
    //   36: invokespecial <init> : ()V
    //   39: invokestatic c : (Lcom/google/android/gms/internal/ads/zzazn;Landroid/content/Context;Lcom/google/android/gms/internal/ads/yu$a;)Lcom/google/android/gms/internal/ads/ss;
    //   42: areturn
    //   43: astore_0
    //   44: ldc com/google/android/gms/internal/ads/ss
    //   46: monitorexit
    //   47: aload_0
    //   48: athrow
    // Exception table:
    //   from	to	target	type
    //   3	7	43	finally
    //   11	14	43	finally
    //   16	19	43	finally
    //   44	47	43	finally
  }
  
  public static ss b(Context paramContext, mb parammb, int paramInt) {
    ss ss1 = A(paramContext, paramInt);
    ss1.k().c(parammb);
    return ss1;
  }
  
  @Deprecated
  private static ss c(zzazn paramzzazn, Context paramContext, yu.a parama) {
    // Byte code:
    //   0: ldc com/google/android/gms/internal/ads/ss
    //   2: monitorenter
    //   3: getstatic com/google/android/gms/internal/ads/ss.a : Lcom/google/android/gms/internal/ads/ss;
    //   6: ifnonnull -> 284
    //   9: new com/google/android/gms/internal/ads/ju
    //   12: astore_3
    //   13: aload_3
    //   14: aconst_null
    //   15: invokespecial <init> : (Lcom/google/android/gms/internal/ads/ot;)V
    //   18: new com/google/android/gms/internal/ads/rs$a
    //   21: astore #4
    //   23: aload #4
    //   25: invokespecial <init> : ()V
    //   28: aload #4
    //   30: aload_0
    //   31: invokevirtual b : (Lcom/google/android/gms/internal/ads/zzazn;)Lcom/google/android/gms/internal/ads/rs$a;
    //   34: aload_1
    //   35: invokevirtual d : (Landroid/content/Context;)Lcom/google/android/gms/internal/ads/rs$a;
    //   38: astore #5
    //   40: new com/google/android/gms/internal/ads/rs
    //   43: astore #4
    //   45: aload #4
    //   47: aload #5
    //   49: aconst_null
    //   50: invokespecial <init> : (Lcom/google/android/gms/internal/ads/rs$a;Lcom/google/android/gms/internal/ads/ts;)V
    //   53: aload_3
    //   54: aload #4
    //   56: invokevirtual c : (Lcom/google/android/gms/internal/ads/rs;)Lcom/google/android/gms/internal/ads/ju;
    //   59: astore_3
    //   60: new com/google/android/gms/internal/ads/yu
    //   63: astore #4
    //   65: aload #4
    //   67: aload_2
    //   68: invokespecial <init> : (Lcom/google/android/gms/internal/ads/yu$a;)V
    //   71: aload_3
    //   72: aload #4
    //   74: invokevirtual a : (Lcom/google/android/gms/internal/ads/yu;)Lcom/google/android/gms/internal/ads/ju;
    //   77: invokevirtual b : ()Lcom/google/android/gms/internal/ads/ss;
    //   80: putstatic com/google/android/gms/internal/ads/ss.a : Lcom/google/android/gms/internal/ads/ss;
    //   83: aload_1
    //   84: invokestatic a : (Landroid/content/Context;)V
    //   87: invokestatic g : ()Lcom/google/android/gms/internal/ads/fl;
    //   90: aload_1
    //   91: aload_0
    //   92: invokevirtual k : (Landroid/content/Context;Lcom/google/android/gms/internal/ads/zzazn;)V
    //   95: invokestatic i : ()Lcom/google/android/gms/internal/ads/dn2;
    //   98: aload_1
    //   99: invokevirtual c : (Landroid/content/Context;)V
    //   102: invokestatic c : ()Lcom/google/android/gms/ads/internal/util/h1;
    //   105: aload_1
    //   106: invokevirtual v : (Landroid/content/Context;)Z
    //   109: pop
    //   110: invokestatic c : ()Lcom/google/android/gms/ads/internal/util/h1;
    //   113: aload_1
    //   114: invokevirtual w : (Landroid/content/Context;)Z
    //   117: pop
    //   118: invokestatic c : ()Lcom/google/android/gms/ads/internal/util/h1;
    //   121: pop
    //   122: aload_1
    //   123: invokestatic P : (Landroid/content/Context;)V
    //   126: aload_1
    //   127: invokestatic a : (Landroid/content/Context;)V
    //   130: invokestatic f : ()Lcom/google/android/gms/internal/ads/ol2;
    //   133: aload_1
    //   134: invokevirtual c : (Landroid/content/Context;)V
    //   137: invokestatic x : ()Lcom/google/android/gms/ads/internal/util/v0;
    //   140: aload_1
    //   141: invokevirtual a : (Landroid/content/Context;)V
    //   144: invokestatic g : ()Lcom/google/android/gms/internal/ads/fl;
    //   147: invokevirtual r : ()Lcom/google/android/gms/ads/internal/util/d1;
    //   150: astore_2
    //   151: aload_2
    //   152: aload_1
    //   153: invokeinterface c : (Landroid/content/Context;)V
    //   158: aload_1
    //   159: aload_2
    //   160: invokestatic a : (Landroid/content/Context;Lcom/google/android/gms/ads/internal/util/d1;)Lcom/google/android/gms/internal/ads/wj;
    //   163: pop
    //   164: getstatic com/google/android/gms/internal/ads/m0.P4 : Lcom/google/android/gms/internal/ads/x;
    //   167: astore_2
    //   168: invokestatic e : ()Lcom/google/android/gms/internal/ads/i0;
    //   171: aload_2
    //   172: invokevirtual c : (Lcom/google/android/gms/internal/ads/x;)Ljava/lang/Object;
    //   175: checkcast java/lang/Boolean
    //   178: invokevirtual booleanValue : ()Z
    //   181: ifeq -> 284
    //   184: getstatic com/google/android/gms/internal/ads/m0.k0 : Lcom/google/android/gms/internal/ads/x;
    //   187: astore_2
    //   188: invokestatic e : ()Lcom/google/android/gms/internal/ads/i0;
    //   191: aload_2
    //   192: invokevirtual c : (Lcom/google/android/gms/internal/ads/x;)Ljava/lang/Object;
    //   195: checkcast java/lang/Boolean
    //   198: invokevirtual booleanValue : ()Z
    //   201: ifne -> 284
    //   204: new com/google/android/gms/internal/ads/ju0
    //   207: astore_2
    //   208: new com/google/android/gms/internal/ads/xn2
    //   211: astore_3
    //   212: new com/google/android/gms/internal/ads/ao2
    //   215: astore #4
    //   217: aload #4
    //   219: aload_1
    //   220: invokespecial <init> : (Landroid/content/Context;)V
    //   223: aload_3
    //   224: aload #4
    //   226: invokespecial <init> : (Lcom/google/android/gms/internal/ads/ao2;)V
    //   229: new com/google/android/gms/internal/ads/tt0
    //   232: astore #4
    //   234: new com/google/android/gms/internal/ads/rt0
    //   237: astore #5
    //   239: aload #5
    //   241: aload_1
    //   242: invokespecial <init> : (Landroid/content/Context;)V
    //   245: aload #4
    //   247: aload #5
    //   249: getstatic com/google/android/gms/internal/ads/ss.a : Lcom/google/android/gms/internal/ads/ss;
    //   252: invokevirtual i : ()Lcom/google/android/gms/internal/ads/nt1;
    //   255: invokespecial <init> : (Lcom/google/android/gms/internal/ads/rt0;Lcom/google/android/gms/internal/ads/nt1;)V
    //   258: invokestatic c : ()Lcom/google/android/gms/ads/internal/util/h1;
    //   261: pop
    //   262: aload_2
    //   263: aload_1
    //   264: aload_0
    //   265: aload_3
    //   266: aload #4
    //   268: invokestatic x0 : ()Ljava/lang/String;
    //   271: getstatic com/google/android/gms/internal/ads/ss.a : Lcom/google/android/gms/internal/ads/ss;
    //   274: invokevirtual e : ()Lcom/google/android/gms/internal/ads/pm1;
    //   277: invokespecial <init> : (Landroid/content/Context;Lcom/google/android/gms/internal/ads/zzazn;Lcom/google/android/gms/internal/ads/xn2;Lcom/google/android/gms/internal/ads/tt0;Ljava/lang/String;Lcom/google/android/gms/internal/ads/pm1;)V
    //   280: aload_2
    //   281: invokevirtual c : ()V
    //   284: getstatic com/google/android/gms/internal/ads/ss.a : Lcom/google/android/gms/internal/ads/ss;
    //   287: astore_0
    //   288: ldc com/google/android/gms/internal/ads/ss
    //   290: monitorexit
    //   291: aload_0
    //   292: areturn
    //   293: astore_0
    //   294: ldc com/google/android/gms/internal/ads/ss
    //   296: monitorexit
    //   297: aload_0
    //   298: athrow
    // Exception table:
    //   from	to	target	type
    //   3	284	293	finally
    //   284	291	293	finally
    //   294	297	293	finally
  }
  
  public final la1 a(zzatq paramzzatq, int paramInt) {
    return d(new vb1(paramzzatq, paramInt));
  }
  
  protected abstract la1 d(vb1 paramvb1);
  
  public abstract pm1 e();
  
  public abstract Executor f();
  
  public abstract ScheduledExecutorService g();
  
  public abstract Executor h();
  
  public abstract nt1 i();
  
  public abstract u60 j();
  
  public abstract hm0 k();
  
  public abstract ev l();
  
  public abstract qz m();
  
  public abstract be1 n();
  
  public abstract vx o();
  
  public abstract ey p();
  
  public abstract pc1 q();
  
  public abstract ed0 r();
  
  public abstract uf1 s();
  
  public abstract be0 t();
  
  public abstract bl0 u();
  
  public abstract ih1 v();
  
  public abstract o31 w();
  
  public abstract r31 x();
  
  public abstract zu0 y();
  
  public abstract wi1<dk0> z();
}


/* Location:              /home/sumith/decompile/test/classes-dex2jar.jar!/com/google/android/gms/internal/ads/ss.class
 * Java compiler version: 6 (50.0)
 * JD-Core Version:       1.1.3
 */