package com.google.android.gms.internal.ads;

public final class te1<RequestComponentT extends u30<AdT>, AdT> implements cf1<RequestComponentT, AdT> {
  private final cf1<RequestComponentT, AdT> a;
  
  private RequestComponentT b;
  
  public te1(cf1<RequestComponentT, AdT> paramcf1) {
    this.a = paramcf1;
  }
  
  private final RequestComponentT c() {
    // Byte code:
    //   0: aload_0
    //   1: monitorenter
    //   2: aload_0
    //   3: getfield b : Lcom/google/android/gms/internal/ads/u30;
    //   6: astore_1
    //   7: aload_0
    //   8: monitorexit
    //   9: aload_1
    //   10: areturn
    //   11: astore_1
    //   12: aload_0
    //   13: monitorexit
    //   14: aload_1
    //   15: athrow
    // Exception table:
    //   from	to	target	type
    //   2	7	11	finally
  }
  
  public final ot1<AdT> b(df1 paramdf1, ef1<RequestComponentT> paramef1) {
    // Byte code:
    //   0: aload_0
    //   1: monitorenter
    //   2: aload_1
    //   3: getfield a : Lcom/google/android/gms/internal/ads/zzatq;
    //   6: ifnull -> 51
    //   9: aload_2
    //   10: aload_1
    //   11: getfield b : Lcom/google/android/gms/internal/ads/bf1;
    //   14: invokeinterface a : (Lcom/google/android/gms/internal/ads/bf1;)Lcom/google/android/gms/internal/ads/x30;
    //   19: invokeinterface n : ()Ljava/lang/Object;
    //   24: checkcast com/google/android/gms/internal/ads/u30
    //   27: astore_2
    //   28: aload_0
    //   29: aload_2
    //   30: putfield b : Lcom/google/android/gms/internal/ads/u30;
    //   33: aload_2
    //   34: invokeinterface a : ()Lcom/google/android/gms/internal/ads/r10;
    //   39: aload_1
    //   40: getfield a : Lcom/google/android/gms/internal/ads/zzatq;
    //   43: invokevirtual i : (Lcom/google/android/gms/internal/ads/zzatq;)Lcom/google/android/gms/internal/ads/ot1;
    //   46: astore_1
    //   47: aload_0
    //   48: monitorexit
    //   49: aload_1
    //   50: areturn
    //   51: aload_0
    //   52: getfield a : Lcom/google/android/gms/internal/ads/cf1;
    //   55: aload_1
    //   56: aload_2
    //   57: invokeinterface b : (Lcom/google/android/gms/internal/ads/df1;Lcom/google/android/gms/internal/ads/ef1;)Lcom/google/android/gms/internal/ads/ot1;
    //   62: astore_1
    //   63: aload_0
    //   64: aload_0
    //   65: getfield a : Lcom/google/android/gms/internal/ads/cf1;
    //   68: invokeinterface a : ()Ljava/lang/Object;
    //   73: checkcast com/google/android/gms/internal/ads/u30
    //   76: putfield b : Lcom/google/android/gms/internal/ads/u30;
    //   79: aload_0
    //   80: monitorexit
    //   81: aload_1
    //   82: areturn
    //   83: astore_1
    //   84: aload_0
    //   85: monitorexit
    //   86: aload_1
    //   87: athrow
    // Exception table:
    //   from	to	target	type
    //   2	47	83	finally
    //   51	79	83	finally
  }
}


/* Location:              /home/sumith/decompile/test/classes-dex2jar.jar!/com/google/android/gms/internal/ads/te1.class
 * Java compiler version: 6 (50.0)
 * JD-Core Version:       1.1.3
 */