package com.google.android.gms.internal.ads;

import android.app.Activity;
import android.content.Context;
import android.text.TextUtils;
import android.util.DisplayMetrics;
import android.util.Log;
import android.view.MotionEvent;
import android.view.View;
import java.lang.reflect.InvocationTargetException;
import java.lang.reflect.Method;
import java.util.ArrayList;
import java.util.Arrays;
import java.util.List;
import java.util.concurrent.Callable;
import java.util.concurrent.ExecutorService;
import java.util.concurrent.TimeUnit;

public class tt1 extends kr1 {
  private static boolean A = false;
  
  private static long B = 0L;
  
  private static qm1 v;
  
  private static ExecutorService w;
  
  private static pn1 x;
  
  private static final Object y = new Object();
  
  private static final String z = "tt1";
  
  protected boolean C = false;
  
  private String D;
  
  private boolean E = false;
  
  private boolean F = false;
  
  private ga2 G;
  
  private int H = zy0.a;
  
  protected tt1(Context paramContext, String paramString, boolean paramBoolean, int paramInt) {
    super(paramContext);
    this.D = paramString;
    this.C = paramBoolean;
    this.H = paramInt;
  }
  
  private static fa2 o(z92 paramz92, MotionEvent paramMotionEvent, DisplayMetrics paramDisplayMetrics) {
    Method method = paramz92.e("4/jKG3OOulNSPO3h/QOBI9grdVNVDSagI1Hx7GhBDYKSdd44mJVHq75Xskro2iVZ", "kIN4ZJNX+XXUI4t4wnOjDdUp79K5Xfql0pyqhYW0UXQ=");
    if (method != null && paramMotionEvent != null) {
      try {
        return new fa2((String)method.invoke(null, new Object[] { paramMotionEvent, paramDisplayMetrics }));
      } catch (IllegalAccessException illegalAccessException) {
      
      } catch (InvocationTargetException invocationTargetException) {}
      throw new zzev(invocationTargetException);
    } 
    throw new zzev();
  }
  
  protected static void q(Context paramContext, boolean paramBoolean) {
    // Byte code:
    //   0: ldc com/google/android/gms/internal/ads/tt1
    //   2: monitorenter
    //   3: getstatic com/google/android/gms/internal/ads/tt1.A : Z
    //   6: ifne -> 31
    //   9: invokestatic currentTimeMillis : ()J
    //   12: ldc2_w 1000
    //   15: ldiv
    //   16: putstatic com/google/android/gms/internal/ads/tt1.B : J
    //   19: aload_0
    //   20: iload_1
    //   21: invokestatic u : (Landroid/content/Context;Z)Lcom/google/android/gms/internal/ads/z92;
    //   24: putstatic com/google/android/gms/internal/ads/kr1.b : Lcom/google/android/gms/internal/ads/z92;
    //   27: iconst_1
    //   28: putstatic com/google/android/gms/internal/ads/tt1.A : Z
    //   31: ldc com/google/android/gms/internal/ads/tt1
    //   33: monitorexit
    //   34: return
    //   35: astore_0
    //   36: ldc com/google/android/gms/internal/ads/tt1
    //   38: monitorexit
    //   39: aload_0
    //   40: athrow
    // Exception table:
    //   from	to	target	type
    //   3	31	35	finally
  }
  
  private final void r(z92 paramz92, zzcf$zza.a parama, View paramView, Activity paramActivity, boolean paramBoolean) {
    List<Callable> list;
    ArrayList<sa2> arrayList;
    boolean bool = paramz92.b();
    int i = 0;
    if (!bool) {
      parama.Q(zzcf$zza.zzd.w.zzv());
      list = Arrays.asList(new Callable[] { new sa2(paramz92, parama) });
    } else {
      try {
        fa2 fa2 = o((z92)list, this.c, this.u);
        Long long_ = fa2.b;
        if (long_ != null)
          parama.L(long_.longValue()); 
        long_ = fa2.c;
        if (long_ != null)
          parama.M(long_.longValue()); 
        long_ = fa2.d;
        if (long_ != null)
          parama.O(long_.longValue()); 
        if (this.t) {
          long_ = fa2.e;
          if (long_ != null)
            parama.a0(long_.longValue()); 
          Long long_1 = fa2.f;
          if (long_1 != null)
            parama.b0(long_1.longValue()); 
        } 
      } catch (zzev zzev) {}
      zzcf$zza.b.a a1 = zzcf$zza.b.M();
      if (this.e > 0L && ea2.d(this.u)) {
        a1.I(ea2.b(this.l, this.u));
        a1.J(ea2.b((this.q - this.o), this.u)).K(ea2.b((this.r - this.p), this.u)).N(ea2.b(this.o, this.u)).O(ea2.b(this.p, this.u));
        if (this.t) {
          MotionEvent motionEvent = this.c;
          if (motionEvent != null) {
            long l1 = ea2.b((this.o - this.q + motionEvent.getRawX() - this.c.getX()), this.u);
            if (l1 != 0L)
              a1.L(l1); 
            l1 = ea2.b((this.p - this.r + this.c.getRawY() - this.c.getY()), this.u);
            if (l1 != 0L)
              a1.M(l1); 
          } 
        } 
      } 
      try {
        fa2 fa2 = super.l(this.c);
        Long long_ = fa2.b;
        if (long_ != null)
          a1.y(long_.longValue()); 
        long_ = fa2.c;
        if (long_ != null)
          a1.z(long_.longValue()); 
        a1.E(fa2.d.longValue());
        if (this.t) {
          long_ = fa2.f;
          if (long_ != null)
            a1.A(long_.longValue()); 
          long_ = fa2.e;
          if (long_ != null)
            a1.C(long_.longValue()); 
          long_ = fa2.g;
          if (long_ != null) {
            zzcq zzcq;
            if (long_.longValue() != 0L) {
              zzcq = zzcq.c;
            } else {
              zzcq = zzcq.b;
            } 
            a1.P(zzcq);
          } 
          if (this.f > 0L) {
            if (ea2.d(this.u)) {
              double d3 = this.k;
              long l2 = this.f;
              double d4 = l2;
              Double.isNaN(d3);
              Double.isNaN(d4);
              d3 /= d4;
              long_ = Long.valueOf(Math.round(d3));
            } else {
              long_ = null;
            } 
            if (long_ != null) {
              a1.B(long_.longValue());
            } else {
              a1.x();
            } 
            double d1 = this.j;
            long l1 = this.f;
            double d2 = l1;
            Double.isNaN(d1);
            Double.isNaN(d2);
            d1 /= d2;
            a1.D(Math.round(d1));
          } 
          long_ = fa2.j;
          if (long_ != null)
            a1.G(long_.longValue()); 
          long_ = fa2.k;
          if (long_ != null)
            a1.F(long_.longValue()); 
          long_ = fa2.l;
          if (long_ != null) {
            zzcq zzcq;
            if (long_.longValue() != 0L) {
              zzcq = zzcq.c;
            } else {
              zzcq = zzcq.b;
            } 
            a1.Q(zzcq);
          } 
        } 
      } catch (zzev zzev) {}
      long l = this.i;
      if (l > 0L)
        a1.H(l); 
      parama.r0((zzcf$zza.b)a1.h());
      l = this.e;
      if (l > 0L)
        parama.e0(l); 
      l = this.f;
      if (l > 0L)
        parama.d0(l); 
      l = this.g;
      if (l > 0L)
        parama.c0(l); 
      l = this.h;
      if (l > 0L)
        parama.f0(l); 
      try {
        int j = this.d.size() - 1;
        if (j > 0) {
          parama.N();
          while (i < j) {
            fa2 fa2 = o(kr1.b, this.d.get(i), this.u);
            parama.s0((zzcf$zza.b)zzcf$zza.b.M().y(fa2.b.longValue()).z(fa2.c.longValue()).h());
            i++;
          } 
        } 
      } catch (zzev zzev) {
        parama.N();
      } 
      ArrayList<sa2> arrayList1 = new ArrayList();
      if (list.r() != null) {
        i = list.o();
        arrayList1.add(new sa2((z92)list, parama));
        arrayList1.add(new za2((z92)list, "nbP5fDSCdR7wEZWUUvs/EY3UVS0lOW/IiXfPbY4s4SGuQE3bGWJDQjvI5nPqAZEe", "hv9/8RfhFT56D1pN7knLU59DtwBx8XLY+rfYt8huV7Y=", parama, i, 1));
        arrayList1.add(new qa2((z92)list, "C91vmroXCRvXadHhNn1fnUUiMLNxSpdxkuTy3y75vjwmBhTE1CZWrn2FwsomdoD9", "og/hbeWrV//prjaaA0XDsdZ9G14LUyTOfV9P2mPT3So=", parama, B, i, 25));
        arrayList1.add(new ra2((z92)list, "ME5KocVy2SapB9q1ORxiZZHvrO7+Gp7sTPqB7HB4PyxlYcftUNqyRYOZdBImw/Xw", "jwJ7VYp5Rw7Vy1FHw3D+q7stkTs2swvx61cvm72p99Y=", parama, i, 44));
        arrayList1.add(new wa2((z92)list, "rHKgIi3S816JqTbctm5+ppbCnYA8Mnw8DTFyVKxV8uKBimn7Ro88FU2r2rzeXUH2", "d3Dpd04HpLmOjKGWo3WNDca0uIyveqNwmpynaYW+fEw=", parama, i, 12));
        arrayList1.add(new ya2((z92)list, "j3EFBolOiHR1vPpU9K/L6Iw6mL2C4sYjvF/ZHOznb+kbO8zylKhMnMz2ES2kUAF4", "GDHJJs1hLvcJbxAGg+A3uYefjZ+vbS20/9NgtZFacds=", parama, i, 3));
        arrayList1.add(new va2((z92)list, "38+7Ci1811Ckz2oZVFx6KlDTfbTOOXv4V6VZ4sGWFwdwRadympBztFwtqTY6IAqe", "U2Tb4+i5Qov1YobX2EyBd8CpXvcQSoxTHefIUZmxO7Y=", parama, i, 22));
        arrayList1.add(new oa2((z92)list, "1kM4labg61uxQq/ZliEyWeqiHYnE39xt/ep/InDLrFtCPfp50YmWmda9T2Q0zRzo", "jNtmdGFipTxb+if2EmvF9/j1W8SftlqhBkmz/QXRMc8=", parama, i, 5));
        arrayList1.add(new gb2((z92)list, "Pzb3EQzXTR173k/Bxniq4pkyjDy5KFPfSAziYLw5DVxawc5akYVhekPywPvixjd3", "udzYQv2TkS7+ukw1ODf3tzd5bioILlPFB/M5+Os2CkU=", parama, i, 48));
        arrayList1.add(new ka2((z92)list, "SnOF6hfOOyqRjheOz37gfPBcikgoFyQupOMhQf+gI+V8pAR/vc0Bo3GGspPMqvxg", "GaeKbakS/uQ/Kw8mscu/vCnGoAGgJ8hTp7dBq0ykoWY=", parama, i, 49));
        arrayList1.add(new fb2((z92)list, "jrKnA9m3WijdzGPNGYmR0hcX8iIFG/G0DvoEVKezorg+AQGzgtIGAVOd7Ziq8htD", "9oqpNsO66jSKfhDIuHdM09PLunDxdaPpL7Unu1WWzi8=", parama, i, 51));
        arrayList1.add(new cb2((z92)list, "ZrgqrlpoV6coFYR+EX96hjF0nNAxPts7sE36IIO8Oy3rZakvCLpyZGiwfJeJ2AC2", "ROSCeCbOL6rnP0Dz3oUxLxoVNlrS2W2HeruKuGiIrWg=", parama, i, 45, (new Throwable()).getStackTrace()));
        arrayList1.add(new jb2((z92)list, "BifMZtDDn1k6aXdJ6FXhEKp8nqw0qTvNsmLURv1tlGKlAl7xb6f4vH+hciqo7SWF", "ywlTkLC11yr7mkfYO45Yj/yimKb8nEX1bqgaHDuFxK0=", parama, i, 57, paramView));
        arrayList1.add(new db2((z92)list, "fsZFw843Dvy3M+ALffkgZgeS4xxr1ptHWZBaFyjwF7Xdp6kQlHEPsBezykWp7iKJ", "YqrFXTpE0zhqgXdnuX46L91fkbR49h6qiED5VVltTkk=", parama, i, 61));
        x<Boolean> x = m0.Q1;
        if (((Boolean)er2.e().<Boolean>c(x)).booleanValue())
          arrayList1.add(new la2((z92)list, "WI87GCANEdGubbyq1s01CBcmX+lAhmMzi0YxEtEzesVgqD8QjTfQYxNLX2VeS7+D", "Axpv7G/YgsmP2XLyasiVWCsi+Z3isYbfhhh0kTw/Q3s=", parama, i, 62, paramView, paramActivity)); 
        if (paramBoolean) {
          x<Boolean> x1 = m0.S1;
          if (((Boolean)er2.e().<Boolean>c(x1)).booleanValue())
            arrayList1.add(new eb2((z92)list, "GnrtmFS5BfqcRzWCaoKdIJwd5TxnqJANkvWViogJ1oq97v+cqUOeljHoVb1rUVHD", "99fOdT4VL+CCqqohIB+ZSPeSaMTz3POwNYXWqb2jYJA=", parama, i, 53, this.G)); 
        } 
      } 
      arrayList = arrayList1;
    } 
    t((List)arrayList);
  }
  
  static void s(String paramString, Context paramContext, boolean paramBoolean, int paramInt) {
    // Byte code:
    //   0: ldc com/google/android/gms/internal/ads/tt1
    //   2: monitorenter
    //   3: getstatic com/google/android/gms/internal/ads/tt1.v : Lcom/google/android/gms/internal/ads/qm1;
    //   6: astore #4
    //   8: aload #4
    //   10: ifnull -> 17
    //   13: ldc com/google/android/gms/internal/ads/tt1
    //   15: monitorexit
    //   16: return
    //   17: iload_3
    //   18: invokestatic x : (I)Z
    //   21: istore #5
    //   23: iload #5
    //   25: ifne -> 32
    //   28: ldc com/google/android/gms/internal/ads/tt1
    //   30: monitorexit
    //   31: return
    //   32: invokestatic c : ()Lcom/google/android/gms/internal/ads/tn1;
    //   35: aload_0
    //   36: invokevirtual d : (Ljava/lang/String;)Lcom/google/android/gms/internal/ads/tn1;
    //   39: iload_2
    //   40: invokevirtual b : (Z)Lcom/google/android/gms/internal/ads/tn1;
    //   43: invokevirtual a : ()Lcom/google/android/gms/internal/ads/un1;
    //   46: astore_0
    //   47: aload_1
    //   48: iconst_1
    //   49: invokestatic newFixedThreadPool : (I)Ljava/util/concurrent/ExecutorService;
    //   52: invokestatic a : (Landroid/content/Context;Ljava/util/concurrent/Executor;)Lcom/google/android/gms/internal/ads/pn1;
    //   55: astore #4
    //   57: aload #4
    //   59: putstatic com/google/android/gms/internal/ads/tt1.x : Lcom/google/android/gms/internal/ads/pn1;
    //   62: aload_1
    //   63: aload #4
    //   65: aload_0
    //   66: invokestatic h : (Landroid/content/Context;Lcom/google/android/gms/internal/ads/pn1;Lcom/google/android/gms/internal/ads/un1;)Lcom/google/android/gms/internal/ads/qm1;
    //   69: putstatic com/google/android/gms/internal/ads/tt1.v : Lcom/google/android/gms/internal/ads/qm1;
    //   72: iconst_1
    //   73: invokestatic newFixedThreadPool : (I)Ljava/util/concurrent/ExecutorService;
    //   76: astore_1
    //   77: aload_1
    //   78: putstatic com/google/android/gms/internal/ads/tt1.w : Ljava/util/concurrent/ExecutorService;
    //   81: new com/google/android/gms/internal/ads/ws1
    //   84: astore_0
    //   85: aload_0
    //   86: invokespecial <init> : ()V
    //   89: aload_1
    //   90: aload_0
    //   91: invokeinterface execute : (Ljava/lang/Runnable;)V
    //   96: ldc com/google/android/gms/internal/ads/tt1
    //   98: monitorexit
    //   99: return
    //   100: astore_0
    //   101: ldc com/google/android/gms/internal/ads/tt1
    //   103: monitorexit
    //   104: aload_0
    //   105: athrow
    // Exception table:
    //   from	to	target	type
    //   3	8	100	finally
    //   17	23	100	finally
    //   32	96	100	finally
  }
  
  private static void t(List<Callable<Void>> paramList) {
    if (kr1.b == null)
      return; 
    ExecutorService executorService = kr1.b.r();
    if (executorService == null)
      return; 
    if (!paramList.isEmpty())
      try {
        x<Long> x = m0.P1;
        executorService.invokeAll(paramList, ((Long)er2.e().<Long>c(x)).longValue(), TimeUnit.MILLISECONDS);
        return;
      } catch (InterruptedException interruptedException) {
        Log.d(z, String.format("class methods got exception: %s", new Object[] { ea2.c(interruptedException) }));
      }  
  }
  
  private static z92 u(Context paramContext, boolean paramBoolean) {
    if (kr1.b == null)
      synchronized (y) {
        if (kr1.b == null) {
          z92 z92 = z92.d(paramContext, "ll+nowuQKLxZSE4zpeTvUl3Gha6AS9UBIOMBB5g+5uQ=", "e8mp4jaCizT/LsNfz2/GdPr+FhT8xbi8eTBJyb59Iiv1t5mZH53XMZD16c61GYtM63r7e8a2BJzPRATmVgCaofROUiY/xThJAWlwDgZpD5uOg5tLfowrq7FiETpHsuCKHyyfGosMcMLrZqklTAj8dD2TtdAhHfX1bfYzVAJLqx7zhYrU37M8w644jz2B0IA8hiKqSAPNE8vNKP95qo/3p6Ka1iohuBJXgiXi7EIYUXu8q9jdy+rZXMnIvlyxFF5M0Pt0MtndoU2h1MXvi4mto+JblFhPim4i34HRZHErwFCJXcvNuLYxx+vAWZ7wQT7DPtofJMpu/iZp0utrhjgjCOT1hfmUUGnCm0Zk4Phg5rFhLN6dAXTTWOIMzLdWE2qL6WbH/ukztsmvtg7pmgF2ymxdjfgikSPRUE6hhLLq5NRZVpIKO6ml0KIS8EdgCl/rcehAl2/ywHXzxFzzM4tJ7x4dAHKtg9Tu7ZZDjMwZPv35U11tcqR287CC95QM0gprCRrLacPonOjpV55cQH4aPMMAC6BgO7vvTvWHBfyQTGB45a/0w/MCnD3ujoBkPQ1a+avsQa3mgl/M6uQtxjtj3gllqICd8R/vFALPiEuxGau+24CjrHEpaR4wlbmrHN97IEL94My9TFOLkAfkY+5gUCiYIdcteiJI9LKNVG/d/eW62QTSNTCL2hF4GLnDzVzZ0l47j8RF9riLEH+zKmMotLecpiBCiXO9fPiFrxaf1DXNW8fKKqxpgXJ3h2BzO1hGhszfRlF6j5MkpANZBjCmZL3UEslR/VLFnsS8RlGmli1RwfTfsDB0xLUoGkS2wOzOIjwPRi49bYDNeeiJuZpdaTUw0XN2Wz09HmOJq+xjpyH/WD8XYRXbe5Cc8f+8b55xx2CeVRYVfLPch9G9H1Iceg7ZUQTisVfAuivSD9lINqJeXT+sfA+5RzA1U4OGQZRlqdwx51mzNiLIU4cU01p/NqN7fHLxv4x+EpSTv96Pahjod4ykglQ5gkhf05mY8HYvICm44gkHnsb9JrdL1RkkIBed6KKZSwC3lhHwSxm7rozThJYD+oyEU3kYJ572P2I78Xf6CM7FgZm6V5whOeeNdY0lh9/LFCPHvyJn/T9VRgc29bqXycHNpk6Xaul6hrPUsVAeUkPpOJ6al2N7pO56SaIKxN66ZdlcISU/wifXgoSPPzQkXkShFAALE2gmgMiWekFK+fUvTSU+6QxZs0YTPubiHbLwPvIoMnQsiCpR4isjzJ7s0bnqHacigKJsiaXYEIqZpNQvsGzdcc8f+Gl6RGRtsA8JJk7wygQC2KwWqA/TKmqgcN2f80af18CvF8qX1sTseeYl8Tufgo8A5twmPJCStrE0G8+RWL3z/6dMeUrc9NS3d9TsmG0d6X9ByWwHgrBmw1ZkxGiI/viftEFPxca/fg6mHLhulvKc1e8ztkVdI4nfG78BDBNYsqVxdI0sJ4NbJKznJHKwPq2wtyYxRBtEPlvJpEP7FloTKxEc+ch0NGMlS7ZwIsmjM2Laq2CD0dK12z2wcRSqezTdlhXp5HdKkNjWSmRPnHT5QELisRZLLFXCxxhoabvT0rpmeRhyJAL5OWLLkB8doG4c4vE3tkje6KLREYzIeWErL970lyrOCUjvde6NYu6KFTzusYIKRBxsdVmaPaTNejh7+m4luHhGwunjobR2+olxiA5kjOvU2tL9dPmpBshiUSsCiho0eLWLMyXlL5PESJOSo+l3488kaSTn5tZbORzooINnDKtbHbGpsSj+iI8ty2CUq4pTxguV005vf8x6VnAyE0ZpoqMWRY9jfiLHR46LcxuIHvtWvLyuvuB1cbjBA+Lt9jyQaTPCvVTXCDY9GSMsGptzqwq8LUrpGaLDnKWXncv4EOb0r4WdqQ7JcF6b5JEeOcwx6NaZq/V0OFDxX9Wr4YkgBcs2+0kIGPwX5VoGqpv469ue7ObA+jQgwKSdVoqznRlVfpDz+w3oLqw8oTSmCIFTsVHK9Gy16pM6gU+GgpI9pu1WEkJ69NS4969v7RoN2yTJcCPVTEjnGKd58qwDMEK6IIs511gxQQw9XoDUctEO51c72pXWV5sLUrJ986bghFpdljI/d0ckAs9+DEcgY3lTeO+H3wcC7izfdOyI73NdGYkR2sn1wKw2+bO9o0cJGR9yTrfFgkp22ZR1WlueXYMjVq+jmLgvINbElHQBB3m1V5Z3a/7ULu714ZW1RZG3CZELqFXUFCHbG/KySYWsFvLdgxB70LUnTzxquc5WK2dQOSkgGsxsZ9zMi94aukFCjOEBuYYCoA+5Is02cCuzNWcJosVK3nPnmFvSnLw5h43hoPYTbMUULR5ZFHP93R9uEei0ok07aIiVqcoP3UB9Z06XIVX8wr3n7hX8TiumZhvZ6L+OpSn0tp5l/oYEYhlUzJ/vxy/diYyj1vRHL7kwRdsKk/m7Skh/l0NQIaNcdpNYOEdU4TIrmSCwZc7tH8L35wakr9U95H4s2l8lrg9YqOutQ5iBcHdw6z37xiqZG+/pTmWLRUcS/XBv5vmQkRjdH9PHlN3nTPCygbTHS+Ro+tmV3vabWX0QHp0I5lROkue+dbKP4G7gEumZ8+KDwlb/ReCFTCMdfvcFTFfxVw+4OmmgUOX6RQ0cc/AkASJX1Sf93rxlvW6qocxvv7JS1gqFJSfQHdbZax0D9uiVln2nkEMBpq6qbmV68buTYNh6YbLZ9SzlyHjpTkq0JnDgxDLc28iu21SHFjR/F59w76HVcQb4DX1T5b/GT+uEEp4uqD9d+Fi6m6LEmx9DBuA+IQy7ysRZeROqZLIOqXAYKXagC4JeMHI1g7JJNOxIoFARE9o7HkxS0wA2/4Tj381oU5WFzZwAwih/Lt29QmEQMRt8AuzDdpef24Mu7NW8aObKGhC8uMGhs1eDBzsxfO5rKmiTTW6q0JoyLHjXAtlOwETrdxGy/QX8C+F8GyzSBTgY5otDcTqIM+jzYnAI1MRL0d7zTIGhPi8K+i6IkY6dKfG31YIyakIKUap3cNHMb6Dq9AJV/4S8ZQklfJX9lFgUsYO0xXcjsp3IxKs9X4WJUi0X87hir55HBpBpx/TUS4S2FmLysEIvpwIJVypK3IdonijYXdXBf9iZ3v2gw2ZhEoIaoU5vbT6kEMAVNENfta3SJLPUtYHX1P1PY2IQc64HVzxc7ebYlfCiyeGAhW8CSZCwRsiNyExh+5L/iVnrBfwZXX/eCOzU6VQfuCNdGg3y3bsou+Jk39g7GH6B0zkaFpiPoWEMPxxIhtrkNIHMC0vucZdFDoH+yZj2Wi2y4quYWQAl4wOMDq1+htNreyLnVLplxG8FjvRYY7M2KeqFSRDLxRRgZvU6MJZ77g2U/DID89o5/XNTs4u1/Fy4NR3JE1H9gws6BJ8GJf//GtHne+ry6PY3Gp5A2wLjglNiairP6eQwkc1Sx0WtjFcYTDnanyvqH2t7ukyWEvtLjJwNpa03DXBIk8DEVikmCu+O+SL8vk+unKSfBLIj3NX7g2XJuESYrcEJd4PVOlyPRJN0QqtEejPOzL7W9zYpvHD6/+OZ7Br9i3fDg2AdNn/LfTNO+O9MgccIyAMXsynCQGU+e2+MRujLYiVIahAmUHIecsRaTL5wOF5a9mrr/cWJOP62ZKSgh+oQDkcgL0dOhd+KoEM+B3/2Q8DlVmKIkbaHY0JoDAM/uTJ8NgERf8orXEWzu93eH9QkZYQSxhKXEcJTLSzr2PDYUVPriqUBudh0zaISlf/CMNRs/Ea3owT+ZwKne079BkSXJQz5PWztg4hJ3Dy0tQ1f24RxSFKGVXz+v9QjY3uFZUm3n3ep0j6xnUBlbILHrPR21I7b5Xg8rkL6a/8GNRHhTwJLyHSzO9HwhStl/XPb2RWXr4fiKwtFX1Z//RhXYvuLJNBRAd7pFVU/QiDzKynWEP8U2pam0E8JP6sSok/oIhWu4E+Kx5LJ+ZBD64+3CaO5PoUDMO3uNEiFLcVLKIt0XFZ8Phx5nzuPO9busK3JdJ9U5jHvGRh2300C9k3EdvU2rSipgn8ZIUc63WFjjImU2NQTAnbcDr/Iuz0G6MMH9n88YEUppsGfnW/EDqbNZcL/WYn7OpmxMedD59YYwzWJxLMUgjgaynvpUweAtn8nDwlC8bk/3wAUCVzT4D+BZbd/AmShkOBzUfyfK0FW9wJNpOZtP/KeybXxSGK5SZ1lXLDFzCgDEpj9ksSXArJI6WEDbcX5H8tHAlP4UMpb/vvEWPM3C2ysSdkEV2Ek5E8XFEmOUNiniC2YRNXA+fkFk6y8A+UVo8+9/Hw0F0ef/ymfr2Csc4Sac2Tq7SOrLD3GColRhIXmrzSsLWN+1YqkuW9MEqUQDVz2t4fcAlsMUFGdEhkFYHxTancFdCYBzpuUuFZMo3LekzqXq+4tNc/VtFgOV2XYac9v0ymr1OQkgDP2AblAGO1DOcn0uWNeto6iBNSGRDEFLMIUkaHP6SOfOh4CG0AkmAzSpboDYrjkNNXM2/Qu2brMX1dy5bpUH2CIZ3I2DgbbZAVo/aImLXKwqu5X3uBpVEW1KqbGPK0xQP3VSbqM6z0w3DbRgj2FazelVVWR+XOuJXWm6Foj+LZI3V/FwVimnMOKrTh9CFApNXqQzUHcZyaTUY3s21BZp9H14Sl9smM1i+K8FZ+AQLg1xMjiswjbT0wNG1z2r8O89xDC4kgrqPi2/JAmxryxL+hVg7X34eWP2fgveZ32xEQugUZKEC+pwHr8zLg+xQ6rFebhbe//oDUb+VAdczk2VAvoFI7FKzS0ucAiD6TzaUSciNOy6AuspIPCFvk4eqwxtYKJWOx2RaooKl3cZ3W1J41IoZ1TJORqYXQTQkAU02PjPYx+InttmyH8Hq1Zfo3326fm4bzFIkBdx8vAg9TOtC8LvQ+PHoGC1j7mzOIz27kne128RGihc/W+clLzxM570MGccD7P0+VrfYYfuJ30DhFpGlqehbUKjldfLtwKMkckcjYNQuvEJqRMXyrGGrs5sFbegbS9CiFN1ahr/MHOGxsrG9lOzlpYOxXlLWmAJ/U6jTWS+9z2ha1B+ps3IcvnDSkLbYSWmoMRpMOB4lj/HRGsqZCs+FjUwJRaYkH06sG/49nsxUSGYYy9ozprMDd8m6hYVSvxZabxsnCuABv/1x3/HjM6MlWUCiXWwjBEyL2w2fLV0LRRIQpD1QKPNNnJU8L1tho2It5HAa4X8WEF/09H1gPLh9UfgPbHiJ8UhALSO85ydAhRyittR/iYaUzJM5vID1aqxEVNF8zQuJQJzF82wPIwA+Rx13STN4vVRUH12rgN8VtranAlQupoROLA6s0pTx0SKYirZCa9vQ8/sOKiXMWlkTnc3YtGx+oQ6wfHUmnjtlMoBFCGUH+U8TeWN3dyaZdJXGdAZyQghOINemgeBdUnaCSvhxp7yonubXCm7zFGUTNXwFZvbmIAnW9pioPV+5bwfuL5lxWKOrWD64uHEGTXthenPCBr2eu7DjtjPJTVvh/It6rvOhVf3UsYuXEu75dyfuwqmmarXgu2Et9jkqwzKL7XrCNR5n5mElD77xTKci+vXsdagWAoyRG8FTjBpr2tysjmDvf1wO1FLG/Y3pWrZhmyyMb2hSo2ktAWGeY1Ubf2EAG61uWj2lX+NckJRmtpRNA6nn8lUnf7YtuT7RUsSJhlhk4MgAdDcdBQTlFPg1Un8zsqU2HQ94TS3mbdHHYAyFvLU59LGxOfQ0U8+vk9O49GP/D/lCsnRmbnv2RwF6PZBPPhKp/EMo5+hQ3sQsfIBpYB3uKyLfhEx3BuEjjhVG4esi56F1rb0fqFrYrnp9VQbYqNWIF5NLRnETOCw6yjoB4M9nOEUMk7NDqq5wxuzybcEFUHf48SEsuHBCgFLUYJ0RmzL9hIBUTSIEOon9ikqI9/GozW2hFW3oPYVjTdEVaqqDhb+dK/Aq8zHPanrMzK0ppWGRW7zcI6r0s7aR0hfYPrEGlsX5VnnKGIsmY4DV1qAjXxGHlGC1hfH1RPIZ8C2nQJKoyXgMecAtbHM6NnNXQ6+niCLRAooSG6utV6kmh8RSI5JNnzyjbpKFddTNM7XbNVqBJVX9cjqGWm++nPaTXzFpSeZJzy2OtGuZtNYQkniW6/Ob86ySJn0GzUqiUkpTwLIipk7D7SwDHxLrius5KScMAwHykNNRmB8UQkt1WdX7bsxXwsYMbW5VybpDbKih4Bl8yhxlFIFAeKRwhAkAEQ3+J8ZfrlQlP5s1wAD7egPNxYD2Imt5IbpIfK6T1a2RMhCPJE2cDLJfNRjSUxZxAHZ2NAaSNfBoWQRVshmkI1E2CYYl7098ei70n+hlcVfPdWd+KzNbmWCDrXbjfggCA2LHfppMYr5hA0wcmKwYvBmTBBMpa9+l1YeMxeeHO5gHYCpPBpfxwYsJMqlM+6M7oe7117MWW0b2iyQtuX9cEoY3JhkdkHhaNkK7XPzHtWYxOtAq7oSqv9v0Zyc/LpSIcqCD5Wo9xGJOki9zTnmSRbLWQaxHXLAF/0L/dHUcLdSEd2v+n+gVZJMRpEnMv2cWeoX4LGHBdIxXIn2BpStVUmKhVpJG7McOe24/g8UpSFzmMW+S2deDIXFHLe0/ywmNSz5uwaiZdqvJdRPuLdL1zpgE5Pw8srgxgfHq+huaaerjvRU1yVim++EuMKA0/JCwyWg44bE5+6ZtGLAjhoPwjAV7iykM7ZOQwdj+0t/6FNy9GUogMd+S9SImK+0UFhKVEkCOT6bXtY8jqq/ovjKMPiUmZULQVjS9+3Jau+xwjjhghlfb0N2wT4WtWBdMuV8L1cCKiFDZA1M779fahtIzXvZtoztvS6ml5t0yXnjKGiDK9sxKSJLplBBGleQR68ty2ENriiSgMbLy1Znix7TWA09YFhPx3jpt4uQOkb8lWZJ85J5t2FUsGGu05efoRYNa77QeYiUMVh9ApezLG5okUuJHbtq/NPqSncjCWxLMuOiD+z60sLDj9XRfq/j84YBYJEWfZcMj+XbW/pyINma+DO1VHTMGdM415KXN0OxrxdufPg99INU6BnN64n1VumPOJ7CShev+Mujj5TmcYF0+sHb1t4t14Eg5fEbFnk1D3dzKlHvtxvkDksDBMkYnRa2UvSHcYIKobLt0DhXKPphbaWTgGEyVZ1PQnDVXJHLAlFcmF2IJ+BrAL/yVJEYOEJ6arfcDNu0LNj/YvwwdXZzIPaCNTgygPkq6hVJ92UJIDSow1D2noq74NFSnNDGz40zM1Nvfiiq/jLiv82uv9rU77GO3tWSfkaaskAk9Rnzn/F10gjU+iIXPUTOk5/BClAcMUx8voTt7MRmpLpGnkuB6+Zt843zN/fi4H4aPbc+FSWWDNlz83zNrXxQ2BF24JtoURFhWWbdj82IjBF4pOa4TLYEMAgSXu7elZiG6ytt4oIiijPz6Npy6fK7o1CP0X1KyXxZV+Hb5Sg1KXEY6ZsCKpmkWTwPgfGT6a9O1smiZ3F7J/OomAFMufULQYYpeyImMJKxGlv1q6ejK//LVC8Z190qDbYxbtzsgRDzkQ6hQtuLn9UCTij2JydIvkhRiEryLRolF6qaXQg45I91C826VunSnZbLEodSykmLZcp+6cJmdrc7UYGnXrWAHwmD/FLd1R/p6XKv2npxXjwkCdzdZ71z16ZCAWpLpekMngCISubx7WVO4EFAzlamzZ00uAbaDQvNmEYDYhIfBivcB9OZFw0olMRz6lons6cR88m5+xASAOIowezljsMyZ++k/+bru8Xx25WjKzH56pTWlC5ES6RUyHEXxBTZz3Nv3i4Nm7L/KFObTaRtJbZNtyL5DCL82Cfydu+kUiq8+ZGukMnupx18KqITvt3IJkxBV6pEKf2Wcy/YxQJh52DnPwlrzj1n5/FLNF82VHTlu+Imc/zoIJiXq9AVNd4oPQHut+I2QuTaFPL8Af++LIbq/GgbDDu1pfy3ekOnGDITzPwVRs5kdWBlSZRByUPMHLalkZlmYnKMhSThcSvGFyT9Lg5yv+56+U4jxi/JgjD0mHv7fHO2OXCBOkllIPBM60SsqZsBhw2o8JZ40buFfCt/wP1QKcQtzCv+rxYJFkQdWKZ/f5KqGmcbENhv/u8MUqmNcKpnxbWTRk0gFIVvysWTKjV02OnbKKZzdtaADuQwp7Dflqy9e6rLrn5OP5+G8T4PiBPrubHdUeChPKmJA3XIWLtVBvFPhktB9IdWRuqMXzbhDjMa0k8ltcP07YWo0Z8zUiUKsp2fweF7BvlL77Qt7/zLjtAwLeApULGOogbGQQWwEGzWULP3JPSbYMzke302IoQlegXpGWbPefq9pyo91CRjIi63gEMtuBLN6pnp85MKVgTKPXWWcFS+PAi3zL4ydmeCmOjsWiJm6cVdPBZ9ExGqlgKyR6eucCQqxrI1Wq0wk3mSRoYuElcyry8WL84tHu3EM8YdO/Ze6qZLnxJv+sRzmxR8j1is5BV5K6r2KO4UnVCqgSoJwSDcjyGi4eWu8LugKhTq1pb0+9Jf7SrcSO/sZ6NAYcBHWxtHTqMjhG25JVTl1uI4433nbZQb9ywI3HpS3kxOcM3TKa/1Wb//5OdSAttJ70dzorjNOS70NNYg92ZwHJHq0tntwlJNABQk66XjRi55IHsZAMteG0NhtwkL/TvLwVDaO+WXkb5rVJ1+vRAlBfxKJ+qXPvn1vgUzDwlu+d21t5EfQrZsUbTuJLkTUfVd2WgcENcW4nXYnVfap2yYN8SpSuSgPj+h1kFnpNrJDXAvOd0Bdq7jiDgK1KCbOU9UPy0T+vRaI/VaU4rLU6p/3ybd4gUvLmh5wN3EIN39A8B1i3y3vHUE7q5MFPDai9mLVFy6600P9sZFCtfKMPFe01Zq1Wich4RiNz2TSVDCgaC2jd/SZ+PuErhADBb5jhqAG/PvyvnakPxJQVJTdsb669J7AjVTNYJkH4xc03n/t6tR1aGSzV60CowQ6JLjx9iPlZpajaWfMZzeEpnW75t8CUivV0vommC0wNuAgEMYE2oRekrHidzvfJSVlv7mHEOKFOOwOdeHx7pkXKv6megtV7W3rwVpnx0Qz9DpZIFeny7Y91JtbmVWIV8eQdKHdR/DS4T9xRi5grZzzvSrvEaDS0qwW7Zyak9dvyKfyegtP1TOSM3edq/dSc54PnZ4v46G8kKCT1ggYZvN6e5zuegX+aJwH1C/OfCK9FFO7mLZErZPih0kGU0rPJXDHOq1YT9GAhU81ndtm39oupFKddIu1q1M9Tzx2vy32rQwY8H4l/cAswCoGGUA2JpoQhfoi1Eid1U2kH9zGN+qFxdT2oxfmkkC16QGSNXUGVpc4gIHUWE0hAVygzhQ7B5By6ccF/O4KKNUYcfLyC4uY0JGf1v7IvbjvxNRVOy2ROgueFYz6Ev4IsC9JMS9agj73+5871xdx4yfmf0/aCsGD7oU+GxnYwVqkKeH256pY+2avM2reLjWNJztVUxNIai5IP1dw+Agu9wFKokYvjjR9lOSKbBgeiDuYUdcFVd8TbwyfOxN+8XcH4Mhm9nO5v7YrgIG+5mxHMnzV0wvtPD8joJZOFypel7ZEdPqhy/BecRSZXC7Pezv/vh0T7HswFTiV69nPZH/1pOsDruFXqJF51bFab5TAqxfNubmIaePAgwAl0XSEtm7R96ssmI4ih5qZaTRRimuc7OJ1PXM4lBS8l+dev2jY2yodEjhiyM1V4DKDEPex6XhG2rhBI+8Pt87nsdIfWt5TV1LNs0/QogV5FQp2zkNAw42bjgI3xw+7iCARAvcAIsqOTFK98yLAwlJ/1AiTzlGWAv8+b/8hOeDC3YCRHKGwSUNRQYM05Y8JqaD6vub6xBiXC1uDxNjnlZ8q9OWxKydpkWJ77vfNBQe8Fxqcx3S8jgYN1coo4sNm/TcbLATvw8OU7iIQ3PfiTfofCKxawVFaMG+eoYBLHyfze/88gjw/WfSz7luOmli9GSsAw5zUcDZbQJ/e1YsE05Fy2v+pnL/gv6PRT+K7PxFaDezq04++wKVCq85Faaubq8HcXR0sK1LsmzKft01eXBmFCNeb4QQU9Vu3WYapBnUEdWB/0qkzMLEXIFsefLs7FWZr6NFx2mOntDAmhxiqR3Frtp0aPJ9lgabBkqMS1bvr9ifjHWraz8NJp6IZCCild1kILrUxuKHYSbzwNJeBUx3t9AHfKJfWLjKLgUx4YLcDbcdttIXkwZzBPgmIOIzRmuy77sl+SLkoIXjIusZvIZDV7TJIQ5eCDmvdOrpx6DFgWqSXPcS91bNhm4ddLjvvVbH0RlcQun3StnXYxkH76g4eFuVo/5kvRv0OOcRkIXhICy4vsp0Nlbs93HG/xV81hBUhOQ+Gh89qlKLp6FbCvw9YMsk6630ZT/E0kAb3xX9t0jrFFlOdfR65O46fgfV0VyKoJnhEkqVBN3S3Ht1gh7ZxbpRPuasD/ao2ftJcH2w0tuoj7/67vT1tUXtpwhEnp/kRdw+nILH100pyUAiVLtFFWwjMGjcw2QuuXe/rxGM/4wvqHy2iU/hweXLOq2noPHZ8QYAQnBFwl/m6QE7jXh4vfW8I3Vuh5QMpb/koYJutrZbwALGQoHvECXhlCtFlFEF68ABTYEiIQOqrBgTzT+kGh1i5wBpku8DMfTe4af5J/nVLSTXlwQTOTO1DWoqXTrvs6LXjDk/FYak2/Lch1b6hHpbvVkJe6MBWgUcT9tor1xGzhN70OJHQiLw8PWKMU7VDevfiabXsDny9n8hUcYBM95qa05wS0Xkj3UwOt99p+XcTyKwlncGLkWxYnTMPi0cdBRncd7xmqk4MzCq0+pq4y6hqGvbByVCQfgwJ9UuZddsl0OR8JxWKyG7wrxo142F1qySKw6ae94rluPGaveERRoxjF6lWRYXtbYFpQHDN0Dnr476RJ4MO5ATuJLGlUH6N2eqFCNrYQelnE4vP6ezzsbJzLK2x3KTBcdEx0jkdpwxl0HbyNxJb6PZ8lVpwBlOhoOQQFGg4esTmQ6ZvaUAaq0GJDfso8i3P4pAmf/SyGdIvyejx7ZJvgqkFYqEe3xDo2mcFj3mrM9LhFOUFnH9fCxuqMLspdD/ETFQCXKYtdw3YqY2WdOOcMQQe4lPo1KNG1AWByzBavk2aKTqFz7Cm0ws78VxGB5jaJsXPR4qSQkHwUoJYmXJqOA6EJOFBcHNdCUZ9BeU8182XP6j/yueqzUnrnHGDRwp6IOVrnpBeh9tdLi9Bscjoqkd0ACOyg6y0yoxR6pudlcIfKJe+fFH0i/srtuwz7RAJzRxZVAO3WJT1AXggnihXC+s423+QXPITlP1lU8iiflsTS1nfNuxWhuvfwcPSezMiQ17EHySZ9s4EUWiUu0sV8FtVk5aOq8MGjx6zZ+qLcM1qoNX6lrveJFZM4gj53CdaiGtUlhzWQU8qUXaKMxc5YOgUY+1QWDa+BaajRLkfUyHEd+OKK9M0J30Uvsi2aDSXNFU2wazJ2QSyeU7+JqUqGg7HBXLuKA9Y2QeDA/BWwWr2olbpuP0xIaRpi0VDMB1cq/Uy/KypgmtWQqT0yuBQD9d0brzZQovw5e+HZzhwqqClVMjN/7TjT5BUOMFJDIzZHC1sWt7tNr4UpgEKh2nU6MvWAF/lzW5E6KtEKsasveyOwzFjp0s036nSLeSjpAs6O2qVQYTaWs87ro/crLuO2ZmYPhjp7h5aaI2HLlbvpXLxPPmvUsL/25C7T8rkAkI6iAyTSpciFr9GFzk1njcXczUjDqRzS6+6cfeqDYMoCRJmIz7l9hMCoQfX1hNmzvPtxgKB1xGAKrBAzpOsoly1F+LC1XP1rMC36a0G11oTktQwwjc0UiBHVWDOVrtUe+yaoWvqB2pGYZD810u3M4gG0iaNGRz9sEX6GzSb3c+JI+1f8I5plALfScrf7q+f5axqY8iaGjVR88gMSRW16Yo3CF4/cg7pF3G3PPEcEw/8PJ2rkzA9gT0vblQcfBef2MY0EMOHWZrajnINY2oXx1BPhHWWBn22Ti0WmYt0d6RzbcmN2DSYExrDE80Wg0IX+cQ3czh6ICAgauEshhN+ytV0DqEuWY8YZLS48YA9vL9H9cZR31ILTvINIayYJ6/KNj2lP9OI7cIeHCTzuIVM3PMxHlWmQQixzItpYjuuoaClrU6s3aSMOQloKg6gCvMJbVL4nAmB20LBi9DAepi45Pxvb5ApvZNpfx6CQFWm65p4PBvXRfPWC3bZTyPYZDEc6O2J+5WHAqDSSyJ9oXpDe59wfmZaVlBw/q0I5mNMyERrSK+L1vf0peOeMbhXZRpRR7PQHgHkc+7emRCRJKXSKzI+TG7P1uFnfv49umFU7/2OtpFKqmCWAAPUKCss4se52dQIWXOA4ekWBkIVu6nySsXCphXALyB3EWkdwR5q37XbR9LNW0LN3WQ9FjTIxwjflSCVZbv6Ht9N21mVHK3OUic30HFiG0dHUp1ln5+dCOyDdhtuE1sG1PnxfZPxKcwnSneDOoAFqhKRa6giJQq3PZyfM4/UvX9lpzGozDOrbEDQnPv8nsYhgOJKV6t8GDEx8RkjuRxugr3UhgY2tCXEn1AokdbiBd2pnyrcN9HT5EiouMeJl6pzpr9qFY5r7+1kwB3fMoO8QM6NTZQwHF", paramBoolean);
          paramBoolean = z92.b();
          if (paramBoolean) {
            try {
              x<Boolean> x = m0.W1;
              paramBoolean = ((Boolean)er2.e().<Boolean>c(x)).booleanValue();
            } catch (IllegalStateException illegalStateException) {
              paramBoolean = false;
            } 
            if (paramBoolean)
              z92.j("/TbyeKn5BCGoFXpEYkmkevBjYiDI2cU9nEifSIchqqD5aWfWy6v5sZTpifn+5AIL", "PJXTpPH5Q3JP8R736KmmofmTne3UwIW4eaifsKPbWk4=", new Class[0]); 
            z92.j("STRTQE1n2Nae56fJRHDsAlh+RkDZLMqz8liSxR9TDmqE0af2eosWM09BrF9F7xVl", "is62fUaYcSmzgiuoZcKcHzaXthoDXTG3NdfDayg76F0=", new Class[] { Context.class });
            z92.j("QIJPJ/nE6Ti3USHdmihX9pHzk77Bv0ts8Gyyxxe6Pvur9edAubTosqD4NcEuaF2M", "PSngDUwbxv65jESISlOHKO1bbo4x2Sw0BpS5ru9jcsU=", new Class[] { Context.class });
            z92.j("nmRPrXvuED4NjJ7p5khyMa3L23SeMCDOJCl7mP0tDPFYCZ7FrR8uzqgzg3C6gJRr", "BLiUXvrBFV06UPO/Uu88tFQcN0mwN2KTBq2oJDgWA3w=", new Class[] { Context.class });
            z92.j("1kM4labg61uxQq/ZliEyWeqiHYnE39xt/ep/InDLrFtCPfp50YmWmda9T2Q0zRzo", "jNtmdGFipTxb+if2EmvF9/j1W8SftlqhBkmz/QXRMc8=", new Class[] { Context.class });
            z92.j("rHKgIi3S816JqTbctm5+ppbCnYA8Mnw8DTFyVKxV8uKBimn7Ro88FU2r2rzeXUH2", "d3Dpd04HpLmOjKGWo3WNDca0uIyveqNwmpynaYW+fEw=", new Class[] { Context.class });
            Class<boolean> clazz = boolean.class;
            z92.j("j3EFBolOiHR1vPpU9K/L6Iw6mL2C4sYjvF/ZHOznb+kbO8zylKhMnMz2ES2kUAF4", "GDHJJs1hLvcJbxAGg+A3uYefjZ+vbS20/9NgtZFacds=", new Class[] { Context.class, clazz });
            z92.j("Pzb3EQzXTR173k/Bxniq4pkyjDy5KFPfSAziYLw5DVxawc5akYVhekPywPvixjd3", "udzYQv2TkS7+ukw1ODf3tzd5bioILlPFB/M5+Os2CkU=", new Class[] { Context.class });
            z92.j("SnOF6hfOOyqRjheOz37gfPBcikgoFyQupOMhQf+gI+V8pAR/vc0Bo3GGspPMqvxg", "GaeKbakS/uQ/Kw8mscu/vCnGoAGgJ8hTp7dBq0ykoWY=", new Class[] { Context.class });
            z92.j("4/jKG3OOulNSPO3h/QOBI9grdVNVDSagI1Hx7GhBDYKSdd44mJVHq75Xskro2iVZ", "kIN4ZJNX+XXUI4t4wnOjDdUp79K5Xfql0pyqhYW0UXQ=", new Class[] { MotionEvent.class, DisplayMetrics.class });
            z92.j("4lAQaQqhH0jJeL921AyfWYnx0nRDRGw/UhExoVvOyAIzA6FSKMTn+pLCnjZPPnZH", "UbQur1HfW//bZBe2OwYlLfOMsD4LJDs9rP5YmbdwsSY=", new Class[] { MotionEvent.class, DisplayMetrics.class });
            z92.j("C91vmroXCRvXadHhNn1fnUUiMLNxSpdxkuTy3y75vjwmBhTE1CZWrn2FwsomdoD9", "og/hbeWrV//prjaaA0XDsdZ9G14LUyTOfV9P2mPT3So=", new Class[0]);
            z92.j("tRBcTm/Bq+TFByDRh//gXeFbEbgCRXBuKj9OcMcnfaoxrKjfspAZMe6GEnoKp520", "XQq7RxbNU0bRUgvOxgVm2gLfJVG3os4WGwi6KoQxmns=", new Class[0]);
            z92.j("nbP5fDSCdR7wEZWUUvs/EY3UVS0lOW/IiXfPbY4s4SGuQE3bGWJDQjvI5nPqAZEe", "hv9/8RfhFT56D1pN7knLU59DtwBx8XLY+rfYt8huV7Y=", new Class[0]);
            z92.j("ME5KocVy2SapB9q1ORxiZZHvrO7+Gp7sTPqB7HB4PyxlYcftUNqyRYOZdBImw/Xw", "jwJ7VYp5Rw7Vy1FHw3D+q7stkTs2swvx61cvm72p99Y=", new Class[0]);
            z92.j("38+7Ci1811Ckz2oZVFx6KlDTfbTOOXv4V6VZ4sGWFwdwRadympBztFwtqTY6IAqe", "U2Tb4+i5Qov1YobX2EyBd8CpXvcQSoxTHefIUZmxO7Y=", new Class[0]);
            z92.j("jrKnA9m3WijdzGPNGYmR0hcX8iIFG/G0DvoEVKezorg+AQGzgtIGAVOd7Ziq8htD", "9oqpNsO66jSKfhDIuHdM09PLunDxdaPpL7Unu1WWzi8=", new Class[0]);
            z92.j("vJwPy+EAiWPpN4eKRYYJxjTqYcN5auhHiIT5Mi8T5AKd9+bh3XRhMkkIUjkAKQ9P", "yEDrMO4UToeN+QqMd82wr0vDshBcJwaqEvLd6yiDO9c=", new Class[] { Context.class, clazz });
            z92.j("ZrgqrlpoV6coFYR+EX96hjF0nNAxPts7sE36IIO8Oy3rZakvCLpyZGiwfJeJ2AC2", "ROSCeCbOL6rnP0Dz3oUxLxoVNlrS2W2HeruKuGiIrWg=", new Class[] { StackTraceElement[].class });
            z92.j("BifMZtDDn1k6aXdJ6FXhEKp8nqw0qTvNsmLURv1tlGKlAl7xb6f4vH+hciqo7SWF", "ywlTkLC11yr7mkfYO45Yj/yimKb8nEX1bqgaHDuFxK0=", new Class[] { View.class, DisplayMetrics.class, clazz });
            z92.j("fsZFw843Dvy3M+ALffkgZgeS4xxr1ptHWZBaFyjwF7Xdp6kQlHEPsBezykWp7iKJ", "YqrFXTpE0zhqgXdnuX46L91fkbR49h6qiED5VVltTkk=", new Class[] { Context.class, clazz });
            z92.j("WI87GCANEdGubbyq1s01CBcmX+lAhmMzi0YxEtEzesVgqD8QjTfQYxNLX2VeS7+D", "Axpv7G/YgsmP2XLyasiVWCsi+Z3isYbfhhh0kTw/Q3s=", new Class[] { View.class, Activity.class, clazz });
            z92.j("GnrtmFS5BfqcRzWCaoKdIJwd5TxnqJANkvWViogJ1oq97v+cqUOeljHoVb1rUVHD", "99fOdT4VL+CCqqohIB+ZSPeSaMTz3POwNYXWqb2jYJA=", new Class[] { long.class });
            try {
              x<Boolean> x = m0.b2;
              paramBoolean = ((Boolean)er2.e().<Boolean>c(x)).booleanValue();
            } catch (IllegalStateException illegalStateException) {
              paramBoolean = false;
            } 
            if (paramBoolean)
              z92.j("D9q6Pp7WuKljvrFjEFtuffrDzVuPRIOAEk5gpBh2xnatOnF8JgkDi/z48Ad3PucR", "3ok2WqgpqxXA6wdGctKZBGwIkUdo7fVz8PU1WpEtW1E=", new Class[] { Context.class }); 
            z92.j("8tnV51Kfy7dSsou/LOzGp9CvTnR1xiNPZwzeYndAYTlhe6k3/Y5KoBCdPqe624V4", "BGsAzh2OTvJ/2aDbTwq/0y0K9Pi3H2Q3PbYUMhk57cc=", new Class[] { Context.class });
            try {
              x<Boolean> x = m0.d2;
              paramBoolean = ((Boolean)er2.e().<Boolean>c(x)).booleanValue();
            } catch (IllegalStateException illegalStateException) {
              paramBoolean = false;
            } 
            if (paramBoolean)
              z92.j("fXaCZd6F6m6C8Po/9bllM8noN5nMis1HhplAQbhssZi++G/g5jXfXI48hmb4lQO+", "TkfPlkImPIeiPyhc6xqM/Fkr6nnZ6oUueRFA82qxdFQ=", new Class[] { Context.class }); 
          } 
          kr1.b = z92;
        } 
      }  
    return kr1.b;
  }
  
  private static boolean x(int paramInt) {
    try {
      if (paramInt == zy0.a) {
        x<Boolean> x = m0.H1;
        boolean bool = ((Boolean)er2.e().<Boolean>c(x)).booleanValue();
        if (bool)
          return true; 
      } 
    } catch (IllegalStateException illegalStateException) {}
    return false;
  }
  
  public final void b(View paramView) {
    x<Boolean> x = m0.S1;
    if (!((Boolean)er2.e().<Boolean>c(x)).booleanValue())
      return; 
    if (this.G == null) {
      z92 z92 = kr1.b;
      this.G = new ga2(z92.b, z92.y());
    } 
    this.G.g(paramView);
  }
  
  public final void c(int paramInt1, int paramInt2, int paramInt3) {
    if (x(this.H))
      w.execute(new sz1(this, paramInt3, paramInt1, paramInt2)); 
    super.c(paramInt1, paramInt2, paramInt3);
  }
  
  public final String d(Context paramContext) {
    if (x(this.H))
      w.execute(new rv1(this, paramContext)); 
    return super.d(paramContext);
  }
  
  public final String e(Context paramContext, View paramView, Activity paramActivity) {
    if (x(this.H))
      w.execute(new qu1(this, paramContext, paramView, paramActivity)); 
    return super.e(paramContext, paramView, paramActivity);
  }
  
  public final void f(MotionEvent paramMotionEvent) {
    if (x(this.H))
      w.execute(new sw1(this, paramMotionEvent)); 
    super.f(paramMotionEvent);
  }
  
  public final String g(Context paramContext, String paramString, View paramView, Activity paramActivity) {
    if (x(this.H))
      w.execute(new tx1(this, paramContext, paramString, paramView, paramActivity)); 
    return super.g(paramContext, paramString, paramView, paramActivity);
  }
  
  protected final long h(StackTraceElement[] paramArrayOfStackTraceElement) {
    Method method = kr1.b.e("ZrgqrlpoV6coFYR+EX96hjF0nNAxPts7sE36IIO8Oy3rZakvCLpyZGiwfJeJ2AC2", "ROSCeCbOL6rnP0Dz3oUxLxoVNlrS2W2HeruKuGiIrWg=");
    if (method != null && paramArrayOfStackTraceElement != null) {
      try {
        v92 v92 = new v92();
        this((String)method.invoke(null, new Object[] { paramArrayOfStackTraceElement }));
        return v92.b.longValue();
      } catch (IllegalAccessException illegalAccessException) {
      
      } catch (InvocationTargetException invocationTargetException) {}
      throw new zzev(invocationTargetException);
    } 
    throw new zzev();
  }
  
  protected final zzcf$zza.a i(Context paramContext, ie0 paramie0) {
    zzcf$zza.a a = zzcf$zza.z0();
    if (!TextUtils.isEmpty(this.D))
      a.y(this.D); 
    z92 z92 = u(paramContext, this.C);
    if (z92.r() != null)
      t(p(z92, paramContext, a, null)); 
    return a;
  }
  
  protected final zzcf$zza.a k(Context paramContext, View paramView, Activity paramActivity) {
    zzcf$zza.a a = zzcf$zza.z0();
    if (!TextUtils.isEmpty(this.D))
      a.y(this.D); 
    r(u(paramContext, this.C), a, paramView, paramActivity, true);
    return a;
  }
  
  protected final fa2 l(MotionEvent paramMotionEvent) {
    Method method = kr1.b.e("4lAQaQqhH0jJeL921AyfWYnx0nRDRGw/UhExoVvOyAIzA6FSKMTn+pLCnjZPPnZH", "UbQur1HfW//bZBe2OwYlLfOMsD4LJDs9rP5YmbdwsSY=");
    if (method != null && paramMotionEvent != null) {
      try {
        return new fa2((String)method.invoke(null, new Object[] { paramMotionEvent, this.u }));
      } catch (IllegalAccessException illegalAccessException) {
      
      } catch (InvocationTargetException invocationTargetException) {}
      throw new zzev(invocationTargetException);
    } 
    throw new zzev();
  }
  
  protected final zzcf$zza.a n(Context paramContext, View paramView, Activity paramActivity) {
    zzcf$zza.a a = zzcf$zza.z0().y(this.D);
    r(u(paramContext, this.C), a, paramView, paramActivity, false);
    return a;
  }
  
  protected List<Callable<Void>> p(z92 paramz92, Context paramContext, zzcf$zza.a parama, ie0 paramie0) {
    int i = paramz92.o();
    ArrayList<Callable<Void>> arrayList = new ArrayList();
    if (!paramz92.b()) {
      parama.Q(zzcf$zza.zzd.w.zzv());
      return arrayList;
    } 
    arrayList.add(new ma2(paramz92, "vJwPy+EAiWPpN4eKRYYJxjTqYcN5auhHiIT5Mi8T5AKd9+bh3XRhMkkIUjkAKQ9P", "yEDrMO4UToeN+QqMd82wr0vDshBcJwaqEvLd6yiDO9c=", parama, i, 27, paramContext, paramie0));
    arrayList.add(new qa2(paramz92, "C91vmroXCRvXadHhNn1fnUUiMLNxSpdxkuTy3y75vjwmBhTE1CZWrn2FwsomdoD9", "og/hbeWrV//prjaaA0XDsdZ9G14LUyTOfV9P2mPT3So=", parama, B, i, 25));
    arrayList.add(new za2(paramz92, "nbP5fDSCdR7wEZWUUvs/EY3UVS0lOW/IiXfPbY4s4SGuQE3bGWJDQjvI5nPqAZEe", "hv9/8RfhFT56D1pN7knLU59DtwBx8XLY+rfYt8huV7Y=", parama, i, 1));
    arrayList.add(new ab2(paramz92, "nmRPrXvuED4NjJ7p5khyMa3L23SeMCDOJCl7mP0tDPFYCZ7FrR8uzqgzg3C6gJRr", "BLiUXvrBFV06UPO/Uu88tFQcN0mwN2KTBq2oJDgWA3w=", parama, i, 31));
    arrayList.add(new hb2(paramz92, "tRBcTm/Bq+TFByDRh//gXeFbEbgCRXBuKj9OcMcnfaoxrKjfspAZMe6GEnoKp520", "XQq7RxbNU0bRUgvOxgVm2gLfJVG3os4WGwi6KoQxmns=", parama, i, 33));
    arrayList.add(new na2(paramz92, "QIJPJ/nE6Ti3USHdmihX9pHzk77Bv0ts8Gyyxxe6Pvur9edAubTosqD4NcEuaF2M", "PSngDUwbxv65jESISlOHKO1bbo4x2Sw0BpS5ru9jcsU=", parama, i, 29, paramContext));
    arrayList.add(new oa2(paramz92, "1kM4labg61uxQq/ZliEyWeqiHYnE39xt/ep/InDLrFtCPfp50YmWmda9T2Q0zRzo", "jNtmdGFipTxb+if2EmvF9/j1W8SftlqhBkmz/QXRMc8=", parama, i, 5));
    arrayList.add(new wa2(paramz92, "rHKgIi3S816JqTbctm5+ppbCnYA8Mnw8DTFyVKxV8uKBimn7Ro88FU2r2rzeXUH2", "d3Dpd04HpLmOjKGWo3WNDca0uIyveqNwmpynaYW+fEw=", parama, i, 12));
    arrayList.add(new ya2(paramz92, "j3EFBolOiHR1vPpU9K/L6Iw6mL2C4sYjvF/ZHOznb+kbO8zylKhMnMz2ES2kUAF4", "GDHJJs1hLvcJbxAGg+A3uYefjZ+vbS20/9NgtZFacds=", parama, i, 3));
    arrayList.add(new ra2(paramz92, "ME5KocVy2SapB9q1ORxiZZHvrO7+Gp7sTPqB7HB4PyxlYcftUNqyRYOZdBImw/Xw", "jwJ7VYp5Rw7Vy1FHw3D+q7stkTs2swvx61cvm72p99Y=", parama, i, 44));
    arrayList.add(new va2(paramz92, "38+7Ci1811Ckz2oZVFx6KlDTfbTOOXv4V6VZ4sGWFwdwRadympBztFwtqTY6IAqe", "U2Tb4+i5Qov1YobX2EyBd8CpXvcQSoxTHefIUZmxO7Y=", parama, i, 22));
    arrayList.add(new gb2(paramz92, "Pzb3EQzXTR173k/Bxniq4pkyjDy5KFPfSAziYLw5DVxawc5akYVhekPywPvixjd3", "udzYQv2TkS7+ukw1ODf3tzd5bioILlPFB/M5+Os2CkU=", parama, i, 48));
    arrayList.add(new ka2(paramz92, "SnOF6hfOOyqRjheOz37gfPBcikgoFyQupOMhQf+gI+V8pAR/vc0Bo3GGspPMqvxg", "GaeKbakS/uQ/Kw8mscu/vCnGoAGgJ8hTp7dBq0ykoWY=", parama, i, 49));
    arrayList.add(new fb2(paramz92, "jrKnA9m3WijdzGPNGYmR0hcX8iIFG/G0DvoEVKezorg+AQGzgtIGAVOd7Ziq8htD", "9oqpNsO66jSKfhDIuHdM09PLunDxdaPpL7Unu1WWzi8=", parama, i, 51));
    arrayList.add(new db2(paramz92, "fsZFw843Dvy3M+ALffkgZgeS4xxr1ptHWZBaFyjwF7Xdp6kQlHEPsBezykWp7iKJ", "YqrFXTpE0zhqgXdnuX46L91fkbR49h6qiED5VVltTkk=", parama, i, 61));
    x<Boolean> x = m0.d2;
    if (((Boolean)er2.e().<Boolean>c(x)).booleanValue())
      arrayList.add(new xa2(paramz92, "fXaCZd6F6m6C8Po/9bllM8noN5nMis1HhplAQbhssZi++G/g5jXfXI48hmb4lQO+", "TkfPlkImPIeiPyhc6xqM/Fkr6nnZ6oUueRFA82qxdFQ=", parama, i, 11)); 
    x = m0.b2;
    if (((Boolean)er2.e().<Boolean>c(x)).booleanValue())
      arrayList.add(new bb2(paramz92, "D9q6Pp7WuKljvrFjEFtuffrDzVuPRIOAEk5gpBh2xnatOnF8JgkDi/z48Ad3PucR", "3ok2WqgpqxXA6wdGctKZBGwIkUdo7fVz8PU1WpEtW1E=", parama, i, 73)); 
    arrayList.add(new ua2(paramz92, "8tnV51Kfy7dSsou/LOzGp9CvTnR1xiNPZwzeYndAYTlhe6k3/Y5KoBCdPqe624V4", "BGsAzh2OTvJ/2aDbTwq/0y0K9Pi3H2Q3PbYUMhk57cc=", parama, i, 76));
    return arrayList;
  }
}


/* Location:              /home/sumith/decompile/test/classes-dex2jar.jar!/com/google/android/gms/internal/ads/tt1.class
 * Java compiler version: 6 (50.0)
 * JD-Core Version:       1.1.3
 */