package com.google.android.gms.internal.ads;

import android.content.Context;

public final class u11 extends sr2 {
  private final a31 b;
  
  public u11(Context paramContext, ss paramss, ii1 paramii1, ag0 paramag0, jr2 paramjr2) {
    d31 d31 = new d31(paramag0, paramss.e());
    d31.e(paramjr2);
    this.b = new a31(new j31(paramss, paramContext, d31, paramii1), paramii1.c());
  }
  
  public final String X0() {
    // Byte code:
    //   0: aload_0
    //   1: monitorenter
    //   2: aload_0
    //   3: getfield b : Lcom/google/android/gms/internal/ads/a31;
    //   6: invokevirtual f : ()Ljava/lang/String;
    //   9: astore_1
    //   10: aload_0
    //   11: monitorexit
    //   12: aload_1
    //   13: areturn
    //   14: astore_1
    //   15: aload_0
    //   16: monitorexit
    //   17: aload_1
    //   18: athrow
    // Exception table:
    //   from	to	target	type
    //   2	10	14	finally
  }
  
  public final void Y5(zzvl paramzzvl) {
    this.b.d(paramzzvl, 1);
  }
  
  public final String a() {
    // Byte code:
    //   0: aload_0
    //   1: monitorenter
    //   2: aload_0
    //   3: getfield b : Lcom/google/android/gms/internal/ads/a31;
    //   6: invokevirtual a : ()Ljava/lang/String;
    //   9: astore_1
    //   10: aload_0
    //   11: monitorexit
    //   12: aload_1
    //   13: areturn
    //   14: astore_1
    //   15: aload_0
    //   16: monitorexit
    //   17: aload_1
    //   18: athrow
    // Exception table:
    //   from	to	target	type
    //   2	10	14	finally
  }
  
  public final boolean r() {
    // Byte code:
    //   0: aload_0
    //   1: monitorenter
    //   2: aload_0
    //   3: getfield b : Lcom/google/android/gms/internal/ads/a31;
    //   6: invokevirtual b : ()Z
    //   9: istore_1
    //   10: aload_0
    //   11: monitorexit
    //   12: iload_1
    //   13: ireturn
    //   14: astore_2
    //   15: aload_0
    //   16: monitorexit
    //   17: aload_2
    //   18: athrow
    // Exception table:
    //   from	to	target	type
    //   2	10	14	finally
  }
  
  public final void s2(zzvl paramzzvl, int paramInt) {
    // Byte code:
    //   0: aload_0
    //   1: monitorenter
    //   2: aload_0
    //   3: getfield b : Lcom/google/android/gms/internal/ads/a31;
    //   6: aload_1
    //   7: iload_2
    //   8: invokevirtual d : (Lcom/google/android/gms/internal/ads/zzvl;I)V
    //   11: aload_0
    //   12: monitorexit
    //   13: return
    //   14: astore_1
    //   15: aload_0
    //   16: monitorexit
    //   17: aload_1
    //   18: athrow
    // Exception table:
    //   from	to	target	type
    //   2	11	14	finally
  }
}


/* Location:              /home/sumith/decompile/test/classes-dex2jar.jar!/com/google/android/gms/internal/ads/u11.class
 * Java compiler version: 6 (50.0)
 * JD-Core Version:       1.1.3
 */