package com.google.android.gms.internal.ads;

final class uy0 implements et1<T> {
  uy0(vy0 paramvy0, long paramLong, String paramString, nh1 paramnh1, sh1 paramsh1) {}
  
  public final void a(Throwable paramThrowable) {
    // Byte code:
    //   0: aload_0
    //   1: getfield e : Lcom/google/android/gms/internal/ads/vy0;
    //   4: invokestatic a : (Lcom/google/android/gms/internal/ads/vy0;)Lcom/google/android/gms/common/util/e;
    //   7: invokeinterface b : ()J
    //   12: aload_0
    //   13: getfield a : J
    //   16: lsub
    //   17: lstore_2
    //   18: aload_1
    //   19: instanceof java/util/concurrent/TimeoutException
    //   22: ifeq -> 31
    //   25: iconst_2
    //   26: istore #4
    //   28: goto -> 98
    //   31: aload_1
    //   32: instanceof com/google/android/gms/internal/ads/zzcum
    //   35: ifeq -> 44
    //   38: iconst_3
    //   39: istore #4
    //   41: goto -> 98
    //   44: aload_1
    //   45: instanceof java/util/concurrent/CancellationException
    //   48: ifeq -> 57
    //   51: iconst_4
    //   52: istore #4
    //   54: goto -> 98
    //   57: aload_1
    //   58: instanceof com/google/android/gms/internal/ads/zzdnt
    //   61: ifeq -> 70
    //   64: iconst_5
    //   65: istore #4
    //   67: goto -> 98
    //   70: aload_1
    //   71: instanceof com/google/android/gms/internal/ads/zzcmb
    //   74: ifeq -> 94
    //   77: aload_1
    //   78: invokestatic d : (Ljava/lang/Throwable;)Lcom/google/android/gms/internal/ads/zzvg;
    //   81: getfield b : I
    //   84: iconst_3
    //   85: if_icmpne -> 94
    //   88: iconst_1
    //   89: istore #4
    //   91: goto -> 98
    //   94: bipush #6
    //   96: istore #4
    //   98: aload_0
    //   99: getfield e : Lcom/google/android/gms/internal/ads/vy0;
    //   102: aload_0
    //   103: getfield b : Ljava/lang/String;
    //   106: iload #4
    //   108: lload_2
    //   109: aload_0
    //   110: getfield c : Lcom/google/android/gms/internal/ads/nh1;
    //   113: getfield a0 : Ljava/lang/String;
    //   116: invokestatic c : (Lcom/google/android/gms/internal/ads/vy0;Ljava/lang/String;IJLjava/lang/String;)V
    //   119: aload_0
    //   120: getfield e : Lcom/google/android/gms/internal/ads/vy0;
    //   123: invokestatic f : (Lcom/google/android/gms/internal/ads/vy0;)Z
    //   126: ifeq -> 183
    //   129: aload_0
    //   130: getfield e : Lcom/google/android/gms/internal/ads/vy0;
    //   133: invokestatic g : (Lcom/google/android/gms/internal/ads/vy0;)Lcom/google/android/gms/internal/ads/xy0;
    //   136: astore #5
    //   138: aload_0
    //   139: getfield d : Lcom/google/android/gms/internal/ads/sh1;
    //   142: astore #6
    //   144: aload_0
    //   145: getfield c : Lcom/google/android/gms/internal/ads/nh1;
    //   148: astore #7
    //   150: aload_1
    //   151: instanceof com/google/android/gms/internal/ads/zzcrn
    //   154: ifeq -> 166
    //   157: aload_1
    //   158: checkcast com/google/android/gms/internal/ads/zzcrn
    //   161: astore #8
    //   163: goto -> 169
    //   166: aconst_null
    //   167: astore #8
    //   169: aload #5
    //   171: aload #6
    //   173: aload #7
    //   175: iload #4
    //   177: aload #8
    //   179: lload_2
    //   180: invokevirtual a : (Lcom/google/android/gms/internal/ads/sh1;Lcom/google/android/gms/internal/ads/nh1;ILcom/google/android/gms/internal/ads/zzcrn;J)V
    //   183: getstatic com/google/android/gms/internal/ads/m0.S5 : Lcom/google/android/gms/internal/ads/x;
    //   186: astore #8
    //   188: invokestatic e : ()Lcom/google/android/gms/internal/ads/i0;
    //   191: aload #8
    //   193: invokevirtual c : (Lcom/google/android/gms/internal/ads/x;)Ljava/lang/Object;
    //   196: checkcast java/lang/Boolean
    //   199: invokevirtual booleanValue : ()Z
    //   202: ifeq -> 298
    //   205: aload_1
    //   206: invokestatic d : (Ljava/lang/Throwable;)Lcom/google/android/gms/internal/ads/zzvg;
    //   209: astore #8
    //   211: aload #8
    //   213: getfield b : I
    //   216: istore #4
    //   218: iload #4
    //   220: iconst_3
    //   221: if_icmpeq -> 232
    //   224: aload #8
    //   226: astore_1
    //   227: iload #4
    //   229: ifne -> 282
    //   232: aload #8
    //   234: getfield e : Lcom/google/android/gms/internal/ads/zzvg;
    //   237: astore #5
    //   239: aload #8
    //   241: astore_1
    //   242: aload #5
    //   244: ifnull -> 282
    //   247: aload #8
    //   249: astore_1
    //   250: aload #5
    //   252: getfield d : Ljava/lang/String;
    //   255: ldc 'com.google.android.gms.ads'
    //   257: invokevirtual equals : (Ljava/lang/Object;)Z
    //   260: ifne -> 282
    //   263: new com/google/android/gms/internal/ads/zzcrn
    //   266: dup
    //   267: getstatic com/google/android/gms/internal/ads/zzdom.n : Lcom/google/android/gms/internal/ads/zzdom;
    //   270: aload #8
    //   272: getfield e : Lcom/google/android/gms/internal/ads/zzvg;
    //   275: invokespecial <init> : (Lcom/google/android/gms/internal/ads/zzdom;Lcom/google/android/gms/internal/ads/zzvg;)V
    //   278: invokestatic d : (Ljava/lang/Throwable;)Lcom/google/android/gms/internal/ads/zzvg;
    //   281: astore_1
    //   282: aload_0
    //   283: getfield e : Lcom/google/android/gms/internal/ads/vy0;
    //   286: invokestatic h : (Lcom/google/android/gms/internal/ads/vy0;)Lcom/google/android/gms/internal/ads/nv0;
    //   289: aload_0
    //   290: getfield c : Lcom/google/android/gms/internal/ads/nh1;
    //   293: lload_2
    //   294: aload_1
    //   295: invokevirtual b : (Lcom/google/android/gms/internal/ads/nh1;JLcom/google/android/gms/internal/ads/zzvg;)V
    //   298: return
  }
  
  public final void onSuccess(T paramT) {
    long l = vy0.a(this.e).b() - this.a;
    vy0.c(this.e, this.b, 0, l, this.c.a0);
    if (vy0.f(this.e))
      vy0.g(this.e).a(this.d, this.c, 0, null, l); 
    x<Boolean> x = m0.S5;
    if (((Boolean)er2.e().<Boolean>c(x)).booleanValue())
      vy0.h(this.e).b(this.c, l, null); 
  }
}


/* Location:              /home/sumith/decompile/test/classes-dex2jar.jar!/com/google/android/gms/internal/ads/uy0.class
 * Java compiler version: 6 (50.0)
 * JD-Core Version:       1.1.3
 */