package com.google.android.gms.internal.ads;

import android.content.Context;
import android.os.Bundle;
import com.google.android.gms.common.internal.t;
import com.google.android.gms.dynamic.a;

public final class v21 extends as2 {
  private final zzvs b;
  
  private final Context c;
  
  private final mf1 d;
  
  private final String e;
  
  private final z11 f;
  
  private final xf1 g;
  
  private ec0 h;
  
  private boolean i;
  
  public v21(Context paramContext, zzvs paramzzvs, String paramString, mf1 parammf1, z11 paramz11, xf1 paramxf1) {
    this.b = paramzzvs;
    this.e = paramString;
    this.c = paramContext;
    this.d = parammf1;
    this.f = paramz11;
    this.g = paramxf1;
    x<Boolean> x = m0.o0;
    this.i = ((Boolean)er2.e().<Boolean>c(x)).booleanValue();
  }
  
  private final boolean V9() {
    // Byte code:
    //   0: aload_0
    //   1: monitorenter
    //   2: aload_0
    //   3: getfield h : Lcom/google/android/gms/internal/ads/ec0;
    //   6: astore_1
    //   7: aload_1
    //   8: ifnull -> 26
    //   11: aload_1
    //   12: invokevirtual g : ()Z
    //   15: istore_2
    //   16: iload_2
    //   17: ifne -> 26
    //   20: iconst_1
    //   21: istore_2
    //   22: aload_0
    //   23: monitorexit
    //   24: iload_2
    //   25: ireturn
    //   26: iconst_0
    //   27: istore_2
    //   28: goto -> 22
    //   31: astore_1
    //   32: aload_0
    //   33: monitorexit
    //   34: goto -> 39
    //   37: aload_1
    //   38: athrow
    //   39: goto -> 37
    // Exception table:
    //   from	to	target	type
    //   2	7	31	finally
    //   11	16	31	finally
  }
  
  public final void B6(zzzi paramzzzi) {}
  
  public final String E8() {
    // Byte code:
    //   0: aload_0
    //   1: monitorenter
    //   2: aload_0
    //   3: getfield e : Ljava/lang/String;
    //   6: astore_1
    //   7: aload_0
    //   8: monitorexit
    //   9: aload_1
    //   10: areturn
    //   11: astore_1
    //   12: aload_0
    //   13: monitorexit
    //   14: aload_1
    //   15: athrow
    // Exception table:
    //   from	to	target	type
    //   2	7	11	finally
  }
  
  public final void G8() {}
  
  public final Bundle H() {
    t.e("getAdMetadata must be called on the main UI thread.");
    return new Bundle();
  }
  
  public final void J() {
    // Byte code:
    //   0: aload_0
    //   1: monitorenter
    //   2: ldc 'resume must be called on the main UI thread.'
    //   4: invokestatic e : (Ljava/lang/String;)V
    //   7: aload_0
    //   8: getfield h : Lcom/google/android/gms/internal/ads/ec0;
    //   11: astore_1
    //   12: aload_1
    //   13: ifnull -> 24
    //   16: aload_1
    //   17: invokevirtual c : ()Lcom/google/android/gms/internal/ads/h50;
    //   20: aconst_null
    //   21: invokevirtual d1 : (Landroid/content/Context;)V
    //   24: aload_0
    //   25: monitorexit
    //   26: return
    //   27: astore_1
    //   28: aload_0
    //   29: monitorexit
    //   30: aload_1
    //   31: athrow
    // Exception table:
    //   from	to	target	type
    //   2	12	27	finally
    //   16	24	27	finally
  }
  
  public final void K0(uh paramuh) {
    this.g.J(paramuh);
  }
  
  public final void K2(zzaau paramzzaau) {}
  
  public final zzvs L9() {
    return null;
  }
  
  public final void O4(ns2 paramns2) {
    this.f.g0(paramns2);
  }
  
  public final void R6(String paramString) {}
  
  public final void U(gt2 paramgt2) {
    t.e("setPaidEventListener must be called on the main UI thread.");
    this.f.k0(paramgt2);
  }
  
  public final void U4(zzvl paramzzvl, or2 paramor2) {
    this.f.y(paramor2);
    o7(paramzzvl);
  }
  
  public final void U6(jr2 paramjr2) {
    t.e("setAdListener must be called on the main UI thread.");
    this.f.l0(paramjr2);
  }
  
  public final String X0() {
    // Byte code:
    //   0: aload_0
    //   1: monitorenter
    //   2: aload_0
    //   3: getfield h : Lcom/google/android/gms/internal/ads/ec0;
    //   6: astore_1
    //   7: aload_1
    //   8: ifnull -> 33
    //   11: aload_1
    //   12: invokevirtual d : ()Lcom/google/android/gms/internal/ads/h40;
    //   15: ifnull -> 33
    //   18: aload_0
    //   19: getfield h : Lcom/google/android/gms/internal/ads/ec0;
    //   22: invokevirtual d : ()Lcom/google/android/gms/internal/ads/h40;
    //   25: invokevirtual a : ()Ljava/lang/String;
    //   28: astore_1
    //   29: aload_0
    //   30: monitorexit
    //   31: aload_1
    //   32: areturn
    //   33: aload_0
    //   34: monitorexit
    //   35: aconst_null
    //   36: areturn
    //   37: astore_1
    //   38: aload_0
    //   39: monitorexit
    //   40: aload_1
    //   41: athrow
    // Exception table:
    //   from	to	target	type
    //   2	7	37	finally
    //   11	29	37	finally
  }
  
  public final a Z2() {
    return null;
  }
  
  public final void Z3(qf paramqf, String paramString) {}
  
  public final void Z7(zzvx paramzzvx) {}
  
  public final String a() {
    // Byte code:
    //   0: aload_0
    //   1: monitorenter
    //   2: aload_0
    //   3: getfield h : Lcom/google/android/gms/internal/ads/ec0;
    //   6: astore_1
    //   7: aload_1
    //   8: ifnull -> 33
    //   11: aload_1
    //   12: invokevirtual d : ()Lcom/google/android/gms/internal/ads/h40;
    //   15: ifnull -> 33
    //   18: aload_0
    //   19: getfield h : Lcom/google/android/gms/internal/ads/ec0;
    //   22: invokevirtual d : ()Lcom/google/android/gms/internal/ads/h40;
    //   25: invokevirtual a : ()Ljava/lang/String;
    //   28: astore_1
    //   29: aload_0
    //   30: monitorexit
    //   31: aload_1
    //   32: areturn
    //   33: aload_0
    //   34: monitorexit
    //   35: aconst_null
    //   36: areturn
    //   37: astore_1
    //   38: aload_0
    //   39: monitorexit
    //   40: aload_1
    //   41: athrow
    // Exception table:
    //   from	to	target	type
    //   2	7	37	finally
    //   11	29	37	finally
  }
  
  public final void b1(es2 parames2) {
    t.e("setAdMetadataListener must be called on the main UI thread.");
  }
  
  public final fs2 b7() {
    return this.f.C();
  }
  
  public final void c2(boolean paramBoolean) {}
  
  public final void d9(i1 parami1) {
    // Byte code:
    //   0: aload_0
    //   1: monitorenter
    //   2: ldc 'setOnCustomRenderedAdLoadedListener must be called on the main UI thread.'
    //   4: invokestatic e : (Ljava/lang/String;)V
    //   7: aload_0
    //   8: getfield d : Lcom/google/android/gms/internal/ads/mf1;
    //   11: aload_1
    //   12: invokevirtual d : (Lcom/google/android/gms/internal/ads/i1;)V
    //   15: aload_0
    //   16: monitorexit
    //   17: return
    //   18: astore_1
    //   19: aload_0
    //   20: monitorexit
    //   21: aload_1
    //   22: athrow
    // Exception table:
    //   from	to	target	type
    //   2	15	18	finally
  }
  
  public final void destroy() {
    // Byte code:
    //   0: aload_0
    //   1: monitorenter
    //   2: ldc 'destroy must be called on the main UI thread.'
    //   4: invokestatic e : (Ljava/lang/String;)V
    //   7: aload_0
    //   8: getfield h : Lcom/google/android/gms/internal/ads/ec0;
    //   11: astore_1
    //   12: aload_1
    //   13: ifnull -> 24
    //   16: aload_1
    //   17: invokevirtual c : ()Lcom/google/android/gms/internal/ads/h50;
    //   20: aconst_null
    //   21: invokevirtual e1 : (Landroid/content/Context;)V
    //   24: aload_0
    //   25: monitorexit
    //   26: return
    //   27: astore_1
    //   28: aload_0
    //   29: monitorexit
    //   30: aload_1
    //   31: athrow
    // Exception table:
    //   from	to	target	type
    //   2	12	27	finally
    //   16	24	27	finally
  }
  
  public final void f6() {}
  
  public final void g8(kf paramkf) {}
  
  public final nt2 getVideoController() {
    return null;
  }
  
  public final void h3(tm2 paramtm2) {}
  
  public final void i4(ir2 paramir2) {}
  
  public final boolean m() {
    // Byte code:
    //   0: aload_0
    //   1: monitorenter
    //   2: ldc 'isLoaded must be called on the main UI thread.'
    //   4: invokestatic e : (Ljava/lang/String;)V
    //   7: aload_0
    //   8: invokespecial V9 : ()Z
    //   11: istore_1
    //   12: aload_0
    //   13: monitorexit
    //   14: iload_1
    //   15: ireturn
    //   16: astore_2
    //   17: aload_0
    //   18: monitorexit
    //   19: aload_2
    //   20: athrow
    // Exception table:
    //   from	to	target	type
    //   2	12	16	finally
  }
  
  public final void n5(zzvs paramzzvs) {}
  
  public final void o(boolean paramBoolean) {
    // Byte code:
    //   0: aload_0
    //   1: monitorenter
    //   2: ldc 'setImmersiveMode must be called on the main UI thread.'
    //   4: invokestatic e : (Ljava/lang/String;)V
    //   7: aload_0
    //   8: iload_1
    //   9: putfield i : Z
    //   12: aload_0
    //   13: monitorexit
    //   14: return
    //   15: astore_2
    //   16: aload_0
    //   17: monitorexit
    //   18: aload_2
    //   19: athrow
    // Exception table:
    //   from	to	target	type
    //   2	12	15	finally
  }
  
  public final boolean o7(zzvl paramzzvl) {
    // Byte code:
    //   0: aload_0
    //   1: monitorenter
    //   2: ldc 'loadAd must be called on the main UI thread.'
    //   4: invokestatic e : (Ljava/lang/String;)V
    //   7: invokestatic c : ()Lcom/google/android/gms/ads/internal/util/h1;
    //   10: pop
    //   11: aload_0
    //   12: getfield c : Landroid/content/Context;
    //   15: invokestatic K : (Landroid/content/Context;)Z
    //   18: ifeq -> 58
    //   21: aload_1
    //   22: getfield t : Lcom/google/android/gms/internal/ads/zzve;
    //   25: ifnonnull -> 58
    //   28: ldc 'Failed to load the ad because app ID is missing.'
    //   30: invokestatic g : (Ljava/lang/String;)V
    //   33: aload_0
    //   34: getfield f : Lcom/google/android/gms/internal/ads/z11;
    //   37: astore_1
    //   38: aload_1
    //   39: ifnull -> 54
    //   42: aload_1
    //   43: getstatic com/google/android/gms/internal/ads/zzdom.e : Lcom/google/android/gms/internal/ads/zzdom;
    //   46: aconst_null
    //   47: aconst_null
    //   48: invokestatic b : (Lcom/google/android/gms/internal/ads/zzdom;Ljava/lang/String;Lcom/google/android/gms/internal/ads/zzvg;)Lcom/google/android/gms/internal/ads/zzvg;
    //   51: invokevirtual E : (Lcom/google/android/gms/internal/ads/zzvg;)V
    //   54: aload_0
    //   55: monitorexit
    //   56: iconst_0
    //   57: ireturn
    //   58: aload_0
    //   59: invokespecial V9 : ()Z
    //   62: istore_2
    //   63: iload_2
    //   64: ifeq -> 71
    //   67: aload_0
    //   68: monitorexit
    //   69: iconst_0
    //   70: ireturn
    //   71: aload_0
    //   72: getfield c : Landroid/content/Context;
    //   75: aload_1
    //   76: getfield g : Z
    //   79: invokestatic b : (Landroid/content/Context;Z)V
    //   82: aload_0
    //   83: aconst_null
    //   84: putfield h : Lcom/google/android/gms/internal/ads/ec0;
    //   87: aload_0
    //   88: getfield d : Lcom/google/android/gms/internal/ads/mf1;
    //   91: astore_3
    //   92: aload_0
    //   93: getfield e : Ljava/lang/String;
    //   96: astore #4
    //   98: new com/google/android/gms/internal/ads/jf1
    //   101: astore #5
    //   103: aload #5
    //   105: aload_0
    //   106: getfield b : Lcom/google/android/gms/internal/ads/zzvs;
    //   109: invokespecial <init> : (Lcom/google/android/gms/internal/ads/zzvs;)V
    //   112: new com/google/android/gms/internal/ads/y21
    //   115: astore #6
    //   117: aload #6
    //   119: aload_0
    //   120: invokespecial <init> : (Lcom/google/android/gms/internal/ads/v21;)V
    //   123: aload_3
    //   124: aload_1
    //   125: aload #4
    //   127: aload #5
    //   129: aload #6
    //   131: invokevirtual a : (Lcom/google/android/gms/internal/ads/zzvl;Ljava/lang/String;Lcom/google/android/gms/internal/ads/e31;Lcom/google/android/gms/internal/ads/h31;)Z
    //   134: istore_2
    //   135: aload_0
    //   136: monitorexit
    //   137: iload_2
    //   138: ireturn
    //   139: astore_1
    //   140: aload_0
    //   141: monitorexit
    //   142: aload_1
    //   143: athrow
    // Exception table:
    //   from	to	target	type
    //   2	38	139	finally
    //   42	54	139	finally
    //   58	63	139	finally
    //   71	135	139	finally
  }
  
  public final ht2 p() {
    // Byte code:
    //   0: aload_0
    //   1: monitorenter
    //   2: getstatic com/google/android/gms/internal/ads/m0.p5 : Lcom/google/android/gms/internal/ads/x;
    //   5: astore_1
    //   6: invokestatic e : ()Lcom/google/android/gms/internal/ads/i0;
    //   9: aload_1
    //   10: invokevirtual c : (Lcom/google/android/gms/internal/ads/x;)Ljava/lang/Object;
    //   13: checkcast java/lang/Boolean
    //   16: invokevirtual booleanValue : ()Z
    //   19: istore_2
    //   20: iload_2
    //   21: ifne -> 28
    //   24: aload_0
    //   25: monitorexit
    //   26: aconst_null
    //   27: areturn
    //   28: aload_0
    //   29: getfield h : Lcom/google/android/gms/internal/ads/ec0;
    //   32: astore_1
    //   33: aload_1
    //   34: ifnonnull -> 41
    //   37: aload_0
    //   38: monitorexit
    //   39: aconst_null
    //   40: areturn
    //   41: aload_1
    //   42: invokevirtual d : ()Lcom/google/android/gms/internal/ads/h40;
    //   45: astore_1
    //   46: aload_0
    //   47: monitorexit
    //   48: aload_1
    //   49: areturn
    //   50: astore_1
    //   51: aload_0
    //   52: monitorexit
    //   53: aload_1
    //   54: athrow
    // Exception table:
    //   from	to	target	type
    //   2	20	50	finally
    //   28	33	50	finally
    //   41	46	50	finally
  }
  
  public final void p0(a parama) {
    // Byte code:
    //   0: aload_0
    //   1: monitorenter
    //   2: aload_0
    //   3: getfield h : Lcom/google/android/gms/internal/ads/ec0;
    //   6: ifnonnull -> 33
    //   9: ldc_w 'Interstitial can not be shown before loaded.'
    //   12: invokestatic i : (Ljava/lang/String;)V
    //   15: aload_0
    //   16: getfield f : Lcom/google/android/gms/internal/ads/z11;
    //   19: getstatic com/google/android/gms/internal/ads/zzdom.j : Lcom/google/android/gms/internal/ads/zzdom;
    //   22: aconst_null
    //   23: aconst_null
    //   24: invokestatic b : (Lcom/google/android/gms/internal/ads/zzdom;Ljava/lang/String;Lcom/google/android/gms/internal/ads/zzvg;)Lcom/google/android/gms/internal/ads/zzvg;
    //   27: invokevirtual r : (Lcom/google/android/gms/internal/ads/zzvg;)V
    //   30: aload_0
    //   31: monitorexit
    //   32: return
    //   33: aload_1
    //   34: invokestatic o1 : (Lcom/google/android/gms/dynamic/a;)Ljava/lang/Object;
    //   37: checkcast android/app/Activity
    //   40: astore_1
    //   41: aload_0
    //   42: getfield h : Lcom/google/android/gms/internal/ads/ec0;
    //   45: aload_0
    //   46: getfield i : Z
    //   49: aload_1
    //   50: invokevirtual h : (ZLandroid/app/Activity;)Z
    //   53: pop
    //   54: aload_0
    //   55: monitorexit
    //   56: return
    //   57: astore_1
    //   58: aload_0
    //   59: monitorexit
    //   60: aload_1
    //   61: athrow
    // Exception table:
    //   from	to	target	type
    //   2	30	57	finally
    //   33	54	57	finally
  }
  
  public final void pause() {
    // Byte code:
    //   0: aload_0
    //   1: monitorenter
    //   2: ldc_w 'pause must be called on the main UI thread.'
    //   5: invokestatic e : (Ljava/lang/String;)V
    //   8: aload_0
    //   9: getfield h : Lcom/google/android/gms/internal/ads/ec0;
    //   12: astore_1
    //   13: aload_1
    //   14: ifnull -> 25
    //   17: aload_1
    //   18: invokevirtual c : ()Lcom/google/android/gms/internal/ads/h50;
    //   21: aconst_null
    //   22: invokevirtual c1 : (Landroid/content/Context;)V
    //   25: aload_0
    //   26: monitorexit
    //   27: return
    //   28: astore_1
    //   29: aload_0
    //   30: monitorexit
    //   31: aload_1
    //   32: athrow
    // Exception table:
    //   from	to	target	type
    //   2	13	28	finally
    //   17	25	28	finally
  }
  
  public final void q3(ls2 paramls2) {}
  
  public final boolean r() {
    // Byte code:
    //   0: aload_0
    //   1: monitorenter
    //   2: aload_0
    //   3: getfield d : Lcom/google/android/gms/internal/ads/mf1;
    //   6: invokevirtual r : ()Z
    //   9: istore_1
    //   10: aload_0
    //   11: monitorexit
    //   12: iload_1
    //   13: ireturn
    //   14: astore_2
    //   15: aload_0
    //   16: monitorexit
    //   17: aload_2
    //   18: athrow
    // Exception table:
    //   from	to	target	type
    //   2	10	14	finally
  }
  
  public final void showInterstitial() {
    // Byte code:
    //   0: aload_0
    //   1: monitorenter
    //   2: ldc_w 'showInterstitial must be called on the main UI thread.'
    //   5: invokestatic e : (Ljava/lang/String;)V
    //   8: aload_0
    //   9: getfield h : Lcom/google/android/gms/internal/ads/ec0;
    //   12: astore_1
    //   13: aload_1
    //   14: ifnonnull -> 20
    //   17: aload_0
    //   18: monitorexit
    //   19: return
    //   20: aload_1
    //   21: aload_0
    //   22: getfield i : Z
    //   25: aconst_null
    //   26: invokevirtual h : (ZLandroid/app/Activity;)Z
    //   29: pop
    //   30: aload_0
    //   31: monitorexit
    //   32: return
    //   33: astore_1
    //   34: aload_0
    //   35: monitorexit
    //   36: aload_1
    //   37: athrow
    // Exception table:
    //   from	to	target	type
    //   2	13	33	finally
    //   20	30	33	finally
  }
  
  public final jr2 t3() {
    return this.f.B();
  }
  
  public final void y0(String paramString) {}
  
  public final void y6(fs2 paramfs2) {
    t.e("setAppEventListener must be called on the main UI thread.");
    this.f.D(paramfs2);
  }
}


/* Location:              /home/sumith/decompile/test/classes-dex2jar.jar!/com/google/android/gms/internal/ads/v21.class
 * Java compiler version: 6 (50.0)
 * JD-Core Version:       1.1.3
 */