package com.google.android.gms.internal.ads;

import com.google.android.gms.ads.t;
import java.util.Set;

public final class vb0 extends j90<t.a> {
  private boolean c;
  
  protected vb0(Set<gb0<t.a>> paramSet) {
    super(paramSet);
  }
  
  public final void b1() {
    X0(xb0.a);
  }
  
  public final void c1() {
    X0(yb0.a);
  }
  
  public final void d1() {
    // Byte code:
    //   0: aload_0
    //   1: monitorenter
    //   2: aload_0
    //   3: getfield c : Z
    //   6: ifne -> 21
    //   9: aload_0
    //   10: getstatic com/google/android/gms/internal/ads/zb0.a : Lcom/google/android/gms/internal/ads/l90;
    //   13: invokevirtual X0 : (Lcom/google/android/gms/internal/ads/l90;)V
    //   16: aload_0
    //   17: iconst_1
    //   18: putfield c : Z
    //   21: aload_0
    //   22: getstatic com/google/android/gms/internal/ads/cc0.a : Lcom/google/android/gms/internal/ads/l90;
    //   25: invokevirtual X0 : (Lcom/google/android/gms/internal/ads/l90;)V
    //   28: aload_0
    //   29: monitorexit
    //   30: return
    //   31: astore_1
    //   32: aload_0
    //   33: monitorexit
    //   34: aload_1
    //   35: athrow
    // Exception table:
    //   from	to	target	type
    //   2	21	31	finally
    //   21	28	31	finally
  }
  
  public final void e1() {
    // Byte code:
    //   0: aload_0
    //   1: monitorenter
    //   2: aload_0
    //   3: getstatic com/google/android/gms/internal/ads/ac0.a : Lcom/google/android/gms/internal/ads/l90;
    //   6: invokevirtual X0 : (Lcom/google/android/gms/internal/ads/l90;)V
    //   9: aload_0
    //   10: iconst_1
    //   11: putfield c : Z
    //   14: aload_0
    //   15: monitorexit
    //   16: return
    //   17: astore_1
    //   18: aload_0
    //   19: monitorexit
    //   20: aload_1
    //   21: athrow
    // Exception table:
    //   from	to	target	type
    //   2	14	17	finally
  }
}


/* Location:              /home/sumith/decompile/test/classes-dex2jar.jar!/com/google/android/gms/internal/ads/vb0.class
 * Java compiler version: 6 (50.0)
 * JD-Core Version:       1.1.3
 */