package com.google.android.gms.internal.ads;

import android.content.Context;
import android.os.Bundle;
import com.google.android.gms.common.internal.t;
import com.google.android.gms.dynamic.a;
import com.google.android.gms.dynamic.b;

public final class x11 extends as2 implements y60 {
  private final Context b;
  
  private final sd1 c;
  
  private final String d;
  
  private final z11 e;
  
  private zzvs f;
  
  private final ii1 g;
  
  private qy h;
  
  public x11(Context paramContext, zzvs paramzzvs, String paramString, sd1 paramsd1, z11 paramz11) {
    this.b = paramContext;
    this.c = paramsd1;
    this.f = paramzzvs;
    this.d = paramString;
    this.e = paramz11;
    this.g = paramsd1.h();
    paramsd1.e(this);
  }
  
  private final void V9(zzvs paramzzvs) {
    // Byte code:
    //   0: aload_0
    //   1: monitorenter
    //   2: aload_0
    //   3: getfield g : Lcom/google/android/gms/internal/ads/ii1;
    //   6: aload_1
    //   7: invokevirtual z : (Lcom/google/android/gms/internal/ads/zzvs;)Lcom/google/android/gms/internal/ads/ii1;
    //   10: pop
    //   11: aload_0
    //   12: getfield g : Lcom/google/android/gms/internal/ads/ii1;
    //   15: aload_0
    //   16: getfield f : Lcom/google/android/gms/internal/ads/zzvs;
    //   19: getfield o : Z
    //   22: invokevirtual l : (Z)Lcom/google/android/gms/internal/ads/ii1;
    //   25: pop
    //   26: aload_0
    //   27: monitorexit
    //   28: return
    //   29: astore_1
    //   30: aload_0
    //   31: monitorexit
    //   32: aload_1
    //   33: athrow
    // Exception table:
    //   from	to	target	type
    //   2	26	29	finally
  }
  
  private final boolean W9(zzvl paramzzvl) {
    // Byte code:
    //   0: aload_0
    //   1: monitorenter
    //   2: ldc 'loadAd must be called on the main UI thread.'
    //   4: invokestatic e : (Ljava/lang/String;)V
    //   7: invokestatic c : ()Lcom/google/android/gms/ads/internal/util/h1;
    //   10: pop
    //   11: aload_0
    //   12: getfield b : Landroid/content/Context;
    //   15: invokestatic K : (Landroid/content/Context;)Z
    //   18: ifeq -> 58
    //   21: aload_1
    //   22: getfield t : Lcom/google/android/gms/internal/ads/zzve;
    //   25: ifnonnull -> 58
    //   28: ldc 'Failed to load the ad because app ID is missing.'
    //   30: invokestatic g : (Ljava/lang/String;)V
    //   33: aload_0
    //   34: getfield e : Lcom/google/android/gms/internal/ads/z11;
    //   37: astore_1
    //   38: aload_1
    //   39: ifnull -> 54
    //   42: aload_1
    //   43: getstatic com/google/android/gms/internal/ads/zzdom.e : Lcom/google/android/gms/internal/ads/zzdom;
    //   46: aconst_null
    //   47: aconst_null
    //   48: invokestatic b : (Lcom/google/android/gms/internal/ads/zzdom;Ljava/lang/String;Lcom/google/android/gms/internal/ads/zzvg;)Lcom/google/android/gms/internal/ads/zzvg;
    //   51: invokevirtual E : (Lcom/google/android/gms/internal/ads/zzvg;)V
    //   54: aload_0
    //   55: monitorexit
    //   56: iconst_0
    //   57: ireturn
    //   58: aload_0
    //   59: getfield b : Landroid/content/Context;
    //   62: aload_1
    //   63: getfield g : Z
    //   66: invokestatic b : (Landroid/content/Context;Z)V
    //   69: aload_0
    //   70: getfield c : Lcom/google/android/gms/internal/ads/sd1;
    //   73: astore_2
    //   74: aload_0
    //   75: getfield d : Ljava/lang/String;
    //   78: astore_3
    //   79: new com/google/android/gms/internal/ads/w11
    //   82: astore #4
    //   84: aload #4
    //   86: aload_0
    //   87: invokespecial <init> : (Lcom/google/android/gms/internal/ads/x11;)V
    //   90: aload_2
    //   91: aload_1
    //   92: aload_3
    //   93: aconst_null
    //   94: aload #4
    //   96: invokevirtual a : (Lcom/google/android/gms/internal/ads/zzvl;Ljava/lang/String;Lcom/google/android/gms/internal/ads/e31;Lcom/google/android/gms/internal/ads/h31;)Z
    //   99: istore #5
    //   101: aload_0
    //   102: monitorexit
    //   103: iload #5
    //   105: ireturn
    //   106: astore_1
    //   107: aload_0
    //   108: monitorexit
    //   109: aload_1
    //   110: athrow
    // Exception table:
    //   from	to	target	type
    //   2	38	106	finally
    //   42	54	106	finally
    //   58	101	106	finally
  }
  
  public final void B6(zzzi paramzzzi) {}
  
  public final String E8() {
    // Byte code:
    //   0: aload_0
    //   1: monitorenter
    //   2: aload_0
    //   3: getfield d : Ljava/lang/String;
    //   6: astore_1
    //   7: aload_0
    //   8: monitorexit
    //   9: aload_1
    //   10: areturn
    //   11: astore_1
    //   12: aload_0
    //   13: monitorexit
    //   14: aload_1
    //   15: athrow
    // Exception table:
    //   from	to	target	type
    //   2	7	11	finally
  }
  
  public final void G8() {
    // Byte code:
    //   0: aload_0
    //   1: monitorenter
    //   2: ldc 'recordManualImpression must be called on the main UI thread.'
    //   4: invokestatic e : (Ljava/lang/String;)V
    //   7: aload_0
    //   8: getfield h : Lcom/google/android/gms/internal/ads/qy;
    //   11: astore_1
    //   12: aload_1
    //   13: ifnull -> 20
    //   16: aload_1
    //   17: invokevirtual m : ()V
    //   20: aload_0
    //   21: monitorexit
    //   22: return
    //   23: astore_1
    //   24: aload_0
    //   25: monitorexit
    //   26: aload_1
    //   27: athrow
    // Exception table:
    //   from	to	target	type
    //   2	12	23	finally
    //   16	20	23	finally
  }
  
  public final Bundle H() {
    t.e("getAdMetadata must be called on the main UI thread.");
    return new Bundle();
  }
  
  public final void J() {
    // Byte code:
    //   0: aload_0
    //   1: monitorenter
    //   2: ldc 'resume must be called on the main UI thread.'
    //   4: invokestatic e : (Ljava/lang/String;)V
    //   7: aload_0
    //   8: getfield h : Lcom/google/android/gms/internal/ads/qy;
    //   11: astore_1
    //   12: aload_1
    //   13: ifnull -> 24
    //   16: aload_1
    //   17: invokevirtual c : ()Lcom/google/android/gms/internal/ads/h50;
    //   20: aconst_null
    //   21: invokevirtual d1 : (Landroid/content/Context;)V
    //   24: aload_0
    //   25: monitorexit
    //   26: return
    //   27: astore_1
    //   28: aload_0
    //   29: monitorexit
    //   30: aload_1
    //   31: athrow
    // Exception table:
    //   from	to	target	type
    //   2	12	27	finally
    //   16	24	27	finally
  }
  
  public final void K0(uh paramuh) {}
  
  public final void K2(zzaau paramzzaau) {
    // Byte code:
    //   0: aload_0
    //   1: monitorenter
    //   2: ldc 'setVideoOptions must be called on the main UI thread.'
    //   4: invokestatic e : (Ljava/lang/String;)V
    //   7: aload_0
    //   8: getfield g : Lcom/google/android/gms/internal/ads/ii1;
    //   11: aload_1
    //   12: invokevirtual n : (Lcom/google/android/gms/internal/ads/zzaau;)Lcom/google/android/gms/internal/ads/ii1;
    //   15: pop
    //   16: aload_0
    //   17: monitorexit
    //   18: return
    //   19: astore_1
    //   20: aload_0
    //   21: monitorexit
    //   22: aload_1
    //   23: athrow
    // Exception table:
    //   from	to	target	type
    //   2	16	19	finally
  }
  
  public final zzvs L9() {
    // Byte code:
    //   0: aload_0
    //   1: monitorenter
    //   2: ldc 'getAdSize must be called on the main UI thread.'
    //   4: invokestatic e : (Ljava/lang/String;)V
    //   7: aload_0
    //   8: getfield h : Lcom/google/android/gms/internal/ads/qy;
    //   11: astore_1
    //   12: aload_1
    //   13: ifnull -> 35
    //   16: aload_0
    //   17: getfield b : Landroid/content/Context;
    //   20: aload_1
    //   21: invokevirtual i : ()Lcom/google/android/gms/internal/ads/qh1;
    //   24: invokestatic singletonList : (Ljava/lang/Object;)Ljava/util/List;
    //   27: invokestatic b : (Landroid/content/Context;Ljava/util/List;)Lcom/google/android/gms/internal/ads/zzvs;
    //   30: astore_1
    //   31: aload_0
    //   32: monitorexit
    //   33: aload_1
    //   34: areturn
    //   35: aload_0
    //   36: getfield g : Lcom/google/android/gms/internal/ads/ii1;
    //   39: invokevirtual G : ()Lcom/google/android/gms/internal/ads/zzvs;
    //   42: astore_1
    //   43: aload_0
    //   44: monitorexit
    //   45: aload_1
    //   46: areturn
    //   47: astore_1
    //   48: aload_0
    //   49: monitorexit
    //   50: aload_1
    //   51: athrow
    // Exception table:
    //   from	to	target	type
    //   2	12	47	finally
    //   16	31	47	finally
    //   35	43	47	finally
  }
  
  public final void O4(ns2 paramns2) {}
  
  public final void R6(String paramString) {}
  
  public final void U(gt2 paramgt2) {
    t.e("setPaidEventListener must be called on the main UI thread.");
    this.e.k0(paramgt2);
  }
  
  public final void U4(zzvl paramzzvl, or2 paramor2) {}
  
  public final void U6(jr2 paramjr2) {
    t.e("setAdListener must be called on the main UI thread.");
    this.e.l0(paramjr2);
  }
  
  public final String X0() {
    // Byte code:
    //   0: aload_0
    //   1: monitorenter
    //   2: aload_0
    //   3: getfield h : Lcom/google/android/gms/internal/ads/qy;
    //   6: astore_1
    //   7: aload_1
    //   8: ifnull -> 33
    //   11: aload_1
    //   12: invokevirtual d : ()Lcom/google/android/gms/internal/ads/h40;
    //   15: ifnull -> 33
    //   18: aload_0
    //   19: getfield h : Lcom/google/android/gms/internal/ads/qy;
    //   22: invokevirtual d : ()Lcom/google/android/gms/internal/ads/h40;
    //   25: invokevirtual a : ()Ljava/lang/String;
    //   28: astore_1
    //   29: aload_0
    //   30: monitorexit
    //   31: aload_1
    //   32: areturn
    //   33: aload_0
    //   34: monitorexit
    //   35: aconst_null
    //   36: areturn
    //   37: astore_1
    //   38: aload_0
    //   39: monitorexit
    //   40: aload_1
    //   41: athrow
    // Exception table:
    //   from	to	target	type
    //   2	7	37	finally
    //   11	29	37	finally
  }
  
  public final a Z2() {
    t.e("destroy must be called on the main UI thread.");
    return b.a2(this.c.g());
  }
  
  public final void Z3(qf paramqf, String paramString) {}
  
  public final void Z7(zzvx paramzzvx) {}
  
  public final String a() {
    // Byte code:
    //   0: aload_0
    //   1: monitorenter
    //   2: aload_0
    //   3: getfield h : Lcom/google/android/gms/internal/ads/qy;
    //   6: astore_1
    //   7: aload_1
    //   8: ifnull -> 33
    //   11: aload_1
    //   12: invokevirtual d : ()Lcom/google/android/gms/internal/ads/h40;
    //   15: ifnull -> 33
    //   18: aload_0
    //   19: getfield h : Lcom/google/android/gms/internal/ads/qy;
    //   22: invokevirtual d : ()Lcom/google/android/gms/internal/ads/h40;
    //   25: invokevirtual a : ()Ljava/lang/String;
    //   28: astore_1
    //   29: aload_0
    //   30: monitorexit
    //   31: aload_1
    //   32: areturn
    //   33: aload_0
    //   34: monitorexit
    //   35: aconst_null
    //   36: areturn
    //   37: astore_1
    //   38: aload_0
    //   39: monitorexit
    //   40: aload_1
    //   41: athrow
    // Exception table:
    //   from	to	target	type
    //   2	7	37	finally
    //   11	29	37	finally
  }
  
  public final void b1(es2 parames2) {
    t.e("setAdMetadataListener must be called on the main UI thread.");
  }
  
  public final fs2 b7() {
    return this.e.C();
  }
  
  public final void c2(boolean paramBoolean) {
    // Byte code:
    //   0: aload_0
    //   1: monitorenter
    //   2: ldc_w 'setManualImpressionsEnabled must be called from the main thread.'
    //   5: invokestatic e : (Ljava/lang/String;)V
    //   8: aload_0
    //   9: getfield g : Lcom/google/android/gms/internal/ads/ii1;
    //   12: iload_1
    //   13: invokevirtual m : (Z)Lcom/google/android/gms/internal/ads/ii1;
    //   16: pop
    //   17: aload_0
    //   18: monitorexit
    //   19: return
    //   20: astore_2
    //   21: aload_0
    //   22: monitorexit
    //   23: aload_2
    //   24: athrow
    // Exception table:
    //   from	to	target	type
    //   2	17	20	finally
  }
  
  public final void d9(i1 parami1) {
    // Byte code:
    //   0: aload_0
    //   1: monitorenter
    //   2: ldc_w 'setOnCustomRenderedAdLoadedListener must be called on the main UI thread.'
    //   5: invokestatic e : (Ljava/lang/String;)V
    //   8: aload_0
    //   9: getfield c : Lcom/google/android/gms/internal/ads/sd1;
    //   12: aload_1
    //   13: invokevirtual d : (Lcom/google/android/gms/internal/ads/i1;)V
    //   16: aload_0
    //   17: monitorexit
    //   18: return
    //   19: astore_1
    //   20: aload_0
    //   21: monitorexit
    //   22: aload_1
    //   23: athrow
    // Exception table:
    //   from	to	target	type
    //   2	16	19	finally
  }
  
  public final void destroy() {
    // Byte code:
    //   0: aload_0
    //   1: monitorenter
    //   2: ldc 'destroy must be called on the main UI thread.'
    //   4: invokestatic e : (Ljava/lang/String;)V
    //   7: aload_0
    //   8: getfield h : Lcom/google/android/gms/internal/ads/qy;
    //   11: astore_1
    //   12: aload_1
    //   13: ifnull -> 20
    //   16: aload_1
    //   17: invokevirtual a : ()V
    //   20: aload_0
    //   21: monitorexit
    //   22: return
    //   23: astore_1
    //   24: aload_0
    //   25: monitorexit
    //   26: aload_1
    //   27: athrow
    // Exception table:
    //   from	to	target	type
    //   2	12	23	finally
    //   16	20	23	finally
  }
  
  public final void f6() {}
  
  public final void g8(kf paramkf) {}
  
  public final nt2 getVideoController() {
    // Byte code:
    //   0: aload_0
    //   1: monitorenter
    //   2: ldc_w 'getVideoController must be called from the main thread.'
    //   5: invokestatic e : (Ljava/lang/String;)V
    //   8: aload_0
    //   9: getfield h : Lcom/google/android/gms/internal/ads/qy;
    //   12: astore_1
    //   13: aload_1
    //   14: ifnull -> 26
    //   17: aload_1
    //   18: invokevirtual g : ()Lcom/google/android/gms/internal/ads/nt2;
    //   21: astore_1
    //   22: aload_0
    //   23: monitorexit
    //   24: aload_1
    //   25: areturn
    //   26: aload_0
    //   27: monitorexit
    //   28: aconst_null
    //   29: areturn
    //   30: astore_1
    //   31: aload_0
    //   32: monitorexit
    //   33: aload_1
    //   34: athrow
    // Exception table:
    //   from	to	target	type
    //   2	13	30	finally
    //   17	22	30	finally
  }
  
  public final void h3(tm2 paramtm2) {}
  
  public final void i4(ir2 paramir2) {
    t.e("setAdListener must be called on the main UI thread.");
    this.c.f(paramir2);
  }
  
  public final void j6() {
    // Byte code:
    //   0: aload_0
    //   1: monitorenter
    //   2: aload_0
    //   3: getfield c : Lcom/google/android/gms/internal/ads/sd1;
    //   6: invokevirtual i : ()Z
    //   9: ifeq -> 100
    //   12: aload_0
    //   13: getfield g : Lcom/google/android/gms/internal/ads/ii1;
    //   16: invokevirtual G : ()Lcom/google/android/gms/internal/ads/zzvs;
    //   19: astore_1
    //   20: aload_0
    //   21: getfield h : Lcom/google/android/gms/internal/ads/qy;
    //   24: astore_2
    //   25: aload_1
    //   26: astore_3
    //   27: aload_2
    //   28: ifnull -> 70
    //   31: aload_1
    //   32: astore_3
    //   33: aload_2
    //   34: invokevirtual k : ()Lcom/google/android/gms/internal/ads/qh1;
    //   37: ifnull -> 70
    //   40: aload_1
    //   41: astore_3
    //   42: aload_0
    //   43: getfield g : Lcom/google/android/gms/internal/ads/ii1;
    //   46: invokevirtual f : ()Z
    //   49: ifeq -> 70
    //   52: aload_0
    //   53: getfield b : Landroid/content/Context;
    //   56: aload_0
    //   57: getfield h : Lcom/google/android/gms/internal/ads/qy;
    //   60: invokevirtual k : ()Lcom/google/android/gms/internal/ads/qh1;
    //   63: invokestatic singletonList : (Ljava/lang/Object;)Ljava/util/List;
    //   66: invokestatic b : (Landroid/content/Context;Ljava/util/List;)Lcom/google/android/gms/internal/ads/zzvs;
    //   69: astore_3
    //   70: aload_0
    //   71: aload_3
    //   72: invokespecial V9 : (Lcom/google/android/gms/internal/ads/zzvs;)V
    //   75: aload_0
    //   76: aload_0
    //   77: getfield g : Lcom/google/android/gms/internal/ads/ii1;
    //   80: invokevirtual b : ()Lcom/google/android/gms/internal/ads/zzvl;
    //   83: invokespecial W9 : (Lcom/google/android/gms/internal/ads/zzvl;)Z
    //   86: pop
    //   87: aload_0
    //   88: monitorexit
    //   89: return
    //   90: astore_3
    //   91: ldc_w 'Failed to refresh the banner ad.'
    //   94: invokestatic i : (Ljava/lang/String;)V
    //   97: aload_0
    //   98: monitorexit
    //   99: return
    //   100: aload_0
    //   101: getfield c : Lcom/google/android/gms/internal/ads/sd1;
    //   104: invokevirtual j : ()V
    //   107: aload_0
    //   108: monitorexit
    //   109: return
    //   110: astore_3
    //   111: aload_0
    //   112: monitorexit
    //   113: aload_3
    //   114: athrow
    // Exception table:
    //   from	to	target	type
    //   2	25	110	finally
    //   33	40	110	finally
    //   42	70	110	finally
    //   70	75	110	finally
    //   75	87	90	android/os/RemoteException
    //   75	87	110	finally
    //   91	97	110	finally
    //   100	107	110	finally
  }
  
  public final boolean m() {
    return false;
  }
  
  public final void n5(zzvs paramzzvs) {
    // Byte code:
    //   0: aload_0
    //   1: monitorenter
    //   2: ldc_w 'setAdSize must be called on the main UI thread.'
    //   5: invokestatic e : (Ljava/lang/String;)V
    //   8: aload_0
    //   9: getfield g : Lcom/google/android/gms/internal/ads/ii1;
    //   12: aload_1
    //   13: invokevirtual z : (Lcom/google/android/gms/internal/ads/zzvs;)Lcom/google/android/gms/internal/ads/ii1;
    //   16: pop
    //   17: aload_0
    //   18: aload_1
    //   19: putfield f : Lcom/google/android/gms/internal/ads/zzvs;
    //   22: aload_0
    //   23: getfield h : Lcom/google/android/gms/internal/ads/qy;
    //   26: astore_2
    //   27: aload_2
    //   28: ifnull -> 43
    //   31: aload_2
    //   32: aload_0
    //   33: getfield c : Lcom/google/android/gms/internal/ads/sd1;
    //   36: invokevirtual g : ()Landroid/view/ViewGroup;
    //   39: aload_1
    //   40: invokevirtual h : (Landroid/view/ViewGroup;Lcom/google/android/gms/internal/ads/zzvs;)V
    //   43: aload_0
    //   44: monitorexit
    //   45: return
    //   46: astore_1
    //   47: aload_0
    //   48: monitorexit
    //   49: aload_1
    //   50: athrow
    // Exception table:
    //   from	to	target	type
    //   2	27	46	finally
    //   31	43	46	finally
  }
  
  public final void o(boolean paramBoolean) {}
  
  public final boolean o7(zzvl paramzzvl) {
    // Byte code:
    //   0: aload_0
    //   1: monitorenter
    //   2: aload_0
    //   3: aload_0
    //   4: getfield f : Lcom/google/android/gms/internal/ads/zzvs;
    //   7: invokespecial V9 : (Lcom/google/android/gms/internal/ads/zzvs;)V
    //   10: aload_0
    //   11: aload_1
    //   12: invokespecial W9 : (Lcom/google/android/gms/internal/ads/zzvl;)Z
    //   15: istore_2
    //   16: aload_0
    //   17: monitorexit
    //   18: iload_2
    //   19: ireturn
    //   20: astore_1
    //   21: aload_0
    //   22: monitorexit
    //   23: aload_1
    //   24: athrow
    // Exception table:
    //   from	to	target	type
    //   2	16	20	finally
  }
  
  public final ht2 p() {
    // Byte code:
    //   0: aload_0
    //   1: monitorenter
    //   2: getstatic com/google/android/gms/internal/ads/m0.p5 : Lcom/google/android/gms/internal/ads/x;
    //   5: astore_1
    //   6: invokestatic e : ()Lcom/google/android/gms/internal/ads/i0;
    //   9: aload_1
    //   10: invokevirtual c : (Lcom/google/android/gms/internal/ads/x;)Ljava/lang/Object;
    //   13: checkcast java/lang/Boolean
    //   16: invokevirtual booleanValue : ()Z
    //   19: istore_2
    //   20: iload_2
    //   21: ifne -> 28
    //   24: aload_0
    //   25: monitorexit
    //   26: aconst_null
    //   27: areturn
    //   28: aload_0
    //   29: getfield h : Lcom/google/android/gms/internal/ads/qy;
    //   32: astore_1
    //   33: aload_1
    //   34: ifnonnull -> 41
    //   37: aload_0
    //   38: monitorexit
    //   39: aconst_null
    //   40: areturn
    //   41: aload_1
    //   42: invokevirtual d : ()Lcom/google/android/gms/internal/ads/h40;
    //   45: astore_1
    //   46: aload_0
    //   47: monitorexit
    //   48: aload_1
    //   49: areturn
    //   50: astore_1
    //   51: aload_0
    //   52: monitorexit
    //   53: aload_1
    //   54: athrow
    // Exception table:
    //   from	to	target	type
    //   2	20	50	finally
    //   28	33	50	finally
    //   41	46	50	finally
  }
  
  public final void p0(a parama) {}
  
  public final void pause() {
    // Byte code:
    //   0: aload_0
    //   1: monitorenter
    //   2: ldc_w 'pause must be called on the main UI thread.'
    //   5: invokestatic e : (Ljava/lang/String;)V
    //   8: aload_0
    //   9: getfield h : Lcom/google/android/gms/internal/ads/qy;
    //   12: astore_1
    //   13: aload_1
    //   14: ifnull -> 25
    //   17: aload_1
    //   18: invokevirtual c : ()Lcom/google/android/gms/internal/ads/h50;
    //   21: aconst_null
    //   22: invokevirtual c1 : (Landroid/content/Context;)V
    //   25: aload_0
    //   26: monitorexit
    //   27: return
    //   28: astore_1
    //   29: aload_0
    //   30: monitorexit
    //   31: aload_1
    //   32: athrow
    // Exception table:
    //   from	to	target	type
    //   2	13	28	finally
    //   17	25	28	finally
  }
  
  public final void q3(ls2 paramls2) {
    // Byte code:
    //   0: aload_0
    //   1: monitorenter
    //   2: ldc_w 'setCorrelationIdProvider must be called on the main UI thread'
    //   5: invokestatic e : (Ljava/lang/String;)V
    //   8: aload_0
    //   9: getfield g : Lcom/google/android/gms/internal/ads/ii1;
    //   12: aload_1
    //   13: invokevirtual p : (Lcom/google/android/gms/internal/ads/ls2;)Lcom/google/android/gms/internal/ads/ii1;
    //   16: pop
    //   17: aload_0
    //   18: monitorexit
    //   19: return
    //   20: astore_1
    //   21: aload_0
    //   22: monitorexit
    //   23: aload_1
    //   24: athrow
    // Exception table:
    //   from	to	target	type
    //   2	17	20	finally
  }
  
  public final boolean r() {
    // Byte code:
    //   0: aload_0
    //   1: monitorenter
    //   2: aload_0
    //   3: getfield c : Lcom/google/android/gms/internal/ads/sd1;
    //   6: invokevirtual r : ()Z
    //   9: istore_1
    //   10: aload_0
    //   11: monitorexit
    //   12: iload_1
    //   13: ireturn
    //   14: astore_2
    //   15: aload_0
    //   16: monitorexit
    //   17: aload_2
    //   18: athrow
    // Exception table:
    //   from	to	target	type
    //   2	10	14	finally
  }
  
  public final void showInterstitial() {}
  
  public final jr2 t3() {
    return this.e.B();
  }
  
  public final void y0(String paramString) {}
  
  public final void y6(fs2 paramfs2) {
    t.e("setAppEventListener must be called on the main UI thread.");
    this.e.D(paramfs2);
  }
}


/* Location:              /home/sumith/decompile/test/classes-dex2jar.jar!/com/google/android/gms/internal/ads/x11.class
 * Java compiler version: 6 (50.0)
 * JD-Core Version:       1.1.3
 */