package com.google.android.gms.internal.ads;

import com.google.android.gms.ads.doubleclick.a;
import java.util.Set;

public final class x80 extends j90<a> implements b6 {
  public x80(Set<gb0<a>> paramSet) {
    super(paramSet);
  }
  
  public final void n(String paramString1, String paramString2) {
    // Byte code:
    //   0: aload_0
    //   1: monitorenter
    //   2: new com/google/android/gms/internal/ads/w80
    //   5: astore_3
    //   6: aload_3
    //   7: aload_1
    //   8: aload_2
    //   9: invokespecial <init> : (Ljava/lang/String;Ljava/lang/String;)V
    //   12: aload_0
    //   13: aload_3
    //   14: invokevirtual X0 : (Lcom/google/android/gms/internal/ads/l90;)V
    //   17: aload_0
    //   18: monitorexit
    //   19: return
    //   20: astore_1
    //   21: aload_0
    //   22: monitorexit
    //   23: aload_1
    //   24: athrow
    // Exception table:
    //   from	to	target	type
    //   2	17	20	finally
  }
}


/* Location:              /home/sumith/decompile/test/classes-dex2jar.jar!/com/google/android/gms/internal/ads/x80.class
 * Java compiler version: 6 (50.0)
 * JD-Core Version:       1.1.3
 */