package com.google.android.gms.internal.ads;

import java.util.concurrent.Executor;

final class yg1 implements et1<vk0> {
  yg1(tg1 paramtg1, h31 paramh31, zg1 paramzg1) {}
  
  public final void a(Throwable paramThrowable) {
    // Byte code:
    //   0: aload_0
    //   1: getfield c : Lcom/google/android/gms/internal/ads/tg1;
    //   4: invokestatic f : (Lcom/google/android/gms/internal/ads/tg1;)Lcom/google/android/gms/internal/ads/cf1;
    //   7: invokeinterface a : ()Ljava/lang/Object;
    //   12: checkcast com/google/android/gms/internal/ads/cl0
    //   15: astore_2
    //   16: aload_2
    //   17: ifnonnull -> 29
    //   20: aload_1
    //   21: aconst_null
    //   22: invokestatic c : (Ljava/lang/Throwable;Lcom/google/android/gms/internal/ads/nv0;)Lcom/google/android/gms/internal/ads/zzvg;
    //   25: astore_3
    //   26: goto -> 38
    //   29: aload_2
    //   30: invokevirtual a : ()Lcom/google/android/gms/internal/ads/r10;
    //   33: aload_1
    //   34: invokevirtual l : (Ljava/lang/Throwable;)Lcom/google/android/gms/internal/ads/zzvg;
    //   37: astore_3
    //   38: aload_0
    //   39: getfield c : Lcom/google/android/gms/internal/ads/tg1;
    //   42: astore #4
    //   44: aload #4
    //   46: monitorenter
    //   47: aload_2
    //   48: ifnull -> 89
    //   51: aload_2
    //   52: invokevirtual b : ()Lcom/google/android/gms/internal/ads/p40;
    //   55: aload_3
    //   56: invokevirtual E : (Lcom/google/android/gms/internal/ads/zzvg;)V
    //   59: aload_0
    //   60: getfield c : Lcom/google/android/gms/internal/ads/tg1;
    //   63: invokestatic e : (Lcom/google/android/gms/internal/ads/tg1;)Ljava/util/concurrent/Executor;
    //   66: astore #5
    //   68: new com/google/android/gms/internal/ads/ah1
    //   71: astore_2
    //   72: aload_2
    //   73: aload_0
    //   74: aload_3
    //   75: invokespecial <init> : (Lcom/google/android/gms/internal/ads/yg1;Lcom/google/android/gms/internal/ads/zzvg;)V
    //   78: aload #5
    //   80: aload_2
    //   81: invokeinterface execute : (Ljava/lang/Runnable;)V
    //   86: goto -> 125
    //   89: aload_0
    //   90: getfield c : Lcom/google/android/gms/internal/ads/tg1;
    //   93: invokestatic c : (Lcom/google/android/gms/internal/ads/tg1;)Lcom/google/android/gms/internal/ads/xf1;
    //   96: aload_3
    //   97: invokevirtual E : (Lcom/google/android/gms/internal/ads/zzvg;)V
    //   100: aload_0
    //   101: getfield c : Lcom/google/android/gms/internal/ads/tg1;
    //   104: aload_0
    //   105: getfield b : Lcom/google/android/gms/internal/ads/zg1;
    //   108: invokestatic b : (Lcom/google/android/gms/internal/ads/tg1;Lcom/google/android/gms/internal/ads/bf1;)Lcom/google/android/gms/internal/ads/bl0;
    //   111: invokeinterface w : ()Lcom/google/android/gms/internal/ads/cl0;
    //   116: invokevirtual a : ()Lcom/google/android/gms/internal/ads/r10;
    //   119: invokevirtual h : ()Lcom/google/android/gms/internal/ads/y80;
    //   122: invokevirtual W0 : ()V
    //   125: aload_3
    //   126: getfield b : I
    //   129: aload_1
    //   130: ldc 'RewardedAdLoader.onFailure'
    //   132: invokestatic a : (ILjava/lang/Throwable;Ljava/lang/String;)V
    //   135: aload_0
    //   136: getfield a : Lcom/google/android/gms/internal/ads/h31;
    //   139: invokeinterface a : ()V
    //   144: aload #4
    //   146: monitorexit
    //   147: return
    //   148: astore_1
    //   149: aload #4
    //   151: monitorexit
    //   152: aload_1
    //   153: athrow
    // Exception table:
    //   from	to	target	type
    //   51	86	148	finally
    //   89	125	148	finally
    //   125	147	148	finally
    //   149	152	148	finally
  }
}


/* Location:              /home/sumith/decompile/test/classes-dex2jar.jar!/com/google/android/gms/internal/ads/yg1.class
 * Java compiler version: 6 (50.0)
 * JD-Core Version:       1.1.3
 */