package com.google.android.gms.internal.ads;

import android.content.Context;

final class yv0 implements od0 {
  private final zzazn a;
  
  private final ot1<dy> b;
  
  private final nh1 c;
  
  private final tq d;
  
  private final gi1 e;
  
  yv0(zzazn paramzzazn, ot1<dy> paramot1, nh1 paramnh1, tq paramtq, gi1 paramgi1) {
    this.a = paramzzazn;
    this.b = paramot1;
    this.c = paramnh1;
    this.d = paramtq;
    this.e = paramgi1;
  }
  
  public final void a(boolean paramBoolean, Context paramContext) {
    // Byte code:
    //   0: aload_0
    //   1: getfield b : Lcom/google/android/gms/internal/ads/ot1;
    //   4: invokestatic m : (Ljava/util/concurrent/Future;)Ljava/lang/Object;
    //   7: checkcast com/google/android/gms/internal/ads/dy
    //   10: astore_3
    //   11: aload_0
    //   12: getfield d : Lcom/google/android/gms/internal/ads/tq;
    //   15: iconst_1
    //   16: invokeinterface h0 : (Z)V
    //   21: new com/google/android/gms/ads/internal/zzk
    //   24: dup
    //   25: iconst_1
    //   26: iconst_1
    //   27: iconst_0
    //   28: fconst_0
    //   29: iconst_m1
    //   30: iload_1
    //   31: aload_0
    //   32: getfield c : Lcom/google/android/gms/internal/ads/nh1;
    //   35: getfield J : Z
    //   38: iconst_0
    //   39: invokespecial <init> : (ZZZFIZZZ)V
    //   42: astore #4
    //   44: invokestatic b : ()Lcom/google/android/gms/ads/internal/overlay/n;
    //   47: pop
    //   48: aload_3
    //   49: invokevirtual j : ()Lcom/google/android/gms/internal/ads/dd0;
    //   52: astore #5
    //   54: aload_0
    //   55: getfield d : Lcom/google/android/gms/internal/ads/tq;
    //   58: astore_3
    //   59: aload_0
    //   60: getfield c : Lcom/google/android/gms/internal/ads/nh1;
    //   63: getfield L : I
    //   66: istore #6
    //   68: iload #6
    //   70: iconst_m1
    //   71: if_icmpeq -> 77
    //   74: goto -> 141
    //   77: aload_0
    //   78: getfield e : Lcom/google/android/gms/internal/ads/gi1;
    //   81: getfield j : Lcom/google/android/gms/internal/ads/zzvx;
    //   84: astore #7
    //   86: aload #7
    //   88: ifnull -> 124
    //   91: aload #7
    //   93: getfield b : I
    //   96: istore #6
    //   98: iload #6
    //   100: iconst_1
    //   101: if_icmpne -> 111
    //   104: bipush #7
    //   106: istore #6
    //   108: goto -> 141
    //   111: iload #6
    //   113: iconst_2
    //   114: if_icmpne -> 124
    //   117: bipush #6
    //   119: istore #6
    //   121: goto -> 141
    //   124: ldc 'Error setting app open orientation; no targeting orientation available.'
    //   126: invokestatic e : (Ljava/lang/String;)V
    //   129: aload_0
    //   130: getfield c : Lcom/google/android/gms/internal/ads/nh1;
    //   133: getfield L : I
    //   136: istore #6
    //   138: goto -> 74
    //   141: aload_0
    //   142: getfield a : Lcom/google/android/gms/internal/ads/zzazn;
    //   145: astore #7
    //   147: aload_0
    //   148: getfield c : Lcom/google/android/gms/internal/ads/nh1;
    //   151: astore #8
    //   153: aload #8
    //   155: getfield A : Ljava/lang/String;
    //   158: astore #9
    //   160: aload #8
    //   162: getfield r : Lcom/google/android/gms/internal/ads/uh1;
    //   165: astore #8
    //   167: aload_2
    //   168: new com/google/android/gms/ads/internal/overlay/AdOverlayInfoParcel
    //   171: dup
    //   172: aconst_null
    //   173: aload #5
    //   175: aconst_null
    //   176: aload_3
    //   177: iload #6
    //   179: aload #7
    //   181: aload #9
    //   183: aload #4
    //   185: aload #8
    //   187: getfield b : Ljava/lang/String;
    //   190: aload #8
    //   192: getfield a : Ljava/lang/String;
    //   195: invokespecial <init> : (Lcom/google/android/gms/internal/ads/bq2;Lcom/google/android/gms/ads/internal/overlay/p;Lcom/google/android/gms/ads/internal/overlay/u;Lcom/google/android/gms/internal/ads/tq;ILcom/google/android/gms/internal/ads/zzazn;Ljava/lang/String;Lcom/google/android/gms/ads/internal/zzk;Ljava/lang/String;Ljava/lang/String;)V
    //   198: iconst_1
    //   199: invokestatic a : (Landroid/content/Context;Lcom/google/android/gms/ads/internal/overlay/AdOverlayInfoParcel;Z)V
    //   202: return
  }
}


/* Location:              /home/sumith/decompile/test/classes-dex2jar.jar!/com/google/android/gms/internal/ads/yv0.class
 * Java compiler version: 6 (50.0)
 * JD-Core Version:       1.1.3
 */