package com.google.android.gms.internal.ads;

final class zt1<V> implements Runnable {
  private xt1<V> b;
  
  zt1(xt1<V> paramxt1) {
    this.b = paramxt1;
  }
  
  public final void run() {
    // Byte code:
    //   0: aload_0
    //   1: getfield b : Lcom/google/android/gms/internal/ads/xt1;
    //   4: astore_1
    //   5: aload_1
    //   6: ifnonnull -> 10
    //   9: return
    //   10: aload_1
    //   11: invokestatic I : (Lcom/google/android/gms/internal/ads/xt1;)Lcom/google/android/gms/internal/ads/ot1;
    //   14: astore_2
    //   15: aload_2
    //   16: ifnonnull -> 20
    //   19: return
    //   20: aload_0
    //   21: aconst_null
    //   22: putfield b : Lcom/google/android/gms/internal/ads/xt1;
    //   25: aload_2
    //   26: invokeinterface isDone : ()Z
    //   31: ifeq -> 41
    //   34: aload_1
    //   35: aload_2
    //   36: invokevirtual k : (Lcom/google/android/gms/internal/ads/ot1;)Z
    //   39: pop
    //   40: return
    //   41: aload_1
    //   42: invokestatic L : (Lcom/google/android/gms/internal/ads/xt1;)Ljava/util/concurrent/ScheduledFuture;
    //   45: astore_3
    //   46: aload_1
    //   47: aconst_null
    //   48: invokestatic J : (Lcom/google/android/gms/internal/ads/xt1;Ljava/util/concurrent/ScheduledFuture;)Ljava/util/concurrent/ScheduledFuture;
    //   51: pop
    //   52: ldc 'Timed out'
    //   54: astore #4
    //   56: aload #4
    //   58: astore #5
    //   60: aload_3
    //   61: ifnull -> 188
    //   64: aload #4
    //   66: astore #6
    //   68: aload_3
    //   69: getstatic java/util/concurrent/TimeUnit.MILLISECONDS : Ljava/util/concurrent/TimeUnit;
    //   72: invokeinterface getDelay : (Ljava/util/concurrent/TimeUnit;)J
    //   77: invokestatic abs : (J)J
    //   80: lstore #7
    //   82: aload #4
    //   84: astore #5
    //   86: lload #7
    //   88: ldc2_w 10
    //   91: lcmp
    //   92: ifle -> 188
    //   95: aload #4
    //   97: astore #6
    //   99: ldc 'Timed out'
    //   101: invokevirtual length : ()I
    //   104: istore #9
    //   106: aload #4
    //   108: astore #6
    //   110: new java/lang/StringBuilder
    //   113: astore #5
    //   115: aload #4
    //   117: astore #6
    //   119: aload #5
    //   121: iload #9
    //   123: bipush #66
    //   125: iadd
    //   126: invokespecial <init> : (I)V
    //   129: aload #4
    //   131: astore #6
    //   133: aload #5
    //   135: ldc 'Timed out'
    //   137: invokevirtual append : (Ljava/lang/String;)Ljava/lang/StringBuilder;
    //   140: pop
    //   141: aload #4
    //   143: astore #6
    //   145: aload #5
    //   147: ldc ' (timeout delayed by '
    //   149: invokevirtual append : (Ljava/lang/String;)Ljava/lang/StringBuilder;
    //   152: pop
    //   153: aload #4
    //   155: astore #6
    //   157: aload #5
    //   159: lload #7
    //   161: invokevirtual append : (J)Ljava/lang/StringBuilder;
    //   164: pop
    //   165: aload #4
    //   167: astore #6
    //   169: aload #5
    //   171: ldc ' ms after scheduled time)'
    //   173: invokevirtual append : (Ljava/lang/String;)Ljava/lang/StringBuilder;
    //   176: pop
    //   177: aload #4
    //   179: astore #6
    //   181: aload #5
    //   183: invokevirtual toString : ()Ljava/lang/String;
    //   186: astore #5
    //   188: aload #5
    //   190: astore #6
    //   192: aload #5
    //   194: invokestatic valueOf : (Ljava/lang/Object;)Ljava/lang/String;
    //   197: astore #4
    //   199: aload #5
    //   201: astore #6
    //   203: aload_2
    //   204: invokestatic valueOf : (Ljava/lang/Object;)Ljava/lang/String;
    //   207: astore #10
    //   209: aload #5
    //   211: astore #6
    //   213: aload #4
    //   215: invokevirtual length : ()I
    //   218: istore #11
    //   220: aload #5
    //   222: astore #6
    //   224: aload #10
    //   226: invokevirtual length : ()I
    //   229: istore #9
    //   231: aload #5
    //   233: astore #6
    //   235: new java/lang/StringBuilder
    //   238: astore_3
    //   239: aload #5
    //   241: astore #6
    //   243: aload_3
    //   244: iload #11
    //   246: iconst_2
    //   247: iadd
    //   248: iload #9
    //   250: iadd
    //   251: invokespecial <init> : (I)V
    //   254: aload #5
    //   256: astore #6
    //   258: aload_3
    //   259: aload #4
    //   261: invokevirtual append : (Ljava/lang/String;)Ljava/lang/StringBuilder;
    //   264: pop
    //   265: aload #5
    //   267: astore #6
    //   269: aload_3
    //   270: ldc ': '
    //   272: invokevirtual append : (Ljava/lang/String;)Ljava/lang/StringBuilder;
    //   275: pop
    //   276: aload #5
    //   278: astore #6
    //   280: aload_3
    //   281: aload #10
    //   283: invokevirtual append : (Ljava/lang/String;)Ljava/lang/StringBuilder;
    //   286: pop
    //   287: aload #5
    //   289: astore #6
    //   291: aload_3
    //   292: invokevirtual toString : ()Ljava/lang/String;
    //   295: astore #5
    //   297: new com/google/android/gms/internal/ads/zzeai
    //   300: astore #6
    //   302: aload #6
    //   304: aload #5
    //   306: aconst_null
    //   307: invokespecial <init> : (Ljava/lang/String;Lcom/google/android/gms/internal/ads/au1;)V
    //   310: aload_1
    //   311: aload #6
    //   313: invokevirtual j : (Ljava/lang/Throwable;)Z
    //   316: pop
    //   317: aload_2
    //   318: iconst_1
    //   319: invokeinterface cancel : (Z)Z
    //   324: pop
    //   325: return
    //   326: astore #4
    //   328: new com/google/android/gms/internal/ads/zzeai
    //   331: astore #5
    //   333: aload #5
    //   335: aload #6
    //   337: aconst_null
    //   338: invokespecial <init> : (Ljava/lang/String;Lcom/google/android/gms/internal/ads/au1;)V
    //   341: aload_1
    //   342: aload #5
    //   344: invokevirtual j : (Ljava/lang/Throwable;)Z
    //   347: pop
    //   348: aload #4
    //   350: athrow
    //   351: astore #5
    //   353: aload_2
    //   354: iconst_1
    //   355: invokeinterface cancel : (Z)Z
    //   360: pop
    //   361: aload #5
    //   363: athrow
    // Exception table:
    //   from	to	target	type
    //   41	52	351	finally
    //   68	82	326	finally
    //   99	106	326	finally
    //   110	115	326	finally
    //   119	129	326	finally
    //   133	141	326	finally
    //   145	153	326	finally
    //   157	165	326	finally
    //   169	177	326	finally
    //   181	188	326	finally
    //   192	199	326	finally
    //   203	209	326	finally
    //   213	220	326	finally
    //   224	231	326	finally
    //   235	239	326	finally
    //   243	254	326	finally
    //   258	265	326	finally
    //   269	276	326	finally
    //   280	287	326	finally
    //   291	297	326	finally
    //   297	317	351	finally
    //   328	351	351	finally
  }
}


/* Location:              /home/sumith/decompile/test/classes-dex2jar.jar!/com/google/android/gms/internal/ads/zt1.class
 * Java compiler version: 6 (50.0)
 * JD-Core Version:       1.1.3
 */