package androidx.constraintlayout.solver.widgets;

import androidx.constraintlayout.solver.d;
import java.util.ArrayList;

public class b {
  static void a(d paramd, d paramd1, int paramInt1, int paramInt2, c paramc) {
    // Byte code:
    //   0: aload #4
    //   2: getfield a : Landroidx/constraintlayout/solver/widgets/ConstraintWidget;
    //   5: astore #5
    //   7: aload #4
    //   9: getfield c : Landroidx/constraintlayout/solver/widgets/ConstraintWidget;
    //   12: astore #6
    //   14: aload #4
    //   16: getfield b : Landroidx/constraintlayout/solver/widgets/ConstraintWidget;
    //   19: astore #7
    //   21: aload #4
    //   23: getfield d : Landroidx/constraintlayout/solver/widgets/ConstraintWidget;
    //   26: astore #8
    //   28: aload #4
    //   30: getfield e : Landroidx/constraintlayout/solver/widgets/ConstraintWidget;
    //   33: astore #9
    //   35: aload #4
    //   37: getfield k : F
    //   40: fstore #10
    //   42: aload_0
    //   43: getfield V : [Landroidx/constraintlayout/solver/widgets/ConstraintWidget$DimensionBehaviour;
    //   46: iload_2
    //   47: aaload
    //   48: getstatic androidx/constraintlayout/solver/widgets/ConstraintWidget$DimensionBehaviour.c : Landroidx/constraintlayout/solver/widgets/ConstraintWidget$DimensionBehaviour;
    //   51: if_acmpne -> 60
    //   54: iconst_1
    //   55: istore #11
    //   57: goto -> 63
    //   60: iconst_0
    //   61: istore #11
    //   63: iload_2
    //   64: ifne -> 120
    //   67: aload #9
    //   69: getfield C0 : I
    //   72: istore #12
    //   74: iload #12
    //   76: ifne -> 85
    //   79: iconst_1
    //   80: istore #13
    //   82: goto -> 88
    //   85: iconst_0
    //   86: istore #13
    //   88: iload #12
    //   90: iconst_1
    //   91: if_icmpne -> 100
    //   94: iconst_1
    //   95: istore #14
    //   97: goto -> 103
    //   100: iconst_0
    //   101: istore #14
    //   103: iload #13
    //   105: istore #15
    //   107: iload #14
    //   109: istore #16
    //   111: iload #12
    //   113: iconst_2
    //   114: if_icmpne -> 180
    //   117: goto -> 170
    //   120: aload #9
    //   122: getfield D0 : I
    //   125: istore #12
    //   127: iload #12
    //   129: ifne -> 138
    //   132: iconst_1
    //   133: istore #13
    //   135: goto -> 141
    //   138: iconst_0
    //   139: istore #13
    //   141: iload #12
    //   143: iconst_1
    //   144: if_icmpne -> 153
    //   147: iconst_1
    //   148: istore #14
    //   150: goto -> 156
    //   153: iconst_0
    //   154: istore #14
    //   156: iload #13
    //   158: istore #15
    //   160: iload #14
    //   162: istore #16
    //   164: iload #12
    //   166: iconst_2
    //   167: if_icmpne -> 180
    //   170: iconst_1
    //   171: istore #12
    //   173: iload #13
    //   175: istore #15
    //   177: goto -> 187
    //   180: iconst_0
    //   181: istore #12
    //   183: iload #16
    //   185: istore #14
    //   187: aload #5
    //   189: astore #17
    //   191: iconst_0
    //   192: istore #13
    //   194: iload #14
    //   196: istore #16
    //   198: aconst_null
    //   199: astore #18
    //   201: aconst_null
    //   202: astore #19
    //   204: iload #13
    //   206: ifne -> 621
    //   209: aload #17
    //   211: getfield S : [Landroidx/constraintlayout/solver/widgets/ConstraintAnchor;
    //   214: iload_3
    //   215: aaload
    //   216: astore #20
    //   218: iload #12
    //   220: ifeq -> 229
    //   223: iconst_1
    //   224: istore #14
    //   226: goto -> 232
    //   229: iconst_4
    //   230: istore #14
    //   232: aload #20
    //   234: invokevirtual f : ()I
    //   237: istore #21
    //   239: aload #17
    //   241: getfield V : [Landroidx/constraintlayout/solver/widgets/ConstraintWidget$DimensionBehaviour;
    //   244: iload_2
    //   245: aaload
    //   246: astore #18
    //   248: getstatic androidx/constraintlayout/solver/widgets/ConstraintWidget$DimensionBehaviour.d : Landroidx/constraintlayout/solver/widgets/ConstraintWidget$DimensionBehaviour;
    //   251: astore #22
    //   253: aload #18
    //   255: aload #22
    //   257: if_acmpne -> 276
    //   260: aload #17
    //   262: getfield s : [I
    //   265: iload_2
    //   266: iaload
    //   267: ifne -> 276
    //   270: iconst_1
    //   271: istore #23
    //   273: goto -> 279
    //   276: iconst_0
    //   277: istore #23
    //   279: aload #20
    //   281: getfield f : Landroidx/constraintlayout/solver/widgets/ConstraintAnchor;
    //   284: astore #18
    //   286: iload #21
    //   288: istore #24
    //   290: aload #18
    //   292: ifnull -> 316
    //   295: iload #21
    //   297: istore #24
    //   299: aload #17
    //   301: aload #5
    //   303: if_acmpeq -> 316
    //   306: iload #21
    //   308: aload #18
    //   310: invokevirtual f : ()I
    //   313: iadd
    //   314: istore #24
    //   316: iload #12
    //   318: ifeq -> 342
    //   321: aload #17
    //   323: aload #5
    //   325: if_acmpeq -> 342
    //   328: aload #17
    //   330: aload #7
    //   332: if_acmpeq -> 342
    //   335: bipush #8
    //   337: istore #14
    //   339: goto -> 342
    //   342: aload #20
    //   344: getfield f : Landroidx/constraintlayout/solver/widgets/ConstraintAnchor;
    //   347: astore #18
    //   349: aload #18
    //   351: ifnull -> 441
    //   354: aload #17
    //   356: aload #7
    //   358: if_acmpne -> 382
    //   361: aload_1
    //   362: aload #20
    //   364: getfield i : Landroidx/constraintlayout/solver/SolverVariable;
    //   367: aload #18
    //   369: getfield i : Landroidx/constraintlayout/solver/SolverVariable;
    //   372: iload #24
    //   374: bipush #6
    //   376: invokevirtual h : (Landroidx/constraintlayout/solver/SolverVariable;Landroidx/constraintlayout/solver/SolverVariable;II)V
    //   379: goto -> 400
    //   382: aload_1
    //   383: aload #20
    //   385: getfield i : Landroidx/constraintlayout/solver/SolverVariable;
    //   388: aload #18
    //   390: getfield i : Landroidx/constraintlayout/solver/SolverVariable;
    //   393: iload #24
    //   395: bipush #8
    //   397: invokevirtual h : (Landroidx/constraintlayout/solver/SolverVariable;Landroidx/constraintlayout/solver/SolverVariable;II)V
    //   400: iload #23
    //   402: ifeq -> 416
    //   405: iload #12
    //   407: ifne -> 416
    //   410: iconst_5
    //   411: istore #14
    //   413: goto -> 416
    //   416: aload_1
    //   417: aload #20
    //   419: getfield i : Landroidx/constraintlayout/solver/SolverVariable;
    //   422: aload #20
    //   424: getfield f : Landroidx/constraintlayout/solver/widgets/ConstraintAnchor;
    //   427: getfield i : Landroidx/constraintlayout/solver/SolverVariable;
    //   430: iload #24
    //   432: iload #14
    //   434: invokevirtual e : (Landroidx/constraintlayout/solver/SolverVariable;Landroidx/constraintlayout/solver/SolverVariable;II)Landroidx/constraintlayout/solver/b;
    //   437: pop
    //   438: goto -> 441
    //   441: iload #11
    //   443: ifeq -> 526
    //   446: aload #17
    //   448: invokevirtual T : ()I
    //   451: bipush #8
    //   453: if_icmpeq -> 500
    //   456: aload #17
    //   458: getfield V : [Landroidx/constraintlayout/solver/widgets/ConstraintWidget$DimensionBehaviour;
    //   461: iload_2
    //   462: aaload
    //   463: aload #22
    //   465: if_acmpne -> 500
    //   468: aload #17
    //   470: getfield S : [Landroidx/constraintlayout/solver/widgets/ConstraintAnchor;
    //   473: astore #22
    //   475: aload_1
    //   476: aload #22
    //   478: iload_3
    //   479: iconst_1
    //   480: iadd
    //   481: aaload
    //   482: getfield i : Landroidx/constraintlayout/solver/SolverVariable;
    //   485: aload #22
    //   487: iload_3
    //   488: aaload
    //   489: getfield i : Landroidx/constraintlayout/solver/SolverVariable;
    //   492: iconst_0
    //   493: iconst_5
    //   494: invokevirtual h : (Landroidx/constraintlayout/solver/SolverVariable;Landroidx/constraintlayout/solver/SolverVariable;II)V
    //   497: goto -> 500
    //   500: aload_1
    //   501: aload #17
    //   503: getfield S : [Landroidx/constraintlayout/solver/widgets/ConstraintAnchor;
    //   506: iload_3
    //   507: aaload
    //   508: getfield i : Landroidx/constraintlayout/solver/SolverVariable;
    //   511: aload_0
    //   512: getfield S : [Landroidx/constraintlayout/solver/widgets/ConstraintAnchor;
    //   515: iload_3
    //   516: aaload
    //   517: getfield i : Landroidx/constraintlayout/solver/SolverVariable;
    //   520: iconst_0
    //   521: bipush #8
    //   523: invokevirtual h : (Landroidx/constraintlayout/solver/SolverVariable;Landroidx/constraintlayout/solver/SolverVariable;II)V
    //   526: aload #17
    //   528: getfield S : [Landroidx/constraintlayout/solver/widgets/ConstraintAnchor;
    //   531: iload_3
    //   532: iconst_1
    //   533: iadd
    //   534: aaload
    //   535: getfield f : Landroidx/constraintlayout/solver/widgets/ConstraintAnchor;
    //   538: astore #20
    //   540: aload #19
    //   542: astore #22
    //   544: aload #20
    //   546: ifnull -> 603
    //   549: aload #20
    //   551: getfield d : Landroidx/constraintlayout/solver/widgets/ConstraintWidget;
    //   554: astore #20
    //   556: aload #20
    //   558: getfield S : [Landroidx/constraintlayout/solver/widgets/ConstraintAnchor;
    //   561: astore #18
    //   563: aload #19
    //   565: astore #22
    //   567: aload #18
    //   569: iload_3
    //   570: aaload
    //   571: getfield f : Landroidx/constraintlayout/solver/widgets/ConstraintAnchor;
    //   574: ifnull -> 603
    //   577: aload #18
    //   579: iload_3
    //   580: aaload
    //   581: getfield f : Landroidx/constraintlayout/solver/widgets/ConstraintAnchor;
    //   584: getfield d : Landroidx/constraintlayout/solver/widgets/ConstraintWidget;
    //   587: aload #17
    //   589: if_acmpeq -> 599
    //   592: aload #19
    //   594: astore #22
    //   596: goto -> 603
    //   599: aload #20
    //   601: astore #22
    //   603: aload #22
    //   605: ifnull -> 615
    //   608: aload #22
    //   610: astore #17
    //   612: goto -> 618
    //   615: iconst_1
    //   616: istore #13
    //   618: goto -> 198
    //   621: aload #8
    //   623: ifnull -> 819
    //   626: aload #6
    //   628: getfield S : [Landroidx/constraintlayout/solver/widgets/ConstraintAnchor;
    //   631: astore #22
    //   633: iload_3
    //   634: iconst_1
    //   635: iadd
    //   636: istore #14
    //   638: aload #22
    //   640: iload #14
    //   642: aaload
    //   643: getfield f : Landroidx/constraintlayout/solver/widgets/ConstraintAnchor;
    //   646: ifnull -> 819
    //   649: aload #8
    //   651: getfield S : [Landroidx/constraintlayout/solver/widgets/ConstraintAnchor;
    //   654: iload #14
    //   656: aaload
    //   657: astore #22
    //   659: aload #8
    //   661: getfield V : [Landroidx/constraintlayout/solver/widgets/ConstraintWidget$DimensionBehaviour;
    //   664: iload_2
    //   665: aaload
    //   666: getstatic androidx/constraintlayout/solver/widgets/ConstraintWidget$DimensionBehaviour.d : Landroidx/constraintlayout/solver/widgets/ConstraintWidget$DimensionBehaviour;
    //   669: if_acmpne -> 688
    //   672: aload #8
    //   674: getfield s : [I
    //   677: iload_2
    //   678: iaload
    //   679: ifne -> 688
    //   682: iconst_1
    //   683: istore #13
    //   685: goto -> 691
    //   688: iconst_0
    //   689: istore #13
    //   691: iload #13
    //   693: ifeq -> 742
    //   696: iload #12
    //   698: ifne -> 742
    //   701: aload #22
    //   703: getfield f : Landroidx/constraintlayout/solver/widgets/ConstraintAnchor;
    //   706: astore #17
    //   708: aload #17
    //   710: getfield d : Landroidx/constraintlayout/solver/widgets/ConstraintWidget;
    //   713: aload_0
    //   714: if_acmpne -> 742
    //   717: aload_1
    //   718: aload #22
    //   720: getfield i : Landroidx/constraintlayout/solver/SolverVariable;
    //   723: aload #17
    //   725: getfield i : Landroidx/constraintlayout/solver/SolverVariable;
    //   728: aload #22
    //   730: invokevirtual f : ()I
    //   733: ineg
    //   734: iconst_5
    //   735: invokevirtual e : (Landroidx/constraintlayout/solver/SolverVariable;Landroidx/constraintlayout/solver/SolverVariable;II)Landroidx/constraintlayout/solver/b;
    //   738: pop
    //   739: goto -> 785
    //   742: iload #12
    //   744: ifeq -> 785
    //   747: aload #22
    //   749: getfield f : Landroidx/constraintlayout/solver/widgets/ConstraintAnchor;
    //   752: astore #17
    //   754: aload #17
    //   756: getfield d : Landroidx/constraintlayout/solver/widgets/ConstraintWidget;
    //   759: aload_0
    //   760: if_acmpne -> 785
    //   763: aload_1
    //   764: aload #22
    //   766: getfield i : Landroidx/constraintlayout/solver/SolverVariable;
    //   769: aload #17
    //   771: getfield i : Landroidx/constraintlayout/solver/SolverVariable;
    //   774: aload #22
    //   776: invokevirtual f : ()I
    //   779: ineg
    //   780: iconst_4
    //   781: invokevirtual e : (Landroidx/constraintlayout/solver/SolverVariable;Landroidx/constraintlayout/solver/SolverVariable;II)Landroidx/constraintlayout/solver/b;
    //   784: pop
    //   785: aload_1
    //   786: aload #22
    //   788: getfield i : Landroidx/constraintlayout/solver/SolverVariable;
    //   791: aload #6
    //   793: getfield S : [Landroidx/constraintlayout/solver/widgets/ConstraintAnchor;
    //   796: iload #14
    //   798: aaload
    //   799: getfield f : Landroidx/constraintlayout/solver/widgets/ConstraintAnchor;
    //   802: getfield i : Landroidx/constraintlayout/solver/SolverVariable;
    //   805: aload #22
    //   807: invokevirtual f : ()I
    //   810: ineg
    //   811: bipush #6
    //   813: invokevirtual j : (Landroidx/constraintlayout/solver/SolverVariable;Landroidx/constraintlayout/solver/SolverVariable;II)V
    //   816: goto -> 819
    //   819: iload #11
    //   821: ifeq -> 871
    //   824: aload_0
    //   825: getfield S : [Landroidx/constraintlayout/solver/widgets/ConstraintAnchor;
    //   828: astore_0
    //   829: iload_3
    //   830: iconst_1
    //   831: iadd
    //   832: istore #13
    //   834: aload_0
    //   835: iload #13
    //   837: aaload
    //   838: getfield i : Landroidx/constraintlayout/solver/SolverVariable;
    //   841: astore #22
    //   843: aload #6
    //   845: getfield S : [Landroidx/constraintlayout/solver/widgets/ConstraintAnchor;
    //   848: astore_0
    //   849: aload_1
    //   850: aload #22
    //   852: aload_0
    //   853: iload #13
    //   855: aaload
    //   856: getfield i : Landroidx/constraintlayout/solver/SolverVariable;
    //   859: aload_0
    //   860: iload #13
    //   862: aaload
    //   863: invokevirtual f : ()I
    //   866: bipush #8
    //   868: invokevirtual h : (Landroidx/constraintlayout/solver/SolverVariable;Landroidx/constraintlayout/solver/SolverVariable;II)V
    //   871: aload #4
    //   873: getfield h : Ljava/util/ArrayList;
    //   876: astore_0
    //   877: aload_0
    //   878: ifnull -> 1166
    //   881: aload_0
    //   882: invokevirtual size : ()I
    //   885: istore #14
    //   887: iload #14
    //   889: iconst_1
    //   890: if_icmple -> 1166
    //   893: aload #4
    //   895: getfield r : Z
    //   898: ifeq -> 920
    //   901: aload #4
    //   903: getfield t : Z
    //   906: ifne -> 920
    //   909: aload #4
    //   911: getfield j : I
    //   914: i2f
    //   915: fstore #25
    //   917: goto -> 924
    //   920: fload #10
    //   922: fstore #25
    //   924: aconst_null
    //   925: astore #22
    //   927: iconst_0
    //   928: istore #13
    //   930: fconst_0
    //   931: fstore #26
    //   933: iload #13
    //   935: iload #14
    //   937: if_icmpge -> 1166
    //   940: aload_0
    //   941: iload #13
    //   943: invokevirtual get : (I)Ljava/lang/Object;
    //   946: checkcast androidx/constraintlayout/solver/widgets/ConstraintWidget
    //   949: astore #17
    //   951: aload #17
    //   953: getfield G0 : [F
    //   956: iload_2
    //   957: faload
    //   958: fstore #10
    //   960: fload #10
    //   962: fconst_0
    //   963: fcmpg
    //   964: ifge -> 1014
    //   967: aload #4
    //   969: getfield t : Z
    //   972: ifeq -> 1008
    //   975: aload #17
    //   977: getfield S : [Landroidx/constraintlayout/solver/widgets/ConstraintAnchor;
    //   980: astore #17
    //   982: aload_1
    //   983: aload #17
    //   985: iload_3
    //   986: iconst_1
    //   987: iadd
    //   988: aaload
    //   989: getfield i : Landroidx/constraintlayout/solver/SolverVariable;
    //   992: aload #17
    //   994: iload_3
    //   995: aaload
    //   996: getfield i : Landroidx/constraintlayout/solver/SolverVariable;
    //   999: iconst_0
    //   1000: iconst_4
    //   1001: invokevirtual e : (Landroidx/constraintlayout/solver/SolverVariable;Landroidx/constraintlayout/solver/SolverVariable;II)Landroidx/constraintlayout/solver/b;
    //   1004: pop
    //   1005: goto -> 1052
    //   1008: fconst_1
    //   1009: fstore #10
    //   1011: goto -> 1014
    //   1014: fload #10
    //   1016: fconst_0
    //   1017: fcmpl
    //   1018: ifne -> 1055
    //   1021: aload #17
    //   1023: getfield S : [Landroidx/constraintlayout/solver/widgets/ConstraintAnchor;
    //   1026: astore #17
    //   1028: aload_1
    //   1029: aload #17
    //   1031: iload_3
    //   1032: iconst_1
    //   1033: iadd
    //   1034: aaload
    //   1035: getfield i : Landroidx/constraintlayout/solver/SolverVariable;
    //   1038: aload #17
    //   1040: iload_3
    //   1041: aaload
    //   1042: getfield i : Landroidx/constraintlayout/solver/SolverVariable;
    //   1045: iconst_0
    //   1046: bipush #8
    //   1048: invokevirtual e : (Landroidx/constraintlayout/solver/SolverVariable;Landroidx/constraintlayout/solver/SolverVariable;II)Landroidx/constraintlayout/solver/b;
    //   1051: pop
    //   1052: goto -> 1160
    //   1055: aload #22
    //   1057: ifnull -> 1152
    //   1060: aload #22
    //   1062: getfield S : [Landroidx/constraintlayout/solver/widgets/ConstraintAnchor;
    //   1065: astore #19
    //   1067: aload #19
    //   1069: iload_3
    //   1070: aaload
    //   1071: getfield i : Landroidx/constraintlayout/solver/SolverVariable;
    //   1074: astore #22
    //   1076: iload_3
    //   1077: iconst_1
    //   1078: iadd
    //   1079: istore #11
    //   1081: aload #19
    //   1083: iload #11
    //   1085: aaload
    //   1086: getfield i : Landroidx/constraintlayout/solver/SolverVariable;
    //   1089: astore #20
    //   1091: aload #17
    //   1093: getfield S : [Landroidx/constraintlayout/solver/widgets/ConstraintAnchor;
    //   1096: astore #27
    //   1098: aload #27
    //   1100: iload_3
    //   1101: aaload
    //   1102: getfield i : Landroidx/constraintlayout/solver/SolverVariable;
    //   1105: astore #19
    //   1107: aload #27
    //   1109: iload #11
    //   1111: aaload
    //   1112: getfield i : Landroidx/constraintlayout/solver/SolverVariable;
    //   1115: astore #28
    //   1117: aload_1
    //   1118: invokevirtual r : ()Landroidx/constraintlayout/solver/b;
    //   1121: astore #27
    //   1123: aload #27
    //   1125: fload #26
    //   1127: fload #25
    //   1129: fload #10
    //   1131: aload #22
    //   1133: aload #20
    //   1135: aload #19
    //   1137: aload #28
    //   1139: invokevirtual l : (FFFLandroidx/constraintlayout/solver/SolverVariable;Landroidx/constraintlayout/solver/SolverVariable;Landroidx/constraintlayout/solver/SolverVariable;Landroidx/constraintlayout/solver/SolverVariable;)Landroidx/constraintlayout/solver/b;
    //   1142: pop
    //   1143: aload_1
    //   1144: aload #27
    //   1146: invokevirtual d : (Landroidx/constraintlayout/solver/b;)V
    //   1149: goto -> 1152
    //   1152: aload #17
    //   1154: astore #22
    //   1156: fload #10
    //   1158: fstore #26
    //   1160: iinc #13, 1
    //   1163: goto -> 933
    //   1166: aload #7
    //   1168: ifnull -> 1343
    //   1171: aload #7
    //   1173: aload #8
    //   1175: if_acmpeq -> 1183
    //   1178: iload #12
    //   1180: ifeq -> 1343
    //   1183: aload #5
    //   1185: getfield S : [Landroidx/constraintlayout/solver/widgets/ConstraintAnchor;
    //   1188: iload_3
    //   1189: aaload
    //   1190: astore_0
    //   1191: aload #6
    //   1193: getfield S : [Landroidx/constraintlayout/solver/widgets/ConstraintAnchor;
    //   1196: astore #4
    //   1198: iload_3
    //   1199: iconst_1
    //   1200: iadd
    //   1201: istore #13
    //   1203: aload #4
    //   1205: iload #13
    //   1207: aaload
    //   1208: astore #4
    //   1210: aload_0
    //   1211: getfield f : Landroidx/constraintlayout/solver/widgets/ConstraintAnchor;
    //   1214: astore_0
    //   1215: aload_0
    //   1216: ifnull -> 1227
    //   1219: aload_0
    //   1220: getfield i : Landroidx/constraintlayout/solver/SolverVariable;
    //   1223: astore_0
    //   1224: goto -> 1229
    //   1227: aconst_null
    //   1228: astore_0
    //   1229: aload #4
    //   1231: getfield f : Landroidx/constraintlayout/solver/widgets/ConstraintAnchor;
    //   1234: astore #4
    //   1236: aload #4
    //   1238: ifnull -> 1251
    //   1241: aload #4
    //   1243: getfield i : Landroidx/constraintlayout/solver/SolverVariable;
    //   1246: astore #4
    //   1248: goto -> 1254
    //   1251: aconst_null
    //   1252: astore #4
    //   1254: aload #7
    //   1256: getfield S : [Landroidx/constraintlayout/solver/widgets/ConstraintAnchor;
    //   1259: iload_3
    //   1260: aaload
    //   1261: astore #17
    //   1263: aload #8
    //   1265: getfield S : [Landroidx/constraintlayout/solver/widgets/ConstraintAnchor;
    //   1268: iload #13
    //   1270: aaload
    //   1271: astore #22
    //   1273: aload_0
    //   1274: ifnull -> 2401
    //   1277: aload #4
    //   1279: ifnull -> 2401
    //   1282: iload_2
    //   1283: ifne -> 1296
    //   1286: aload #9
    //   1288: getfield k0 : F
    //   1291: fstore #10
    //   1293: goto -> 1303
    //   1296: aload #9
    //   1298: getfield l0 : F
    //   1301: fstore #10
    //   1303: aload #17
    //   1305: invokevirtual f : ()I
    //   1308: istore_2
    //   1309: aload #22
    //   1311: invokevirtual f : ()I
    //   1314: istore #13
    //   1316: aload_1
    //   1317: aload #17
    //   1319: getfield i : Landroidx/constraintlayout/solver/SolverVariable;
    //   1322: aload_0
    //   1323: iload_2
    //   1324: fload #10
    //   1326: aload #4
    //   1328: aload #22
    //   1330: getfield i : Landroidx/constraintlayout/solver/SolverVariable;
    //   1333: iload #13
    //   1335: bipush #7
    //   1337: invokevirtual c : (Landroidx/constraintlayout/solver/SolverVariable;Landroidx/constraintlayout/solver/SolverVariable;IFLandroidx/constraintlayout/solver/SolverVariable;Landroidx/constraintlayout/solver/SolverVariable;II)V
    //   1340: goto -> 2401
    //   1343: iload #15
    //   1345: ifeq -> 1832
    //   1348: aload #7
    //   1350: ifnull -> 1832
    //   1353: aload #4
    //   1355: getfield j : I
    //   1358: istore #13
    //   1360: iload #13
    //   1362: ifle -> 1381
    //   1365: aload #4
    //   1367: getfield i : I
    //   1370: iload #13
    //   1372: if_icmpne -> 1381
    //   1375: iconst_1
    //   1376: istore #11
    //   1378: goto -> 1384
    //   1381: iconst_0
    //   1382: istore #11
    //   1384: aload #7
    //   1386: astore #4
    //   1388: aload #4
    //   1390: astore #17
    //   1392: aload #4
    //   1394: ifnull -> 2401
    //   1397: aload #4
    //   1399: getfield I0 : [Landroidx/constraintlayout/solver/widgets/ConstraintWidget;
    //   1402: iload_2
    //   1403: aaload
    //   1404: astore #22
    //   1406: aload #22
    //   1408: ifnull -> 1433
    //   1411: aload #22
    //   1413: invokevirtual T : ()I
    //   1416: bipush #8
    //   1418: if_icmpne -> 1433
    //   1421: aload #22
    //   1423: getfield I0 : [Landroidx/constraintlayout/solver/widgets/ConstraintWidget;
    //   1426: iload_2
    //   1427: aaload
    //   1428: astore #22
    //   1430: goto -> 1406
    //   1433: aload #22
    //   1435: ifnonnull -> 1451
    //   1438: aload #4
    //   1440: aload #8
    //   1442: if_acmpne -> 1448
    //   1445: goto -> 1451
    //   1448: goto -> 1811
    //   1451: aload #4
    //   1453: getfield S : [Landroidx/constraintlayout/solver/widgets/ConstraintAnchor;
    //   1456: iload_3
    //   1457: aaload
    //   1458: astore #19
    //   1460: aload #19
    //   1462: getfield i : Landroidx/constraintlayout/solver/SolverVariable;
    //   1465: astore #27
    //   1467: aload #19
    //   1469: getfield f : Landroidx/constraintlayout/solver/widgets/ConstraintAnchor;
    //   1472: astore_0
    //   1473: aload_0
    //   1474: ifnull -> 1486
    //   1477: aload_0
    //   1478: getfield i : Landroidx/constraintlayout/solver/SolverVariable;
    //   1481: astore #9
    //   1483: goto -> 1489
    //   1486: aconst_null
    //   1487: astore #9
    //   1489: aload #17
    //   1491: aload #4
    //   1493: if_acmpeq -> 1512
    //   1496: aload #17
    //   1498: getfield S : [Landroidx/constraintlayout/solver/widgets/ConstraintAnchor;
    //   1501: iload_3
    //   1502: iconst_1
    //   1503: iadd
    //   1504: aaload
    //   1505: getfield i : Landroidx/constraintlayout/solver/SolverVariable;
    //   1508: astore_0
    //   1509: goto -> 1562
    //   1512: aload #9
    //   1514: astore_0
    //   1515: aload #4
    //   1517: aload #7
    //   1519: if_acmpne -> 1562
    //   1522: aload #9
    //   1524: astore_0
    //   1525: aload #17
    //   1527: aload #4
    //   1529: if_acmpne -> 1562
    //   1532: aload #5
    //   1534: getfield S : [Landroidx/constraintlayout/solver/widgets/ConstraintAnchor;
    //   1537: astore_0
    //   1538: aload_0
    //   1539: iload_3
    //   1540: aaload
    //   1541: getfield f : Landroidx/constraintlayout/solver/widgets/ConstraintAnchor;
    //   1544: ifnull -> 1560
    //   1547: aload_0
    //   1548: iload_3
    //   1549: aaload
    //   1550: getfield f : Landroidx/constraintlayout/solver/widgets/ConstraintAnchor;
    //   1553: getfield i : Landroidx/constraintlayout/solver/SolverVariable;
    //   1556: astore_0
    //   1557: goto -> 1562
    //   1560: aconst_null
    //   1561: astore_0
    //   1562: aload #19
    //   1564: invokevirtual f : ()I
    //   1567: istore #12
    //   1569: aload #4
    //   1571: getfield S : [Landroidx/constraintlayout/solver/widgets/ConstraintAnchor;
    //   1574: astore #9
    //   1576: iload_3
    //   1577: iconst_1
    //   1578: iadd
    //   1579: istore #24
    //   1581: aload #9
    //   1583: iload #24
    //   1585: aaload
    //   1586: invokevirtual f : ()I
    //   1589: istore #14
    //   1591: aload #22
    //   1593: ifnull -> 1628
    //   1596: aload #22
    //   1598: getfield S : [Landroidx/constraintlayout/solver/widgets/ConstraintAnchor;
    //   1601: iload_3
    //   1602: aaload
    //   1603: astore #19
    //   1605: aload #19
    //   1607: getfield i : Landroidx/constraintlayout/solver/SolverVariable;
    //   1610: astore #9
    //   1612: aload #4
    //   1614: getfield S : [Landroidx/constraintlayout/solver/widgets/ConstraintAnchor;
    //   1617: iload #24
    //   1619: aaload
    //   1620: getfield i : Landroidx/constraintlayout/solver/SolverVariable;
    //   1623: astore #20
    //   1625: goto -> 1672
    //   1628: aload #6
    //   1630: getfield S : [Landroidx/constraintlayout/solver/widgets/ConstraintAnchor;
    //   1633: iload #24
    //   1635: aaload
    //   1636: getfield f : Landroidx/constraintlayout/solver/widgets/ConstraintAnchor;
    //   1639: astore #19
    //   1641: aload #19
    //   1643: ifnull -> 1656
    //   1646: aload #19
    //   1648: getfield i : Landroidx/constraintlayout/solver/SolverVariable;
    //   1651: astore #9
    //   1653: goto -> 1659
    //   1656: aconst_null
    //   1657: astore #9
    //   1659: aload #4
    //   1661: getfield S : [Landroidx/constraintlayout/solver/widgets/ConstraintAnchor;
    //   1664: iload #24
    //   1666: aaload
    //   1667: getfield i : Landroidx/constraintlayout/solver/SolverVariable;
    //   1670: astore #20
    //   1672: iload #14
    //   1674: istore #13
    //   1676: aload #19
    //   1678: ifnull -> 1691
    //   1681: iload #14
    //   1683: aload #19
    //   1685: invokevirtual f : ()I
    //   1688: iadd
    //   1689: istore #13
    //   1691: iload #12
    //   1693: istore #14
    //   1695: aload #17
    //   1697: ifnull -> 1716
    //   1700: iload #12
    //   1702: aload #17
    //   1704: getfield S : [Landroidx/constraintlayout/solver/widgets/ConstraintAnchor;
    //   1707: iload #24
    //   1709: aaload
    //   1710: invokevirtual f : ()I
    //   1713: iadd
    //   1714: istore #14
    //   1716: aload #27
    //   1718: ifnull -> 1448
    //   1721: aload_0
    //   1722: ifnull -> 1448
    //   1725: aload #9
    //   1727: ifnull -> 1448
    //   1730: aload #20
    //   1732: ifnull -> 1448
    //   1735: aload #4
    //   1737: aload #7
    //   1739: if_acmpne -> 1754
    //   1742: aload #7
    //   1744: getfield S : [Landroidx/constraintlayout/solver/widgets/ConstraintAnchor;
    //   1747: iload_3
    //   1748: aaload
    //   1749: invokevirtual f : ()I
    //   1752: istore #14
    //   1754: aload #4
    //   1756: aload #8
    //   1758: if_acmpne -> 1777
    //   1761: aload #8
    //   1763: getfield S : [Landroidx/constraintlayout/solver/widgets/ConstraintAnchor;
    //   1766: iload #24
    //   1768: aaload
    //   1769: invokevirtual f : ()I
    //   1772: istore #13
    //   1774: goto -> 1777
    //   1777: iload #11
    //   1779: ifeq -> 1789
    //   1782: bipush #8
    //   1784: istore #12
    //   1786: goto -> 1792
    //   1789: iconst_5
    //   1790: istore #12
    //   1792: aload_1
    //   1793: aload #27
    //   1795: aload_0
    //   1796: iload #14
    //   1798: ldc 0.5
    //   1800: aload #9
    //   1802: aload #20
    //   1804: iload #13
    //   1806: iload #12
    //   1808: invokevirtual c : (Landroidx/constraintlayout/solver/SolverVariable;Landroidx/constraintlayout/solver/SolverVariable;IFLandroidx/constraintlayout/solver/SolverVariable;Landroidx/constraintlayout/solver/SolverVariable;II)V
    //   1811: aload #4
    //   1813: invokevirtual T : ()I
    //   1816: bipush #8
    //   1818: if_icmpeq -> 1825
    //   1821: aload #4
    //   1823: astore #17
    //   1825: aload #22
    //   1827: astore #4
    //   1829: goto -> 1392
    //   1832: iload #16
    //   1834: ifeq -> 2401
    //   1837: aload #7
    //   1839: ifnull -> 2401
    //   1842: aload #4
    //   1844: getfield j : I
    //   1847: istore #13
    //   1849: iload #13
    //   1851: ifle -> 1870
    //   1854: aload #4
    //   1856: getfield i : I
    //   1859: iload #13
    //   1861: if_icmpne -> 1870
    //   1864: iconst_1
    //   1865: istore #13
    //   1867: goto -> 1873
    //   1870: iconst_0
    //   1871: istore #13
    //   1873: aload #7
    //   1875: astore #4
    //   1877: aload #4
    //   1879: astore #22
    //   1881: aload #4
    //   1883: ifnull -> 2241
    //   1886: aload #4
    //   1888: getfield I0 : [Landroidx/constraintlayout/solver/widgets/ConstraintWidget;
    //   1891: iload_2
    //   1892: aaload
    //   1893: astore_0
    //   1894: aload_0
    //   1895: ifnull -> 1917
    //   1898: aload_0
    //   1899: invokevirtual T : ()I
    //   1902: bipush #8
    //   1904: if_icmpne -> 1917
    //   1907: aload_0
    //   1908: getfield I0 : [Landroidx/constraintlayout/solver/widgets/ConstraintWidget;
    //   1911: iload_2
    //   1912: aaload
    //   1913: astore_0
    //   1914: goto -> 1894
    //   1917: aload #4
    //   1919: aload #7
    //   1921: if_acmpeq -> 2214
    //   1924: aload #4
    //   1926: aload #8
    //   1928: if_acmpeq -> 2214
    //   1931: aload_0
    //   1932: ifnull -> 2214
    //   1935: aload_0
    //   1936: aload #8
    //   1938: if_acmpne -> 1946
    //   1941: aconst_null
    //   1942: astore_0
    //   1943: goto -> 1946
    //   1946: aload #4
    //   1948: getfield S : [Landroidx/constraintlayout/solver/widgets/ConstraintAnchor;
    //   1951: iload_3
    //   1952: aaload
    //   1953: astore #9
    //   1955: aload #9
    //   1957: getfield i : Landroidx/constraintlayout/solver/SolverVariable;
    //   1960: astore #27
    //   1962: aload #9
    //   1964: getfield f : Landroidx/constraintlayout/solver/widgets/ConstraintAnchor;
    //   1967: astore #17
    //   1969: aload #17
    //   1971: ifnull -> 1981
    //   1974: aload #17
    //   1976: getfield i : Landroidx/constraintlayout/solver/SolverVariable;
    //   1979: astore #17
    //   1981: aload #22
    //   1983: getfield S : [Landroidx/constraintlayout/solver/widgets/ConstraintAnchor;
    //   1986: astore #17
    //   1988: iload_3
    //   1989: iconst_1
    //   1990: iadd
    //   1991: istore #24
    //   1993: aload #17
    //   1995: iload #24
    //   1997: aaload
    //   1998: getfield i : Landroidx/constraintlayout/solver/SolverVariable;
    //   2001: astore #28
    //   2003: aload #9
    //   2005: invokevirtual f : ()I
    //   2008: istore #12
    //   2010: aload #4
    //   2012: getfield S : [Landroidx/constraintlayout/solver/widgets/ConstraintAnchor;
    //   2015: iload #24
    //   2017: aaload
    //   2018: invokevirtual f : ()I
    //   2021: istore #11
    //   2023: aload_0
    //   2024: ifnull -> 2070
    //   2027: aload_0
    //   2028: getfield S : [Landroidx/constraintlayout/solver/widgets/ConstraintAnchor;
    //   2031: iload_3
    //   2032: aaload
    //   2033: astore #17
    //   2035: aload #17
    //   2037: getfield i : Landroidx/constraintlayout/solver/SolverVariable;
    //   2040: astore #19
    //   2042: aload #17
    //   2044: getfield f : Landroidx/constraintlayout/solver/widgets/ConstraintAnchor;
    //   2047: astore #9
    //   2049: aload #9
    //   2051: ifnull -> 2064
    //   2054: aload #9
    //   2056: getfield i : Landroidx/constraintlayout/solver/SolverVariable;
    //   2059: astore #9
    //   2061: goto -> 2118
    //   2064: aconst_null
    //   2065: astore #9
    //   2067: goto -> 2118
    //   2070: aload #8
    //   2072: getfield S : [Landroidx/constraintlayout/solver/widgets/ConstraintAnchor;
    //   2075: iload_3
    //   2076: aaload
    //   2077: astore #20
    //   2079: aload #20
    //   2081: ifnull -> 2094
    //   2084: aload #20
    //   2086: getfield i : Landroidx/constraintlayout/solver/SolverVariable;
    //   2089: astore #17
    //   2091: goto -> 2097
    //   2094: aconst_null
    //   2095: astore #17
    //   2097: aload #4
    //   2099: getfield S : [Landroidx/constraintlayout/solver/widgets/ConstraintAnchor;
    //   2102: iload #24
    //   2104: aaload
    //   2105: getfield i : Landroidx/constraintlayout/solver/SolverVariable;
    //   2108: astore #9
    //   2110: aload #17
    //   2112: astore #19
    //   2114: aload #20
    //   2116: astore #17
    //   2118: iload #11
    //   2120: istore #14
    //   2122: aload #17
    //   2124: ifnull -> 2137
    //   2127: iload #11
    //   2129: aload #17
    //   2131: invokevirtual f : ()I
    //   2134: iadd
    //   2135: istore #14
    //   2137: aload #22
    //   2139: getfield S : [Landroidx/constraintlayout/solver/widgets/ConstraintAnchor;
    //   2142: iload #24
    //   2144: aaload
    //   2145: invokevirtual f : ()I
    //   2148: istore #24
    //   2150: iload #13
    //   2152: ifeq -> 2162
    //   2155: bipush #8
    //   2157: istore #11
    //   2159: goto -> 2165
    //   2162: iconst_4
    //   2163: istore #11
    //   2165: aload #27
    //   2167: ifnull -> 2211
    //   2170: aload #28
    //   2172: ifnull -> 2211
    //   2175: aload #19
    //   2177: ifnull -> 2211
    //   2180: aload #9
    //   2182: ifnull -> 2211
    //   2185: aload_1
    //   2186: aload #27
    //   2188: aload #28
    //   2190: iload #24
    //   2192: iload #12
    //   2194: iadd
    //   2195: ldc 0.5
    //   2197: aload #19
    //   2199: aload #9
    //   2201: iload #14
    //   2203: iload #11
    //   2205: invokevirtual c : (Landroidx/constraintlayout/solver/SolverVariable;Landroidx/constraintlayout/solver/SolverVariable;IFLandroidx/constraintlayout/solver/SolverVariable;Landroidx/constraintlayout/solver/SolverVariable;II)V
    //   2208: goto -> 2211
    //   2211: goto -> 2214
    //   2214: aload #4
    //   2216: invokevirtual T : ()I
    //   2219: bipush #8
    //   2221: if_icmpeq -> 2227
    //   2224: goto -> 2231
    //   2227: aload #22
    //   2229: astore #4
    //   2231: aload #4
    //   2233: astore #22
    //   2235: aload_0
    //   2236: astore #4
    //   2238: goto -> 1881
    //   2241: aload #7
    //   2243: getfield S : [Landroidx/constraintlayout/solver/widgets/ConstraintAnchor;
    //   2246: iload_3
    //   2247: aaload
    //   2248: astore_0
    //   2249: aload #5
    //   2251: getfield S : [Landroidx/constraintlayout/solver/widgets/ConstraintAnchor;
    //   2254: iload_3
    //   2255: aaload
    //   2256: getfield f : Landroidx/constraintlayout/solver/widgets/ConstraintAnchor;
    //   2259: astore #4
    //   2261: aload #8
    //   2263: getfield S : [Landroidx/constraintlayout/solver/widgets/ConstraintAnchor;
    //   2266: astore #22
    //   2268: iload_3
    //   2269: iconst_1
    //   2270: iadd
    //   2271: istore_2
    //   2272: aload #22
    //   2274: iload_2
    //   2275: aaload
    //   2276: astore #9
    //   2278: aload #6
    //   2280: getfield S : [Landroidx/constraintlayout/solver/widgets/ConstraintAnchor;
    //   2283: iload_2
    //   2284: aaload
    //   2285: getfield f : Landroidx/constraintlayout/solver/widgets/ConstraintAnchor;
    //   2288: astore #22
    //   2290: aload #4
    //   2292: ifnull -> 2367
    //   2295: aload #7
    //   2297: aload #8
    //   2299: if_acmpeq -> 2324
    //   2302: aload_1
    //   2303: aload_0
    //   2304: getfield i : Landroidx/constraintlayout/solver/SolverVariable;
    //   2307: aload #4
    //   2309: getfield i : Landroidx/constraintlayout/solver/SolverVariable;
    //   2312: aload_0
    //   2313: invokevirtual f : ()I
    //   2316: iconst_5
    //   2317: invokevirtual e : (Landroidx/constraintlayout/solver/SolverVariable;Landroidx/constraintlayout/solver/SolverVariable;II)Landroidx/constraintlayout/solver/b;
    //   2320: pop
    //   2321: goto -> 2367
    //   2324: aload #22
    //   2326: ifnull -> 2367
    //   2329: aload_1
    //   2330: aload_0
    //   2331: getfield i : Landroidx/constraintlayout/solver/SolverVariable;
    //   2334: aload #4
    //   2336: getfield i : Landroidx/constraintlayout/solver/SolverVariable;
    //   2339: aload_0
    //   2340: invokevirtual f : ()I
    //   2343: ldc 0.5
    //   2345: aload #9
    //   2347: getfield i : Landroidx/constraintlayout/solver/SolverVariable;
    //   2350: aload #22
    //   2352: getfield i : Landroidx/constraintlayout/solver/SolverVariable;
    //   2355: aload #9
    //   2357: invokevirtual f : ()I
    //   2360: iconst_5
    //   2361: invokevirtual c : (Landroidx/constraintlayout/solver/SolverVariable;Landroidx/constraintlayout/solver/SolverVariable;IFLandroidx/constraintlayout/solver/SolverVariable;Landroidx/constraintlayout/solver/SolverVariable;II)V
    //   2364: goto -> 2367
    //   2367: aload #22
    //   2369: ifnull -> 2401
    //   2372: aload #7
    //   2374: aload #8
    //   2376: if_acmpeq -> 2401
    //   2379: aload_1
    //   2380: aload #9
    //   2382: getfield i : Landroidx/constraintlayout/solver/SolverVariable;
    //   2385: aload #22
    //   2387: getfield i : Landroidx/constraintlayout/solver/SolverVariable;
    //   2390: aload #9
    //   2392: invokevirtual f : ()I
    //   2395: ineg
    //   2396: iconst_5
    //   2397: invokevirtual e : (Landroidx/constraintlayout/solver/SolverVariable;Landroidx/constraintlayout/solver/SolverVariable;II)Landroidx/constraintlayout/solver/b;
    //   2400: pop
    //   2401: iload #15
    //   2403: ifne -> 2411
    //   2406: iload #16
    //   2408: ifeq -> 2593
    //   2411: aload #7
    //   2413: ifnull -> 2593
    //   2416: aload #7
    //   2418: aload #8
    //   2420: if_acmpeq -> 2593
    //   2423: aload #7
    //   2425: getfield S : [Landroidx/constraintlayout/solver/widgets/ConstraintAnchor;
    //   2428: astore #17
    //   2430: aload #17
    //   2432: iload_3
    //   2433: aaload
    //   2434: astore #9
    //   2436: aload #8
    //   2438: getfield S : [Landroidx/constraintlayout/solver/widgets/ConstraintAnchor;
    //   2441: astore_0
    //   2442: iload_3
    //   2443: iconst_1
    //   2444: iadd
    //   2445: istore_2
    //   2446: aload_0
    //   2447: iload_2
    //   2448: aaload
    //   2449: astore #22
    //   2451: aload #9
    //   2453: getfield f : Landroidx/constraintlayout/solver/widgets/ConstraintAnchor;
    //   2456: astore_0
    //   2457: aload_0
    //   2458: ifnull -> 2470
    //   2461: aload_0
    //   2462: getfield i : Landroidx/constraintlayout/solver/SolverVariable;
    //   2465: astore #4
    //   2467: goto -> 2473
    //   2470: aconst_null
    //   2471: astore #4
    //   2473: aload #22
    //   2475: getfield f : Landroidx/constraintlayout/solver/widgets/ConstraintAnchor;
    //   2478: astore_0
    //   2479: aload_0
    //   2480: ifnull -> 2491
    //   2483: aload_0
    //   2484: getfield i : Landroidx/constraintlayout/solver/SolverVariable;
    //   2487: astore_0
    //   2488: goto -> 2493
    //   2491: aconst_null
    //   2492: astore_0
    //   2493: aload #6
    //   2495: aload #8
    //   2497: if_acmpeq -> 2526
    //   2500: aload #6
    //   2502: getfield S : [Landroidx/constraintlayout/solver/widgets/ConstraintAnchor;
    //   2505: iload_2
    //   2506: aaload
    //   2507: getfield f : Landroidx/constraintlayout/solver/widgets/ConstraintAnchor;
    //   2510: astore #5
    //   2512: aload #18
    //   2514: astore_0
    //   2515: aload #5
    //   2517: ifnull -> 2526
    //   2520: aload #5
    //   2522: getfield i : Landroidx/constraintlayout/solver/SolverVariable;
    //   2525: astore_0
    //   2526: aload #7
    //   2528: aload #8
    //   2530: if_acmpne -> 2545
    //   2533: aload #17
    //   2535: iload_3
    //   2536: aaload
    //   2537: astore #9
    //   2539: aload #17
    //   2541: iload_2
    //   2542: aaload
    //   2543: astore #22
    //   2545: aload #4
    //   2547: ifnull -> 2593
    //   2550: aload_0
    //   2551: ifnull -> 2593
    //   2554: aload #9
    //   2556: invokevirtual f : ()I
    //   2559: istore_3
    //   2560: aload #8
    //   2562: getfield S : [Landroidx/constraintlayout/solver/widgets/ConstraintAnchor;
    //   2565: iload_2
    //   2566: aaload
    //   2567: invokevirtual f : ()I
    //   2570: istore_2
    //   2571: aload_1
    //   2572: aload #9
    //   2574: getfield i : Landroidx/constraintlayout/solver/SolverVariable;
    //   2577: aload #4
    //   2579: iload_3
    //   2580: ldc 0.5
    //   2582: aload_0
    //   2583: aload #22
    //   2585: getfield i : Landroidx/constraintlayout/solver/SolverVariable;
    //   2588: iload_2
    //   2589: iconst_5
    //   2590: invokevirtual c : (Landroidx/constraintlayout/solver/SolverVariable;Landroidx/constraintlayout/solver/SolverVariable;IFLandroidx/constraintlayout/solver/SolverVariable;Landroidx/constraintlayout/solver/SolverVariable;II)V
    //   2593: return
  }
  
  public static void b(d paramd, d paramd1, ArrayList<ConstraintWidget> paramArrayList, int paramInt) {
    int i;
    c[] arrayOfC;
    byte b2;
    byte b1 = 0;
    if (paramInt == 0) {
      i = paramd.Y0;
      arrayOfC = paramd.b1;
      b2 = 0;
    } else {
      i = paramd.Z0;
      arrayOfC = paramd.a1;
      b2 = 2;
    } 
    while (b1 < i) {
      c c = arrayOfC[b1];
      c.a();
      if (paramArrayList == null || paramArrayList.contains(c.a))
        a(paramd, paramd1, paramInt, b2, c); 
      b1++;
    } 
  }
}


/* Location:              /home/sumith/decompile/test/classes-dex2jar.jar!/androidx/constraintlayout/solver/widgets/b.class
 * Java compiler version: 6 (50.0)
 * JD-Core Version:       1.1.3
 */