package com.allinone.callerid.util;

import android.text.TextUtils;
import java.text.Collator;
import java.util.ArrayList;
import java.util.Locale;

public class v {
  public static final char[] a = new char[] { 
      -27073, '哎', '安', -32594, '凹', '八', '挀', '扳', -28506, '勹', 
      -27070, '奔', '伻', '屄', -28743, '灬', '憋', '汃', '冫', '癶', 
      '峬', '嚓', '偲', '参', '仓', '撡', '冊', '嵾', '曽', '曾', 
      '層', '叉', -32122, -28737, '伥', '抄', -28826, '抻', '沈', '沉', 
      -27081, '吃', '充', '抽', '出', '欻', '揣', '巛', '刅', '吹', 
      '旾', -28620, '呲', '匆', '凑', '粗', '汆', '崔', -28504, '搓', 
      '咑', '呆', '丹', '当', '刀', '嘚', '扥', '灯', '氐', '嗲', 
      '甸', '刁', '爹', '丁', '丟', '东', '吺', '厾', -32751, -30360, 
      '吨', '多', '妸', -29706, '奀', -26715, '儿', '发', '帆', '匚', 
      -26402, '分', '丰', -30331, '仏', '紑', '伕', '旮', '侅', '甘', 
      '冈', '皋', '戈', '给', '根', '刯', '工', '勾', '估', '瓜', 
      '乖', '关', '光', '归', '丨', '呙', '哈', '咍', '佄', '夯', 
      -31968, -29757, -24878, '拫', '亨', '噷', '叿', -24767, '乯', -32079, 
      '怀', '犿', '巟', '灰', '昏', '吙', '丌', '加', '戋', '江', 
      -32131, -27082, '巾', '坕', '冂', '丩', '凥', '姢', '噘', '军', 
      '咔', '开', '刊', '忼', '尻', '匼', -32626, '劥', '空', '抠', 
      '扝', '夸', -31569, '宽', '匡', '亏', '坤', '扩', '垃', '来', 
      '兰', '啷', '捞', -32629, '勒', '崚', '刕', '俩', '奁', -32145, 
      '撩', '列', '拎', '刢', '溜', '囖', -24679, '瞜', '噜', '娈', 
      '畧', '抡', '罗', '呣', '妈', '埋', '嫚', '牤', '猫', '么', 
      '呅', -27160, '甿', '咪', '宀', '喵', '乜', '民', '名', -29652, 
      '摸', '哞', '毪', '嗯', '拏', -32439, '囡', '囔', '孬', '疒', 
      '娞', '恁', -32515, '妮', '拈', '嬢', -25057, '捏', '囜', '宁', 
      '妞', '农', '羺', '奴', '奻', '疟', -24895, -28467, '喔', -29772, 
      '妑', '拍', '眅', '乓', '抛', '呸', '喷', '匉', '丕', '囨', 
      '剽', '氕', '姘', '乒', -27509, '剖', '仆', '七', '掐', '千', 
      '呛', '悄', '癿', '亲', '狅', -32114, '丘', '区', '峑', '缺', 
      '夋', '呥', '穣', '娆', '惹', '人', '扔', '日', -31944, '厹', 
      -28518, '挼', '堧', '婑', '瞤', '捼', '仨', '毢', '三', '桒', 
      '掻', -27222, '森', '僧', '杀', '筛', '山', '伤', '弰', '奢', 
      '申', -31848, '敒', '升', '尸', '収', '书', '刷', -30608, -27159, 
      '双', -29695, '吮', -29708, '厶', '忪', '捜', -32049, '狻', '夊', 
      '孙', '唆', '他', '囼', '坍', '汤', '夲', '忑', '熥', '剔', 
      '天', '旫', '帖', '厅', '囲', '偷', '凸', '湍', '推', '吞', 
      '乇', '穵', '歪', '弯', '尣', '危', '昷', '翁', '挝', '乌', 
      '夕', -31118, '仚', '乡', '灱', '些', '心', '星', '凶', '休', 
      '吁', '吅', '削', '坃', '丫', '恹', '央', '幺', '倻', '一', 
      '囙', '应', '哟', '佣', '优', '扜', '囦', '曰', '晕', '筠', 
      '筼', '帀', '災', '兂', '匨', '傮', '则', -29380, '怎', '増', 
      '扎', '捚', '沾', '张', -27265, -27273, '佋', -30969, -29410, '争', 
      '之', '峙', '庢', '中', '州', '朱', '抓', '拽', '专', '妆', 
      -26951, '宒', '卓', '乲', '宗', -28487, '租', -27461, '厜', '尊', 
      '昨', '兙', -24637, -24636 };
  
  public static final byte[][] b;
  
  private static final Collator c = Collator.getInstance(Locale.CHINA);
  
  private static v d;
  
  private final boolean e;
  
  protected v(boolean paramBoolean) {
    this.e = paramBoolean;
  }
  
  private void a(StringBuilder paramStringBuilder, ArrayList<a> paramArrayList, int paramInt) {
    String str = paramStringBuilder.toString();
    paramArrayList.add(new a(paramInt, str, str));
    paramStringBuilder.setLength(0);
  }
  
  public static v c() {
    // Byte code:
    //   0: ldc com/allinone/callerid/util/v
    //   2: monitorenter
    //   3: getstatic com/allinone/callerid/util/v.d : Lcom/allinone/callerid/util/v;
    //   6: astore_0
    //   7: aload_0
    //   8: ifnull -> 16
    //   11: ldc com/allinone/callerid/util/v
    //   13: monitorexit
    //   14: aload_0
    //   15: areturn
    //   16: invokestatic getAvailableLocales : ()[Ljava/util/Locale;
    //   19: astore_1
    //   20: new java/util/Locale
    //   23: astore_0
    //   24: aload_0
    //   25: ldc_w 'zh'
    //   28: ldc_w 'HANS'
    //   31: ldc_w 'CN'
    //   34: invokespecial <init> : (Ljava/lang/String;Ljava/lang/String;Ljava/lang/String;)V
    //   37: new java/util/Locale
    //   40: astore_2
    //   41: aload_2
    //   42: ldc_w 'zh'
    //   45: invokespecial <init> : (Ljava/lang/String;)V
    //   48: iconst_0
    //   49: istore_3
    //   50: iload_3
    //   51: aload_1
    //   52: arraylength
    //   53: if_icmpge -> 115
    //   56: aload_1
    //   57: iload_3
    //   58: aaload
    //   59: getstatic java/util/Locale.CHINA : Ljava/util/Locale;
    //   62: invokevirtual equals : (Ljava/lang/Object;)Z
    //   65: ifne -> 97
    //   68: aload_1
    //   69: iload_3
    //   70: aaload
    //   71: aload_0
    //   72: invokevirtual equals : (Ljava/lang/Object;)Z
    //   75: ifne -> 97
    //   78: aload_1
    //   79: iload_3
    //   80: aaload
    //   81: aload_2
    //   82: invokevirtual equals : (Ljava/lang/Object;)Z
    //   85: ifeq -> 91
    //   88: goto -> 97
    //   91: iinc #3, 1
    //   94: goto -> 50
    //   97: new com/allinone/callerid/util/v
    //   100: astore_0
    //   101: aload_0
    //   102: iconst_1
    //   103: invokespecial <init> : (Z)V
    //   106: aload_0
    //   107: putstatic com/allinone/callerid/util/v.d : Lcom/allinone/callerid/util/v;
    //   110: ldc com/allinone/callerid/util/v
    //   112: monitorexit
    //   113: aload_0
    //   114: areturn
    //   115: ldc_w 'HanziToPinyin'
    //   118: ldc_w 'There is no Chinese collator, HanziToPinyin is disabled'
    //   121: invokestatic w : (Ljava/lang/String;Ljava/lang/String;)I
    //   124: pop
    //   125: new com/allinone/callerid/util/v
    //   128: astore_0
    //   129: aload_0
    //   130: iconst_0
    //   131: invokespecial <init> : (Z)V
    //   134: aload_0
    //   135: putstatic com/allinone/callerid/util/v.d : Lcom/allinone/callerid/util/v;
    //   138: ldc com/allinone/callerid/util/v
    //   140: monitorexit
    //   141: aload_0
    //   142: areturn
    //   143: astore_0
    //   144: ldc com/allinone/callerid/util/v
    //   146: monitorexit
    //   147: goto -> 152
    //   150: aload_0
    //   151: athrow
    //   152: goto -> 150
    // Exception table:
    //   from	to	target	type
    //   3	7	143	finally
    //   11	14	143	finally
    //   16	48	143	finally
    //   50	88	143	finally
    //   97	113	143	finally
    //   115	141	143	finally
    //   144	147	143	finally
  }
  
  private a d(char paramChar) {
    a a = new a();
    String str2 = Character.toString(paramChar);
    a.b = str2;
    if (paramChar < 'Ā') {
      a.a = 1;
      a.c = str2;
      return a;
    } 
    Collator collator = c;
    int i = collator.compare(str2, "阿");
    if (i < 0) {
      a.a = 3;
      a.c = str2;
      return a;
    } 
    boolean bool = false;
    if (i == 0) {
      a.a = 2;
      j = 0;
    } else {
      i = collator.compare(str2, "鿿");
      if (i > 0) {
        a.a = 3;
        a.c = str2;
        return a;
      } 
      if (i == 0) {
        a.a = 2;
        j = a.length - 1;
      } else {
        j = -1;
      } 
    } 
    a.a = 2;
    int k = i;
    int m = j;
    if (j < 0) {
      int n = a.length - 1;
      int i1 = 0;
      while (true) {
        k = i;
        m = j;
        if (i1 <= n) {
          j = (i1 + n) / 2;
          String str = Character.toString(a[j]);
          i = c.compare(str2, str);
          if (i == 0) {
            k = i;
            m = j;
            break;
          } 
          if (i > 0) {
            i1 = j + 1;
            continue;
          } 
          n = j - 1;
          continue;
        } 
        break;
      } 
    } 
    int j = m;
    if (k < 0)
      j = m - 1; 
    StringBuilder stringBuilder = new StringBuilder();
    i = bool;
    while (true) {
      byte[][] arrayOfByte = b;
      if (i < (arrayOfByte[j]).length && arrayOfByte[j][i] != 0) {
        stringBuilder.append((char)arrayOfByte[j][i]);
        i++;
        continue;
      } 
      break;
    } 
    String str1 = stringBuilder.toString();
    a.c = str1;
    if (TextUtils.isEmpty(str1)) {
      a.a = 3;
      a.c = a.b;
    } 
    return a;
  }
  
  public ArrayList<a> b(String paramString) {
    ArrayList<a> arrayList = new ArrayList();
    if (this.e && !TextUtils.isEmpty(paramString)) {
      int i = paramString.length();
      StringBuilder stringBuilder = new StringBuilder();
      byte b = 0;
      int j;
      for (j = 1; b < i; j = k) {
        int k;
        char c = paramString.charAt(b);
        if (c == ' ') {
          k = j;
          if (stringBuilder.length() > 0) {
            a(stringBuilder, arrayList, j);
            k = j;
          } 
        } else if (c < 'Ā') {
          if (j != 1 && stringBuilder.length() > 0)
            a(stringBuilder, arrayList, j); 
          stringBuilder.append(c);
          k = 1;
        } else {
          a a = d(c);
          k = a.a;
          if (k == 2) {
            if (stringBuilder.length() > 0)
              a(stringBuilder, arrayList, j); 
            arrayList.add(a);
            k = 2;
          } else {
            if (j != k && stringBuilder.length() > 0)
              a(stringBuilder, arrayList, j); 
            k = a.a;
            stringBuilder.append(c);
          } 
        } 
        b++;
      } 
      if (stringBuilder.length() > 0)
        a(stringBuilder, arrayList, j); 
    } 
    return arrayList;
  }
  
  static {
    byte[] arrayOfByte1 = { 65, 0, 0, 0, 0, 0 };
    byte[] arrayOfByte2 = { 65, 79, 0, 0, 0, 0 };
    byte[] arrayOfByte3 = { 66, 65, 0, 0, 0, 0 };
    byte[] arrayOfByte4 = { 66, 65, 73, 0, 0, 0 };
    byte[] arrayOfByte5 = { 66, 65, 78, 0, 0, 0 };
    byte[] arrayOfByte6 = { 66, 69, 78, 0, 0, 0 };
    byte[] arrayOfByte7 = { 66, 69, 78, 71, 0, 0 };
    byte[] arrayOfByte8 = { 66, 73, 65, 78, 0, 0 };
    byte[] arrayOfByte9 = { 66, 73, 65, 79, 0, 0 };
    byte[] arrayOfByte10 = { 66, 73, 69, 0, 0, 0 };
    byte[] arrayOfByte11 = { 66, 73, 78, 0, 0, 0 };
    byte[] arrayOfByte12 = { 66, 73, 78, 71, 0, 0 };
    byte[] arrayOfByte13 = { 66, 79, 0, 0, 0, 0 };
    byte[] arrayOfByte14 = { 66, 85, 0, 0, 0, 0 };
    byte[] arrayOfByte15 = { 67, 65, 0, 0, 0, 0 };
    byte[] arrayOfByte16 = { 67, 65, 79, 0, 0, 0 };
    byte[] arrayOfByte17 = { 67, 69, 0, 0, 0, 0 };
    byte[] arrayOfByte18 = { 67, 69, 78, 0, 0, 0 };
    byte[] arrayOfByte19 = { 67, 69, 78, 71, 0, 0 };
    byte[] arrayOfByte20 = { 67, 72, 65, 73, 0, 0 };
    byte[] arrayOfByte21 = { 67, 72, 65, 78, 0, 0 };
    byte[] arrayOfByte22 = { 67, 72, 65, 78, 71, 0 };
    byte[] arrayOfByte23 = { 67, 72, 65, 79, 0, 0 };
    byte[] arrayOfByte24 = { 67, 72, 69, 0, 0, 0 };
    byte[] arrayOfByte25 = { 83, 72, 69, 78, 0, 0 };
    byte[] arrayOfByte26 = { 67, 72, 69, 78, 0, 0 };
    byte[] arrayOfByte27 = { 67, 72, 69, 78, 71, 0 };
    byte[] arrayOfByte28 = { 67, 72, 73, 0, 0, 0 };
    byte[] arrayOfByte29 = { 67, 72, 79, 78, 71, 0 };
    byte[] arrayOfByte30 = { 67, 72, 85, 65, 73, 0 };
    byte[] arrayOfByte31 = { 67, 72, 85, 65, 78, 0 };
    byte[] arrayOfByte32 = { 67, 72, 85, 73, 0, 0 };
    byte[] arrayOfByte33 = { 67, 72, 85, 78, 0, 0 };
    byte[] arrayOfByte34 = { 67, 72, 85, 79, 0, 0 };
    byte[] arrayOfByte35 = { 67, 85, 0, 0, 0, 0 };
    byte[] arrayOfByte36 = { 67, 85, 65, 78, 0, 0 };
    byte[] arrayOfByte37 = { 67, 85, 73, 0, 0, 0 };
    byte[] arrayOfByte38 = { 67, 85, 78, 0, 0, 0 };
    byte[] arrayOfByte39 = { 67, 85, 79, 0, 0, 0 };
    byte[] arrayOfByte40 = { 68, 65, 73, 0, 0, 0 };
    byte[] arrayOfByte41 = { 68, 65, 78, 0, 0, 0 };
    byte[] arrayOfByte42 = { 68, 65, 79, 0, 0, 0 };
    byte[] arrayOfByte43 = { 68, 69, 78, 71, 0, 0 };
    byte[] arrayOfByte44 = { 68, 73, 0, 0, 0, 0 };
    byte[] arrayOfByte45 = { 68, 73, 65, 0, 0, 0 };
    byte[] arrayOfByte46 = { 68, 73, 65, 79, 0, 0 };
    byte[] arrayOfByte47 = { 68, 73, 69, 0, 0, 0 };
    byte[] arrayOfByte48 = { 68, 73, 85, 0, 0, 0 };
    byte[] arrayOfByte49 = { 68, 79, 78, 71, 0, 0 };
    byte[] arrayOfByte50 = { 68, 85, 0, 0, 0, 0 };
    byte[] arrayOfByte51 = { 68, 85, 65, 78, 0, 0 };
    byte[] arrayOfByte52 = { 68, 85, 73, 0, 0, 0 };
    byte[] arrayOfByte53 = { 68, 85, 79, 0, 0, 0 };
    byte[] arrayOfByte54 = { 69, 0, 0, 0, 0, 0 };
    byte[] arrayOfByte55 = { 69, 78, 0, 0, 0, 0 };
    byte[] arrayOfByte56 = { 69, 82, 0, 0, 0, 0 };
    byte[] arrayOfByte57 = { 70, 65, 0, 0, 0, 0 };
    byte[] arrayOfByte58 = { 70, 65, 78, 71, 0, 0 };
    byte[] arrayOfByte59 = { 70, 69, 78, 0, 0, 0 };
    byte[] arrayOfByte60 = { 70, 69, 78, 71, 0, 0 };
    byte[] arrayOfByte61 = { 70, 79, 0, 0, 0, 0 };
    byte[] arrayOfByte62 = { 70, 85, 0, 0, 0, 0 };
    byte[] arrayOfByte63 = { 71, 65, 0, 0, 0, 0 };
    byte[] arrayOfByte64 = { 71, 65, 78, 0, 0, 0 };
    byte[] arrayOfByte65 = { 71, 65, 78, 71, 0, 0 };
    byte[] arrayOfByte66 = { 71, 69, 0, 0, 0, 0 };
    byte[] arrayOfByte67 = { 71, 69, 78, 71, 0, 0 };
    byte[] arrayOfByte68 = { 71, 79, 78, 71, 0, 0 };
    byte[] arrayOfByte69 = { 71, 79, 85, 0, 0, 0 };
    byte[] arrayOfByte70 = { 71, 85, 0, 0, 0, 0 };
    byte[] arrayOfByte71 = { 71, 85, 65, 78, 71, 0 };
    byte[] arrayOfByte72 = { 71, 85, 73, 0, 0, 0 };
    byte[] arrayOfByte73 = { 71, 85, 79, 0, 0, 0 };
    byte[] arrayOfByte74 = { 72, 65, 73, 0, 0, 0 };
    byte[] arrayOfByte75 = { 72, 65, 78, 0, 0, 0 };
    byte[] arrayOfByte76 = { 72, 65, 78, 71, 0, 0 };
    byte[] arrayOfByte77 = { 72, 65, 79, 0, 0, 0 };
    byte[] arrayOfByte78 = { 72, 69, 0, 0, 0, 0 };
    byte[] arrayOfByte79 = { 72, 69, 78, 71, 0, 0 };
    byte[] arrayOfByte80 = { 72, 79, 78, 71, 0, 0 };
    byte[] arrayOfByte81 = { 72, 79, 85, 0, 0, 0 };
    byte[] arrayOfByte82 = { 72, 85, 65, 73, 0, 0 };
    byte[] arrayOfByte83 = { 72, 85, 65, 78, 0, 0 };
    byte[] arrayOfByte84 = { 72, 85, 65, 78, 71, 0 };
    byte[] arrayOfByte85 = { 72, 85, 73, 0, 0, 0 };
    byte[] arrayOfByte86 = { 72, 85, 78, 0, 0, 0 };
    byte[] arrayOfByte87 = { 74, 73, 65, 0, 0, 0 };
    byte[] arrayOfByte88 = { 74, 73, 65, 78, 0, 0 };
    byte[] arrayOfByte89 = { 74, 73, 65, 78, 71, 0 };
    byte[] arrayOfByte90 = { 74, 73, 65, 79, 0, 0 };
    byte[] arrayOfByte91 = { 74, 73, 78, 71, 0, 0 };
    byte[] arrayOfByte92 = { 74, 73, 79, 78, 71, 0 };
    byte[] arrayOfByte93 = { 74, 85, 78, 0, 0, 0 };
    byte[] arrayOfByte94 = { 75, 65, 78, 0, 0, 0 };
    byte[] arrayOfByte95 = { 75, 65, 78, 71, 0, 0 };
    byte[] arrayOfByte96 = { 75, 79, 85, 0, 0, 0 };
    byte[] arrayOfByte97 = { 75, 85, 65, 73, 0, 0 };
    byte[] arrayOfByte98 = { 75, 85, 65, 78, 0, 0 };
    byte[] arrayOfByte99 = { 75, 85, 65, 78, 71, 0 };
    byte[] arrayOfByte100 = { 75, 85, 73, 0, 0, 0 };
    byte[] arrayOfByte101 = { 76, 65, 0, 0, 0, 0 };
    byte[] arrayOfByte102 = { 76, 65, 73, 0, 0, 0 };
    byte[] arrayOfByte103 = { 76, 65, 78, 0, 0, 0 };
    byte[] arrayOfByte104 = { 76, 65, 78, 71, 0, 0 };
    byte[] arrayOfByte105 = { 76, 65, 79, 0, 0, 0 };
    byte[] arrayOfByte106 = { 76, 69, 0, 0, 0, 0 };
    byte[] arrayOfByte107 = { 76, 69, 73, 0, 0, 0 };
    byte[] arrayOfByte108 = { 76, 69, 78, 71, 0, 0 };
    byte[] arrayOfByte109 = { 76, 73, 65, 0, 0, 0 };
    byte[] arrayOfByte110 = { 76, 73, 65, 78, 71, 0 };
    byte[] arrayOfByte111 = { 76, 73, 65, 79, 0, 0 };
    byte[] arrayOfByte112 = { 76, 73, 69, 0, 0, 0 };
    byte[] arrayOfByte113 = { 76, 73, 78, 0, 0, 0 };
    byte[] arrayOfByte114 = { 76, 73, 78, 71, 0, 0 };
    byte[] arrayOfByte115 = { 76, 73, 85, 0, 0, 0 };
    byte[] arrayOfByte116 = { 76, 79, 0, 0, 0, 0 };
    byte[] arrayOfByte117 = { 76, 79, 78, 71, 0, 0 };
    byte[] arrayOfByte118 = { 76, 79, 85, 0, 0, 0 };
    byte[] arrayOfByte119 = { 76, 85, 65, 78, 0, 0 };
    byte[] arrayOfByte120 = { 76, 85, 78, 0, 0, 0 };
    byte[] arrayOfByte121 = { 77, 0, 0, 0, 0, 0 };
    byte[] arrayOfByte122 = { 77, 65, 0, 0, 0, 0 };
    byte[] arrayOfByte123 = { 77, 65, 78, 0, 0, 0 };
    byte[] arrayOfByte124 = { 77, 65, 79, 0, 0, 0 };
    byte[] arrayOfByte125 = { 77, 69, 0, 0, 0, 0 };
    byte[] arrayOfByte126 = { 77, 73, 0, 0, 0, 0 };
    byte[] arrayOfByte127 = { 77, 73, 65, 78, 0, 0 };
    byte[] arrayOfByte128 = { 77, 73, 65, 79, 0, 0 };
    byte[] arrayOfByte129 = { 77, 73, 78, 0, 0, 0 };
    byte[] arrayOfByte130 = { 77, 73, 78, 71, 0, 0 };
    byte[] arrayOfByte131 = { 77, 85, 0, 0, 0, 0 };
    byte[] arrayOfByte132 = { 78, 65, 0, 0, 0, 0 };
    byte[] arrayOfByte133 = { 78, 65, 78, 0, 0, 0 };
    byte[] arrayOfByte134 = { 78, 65, 78, 71, 0, 0 };
    byte[] arrayOfByte135 = { 78, 69, 0, 0, 0, 0 };
    byte[] arrayOfByte136 = { 78, 69, 73, 0, 0, 0 };
    byte[] arrayOfByte137 = { 78, 69, 78, 71, 0, 0 };
    byte[] arrayOfByte138 = { 78, 73, 0, 0, 0, 0 };
    byte[] arrayOfByte139 = { 78, 73, 65, 79, 0, 0 };
    byte[] arrayOfByte140 = { 78, 73, 78, 0, 0, 0 };
    byte[] arrayOfByte141 = { 78, 73, 78, 71, 0, 0 };
    byte[] arrayOfByte142 = { 78, 79, 78, 71, 0, 0 };
    byte[] arrayOfByte143 = { 78, 79, 85, 0, 0, 0 };
    byte[] arrayOfByte144 = { 78, 85, 0, 0, 0, 0 };
    byte[] arrayOfByte145 = { 78, 85, 69, 0, 0, 0 };
    byte[] arrayOfByte146 = { 78, 85, 78, 0, 0, 0 };
    byte[] arrayOfByte147 = { 79, 85, 0, 0, 0, 0 };
    byte[] arrayOfByte148 = { 80, 65, 73, 0, 0, 0 };
    byte[] arrayOfByte149 = { 80, 65, 78, 0, 0, 0 };
    byte[] arrayOfByte150 = { 80, 65, 78, 71, 0, 0 };
    byte[] arrayOfByte151 = { 80, 65, 79, 0, 0, 0 };
    byte[] arrayOfByte152 = { 80, 69, 73, 0, 0, 0 };
    byte[] arrayOfByte153 = { 80, 69, 78, 0, 0, 0 };
    byte[] arrayOfByte154 = { 80, 73, 65, 78, 0, 0 };
    byte[] arrayOfByte155 = { 80, 73, 65, 79, 0, 0 };
    byte[] arrayOfByte156 = { 80, 73, 69, 0, 0, 0 };
    byte[] arrayOfByte157 = { 80, 73, 78, 0, 0, 0 };
    byte[] arrayOfByte158 = { 80, 73, 78, 71, 0, 0 };
    byte[] arrayOfByte159 = { 80, 79, 0, 0, 0, 0 };
    byte[] arrayOfByte160 = { 80, 79, 85, 0, 0, 0 };
    byte[] arrayOfByte161 = { 80, 85, 0, 0, 0, 0 };
    byte[] arrayOfByte162 = { 81, 73, 0, 0, 0, 0 };
    byte[] arrayOfByte163 = { 81, 73, 65, 78, 0, 0 };
    byte[] arrayOfByte164 = { 81, 73, 65, 78, 71, 0 };
    byte[] arrayOfByte165 = { 81, 73, 78, 0, 0, 0 };
    byte[] arrayOfByte166 = { 81, 73, 79, 78, 71, 0 };
    byte[] arrayOfByte167 = { 81, 73, 85, 0, 0, 0 };
    byte[] arrayOfByte168 = { 81, 85, 0, 0, 0, 0 };
    byte[] arrayOfByte169 = { 81, 85, 69, 0, 0, 0 };
    byte[] arrayOfByte170 = { 81, 85, 78, 0, 0, 0 };
    byte[] arrayOfByte171 = { 82, 65, 78, 71, 0, 0 };
    byte[] arrayOfByte172 = { 82, 65, 79, 0, 0, 0 };
    byte[] arrayOfByte173 = { 82, 69, 0, 0, 0, 0 };
    byte[] arrayOfByte174 = { 82, 69, 78, 0, 0, 0 };
    byte[] arrayOfByte175 = { 82, 69, 78, 71, 0, 0 };
    byte[] arrayOfByte176 = { 82, 73, 0, 0, 0, 0 };
    byte[] arrayOfByte177 = { 82, 79, 78, 71, 0, 0 };
    byte[] arrayOfByte178 = { 82, 85, 0, 0, 0, 0 };
    byte[] arrayOfByte179 = { 82, 85, 65, 0, 0, 0 };
    byte[] arrayOfByte180 = { 82, 85, 65, 78, 0, 0 };
    byte[] arrayOfByte181 = { 82, 85, 73, 0, 0, 0 };
    byte[] arrayOfByte182 = { 82, 85, 79, 0, 0, 0 };
    byte[] arrayOfByte183 = { 83, 65, 0, 0, 0, 0 };
    byte[] arrayOfByte184 = { 83, 65, 73, 0, 0, 0 };
    byte[] arrayOfByte185 = { 83, 65, 78, 0, 0, 0 };
    byte[] arrayOfByte186 = { 83, 65, 78, 71, 0, 0 };
    byte[] arrayOfByte187 = { 83, 65, 79, 0, 0, 0 };
    byte[] arrayOfByte188 = { 83, 69, 78, 0, 0, 0 };
    byte[] arrayOfByte189 = { 83, 69, 78, 71, 0, 0 };
    byte[] arrayOfByte190 = { 83, 72, 65, 0, 0, 0 };
    byte[] arrayOfByte191 = { 83, 72, 65, 73, 0, 0 };
    byte[] arrayOfByte192 = { 83, 72, 65, 78, 0, 0 };
    byte[] arrayOfByte193 = { 83, 72, 65, 78, 71, 0 };
    byte[] arrayOfByte194 = { 83, 72, 65, 79, 0, 0 };
    byte[] arrayOfByte195 = { 83, 72, 69, 0, 0, 0 };
    byte[] arrayOfByte196 = { 83, 72, 69, 78, 0, 0 };
    byte[] arrayOfByte197 = { 88, 73, 78, 0, 0, 0 };
    byte[] arrayOfByte198 = { 83, 72, 69, 78, 0, 0 };
    byte[] arrayOfByte199 = { 83, 72, 85, 65, 73, 0 };
    byte[] arrayOfByte200 = { 83, 72, 85, 65, 78, 0 };
    byte[] arrayOfByte201 = { 83, 72, 85, 73, 0, 0 };
    byte[] arrayOfByte202 = { 83, 79, 78, 71, 0, 0 };
    byte[] arrayOfByte203 = { 83, 79, 85, 0, 0, 0 };
    byte[] arrayOfByte204 = { 83, 85, 65, 78, 0, 0 };
    byte[] arrayOfByte205 = { 83, 85, 78, 0, 0, 0 };
    byte[] arrayOfByte206 = { 83, 85, 79, 0, 0, 0 };
    byte[] arrayOfByte207 = { 84, 65, 0, 0, 0, 0 };
    byte[] arrayOfByte208 = { 84, 65, 78, 0, 0, 0 };
    byte[] arrayOfByte209 = { 84, 65, 78, 71, 0, 0 };
    byte[] arrayOfByte210 = { 84, 65, 79, 0, 0, 0 };
    byte[] arrayOfByte211 = { 84, 69, 0, 0, 0, 0 };
    byte[] arrayOfByte212 = { 84, 69, 78, 71, 0, 0 };
    byte[] arrayOfByte213 = { 84, 73, 0, 0, 0, 0 };
    byte[] arrayOfByte214 = { 84, 73, 65, 78, 0, 0 };
    byte[] arrayOfByte215 = { 84, 73, 65, 79, 0, 0 };
    byte[] arrayOfByte216 = { 84, 79, 78, 71, 0, 0 };
    byte[] arrayOfByte217 = { 84, 79, 85, 0, 0, 0 };
    byte[] arrayOfByte218 = { 84, 85, 65, 78, 0, 0 };
    byte[] arrayOfByte219 = { 84, 85, 73, 0, 0, 0 };
    byte[] arrayOfByte220 = { 84, 85, 79, 0, 0, 0 };
    byte[] arrayOfByte221 = { 87, 65, 0, 0, 0, 0 };
    byte[] arrayOfByte222 = { 87, 65, 73, 0, 0, 0 };
    byte[] arrayOfByte223 = { 87, 65, 78, 0, 0, 0 };
    byte[] arrayOfByte224 = { 87, 65, 78, 71, 0, 0 };
    byte[] arrayOfByte225 = { 87, 69, 73, 0, 0, 0 };
    byte[] arrayOfByte226 = { 87, 85, 0, 0, 0, 0 };
    byte[] arrayOfByte227 = { 88, 73, 65, 0, 0, 0 };
    byte[] arrayOfByte228 = { 88, 73, 65, 79, 0, 0 };
    byte[] arrayOfByte229 = { 88, 73, 69, 0, 0, 0 };
    byte[] arrayOfByte230 = { 88, 73, 78, 71, 0, 0 };
    byte[] arrayOfByte231 = { 88, 73, 79, 78, 71, 0 };
    byte[] arrayOfByte232 = { 88, 85, 0, 0, 0, 0 };
    byte[] arrayOfByte233 = { 88, 85, 65, 78, 0, 0 };
    byte[] arrayOfByte234 = { 88, 85, 69, 0, 0, 0 };
    byte[] arrayOfByte235 = { 88, 85, 78, 0, 0, 0 };
    byte[] arrayOfByte236 = { 89, 65, 0, 0, 0, 0 };
    byte[] arrayOfByte237 = { 89, 65, 78, 71, 0, 0 };
    byte[] arrayOfByte238 = { 89, 65, 79, 0, 0, 0 };
    byte[] arrayOfByte239 = { 89, 73, 0, 0, 0, 0 };
    byte[] arrayOfByte240 = { 89, 73, 78, 71, 0, 0 };
    byte[] arrayOfByte241 = { 89, 79, 78, 71, 0, 0 };
    byte[] arrayOfByte242 = { 89, 85, 65, 78, 0, 0 };
    byte[] arrayOfByte243 = { 89, 85, 78, 0, 0, 0 };
    byte[] arrayOfByte244 = { 89, 85, 78, 0, 0, 0 };
    byte[] arrayOfByte245 = { 90, 65, 0, 0, 0, 0 };
    byte[] arrayOfByte246 = { 90, 65, 73, 0, 0, 0 };
    byte[] arrayOfByte247 = { 90, 65, 78, 0, 0, 0 };
    byte[] arrayOfByte248 = { 90, 65, 78, 71, 0, 0 };
    byte[] arrayOfByte249 = { 90, 65, 79, 0, 0, 0 };
    byte[] arrayOfByte250 = { 90, 69, 73, 0, 0, 0 };
    byte[] arrayOfByte251 = { 90, 69, 78, 71, 0, 0 };
    byte[] arrayOfByte252 = { 90, 72, 65, 73, 0, 0 };
    byte[] arrayOfByte253 = { 90, 72, 65, 78, 71, 0 };
    byte[] arrayOfByte254 = { 67, 72, 65, 78, 71, 0 };
    byte[] arrayOfByte255 = { 90, 72, 65, 79, 0, 0 };
    byte[] arrayOfByte256 = { 90, 72, 69, 0, 0, 0 };
    byte[] arrayOfByte257 = { 90, 72, 69, 78, 0, 0 };
    byte[] arrayOfByte258 = { 90, 72, 69, 78, 71, 0 };
    byte[] arrayOfByte259 = { 90, 72, 73, 0, 0, 0 };
    byte[] arrayOfByte260 = { 90, 72, 73, 0, 0, 0 };
    byte[] arrayOfByte261 = { 90, 72, 79, 85, 0, 0 };
    byte[] arrayOfByte262 = { 90, 72, 85, 65, 0, 0 };
    byte[] arrayOfByte263 = { 90, 72, 85, 65, 78, 71 };
    byte[] arrayOfByte264 = { 90, 72, 85, 78, 0, 0 };
    byte[] arrayOfByte265 = { 90, 72, 85, 79, 0, 0 };
    byte[] arrayOfByte266 = { 90, 79, 78, 71, 0, 0 };
    byte[] arrayOfByte267 = { 90, 79, 85, 0, 0, 0 };
    byte[] arrayOfByte268 = { 90, 85, 0, 0, 0, 0 };
    byte[] arrayOfByte269 = { 90, 85, 65, 78, 0, 0 };
    byte[] arrayOfByte270 = { 90, 85, 78, 0, 0, 0 };
    byte[] arrayOfByte271 = { 90, 85, 79, 0, 0, 0 };
    byte[] arrayOfByte272 = { 0, 0, 0, 0, 0, 0 };
    b = new byte[][] { 
        arrayOfByte1, { 65, 73, 0, 0, 0, 0 }, { 65, 78, 0, 0, 0, 0 }, { 65, 78, 71, 0, 0, 0 }, arrayOfByte2, arrayOfByte3, arrayOfByte4, arrayOfByte5, { 66, 65, 78, 71, 0, 0 }, { 66, 65, 79, 0, 0, 0 }, 
        { 66, 69, 73, 0, 0, 0 }, arrayOfByte6, arrayOfByte7, { 66, 73, 0, 0, 0, 0 }, arrayOfByte8, arrayOfByte9, arrayOfByte10, arrayOfByte11, arrayOfByte12, arrayOfByte13, 
        arrayOfByte14, arrayOfByte15, { 67, 65, 73, 0, 0, 0 }, { 67, 65, 78, 0, 0, 0 }, { 67, 65, 78, 71, 0, 0 }, arrayOfByte16, arrayOfByte17, arrayOfByte18, arrayOfByte19, { 90, 69, 78, 71, 0, 0 }, 
        { 67, 69, 78, 71, 0, 0 }, { 67, 72, 65, 0, 0, 0 }, arrayOfByte20, arrayOfByte21, arrayOfByte22, arrayOfByte23, arrayOfByte24, { 67, 72, 69, 78, 0, 0 }, arrayOfByte25, arrayOfByte26, 
        arrayOfByte27, arrayOfByte28, arrayOfByte29, { 67, 72, 79, 85, 0, 0 }, { 67, 72, 85, 0, 0, 0 }, { 67, 72, 85, 65, 0, 0 }, arrayOfByte30, arrayOfByte31, { 67, 72, 85, 65, 78, 71 }, arrayOfByte32, 
        arrayOfByte33, arrayOfByte34, { 67, 73, 0, 0, 0, 0 }, { 67, 79, 78, 71, 0, 0 }, { 67, 79, 85, 0, 0, 0 }, arrayOfByte35, arrayOfByte36, arrayOfByte37, arrayOfByte38, arrayOfByte39, 
        { 68, 65, 0, 0, 0, 0 }, arrayOfByte40, arrayOfByte41, { 68, 65, 78, 71, 0, 0 }, arrayOfByte42, { 68, 69, 0, 0, 0, 0 }, { 68, 69, 78, 0, 0, 0 }, arrayOfByte43, arrayOfByte44, arrayOfByte45, 
        { 68, 73, 65, 78, 0, 0 }, arrayOfByte46, arrayOfByte47, { 68, 73, 78, 71, 0, 0 }, arrayOfByte48, arrayOfByte49, { 68, 79, 85, 0, 0, 0 }, arrayOfByte50, arrayOfByte51, arrayOfByte52, 
        { 68, 85, 78, 0, 0, 0 }, arrayOfByte53, arrayOfByte54, { 69, 73, 0, 0, 0, 0 }, arrayOfByte55, { 69, 78, 71, 0, 0, 0 }, arrayOfByte56, arrayOfByte57, { 70, 65, 78, 0, 0, 0 }, arrayOfByte58, 
        { 70, 69, 73, 0, 0, 0 }, arrayOfByte59, arrayOfByte60, { 70, 73, 65, 79, 0, 0 }, arrayOfByte61, { 70, 79, 85, 0, 0, 0 }, arrayOfByte62, arrayOfByte63, { 71, 65, 73, 0, 0, 0 }, arrayOfByte64, 
        arrayOfByte65, { 71, 65, 79, 0, 0, 0 }, arrayOfByte66, { 71, 69, 73, 0, 0, 0 }, { 71, 69, 78, 0, 0, 0 }, arrayOfByte67, arrayOfByte68, arrayOfByte69, arrayOfByte70, { 71, 85, 65, 0, 0, 0 }, 
        { 71, 85, 65, 73, 0, 0 }, { 71, 85, 65, 78, 0, 0 }, arrayOfByte71, arrayOfByte72, { 71, 85, 78, 0, 0, 0 }, arrayOfByte73, { 72, 65, 0, 0, 0, 0 }, arrayOfByte74, arrayOfByte75, arrayOfByte76, 
        arrayOfByte77, arrayOfByte78, { 72, 69, 73, 0, 0, 0 }, { 72, 69, 78, 0, 0, 0 }, arrayOfByte79, { 72, 77, 0, 0, 0, 0 }, arrayOfByte80, arrayOfByte81, { 72, 85, 0, 0, 0, 0 }, { 72, 85, 65, 0, 0, 0 }, 
        arrayOfByte82, arrayOfByte83, arrayOfByte84, arrayOfByte85, arrayOfByte86, { 72, 85, 79, 0, 0, 0 }, { 74, 73, 0, 0, 0, 0 }, arrayOfByte87, arrayOfByte88, arrayOfByte89, 
        arrayOfByte90, { 74, 73, 69, 0, 0, 0 }, { 74, 73, 78, 0, 0, 0 }, arrayOfByte91, arrayOfByte92, { 74, 73, 85, 0, 0, 0 }, { 74, 85, 0, 0, 0, 0 }, { 74, 85, 65, 78, 0, 0 }, { 74, 85, 69, 0, 0, 0 }, arrayOfByte93, 
        { 75, 65, 0, 0, 0, 0 }, { 75, 65, 73, 0, 0, 0 }, arrayOfByte94, arrayOfByte95, { 75, 65, 79, 0, 0, 0 }, { 75, 69, 0, 0, 0, 0 }, { 75, 69, 78, 0, 0, 0 }, { 75, 69, 78, 71, 0, 0 }, { 75, 79, 78, 71, 0, 0 }, arrayOfByte96, 
        { 75, 85, 0, 0, 0, 0 }, { 75, 85, 65, 0, 0, 0 }, arrayOfByte97, arrayOfByte98, arrayOfByte99, arrayOfByte100, { 75, 85, 78, 0, 0, 0 }, { 75, 85, 79, 0, 0, 0 }, arrayOfByte101, arrayOfByte102, 
        arrayOfByte103, arrayOfByte104, arrayOfByte105, arrayOfByte106, arrayOfByte107, arrayOfByte108, { 76, 73, 0, 0, 0, 0 }, arrayOfByte109, { 76, 73, 65, 78, 0, 0 }, arrayOfByte110, 
        arrayOfByte111, arrayOfByte112, arrayOfByte113, arrayOfByte114, arrayOfByte115, arrayOfByte116, arrayOfByte117, arrayOfByte118, { 76, 85, 0, 0, 0, 0 }, arrayOfByte119, 
        { 76, 85, 69, 0, 0, 0 }, arrayOfByte120, { 76, 85, 79, 0, 0, 0 }, arrayOfByte121, arrayOfByte122, { 77, 65, 73, 0, 0, 0 }, arrayOfByte123, { 77, 65, 78, 71, 0, 0 }, arrayOfByte124, arrayOfByte125, 
        { 77, 69, 73, 0, 0, 0 }, { 77, 69, 78, 0, 0, 0 }, { 77, 69, 78, 71, 0, 0 }, arrayOfByte126, arrayOfByte127, arrayOfByte128, { 77, 73, 69, 0, 0, 0 }, arrayOfByte129, arrayOfByte130, { 77, 73, 85, 0, 0, 0 }, 
        { 77, 79, 0, 0, 0, 0 }, { 77, 79, 85, 0, 0, 0 }, arrayOfByte131, { 78, 0, 0, 0, 0, 0 }, arrayOfByte132, { 78, 65, 73, 0, 0, 0 }, arrayOfByte133, arrayOfByte134, { 78, 65, 79, 0, 0, 0 }, arrayOfByte135, 
        arrayOfByte136, { 78, 69, 78, 0, 0, 0 }, arrayOfByte137, arrayOfByte138, { 78, 73, 65, 78, 0, 0 }, { 78, 73, 65, 78, 71, 0 }, arrayOfByte139, { 78, 73, 69, 0, 0, 0 }, arrayOfByte140, arrayOfByte141, 
        { 78, 73, 85, 0, 0, 0 }, arrayOfByte142, arrayOfByte143, arrayOfByte144, { 78, 85, 65, 78, 0, 0 }, arrayOfByte145, arrayOfByte146, { 78, 85, 79, 0, 0, 0 }, { 79, 0, 0, 0, 0, 0 }, arrayOfByte147, 
        { 80, 65, 0, 0, 0, 0 }, arrayOfByte148, arrayOfByte149, arrayOfByte150, arrayOfByte151, arrayOfByte152, arrayOfByte153, { 80, 69, 78, 71, 0, 0 }, { 80, 73, 0, 0, 0, 0 }, arrayOfByte154, 
        arrayOfByte155, arrayOfByte156, arrayOfByte157, arrayOfByte158, arrayOfByte159, arrayOfByte160, arrayOfByte161, arrayOfByte162, { 81, 73, 65, 0, 0, 0 }, arrayOfByte163, 
        arrayOfByte164, { 81, 73, 65, 79, 0, 0 }, { 81, 73, 69, 0, 0, 0 }, arrayOfByte165, { 81, 73, 78, 71, 0, 0 }, arrayOfByte166, arrayOfByte167, arrayOfByte168, { 81, 85, 65, 78, 0, 0 }, arrayOfByte169, 
        arrayOfByte170, { 82, 65, 78, 0, 0, 0 }, arrayOfByte171, arrayOfByte172, arrayOfByte173, arrayOfByte174, arrayOfByte175, arrayOfByte176, arrayOfByte177, { 82, 79, 85, 0, 0, 0 }, 
        arrayOfByte178, arrayOfByte179, arrayOfByte180, arrayOfByte181, { 82, 85, 78, 0, 0, 0 }, arrayOfByte182, arrayOfByte183, arrayOfByte184, arrayOfByte185, arrayOfByte186, 
        arrayOfByte187, { 83, 69, 0, 0, 0, 0 }, arrayOfByte188, arrayOfByte189, arrayOfByte190, arrayOfByte191, arrayOfByte192, arrayOfByte193, arrayOfByte194, arrayOfByte195, 
        arrayOfByte196, arrayOfByte197, arrayOfByte198, { 83, 72, 69, 78, 71, 0 }, { 83, 72, 73, 0, 0, 0 }, { 83, 72, 79, 85, 0, 0 }, { 83, 72, 85, 0, 0, 0 }, { 83, 72, 85, 65, 0, 0 }, arrayOfByte199, arrayOfByte200, 
        { 83, 72, 85, 65, 78, 71 }, arrayOfByte201, { 83, 72, 85, 78, 0, 0 }, { 83, 72, 85, 79, 0, 0 }, { 83, 73, 0, 0, 0, 0 }, arrayOfByte202, arrayOfByte203, { 83, 85, 0, 0, 0, 0 }, arrayOfByte204, { 83, 85, 73, 0, 0, 0 }, 
        arrayOfByte205, arrayOfByte206, arrayOfByte207, { 84, 65, 73, 0, 0, 0 }, arrayOfByte208, arrayOfByte209, arrayOfByte210, arrayOfByte211, arrayOfByte212, arrayOfByte213, 
        arrayOfByte214, arrayOfByte215, { 84, 73, 69, 0, 0, 0 }, { 84, 73, 78, 71, 0, 0 }, arrayOfByte216, arrayOfByte217, { 84, 85, 0, 0, 0, 0 }, arrayOfByte218, arrayOfByte219, { 84, 85, 78, 0, 0, 0 }, 
        arrayOfByte220, arrayOfByte221, arrayOfByte222, arrayOfByte223, arrayOfByte224, arrayOfByte225, { 87, 69, 78, 0, 0, 0 }, { 87, 69, 78, 71, 0, 0 }, { 87, 79, 0, 0, 0, 0 }, arrayOfByte226, 
        { 88, 73, 0, 0, 0, 0 }, arrayOfByte227, { 88, 73, 65, 78, 0, 0 }, { 88, 73, 65, 78, 71, 0 }, arrayOfByte228, arrayOfByte229, { 88, 73, 78, 0, 0, 0 }, arrayOfByte230, arrayOfByte231, { 88, 73, 85, 0, 0, 0 }, 
        arrayOfByte232, arrayOfByte233, arrayOfByte234, arrayOfByte235, arrayOfByte236, { 89, 65, 78, 0, 0, 0 }, arrayOfByte237, arrayOfByte238, { 89, 69, 0, 0, 0, 0 }, arrayOfByte239, 
        { 89, 73, 78, 0, 0, 0 }, arrayOfByte240, { 89, 79, 0, 0, 0, 0 }, arrayOfByte241, { 89, 79, 85, 0, 0, 0 }, { 89, 85, 0, 0, 0, 0 }, arrayOfByte242, { 89, 85, 69, 0, 0, 0 }, arrayOfByte243, { 74, 85, 78, 0, 0, 0 }, 
        arrayOfByte244, arrayOfByte245, arrayOfByte246, arrayOfByte247, arrayOfByte248, arrayOfByte249, { 90, 69, 0, 0, 0, 0 }, arrayOfByte250, { 90, 69, 78, 0, 0, 0 }, arrayOfByte251, 
        { 90, 72, 65, 0, 0, 0 }, arrayOfByte252, { 90, 72, 65, 78, 0, 0 }, arrayOfByte253, arrayOfByte254, { 90, 72, 65, 78, 71, 0 }, arrayOfByte255, arrayOfByte256, arrayOfByte257, arrayOfByte258, 
        arrayOfByte259, { 83, 72, 73, 0, 0, 0 }, arrayOfByte260, { 90, 72, 79, 78, 71, 0 }, arrayOfByte261, { 90, 72, 85, 0, 0, 0 }, arrayOfByte262, { 90, 72, 85, 65, 73, 0 }, { 90, 72, 85, 65, 78, 0 }, arrayOfByte263, 
        { 90, 72, 85, 73, 0, 0 }, arrayOfByte264, arrayOfByte265, { 90, 73, 0, 0, 0, 0 }, arrayOfByte266, arrayOfByte267, arrayOfByte268, arrayOfByte269, { 90, 85, 73, 0, 0, 0 }, arrayOfByte270, 
        arrayOfByte271, arrayOfByte272, { 83, 72, 65, 78, 0, 0 }, { 0, 0, 0, 0, 0, 0 } };
  }
  
  public static class a {
    public int a;
    
    public String b;
    
    public String c;
    
    public a() {}
    
    public a(int param1Int, String param1String1, String param1String2) {
      this.a = param1Int;
      this.b = param1String1;
      this.c = param1String2;
    }
  }
}


/* Location:              /home/sumith/decompile/test/classes-dex2jar.jar!/com/allinone/callerid/util/v.class
 * Java compiler version: 6 (50.0)
 * JD-Core Version:       1.1.3
 */